Workbook

Sheet MP1
B1: Employer ID No. | C1: 2027-4107-0002
B2: Employer/Business Name | C2: AGRICULTURAL TRAINING INSTITUTE
B3: Employer/Business Address | C3: ATI Bldg. Elliptical Rd. Diliman, Quezon City
B4: Contact Number | C4: 929-85(234)/09989741223
B5: Email Address | C5: hrmo.co@ati.da.gov.ph
B6: Total Remittance | C6: =K99+L99 -> 45000
B7: Pag-IBIG IDENTIFICATION NO. | D7: MEMBERSHIP PROGRAM | E7: LAST NAME | F7: FIRST NAME | G7: NAME EXTENSION | H7: MIDDLE NAME | I7: PERCOV | J7: For PAG-IBIG I only | L7: EE SHARE | M7: REMARKS
B8: MID NO. | C8: MP2 ACCOUNT NO. | J8: MONTHLY COMPENSATION | K8: ER SHARE
A9: 1 | B9: 121222125544 | D9: F1-Pag-IBIG 1 | E9: ABCEDE | F9: DIANNE | H9: PALAYA | I9: MAR 2026 | J9: =SUMIF(PAYOUT!$A:$A,'MP1'!$A9,PAYOUT!$L:$L) -> 31705 | K9: 200 | L9: =SUMIF(PAYOUT!$A:$A,'MP1'!$A9,PAYOUT!$AE:$AE) -> 200
A10: 2 | B10: 121294057717 | D10: F1-Pag-IBIG 1 | E10: AGUILAR | F10: ROXETTE GELYN | H10: ROÑO | I10: MAR 2026 | J10: =SUMIF(PAYOUT!$A:$A,'MP1'!$A10,PAYOUT!$L:$L) -> 31705 | K10: 200 | L10: =SUMIF(PAYOUT!$A:$A,'MP1'!$A10,PAYOUT!$AE:$AE) -> 200
A11: 3 | B11: 107002369490 | D11: F1-Pag-IBIG 1 | E11: ALBERTO | F11: CAMILO | H11: MALIT | I11: MAR 2026 | J11: =SUMIF(PAYOUT!$A:$A,'MP1'!$A11,PAYOUT!$L:$L) -> 32401 | K11: 200 | L11: =SUMIF(PAYOUT!$A:$A,'MP1'!$A11,PAYOUT!$AE:$AE) -> 200
A12: 4 | B12: 121313175684 | D12: F1-Pag-IBIG 1 | E12: ALCANTARA | F12: JUSTINE ANN | H12: CASTRO | I12: MAR 2026 | J12: =SUMIF(PAYOUT!$A:$A,'MP1'!$A12,PAYOUT!$L:$L) -> 31705 | K12: 200 | L12: =SUMIF(PAYOUT!$A:$A,'MP1'!$A12,PAYOUT!$AE:$AE) -> 200
A13: 5 | B13: 121052246752 | D13: F1-Pag-IBIG 1 | E13: ALFONSO | F13: CINDY | H13: CORCELLES | I13: MAR 2026 | J13: =SUMIF(PAYOUT!$A:$A,'MP1'!$A13,PAYOUT!$L:$L) -> 53818 | K13: 200 | L13: =SUMIF(PAYOUT!$A:$A,'MP1'!$A13,PAYOUT!$AE:$AE) -> 200
A14: 6 | B14: 121019967335 | D14: F1-Pag-IBIG 1 | E14: ALFORQUE | F14: G. MARK ANTHONY | H14: CORDERO | I14: MAR 2026 | J14: =SUMIF(PAYOUT!$A:$A,'MP1'!$A14,PAYOUT!$L:$L) -> 42594 | K14: 200 | L14: =SUMIF(PAYOUT!$A:$A,'MP1'!$A14,PAYOUT!$AE:$AE) -> 1000
A15: 7 | B15: 121143838658 | D15: F1-Pag-IBIG 1 | E15: ALVAREZ | F15: MARIA CLARISSA | H15: MENDEZ | I15: MAR 2026 | J15: =SUMIF(PAYOUT!$A:$A,'MP1'!$A15,PAYOUT!$L:$L) -> 24329 | K15: 200 | L15: =SUMIF(PAYOUT!$A:$A,'MP1'!$A15,PAYOUT!$AE:$AE) -> 200
A16: 8 | B16: 121156058706 | D16: F1-Pag-IBIG 1 | E16: ALVAREZ | F16: MARK NELLO | H16: BOLA | I16: MAR 2026 | J16: =SUMIF(PAYOUT!$A:$A,'MP1'!$A16,PAYOUT!$L:$L) -> 42178 | K16: 200 | L16: =SUMIF(PAYOUT!$A:$A,'MP1'!$A16,PAYOUT!$AE:$AE) -> 500
A17: 9 | B17: 121146103671 | D17: F1-Pag-IBIG 1 | E17: ANINACION | F17: JOSHUA | H17: GERPACIO | I17: MAR 2026 | J17: =SUMIF(PAYOUT!$A:$A,'MP1'!$A17,PAYOUT!$L:$L) -> 42594 | K17: 200 | L17: =SUMIF(PAYOUT!$A:$A,'MP1'!$A17,PAYOUT!$AE:$AE) -> 200
A18: 10 | B18: 121257804768 | D18: F1-Pag-IBIG 1 | E18: ANTIPAS | F18: ANDREA JANE | H18: MURING | I18: MAR 2026 | J18: =SUMIF(PAYOUT!$A:$A,'MP1'!$A18,PAYOUT!$L:$L) -> 20914 | K18: 200 | L18: =SUMIF(PAYOUT!$A:$A,'MP1'!$A18,PAYOUT!$AE:$AE) -> 200
A19: 11 | B19: 107002368645 | D19: F1-Pag-IBIG 1 | E19: ARCEO | F19: ANTONIETA | H19: JAMON | I19: MAR 2026 | J19: =SUMIF(PAYOUT!$A:$A,'MP1'!$A19,PAYOUT!$L:$L) -> 148940 | K19: 200 | L19: =SUMIF(PAYOUT!$A:$A,'MP1'!$A19,PAYOUT!$AE:$AE) -> 200
A20: 12 | B20: 107002369567 | D20: F1-Pag-IBIG 1 | E20: BALANGATAN | F20: JUN | H20: GARCIA | I20: MAR 2026 | J20: =SUMIF(PAYOUT!$A:$A,'MP1'!$A20,PAYOUT!$L:$L) -> 23668 | K20: 200 | L20: =SUMIF(PAYOUT!$A:$A,'MP1'!$A20,PAYOUT!$AE:$AE) -> 200
... A98: 90 | B98: 121080071170 | D98: F1-Pag-IBIG 1 | E98: YAGO | F98: EMERSON | H98: SOLANO | I98: MAR 2026 | J98: =SUMIF(PAYOUT!$A:$A,'MP1'!$A98,PAYOUT!$L:$L) -> 82963 | K98: 200 | L98: =SUMIF(PAYOUT!$A:$A,'MP1'!$A98,PAYOUT!$AE:$AE) -> 200
K99: =SUM(K9:K98) -> 18000 | L99: =SUM(L9:L98) -> 27000

Sheet MP2
B1: Employer ID No. | C1: 2027-4107-0002
B2: Employer/Business Name | C2: AGRICULTURAL TRAINING INSTITUTE
B3: Employer/Business Address | C3: ATI Bldg. Elliptical Rd. Diliman, Quezon City
B4: Contact Number | C4: 929-85(234)/09989741223
B5: Email Address | C5: hrmo.co@ati.da.gov.ph
B6: Total Remittance | C6: =L100 -> 33700
B7: Pag-IBIG IDENTIFICATION NO. | D7: MEMBERSHIP PROGRAM | E7: LAST NAME | F7: FIRST NAME | G7: NAME EXTENSION | H7: MIDDLE NAME | I7: PERCOV | J7: For PAG-IBIG II only | L7: EE SHARE | M7: REMARKS
B8: MID NO. | C8: MP2 ACCOUNT NO. | J8: MONTHLY COMPENSATION | K8: ER SHARE
A9: 1 | B9: 121222125544 | C9: 521037005993 | D9: M2-Modified Pag-IBIG 2 | E9: ABCEDE | F9: DIANNE | H9: PALAYA | I9: MAR 2026 | J9: =SUMIF(PAYOUT!$A:$A,'MP2'!$A9,PAYOUT!$L:$L) -> 31705 | L9: =SUMIF(PAYOUT!$A:$A,'MP2'!$A9,PAYOUT!$AD:$AD) -> 1000
A10: 2 | B10: 121294057717 | D10: M2-Modified Pag-IBIG 2 | E10: AGUILAR | F10: ROXETTE GELYN | H10: ROÑO | I10: MAR 2026 | J10: =SUMIF(PAYOUT!$A:$A,'MP2'!$A10,PAYOUT!$L:$L) -> 31705 | L10: =SUMIF(PAYOUT!$A:$A,'MP2'!$A10,PAYOUT!$AD:$AD) -> 0
A11: 3 | B11: 107002369490 | C11: 521186014249 | D11: M2-Modified Pag-IBIG 2 | E11: ALBERTO | F11: CAMILO | H11: MALIT | I11: MAR 2026 | J11: =SUMIF(PAYOUT!$A:$A,'MP2'!$A11,PAYOUT!$L:$L) -> 32401 | L11: =SUMIF(PAYOUT!$A:$A,'MP2'!$A11,PAYOUT!$AD:$AD) -> 500
A12: 4 | B12: 121313175684 | D12: M2-Modified Pag-IBIG 2 | E12: ALCANTARA | F12: JUSTINE ANN | H12: CASTRO | I12: MAR 2026 | J12: =SUMIF(PAYOUT!$A:$A,'MP2'!$A12,PAYOUT!$L:$L) -> 31705 | L12: =SUMIF(PAYOUT!$A:$A,'MP2'!$A12,PAYOUT!$AD:$AD) -> 0
A13: 5 | B13: 121052246752 | D13: M2-Modified Pag-IBIG 2 | E13: ALFONSO | F13: CINDY | H13: CORCELLES | I13: MAR 2026 | J13: =SUMIF(PAYOUT!$A:$A,'MP2'!$A13,PAYOUT!$L:$L) -> 53818 | L13: =SUMIF(PAYOUT!$A:$A,'MP2'!$A13,PAYOUT!$AD:$AD) -> 0
A14: 6 | B14: 121019967335 | C14: 524026014423 | D14: M2-Modified Pag-IBIG 2 | E14: ALFORQUE | F14: G. MARK ANTHONY | H14: CORDERO | I14: MAR 2026 | J14: =SUMIF(PAYOUT!$A:$A,'MP2'!$A14,PAYOUT!$L:$L) -> 42594 | L14: =SUMIF(PAYOUT!$A:$A,'MP2'!$A14,PAYOUT!$AD:$AD) -> 3000
A15: 7 | B15: 121143838658 | D15: M2-Modified Pag-IBIG 2 | E15: ALVAREZ | F15: MARIA CLARISSA | H15: MENDEZ | I15: MAR 2026 | J15: =SUMIF(PAYOUT!$A:$A,'MP2'!$A15,PAYOUT!$L:$L) -> 24329 | L15: =SUMIF(PAYOUT!$A:$A,'MP2'!$A15,PAYOUT!$AD:$AD) -> 0
A16: 8 | B16: 121156058706 | C16: 523031016397 | D16: M2-Modified Pag-IBIG 2 | E16: ALVAREZ | F16: MARK NELLO | H16: BOLA | I16: MAR 2026 | J16: =SUMIF(PAYOUT!$A:$A,'MP2'!$A16,PAYOUT!$L:$L) -> 42178 | L16: =SUMIF(PAYOUT!$A:$A,'MP2'!$A16,PAYOUT!$AD:$AD) -> 2000
A17: 9 | B17: 121146103671 | D17: M2-Modified Pag-IBIG 2 | E17: ANINACION | F17: JOSHUA | H17: GERPACIO | I17: MAR 2026 | J17: =SUMIF(PAYOUT!$A:$A,'MP2'!$A17,PAYOUT!$L:$L) -> 42594 | L17: =SUMIF(PAYOUT!$A:$A,'MP2'!$A17,PAYOUT!$AD:$AD) -> 0
A18: 10 | B18: 121257804768 | C18: 525058628227 | D18: M2-Modified Pag-IBIG 2 | E18: ANTIPAS | F18: ANDREA JANE | H18: MURING | I18: MAR 2026 | J18: =SUMIF(PAYOUT!$A:$A,'MP2'!$A18,PAYOUT!$L:$L) -> 20914 | L18: =SUMIF(PAYOUT!$A:$A,'MP2'!$A18,PAYOUT!$AD:$AD) -> 1000
A19: 11 | B19: 107002368645 | D19: M2-Modified Pag-IBIG 2 | E19: ARCEO | F19: ANTONIETA | H19: JAMON | I19: MAR 2026 | J19: =SUMIF(PAYOUT!$A:$A,'MP2'!$A19,PAYOUT!$L:$L) -> 148940 | L19: =SUMIF(PAYOUT!$A:$A,'MP2'!$A19,PAYOUT!$AD:$AD) -> 0
A20: 12 | B20: 107002369567 | D20: M2-Modified Pag-IBIG 2 | E20: BALANGATAN | F20: JUN | H20: GARCIA | I20: MAR 2026 | J20: =SUMIF(PAYOUT!$A:$A,'MP2'!$A20,PAYOUT!$L:$L) -> 23668 | L20: =SUMIF(PAYOUT!$A:$A,'MP2'!$A20,PAYOUT!$AD:$AD) -> 0
A21: 13 | B21: 121310118441 | D21: M2-Modified Pag-IBIG 2 | E21: BALUYUT | F21: JULIA MARIE | H21: MEDES | I21: MAR 2026 | J21: =SUMIF(PAYOUT!$A:$A,'MP2'!$A21,PAYOUT!$L:$L) -> 31705 | L21: =SUMIF(PAYOUT!$A:$A,'MP2'!$A21,PAYOUT!$AD:$AD) -> 0
A22: 14 | B22: 107002369611 | D22: M2-Modified Pag-IBIG 2 | E22: BAUTISTA | F22: MARILYN | H22: JOSEF | I22: MAR 2026 | J22: =SUMIF(PAYOUT!$A:$A,'MP2'!$A22,PAYOUT!$L:$L) -> 17360 | L22: =SUMIF(PAYOUT!$A:$A,'MP2'!$A22,PAYOUT!$AD:$AD) -> 0
A23: 16 | B23: 107002369655 | D23: M2-Modified Pag-IBIG 2 | E23: BIBIT | F23: DARWIN | H23: DELA CRUZ | I23: MAR 2026 | J23: =SUMIF(PAYOUT!$A:$A,'MP2'!$A23,PAYOUT!$L:$L) -> 23883 | L23: =SUMIF(PAYOUT!$A:$A,'MP2'!$A23,PAYOUT!$AD:$AD) -> 0
A24: 17 | B24: 107002405368 | D24: M2-Modified Pag-IBIG 2 | E24: BOLON | F24: RICHARD | H24: ENOT | I24: MAR 2026 | J24: =SUMIF(PAYOUT!$A:$A,'MP2'!$A24,PAYOUT!$L:$L) -> 19565 | L24: =SUMIF(PAYOUT!$A:$A,'MP2'!$A24,PAYOUT!$AD:$AD) -> 0
A25: 18 | B25: 121280890824 | D25: M2-Modified Pag-IBIG 2 | E25: BOMBON | F25: MARY ANGELYN | H25: PANIS | I25: MAR 2026 | J25: =SUMIF(PAYOUT!$A:$A,'MP2'!$A25,PAYOUT!$L:$L) -> 42178 | L25: =SUMIF(PAYOUT!$A:$A,'MP2'!$A25,PAYOUT!$AD:$AD) -> 0
A26: 19 | B26: 121090329684 | C26: 522003016377 | D26: M2-Modified Pag-IBIG 2 | E26: BORLAGDAN | F26: FRANCO GABRIEL | H26: PACAO | I26: MAR 2026 | J26: =SUMIF(PAYOUT!$A:$A,'MP2'!$A26,PAYOUT!$L:$L) -> 50066 | L26: =SUMIF(PAYOUT!$A:$A,'MP2'!$A26,PAYOUT!$AD:$AD) -> 1000
A27: 20 | B27: 121084370919 | D27: M2-Modified Pag-IBIG 2 | E27: BORROMEO | F27: KEMUEL | H27: MORAO | I27: MAR 2026 | J27: =SUMIF(PAYOUT!$A:$A,'MP2'!$A27,PAYOUT!$L:$L) -> 53818 | L27: =SUMIF(PAYOUT!$A:$A,'MP2'!$A27,PAYOUT!$AD:$AD) -> 0
A28: 21 | B28: 121155793878 | D28: M2-Modified Pag-IBIG 2 | E28: BUNDA | F28: ARNEL | H28: RAFAEL | I28: MAR 2026 | J28: =SUMIF(PAYOUT!$A:$A,'MP2'!$A28,PAYOUT!$L:$L) -> 32401 | L28: =SUMIF(PAYOUT!$A:$A,'MP2'!$A28,PAYOUT!$AD:$AD) -> 0
A29: 22 | B29: 121009101617 | D29: M2-Modified Pag-IBIG 2 | E29: CALASAGSAG | F29: JOEVEN | H29: CABINAN | I29: MAR 2026 | J29: =SUMIF(PAYOUT!$A:$A,'MP2'!$A29,PAYOUT!$L:$L) -> 81796 | L29: =SUMIF(PAYOUT!$A:$A,'MP2'!$A29,PAYOUT!$AD:$AD) -> 0
A30: 23 | B30: 107001521691 | C30: 521183012186 | D30: M2-Modified Pag-IBIG 2 | E30: CANILANG | F30: ASHLEE | H30: PERALTA | I30: MAR 2026 | J30: =SUMIF(PAYOUT!$A:$A,'MP2'!$A30,PAYOUT!$L:$L) -> 42178 | L30: =SUMIF(PAYOUT!$A:$A,'MP2'!$A30,PAYOUT!$AD:$AD) -> 1000
A31: 24 | B31: 107002404170 | D31: M2-Modified Pag-IBIG 2 | E31: COSICO | F31: THERESA AURORA | H31: BAGAOISAN | I31: MAR 2026 | J31: =SUMIF(PAYOUT!$A:$A,'MP2'!$A31,PAYOUT!$L:$L) -> 55499 | L31: =SUMIF(PAYOUT!$A:$A,'MP2'!$A31,PAYOUT!$AD:$AD) -> 0
A32: 25 | B32: 108000387241 | D32: M2-Modified Pag-IBIG 2 | E32: DACILLO | F32: EDMER | H32: BAUTISTA | I32: MAR 2026 | J32: =SUMIF(PAYOUT!$A:$A,'MP2'!$A32,PAYOUT!$L:$L) -> 42178 | L32: =SUMIF(PAYOUT!$A:$A,'MP2'!$A32,PAYOUT!$AD:$AD) -> 0
A33: 27 | B33: 121161065445 | D33: M2-Modified Pag-IBIG 2 | E33: DE LA CRUZ | F33: ROY SON | H33: REDOMA | I33: MAR 2026 | J33: =SUMIF(PAYOUT!$A:$A,'MP2'!$A33,PAYOUT!$L:$L) -> 53818 | L33: =SUMIF(PAYOUT!$A:$A,'MP2'!$A33,PAYOUT!$AD:$AD) -> 0
A34: 29 | B34: 121156428649 | C34: 524005030600 | D34: M2-Modified Pag-IBIG 2 | E34: DELA CUADRA | F34: JOVANEE | H34: SANSALONA | I34: MAR 2026 | J34: =SUMIF(PAYOUT!$A:$A,'MP2'!$A34,PAYOUT!$L:$L) -> 43442 | L34: =SUMIF(PAYOUT!$A:$A,'MP2'!$A34,PAYOUT!$AD:$AD) -> 1000
A35: 30 | B35: 121143321613 | D35: M2-Modified Pag-IBIG 2 | E35: DELA TORRE | F35: JULROSE | H35: HERNANDEZ | I35: MAR 2026 | J35: =SUMIF(PAYOUT!$A:$A,'MP2'!$A35,PAYOUT!$L:$L) -> 42178 | L35: =SUMIF(PAYOUT!$A:$A,'MP2'!$A35,PAYOUT!$AD:$AD) -> 0
A36: 31 | B36: 107002405379 | C36: 524087001973 | D36: M2-Modified Pag-IBIG 2 | E36: DELLAVA | F36: ROBERT | H36: DORADO | I36: MAR 2026 | J36: =SUMIF(PAYOUT!$A:$A,'MP2'!$A36,PAYOUT!$L:$L) -> 17360 | L36: =SUMIF(PAYOUT!$A:$A,'MP2'!$A36,PAYOUT!$AD:$AD) -> 500
A37: 32 | B37: 107002369811 | D37: M2-Modified Pag-IBIG 2 | E37: DELOS SANTOS | F37: JOSEFINA | H37: MENDOZA | I37: MAR 2026 | J37: =SUMIF(PAYOUT!$A:$A,'MP2'!$A37,PAYOUT!$L:$L) -> 26917 | L37: =SUMIF(PAYOUT!$A:$A,'MP2'!$A37,PAYOUT!$AD:$AD) -> 0
A38: 28 | B38: 121065979598 | D38: M2-Modified Pag-IBIG 2 | E38: DE MESA | F38: MARIA CARMINA | H38: MACABENTA | I38: MAR 2026 | J38: =SUMIF(PAYOUT!$A:$A,'MP2'!$A38,PAYOUT!$L:$L) -> 32109 | L38: =SUMIF(PAYOUT!$A:$A,'MP2'!$A38,PAYOUT!$AD:$AD) -> 0
A39: 33 | B39: 121068518978 | C39: 524005031021 | D39: M2-Modified Pag-IBIG 2 | E39: DEÑADO | F39: EMERSON | H39: RONSAIRO | I39: MAR 2026 | J39: =SUMIF(PAYOUT!$A:$A,'MP2'!$A39,PAYOUT!$L:$L) -> 43015 | L39: =SUMIF(PAYOUT!$A:$A,'MP2'!$A39,PAYOUT!$AD:$AD) -> 1000
A40: 34 | B40: 121134512335 | D40: M2-Modified Pag-IBIG 2 | E40: DREJE | F40: SHERRIE | H40: CORTEZ | I40: MAR 2026 | J40: =SUMIF(PAYOUT!$A:$A,'MP2'!$A40,PAYOUT!$L:$L) -> 54371 | L40: =SUMIF(PAYOUT!$A:$A,'MP2'!$A40,PAYOUT!$AD:$AD) -> 0
A41: 35 | B41: 101001368215 | D41: M2-Modified Pag-IBIG 2 | E41: DRUECO | F41: JANINA | H41: GUIBANI | I41: MAR 2026 | J41: =SUMIF(PAYOUT!$A:$A,'MP2'!$A41,PAYOUT!$L:$L) -> 43442 | L41: =SUMIF(PAYOUT!$A:$A,'MP2'!$A41,PAYOUT!$AD:$AD) -> 0
A42: 36 | B42: 121229976267 | D42: M2-Modified Pag-IBIG 2 | E42: ESPEÑA | F42: GOD RICK | H42: MANGA | I42: MAR 2026 | J42: =SUMIF(PAYOUT!$A:$A,'MP2'!$A42,PAYOUT!$L:$L) -> 31820 | L42: =SUMIF(PAYOUT!$A:$A,'MP2'!$A42,PAYOUT!$AD:$AD) -> 0
A43: 37 | B43: 107002369844 | D43: M2-Modified Pag-IBIG 2 | E43: ESTOESTA | F43: DOMINADOR | H43: NIDUAZA | I43: MAR 2026 | J43: =SUMIF(PAYOUT!$A:$A,'MP2'!$A43,PAYOUT!$L:$L) -> 18433 | L43: =SUMIF(PAYOUT!$A:$A,'MP2'!$A43,PAYOUT!$AD:$AD) -> 0
A44: 39 | B44: 121319049592 | C44: 525062660400 | D44: M2-Modified Pag-IBIG 2 | E44: GABAO | F44: JENNY ROSE | H44: BALOCA | I44: MAR 2026 | J44: =SUMIF(PAYOUT!$A:$A,'MP2'!$A44,PAYOUT!$L:$L) -> 31705 | L44: =SUMIF(PAYOUT!$A:$A,'MP2'!$A44,PAYOUT!$AD:$AD) -> 1000
A45: 40 | B45: 107002369889 | C45: 524087000928 | D45: M2-Modified Pag-IBIG 2 | E45: GABION | F45: CLEMENTE | H45: ABELLANIDA | I45: MAR 2026 | J45: =SUMIF(PAYOUT!$A:$A,'MP2'!$A45,PAYOUT!$L:$L) -> 25725 | L45: =SUMIF(PAYOUT!$A:$A,'MP2'!$A45,PAYOUT!$AD:$AD) -> 700
A46: 41 | B46: 121345497441 | D46: M2-Modified Pag-IBIG 2 | E46: GABUYO | F46: DYNA ROSE | H46: MORA | I46: MAR 2026 | J46: =SUMIF(PAYOUT!$A:$A,'MP2'!$A46,PAYOUT!$L:$L) -> 31705 | L46: =SUMIF(PAYOUT!$A:$A,'MP2'!$A46,PAYOUT!$AD:$AD) -> 0
A47: 42 | B47: 107002369909 | D47: M2-Modified Pag-IBIG 2 | E47: GALGO | F47: MARISA | H47: ORO | I47: MAR 2026 | J47: =SUMIF(PAYOUT!$A:$A,'MP2'!$A47,PAYOUT!$L:$L) -> 55499 | L47: =SUMIF(PAYOUT!$A:$A,'MP2'!$A47,PAYOUT!$AD:$AD) -> 0
A48: 43 | B48: 121009482096 | D48: M2-Modified Pag-IBIG 2 | E48: GALORIO | F48: JARIEN | H48: GALVEZ | I48: MAR 2026 | J48: =SUMIF(PAYOUT!$A:$A,'MP2'!$A48,PAYOUT!$L:$L) -> 42178 | L48: =SUMIF(PAYOUT!$A:$A,'MP2'!$A48,PAYOUT!$AD:$AD) -> 0
A49: 44 | B49: 107002409729 | D49: M2-Modified Pag-IBIG 2 | E49: GREGORIO | F49: RECHILDA | H49: ROCAMORA | I49: MAR 2026 | J49: =SUMIF(PAYOUT!$A:$A,'MP2'!$A49,PAYOUT!$L:$L) -> 23883 | L49: =SUMIF(PAYOUT!$A:$A,'MP2'!$A49,PAYOUT!$AD:$AD) -> 0
A50: 45 | B50: 121116943003 | D50: M2-Modified Pag-IBIG 2 | E50: HALLARES | F50: ROMMEL | H50: TODIÑO | I50: MAR 2026 | J50: =SUMIF(PAYOUT!$A:$A,'MP2'!$A50,PAYOUT!$L:$L) -> 32109 | L50: =SUMIF(PAYOUT!$A:$A,'MP2'!$A50,PAYOUT!$AD:$AD) -> 0
A51: 46 | B51: 121162265294 | C51: 522006028098 | D51: M2-Modified Pag-IBIG 2 | E51: INTERNO | F51: JUSTIN PAOLO | H51: DAYAPAN | I51: MAR 2026 | J51: =SUMIF(PAYOUT!$A:$A,'MP2'!$A51,PAYOUT!$L:$L) -> 42178 | L51: =SUMIF(PAYOUT!$A:$A,'MP2'!$A51,PAYOUT!$AD:$AD) -> 500
A52: 47 | B52: 121161252616 | D52: M2-Modified Pag-IBIG 2 | E52: JOSE | F52: LADYLYN | H52: RAMOS | I52: MAR 2026 | J52: =SUMIF(PAYOUT!$A:$A,'MP2'!$A52,PAYOUT!$L:$L) -> 38764 | L52: =SUMIF(PAYOUT!$A:$A,'MP2'!$A52,PAYOUT!$AD:$AD) -> 0
A53: 48 | B53: 121213883749 | D53: M2-Modified Pag-IBIG 2 | E53: KATIPUNAN | F53: JERUSHA KYLE ANGELA | H53: MOHAMMAD-SALI | I53: MAR 2026 | J53: =SUMIF(PAYOUT!$A:$A,'MP2'!$A53,PAYOUT!$L:$L) -> 31705 | L53: =SUMIF(PAYOUT!$A:$A,'MP2'!$A53,PAYOUT!$AD:$AD) -> 0
A54: 49 | B54: 121180923881 | D54: M2-Modified Pag-IBIG 2 | E54: LABILLES | F54: ERICKA SHANE | H54: REGASPI | I54: MAR 2026 | J54: =SUMIF(PAYOUT!$A:$A,'MP2'!$A54,PAYOUT!$L:$L) -> 42178 | L54: =SUMIF(PAYOUT!$A:$A,'MP2'!$A54,PAYOUT!$AD:$AD) -> 0
A55: 50 | B55: 121215188101 | C55: 523058011211 | D55: M2-Modified Pag-IBIG 2 | E55: LANZON | F55: MC ALTER | H55: ALEGADO | I55: MAR 2026 | J55: =SUMIF(PAYOUT!$A:$A,'MP2'!$A55,PAYOUT!$L:$L) -> 42178 | L55: =SUMIF(PAYOUT!$A:$A,'MP2'!$A55,PAYOUT!$AD:$AD) -> 1000
A56: 51 | B56: 121259085888 | C56: 520111002508 | D56: M2-Modified Pag-IBIG 2 | E56: LAO | F56: REIN | H56: CAPISNON | I56: MAR 2026 | J56: =SUMIF(PAYOUT!$A:$A,'MP2'!$A56,PAYOUT!$L:$L) -> 31820 | L56: =SUMIF(PAYOUT!$A:$A,'MP2'!$A56,PAYOUT!$AD:$AD) -> 500
A57: 79 | B57: 121159986930 | C57: 521012002187 | D57: M2-Modified Pag-IBIG 2 | E57: LARGO | F57: GILLIAN ROSE | H57: CATUCOD | I57: MAR 2026 | J57: =SUMIF(PAYOUT!$A:$A,'MP2'!$A57,PAYOUT!$L:$L) -> 59153 | L57: =SUMIF(PAYOUT!$A:$A,'MP2'!$A57,PAYOUT!$AD:$AD) -> 500
A58: 52 | B58: 121089753116 | C58: 524200206037 | D58: M2-Modified Pag-IBIG 2 | E58: LEGARDE | F58: DONALD | H58: BARQUIO | I58: MAR 2026 | J58: =SUMIF(PAYOUT!$A:$A,'MP2'!$A58,PAYOUT!$L:$L) -> 38764 | L58: =SUMIF(PAYOUT!$A:$A,'MP2'!$A58,PAYOUT!$AD:$AD) -> 2000
A59: 53 | B59: 121089754915 | D59: M2-Modified Pag-IBIG 2 | E59: LEONOR | F59: ROSE ANN | H59: PERNITES | I59: MAR 2026 | J59: =SUMIF(PAYOUT!$A:$A,'MP2'!$A59,PAYOUT!$L:$L) -> 81796 | L59: =SUMIF(PAYOUT!$A:$A,'MP2'!$A59,PAYOUT!$AD:$AD) -> 0
A60: 54 | B60: 121082598985 | C60: 519143003117 | D60: M2-Modified Pag-IBIG 2 | E60: LINAAC | F60: MARY JOY | H60: HILOT | I60: MAR 2026 | J60: =SUMIF(PAYOUT!$A:$A,'MP2'!$A60,PAYOUT!$L:$L) -> 32109 | L60: =SUMIF(PAYOUT!$A:$A,'MP2'!$A60,PAYOUT!$AD:$AD) -> 1500
A61: 55 | B61: 107002409730 | D61: M2-Modified Pag-IBIG 2 | E61: LOPEZ | F61: WILMA | H61: PAD | I61: MAR 2026 | J61: =SUMIF(PAYOUT!$A:$A,'MP2'!$A61,PAYOUT!$L:$L) -> 18433 | L61: =SUMIF(PAYOUT!$A:$A,'MP2'!$A61,PAYOUT!$AD:$AD) -> 0
A62: 56 | B62: 121035740078 | C62: 524114015959 | D62: M2-Modified Pag-IBIG 2 | E62: MAGPANTAY | F62: MARIA FAE LESLIE | H62: DICEN | I62: MAR 2026 | J62: =SUMIF(PAYOUT!$A:$A,'MP2'!$A62,PAYOUT!$L:$L) -> 43442 | L62: 1000
B63: 121035740078 | C63: 521036002474 | D63: M2-Modified Pag-IBIG 2 | E63: MAGPANTAY | F63: MARIA FAE LESLIE | H63: DICEN | I63: MAR 2026 | J63: 43442 | L63: 1000
A64: 15 | B64: 121166885139 | D64: M2-Modified Pag-IBIG 2 | E64: MAMINO | F64: CZARINA | H64: SANTOS | I64: MAR 2026 | J64: =SUMIF(PAYOUT!$A:$A,'MP2'!$A64,PAYOUT!$L:$L) -> 53818 | L64: =SUMIF(PAYOUT!$A:$A,'MP2'!$A64,PAYOUT!$AD:$AD) -> 0
A65: 57 | B65: 107002368480 | C65: 523172005672 | D65: M2-Modified Pag-IBIG 2 | E65: MAPPALA | F65: PAMELA MARIQUITA | H65: GUTIERREZ | I65: MAR 2026 | J65: =SUMIF(PAYOUT!$A:$A,'MP2'!$A65,PAYOUT!$L:$L) -> 85356 | L65: =SUMIF(PAYOUT!$A:$A,'MP2'!$A65,PAYOUT!$AD:$AD) -> 1000
A66: 58 | B66: 121281881433 | D66: M2-Modified Pag-IBIG 2 | E66: MARCOS | F66: JOSHUA ACE | H66: JAMIN | I66: MAR 2026 | J66: =SUMIF(PAYOUT!$A:$A,'MP2'!$A66,PAYOUT!$L:$L) -> 42594 | L66: =SUMIF(PAYOUT!$A:$A,'MP2'!$A66,PAYOUT!$AD:$AD) -> 0
A67: 59 | B67: 121281104678 | C67: 524093000984 | D67: M2-Modified Pag-IBIG 2 | E67: MENDOZA | F67: BRYLL CHRISTIAN | H67: SANCHEZ | I67: MAR 2026 | J67: =SUMIF(PAYOUT!$A:$A,'MP2'!$A67,PAYOUT!$L:$L) -> 31820 | L67: =SUMIF(PAYOUT!$A:$A,'MP2'!$A67,PAYOUT!$AD:$AD) -> 1000
A68: 60 | B68: 107002370012 | D68: M2-Modified Pag-IBIG 2 | E68: MENDOZA | F68: EMMANUEL | H68: IBAÑEZ | I68: MAR 2026 | J68: =SUMIF(PAYOUT!$A:$A,'MP2'!$A68,PAYOUT!$L:$L) -> 20761 | L68: =SUMIF(PAYOUT!$A:$A,'MP2'!$A68,PAYOUT!$AD:$AD) -> 0
A69: 61 | B69: 121189871263 | D69: M2-Modified Pag-IBIG 2 | E69: MERCADER | F69: LYKA | H69: BETINOL | I69: MAR 2026 | J69: =SUMIF(PAYOUT!$A:$A,'MP2'!$A69,PAYOUT!$L:$L) -> 31820 | L69: =SUMIF(PAYOUT!$A:$A,'MP2'!$A69,PAYOUT!$AD:$AD) -> 0
A70: 62 | B70: 107002407843 | C70: 524046004251 | D70: M2-Modified Pag-IBIG 2 | E70: NILO | F70: ARLENE GEMINIANA | H70: SIAPNO | I70: MAR 2026 | J70: =SUMIF(PAYOUT!$A:$A,'MP2'!$A70,PAYOUT!$L:$L) -> 57842 | L70: =SUMIF(PAYOUT!$A:$A,'MP2'!$A70,PAYOUT!$AD:$AD) -> 1500
A71: 63 | B71: 107002401527 | C71: 524124011586 | D71: M2-Modified Pag-IBIG 2 | E71: NILO | F71: DANIEL | H71: UNTALAN | I71: MAR 2026 | J71: =SUMIF(PAYOUT!$A:$A,'MP2'!$A71,PAYOUT!$L:$L) -> 22022 | L71: =SUMIF(PAYOUT!$A:$A,'MP2'!$A71,PAYOUT!$AD:$AD) -> 1000
A72: 64 | B72: 121154223086 | D72: M2-Modified Pag-IBIG 2 | E72: NUÑEZ | F72: BASIL | H72: FERNANDEZ | I72: MAR 2026 | J72: =SUMIF(PAYOUT!$A:$A,'MP2'!$A72,PAYOUT!$L:$L) -> 17898 | L72: =SUMIF(PAYOUT!$A:$A,'MP2'!$A72,PAYOUT!$AD:$AD) -> 0
A73: 38 | B73: 121120484995 | D73: M2-Modified Pag-IBIG 2 | E73: ODULIO | F73: ROLAINE RUZIELLE | H73: DAGUMAN | I73: MAR 2026 | J73: =SUMIF(PAYOUT!$A:$A,'MP2'!$A73,PAYOUT!$L:$L) -> 38764 | L73: =SUMIF(PAYOUT!$A:$A,'MP2'!$A73,PAYOUT!$AD:$AD) -> 0
A74: 65 | B74: 107002409752 | C74: 522028000590 | D74: M2-Modified Pag-IBIG 2 | E74: PANGILINAN | F74: NEMIELYNN | H74: PEÑALBA | I74: MAR 2026 | J74: =SUMIF(PAYOUT!$A:$A,'MP2'!$A74,PAYOUT!$L:$L) -> 55499 | L74: =SUMIF(PAYOUT!$A:$A,'MP2'!$A74,PAYOUT!$AD:$AD) -> 2000
A75: 66 | B75: 121283359388 | D75: M2-Modified Pag-IBIG 2 | E75: PANOL | F75: CHANDRA RACHEL | H75: CATIPON | I75: MAR 2026 | J75: =SUMIF(PAYOUT!$A:$A,'MP2'!$A75,PAYOUT!$L:$L) -> 42178 | L75: =SUMIF(PAYOUT!$A:$A,'MP2'!$A75,PAYOUT!$AD:$AD) -> 0
A76: 67 | B76: 121220013630 | D76: M2-Modified Pag-IBIG 2 | E76: PARDO | F76: KHEVIN | H76: AZULA | I76: MAR 2026 | J76: =SUMIF(PAYOUT!$A:$A,'MP2'!$A76,PAYOUT!$L:$L) -> 31705 | L76: =SUMIF(PAYOUT!$A:$A,'MP2'!$A76,PAYOUT!$AD:$AD) -> 0
A77: 68 | B77: 121156363398 | C77: 523172004695 | D77: M2-Modified Pag-IBIG 2 | E77: PAUIG | F77: YOVINA-CLAIRE | H77: AGSAWA | I77: MAR 2026 | J77: =SUMIF(PAYOUT!$A:$A,'MP2'!$A77,PAYOUT!$L:$L) -> 55499 | L77: =SUMIF(PAYOUT!$A:$A,'MP2'!$A77,PAYOUT!$AD:$AD) -> 3500
A78: 69 | B78: 101004540844 | D78: M2-Modified Pag-IBIG 2 | E78: PEREZ | F78: ALTHEA | H78: DEFIESTA | I78: MAR 2026 | J78: =SUMIF(PAYOUT!$A:$A,'MP2'!$A78,PAYOUT!$L:$L) -> 43442 | L78: =SUMIF(PAYOUT!$A:$A,'MP2'!$A78,PAYOUT!$AD:$AD) -> 0
A79: 70 | B79: 121320086270 | D79: M2-Modified Pag-IBIG 2 | E79: PEROLINO | F79: MARK CHRISTOPHER | H79: ZARATE | I79: MAR 2026 | J79: =SUMIF(PAYOUT!$A:$A,'MP2'!$A79,PAYOUT!$L:$L) -> 31705 | L79: =SUMIF(PAYOUT!$A:$A,'MP2'!$A79,PAYOUT!$AD:$AD) -> 0
A80: 71 | B80: 121156179902 | D80: M2-Modified Pag-IBIG 2 | E80: PEÑAMORA | F80: ROMERMART AUBIGNE | H80: MALDIA | I80: MAR 2026 | J80: =SUMIF(PAYOUT!$A:$A,'MP2'!$A80,PAYOUT!$L:$L) -> 53818 | L80: =SUMIF(PAYOUT!$A:$A,'MP2'!$A80,PAYOUT!$AD:$AD) -> 0
A81: 72 | B81: 121346709320 | D81: M2-Modified Pag-IBIG 2 | E81: PILARIZA | F81: ERIKA NITZ | H81: VALDEZ | I81: MAR 2026 | J81: =SUMIF(PAYOUT!$A:$A,'MP2'!$A81,PAYOUT!$L:$L) -> 31705 | L81: =SUMIF(PAYOUT!$A:$A,'MP2'!$A81,PAYOUT!$AD:$AD) -> 0
A82: 73 | B82: 107002413540 | D82: M2-Modified Pag-IBIG 2 | E82: PINTAC | F82: MARLENE | H82: QUINTANA | I82: MAR 2026 | J82: =SUMIF(PAYOUT!$A:$A,'MP2'!$A82,PAYOUT!$L:$L) -> 43442 | L82: =SUMIF(PAYOUT!$A:$A,'MP2'!$A82,PAYOUT!$AD:$AD) -> 0
A83: 26 | B83: 121107432165 | D83: M2-Modified Pag-IBIG 2 | E83: QUISEL | F83: JEJORIAN | H83: CAÑETE | I83: MAR 2026 | J83: =SUMIF(PAYOUT!$A:$A,'MP2'!$A83,PAYOUT!$L:$L) -> 43015 | L83: =SUMIF(PAYOUT!$A:$A,'MP2'!$A83,PAYOUT!$AD:$AD) -> 0
A84: 74 | B84: 121232304652 | C84: 521172004092 | D84: M2-Modified Pag-IBIG 2 | E84: RABINO | F84: MA. RUBEN ANA | H84: DELOS REYES | I84: MAR 2026 | J84: =SUMIF(PAYOUT!$A:$A,'MP2'!$A84,PAYOUT!$L:$L) -> 26917 | L84: =SUMIF(PAYOUT!$A:$A,'MP2'!$A84,PAYOUT!$AD:$AD) -> 1000
A85: 75 | B85: 107002619882 | D85: M2-Modified Pag-IBIG 2 | E85: RAGUA | F85: MARY ANNE | H85: GABRIEL | I85: MAR 2026 | J85: =SUMIF(PAYOUT!$A:$A,'MP2'!$A85,PAYOUT!$L:$L) -> 24523 | L85: =SUMIF(PAYOUT!$A:$A,'MP2'!$A85,PAYOUT!$AD:$AD) -> 0
A86: 76 | B86: 158000411210 | D86: M2-Modified Pag-IBIG 2 | E86: RECOTER | F86: REMELYN | H86: RETORICO | I86: MAR 2026 | J86: =SUMIF(PAYOUT!$A:$A,'MP2'!$A86,PAYOUT!$L:$L) -> 177545 | L86: =SUMIF(PAYOUT!$A:$A,'MP2'!$A86,PAYOUT!$AD:$AD) -> 0
A87: 77 | B87: 121099451324 | D87: M2-Modified Pag-IBIG 2 | E87: RODRIGUEZ | F87: MOO | H87: CALDERON | I87: MAR 2026 | J87: =SUMIF(PAYOUT!$A:$A,'MP2'!$A87,PAYOUT!$L:$L) -> 42178 | L87: =SUMIF(PAYOUT!$A:$A,'MP2'!$A87,PAYOUT!$AD:$AD) -> 0
A88: 78 | B88: 121165154657 | D88: M2-Modified Pag-IBIG 2 | E88: SALIBIO | F88: KARL LOUISE | H88: MALIGAYA | I88: MAR 2026 | J88: =SUMIF(PAYOUT!$A:$A,'MP2'!$A88,PAYOUT!$L:$L) -> 54933 | L88: =SUMIF(PAYOUT!$A:$A,'MP2'!$A88,PAYOUT!$AD:$AD) -> 0
A89: 80 | B89: 121174633771 | D89: M2-Modified Pag-IBIG 2 | E89: SALVANIA | F89: DIANNE MARIE | H89: UMALI | I89: MAR 2026 | J89: =SUMIF(PAYOUT!$A:$A,'MP2'!$A89,PAYOUT!$L:$L) -> 31705 | L89: =SUMIF(PAYOUT!$A:$A,'MP2'!$A89,PAYOUT!$AD:$AD) -> 0
A90: 81 | B90: 121359062699 | D90: M2-Modified Pag-IBIG 2 | E90: SANGALANG | F90: JANICE | H90: CATINDIG | I90: MAR 2026 | J90: =SUMIF(PAYOUT!$A:$A,'MP2'!$A90,PAYOUT!$L:$L) -> 31705 | L90: =SUMIF(PAYOUT!$A:$A,'MP2'!$A90,PAYOUT!$AD:$AD) -> 0
A91: 82 | B91: 121229119872 | D91: M2-Modified Pag-IBIG 2 | E91: TABOR | F91: JOMAR | H91: ORBIGO | I91: MAR 2026 | J91: =SUMIF(PAYOUT!$A:$A,'MP2'!$A91,PAYOUT!$L:$L) -> 42178 | L91: =SUMIF(PAYOUT!$A:$A,'MP2'!$A91,PAYOUT!$AD:$AD) -> 0
A92: 83 | B92: 121156302395 | D92: M2-Modified Pag-IBIG 2 | E92: TANDANG | F92: BERNARD JAMES | H92: RAMIREZ | I92: MAR 2026 | J92: =SUMIF(PAYOUT!$A:$A,'MP2'!$A92,PAYOUT!$L:$L) -> 54933 | L92: =SUMIF(PAYOUT!$A:$A,'MP2'!$A92,PAYOUT!$AD:$AD) -> 0
A93: 84 | B93: 107002322276 | D93: M2-Modified Pag-IBIG 2 | E93: TARUC | F93: JENNIFER | H93: DACULA | I93: MAR 2026 | J93: =SUMIF(PAYOUT!$A:$A,'MP2'!$A93,PAYOUT!$L:$L) -> 42594 | L93: =SUMIF(PAYOUT!$A:$A,'MP2'!$A93,PAYOUT!$AD:$AD) -> 0
A94: 85 | B94: 121244839237 | C94: 521106006041 | D94: M2-Modified Pag-IBIG 2 | E94: TOLERO | F94: JONALYN | H94: TRINIDAD | I94: MAR 2026 | J94: =SUMIF(PAYOUT!$A:$A,'MP2'!$A94,PAYOUT!$L:$L) -> 24329 | L94: =SUMIF(PAYOUT!$A:$A,'MP2'!$A94,PAYOUT!$AD:$AD) -> 1000
A95: 86 | B95: 121281538164 | D95: M2-Modified Pag-IBIG 2 | E95: TURDA | F95: HERSHEY | H95: MALTO | I95: MAR 2026 | J95: =SUMIF(PAYOUT!$A:$A,'MP2'!$A95,PAYOUT!$L:$L) -> 31705 | L95: =SUMIF(PAYOUT!$A:$A,'MP2'!$A95,PAYOUT!$AD:$AD) -> 0
A96: 87 | B96: 107002370335 | D96: M2-Modified Pag-IBIG 2 | E96: URBANO | F96: MILAGROS | H96: CARDENAS | I96: MAR 2026 | J96: =SUMIF(PAYOUT!$A:$A,'MP2'!$A96,PAYOUT!$L:$L) -> 107500 | L96: =SUMIF(PAYOUT!$A:$A,'MP2'!$A96,PAYOUT!$AD:$AD) -> 0
A97: 88 | B97: 121210992953 | D97: M2-Modified Pag-IBIG 2 | E97: VALENCIA | F97: LIAN JANELLE | H97: DELOS REYES | I97: MAR 2026 | J97: =SUMIF(PAYOUT!$A:$A,'MP2'!$A97,PAYOUT!$L:$L) -> 32109 | L97: =SUMIF(PAYOUT!$A:$A,'MP2'!$A97,PAYOUT!$AD:$AD) -> 0
A98: 89 | B98: 107002370381 | D98: M2-Modified Pag-IBIG 2 | E98: VINUYA | F98: EDITHA | H98: SANTOS | I98: MAR 2026 | J98: =SUMIF(PAYOUT!$A:$A,'MP2'!$A98,PAYOUT!$L:$L) -> 107500 | L98: =SUMIF(PAYOUT!$A:$A,'MP2'!$A98,PAYOUT!$AD:$AD) -> 0
A99: 90 | B99: 121080071170 | D99: M2-Modified Pag-IBIG 2 | E99: YAGO | F99: EMERSON | H99: SOLANO | I99: MAR 2026 | J99: =SUMIF(PAYOUT!$A:$A,'MP2'!$A99,PAYOUT!$L:$L) -> 82963 | L99: =SUMIF(PAYOUT!$A:$A,'MP2'!$A99,PAYOUT!$AD:$AD) -> 0
L100: =SUM(L9:L99) -> 33700

Sheet CODES
A2: MEMBERSHIP PROGRAM
A4: For Pag-IBIG I Savings | B4: F1-Pag-IBIG 1
A5: For MP2 Savings | B5: M2-Modified Pag-IBIG 2
A8: REMARKS
A10: Deceased | B10: D
A11: Leave Without Pay/AWOL | B11: L
A12: Newly Hired | B12: N
A13: Resigned/Separated from the Company | B13: RS
A14: Retired | B14: RT

Sheet PAYOUT
A4: ='[1]PER DIVISION'!A4 -> GENERAL PAYROLL FOR THE MONTH OF MARCH 2026
B6: NAME | O6: GSIS | AC6: HDMF (Pag-ibig) | AE6: HDMF | AG6: ATIEA | AL6: AMPCI | AN6: TENANTS | AW6: Provident
B7: SURNAME | C7: FIRST NAME | D7: MI | E7: ITEM | F7: DIVISION | G7: ITEM NUMBER | H7: DATE OF ORIGINAL APPOINTMENT | I7: DATE OF LAST PROMOTION | J7: SALARY GRADE | K7: STEP | L7: BASIC SALARY | M7: PERA | N7: TOTAL | O7: Life and Retirement (SIC) | P7: Policy Loan (Regular) | Q7: Emerg. Loan | R7: R E L (Housing) | S7: Conso. Loan | T7: Optional Premium (OULI) | U7: Policy Loan (Optional) | V7: MPL | W7: MPL LITE | X7: CPL | Y7: GFAL | Z7: Unutilized Daily Subsistence Allowance | AA7: Withholding Tax | AB7: Philhealth | AC7: MPL/STLRF | AD7: Pag-ibig II/MP2 | AE7: Personal Cont. | AF7: Mobile Phone Amort. | AG7: Monthly Dues | AH7: Loans | AI7: Undeducted Previous Transaction Fee | AJ7: Share | AK7: Healthcard | AL7: Coop Share | AM7: Coop Loans | AN7: Accommodation | AO7: Water Bill | AP7: Electric Bill | AQ7: Repairs | AR7: Security | AS7: Disallowance | AT7: Landbank Loan | AU7: UCPB Loan | AV7: DAMC Loan | AW7: Prov. Fund Share | AX7: Prov. (Healthcard) | AY7: Prov. Fund Loan | AZ7: Total Deductions | BA7: Net Take Home Pay | BB7: 15th | BC7: 30th
A8: 1 | B8: Abcede | C8: Dianne | D8: P. | E8: Agric. I | F8: PAD | G8: OSEC-DAB-AG1-116-2014 | H8: 45376 | I8: 45376 | J8: 11 | K8: 1 | L8: =IFERROR(VLOOKUP(J8, [1]DATA!$A$4:$I$36, MATCH(K8, [1]DATA!$B$3:$I$3, 0)+1, FALSE), "") -> 31705 | M8: 2000 | N8: =L8+M8 -> 33705 | O8: =ROUND(L8*9%,2) -> 2853.45 | AA8: 1468.9 | AB8: =ROUND(IF(L8>79999.99,900,IF(L8<10000.01,137.5,IF(10000<L8>80000,L8*2.5%))),2)-0.01 -> 792.62 | AD8: 1000 | AE8: 200 | AG8: 100 | AN8: 2000 | AO8: 395.48 | AZ8: =ROUND(SUM(O8:AY8),2) -> 8810.45 | BA8: =ROUND(N8-AZ8,2) -> 24894.55 | BB8: =ROUND(BA8/2,2) -> 12447.28 | BC8: =BA8-BB8 -> 12447.27
A9: =A8+1 -> 2 | B9: Aguilar | C9: Roxette Gelyn | D9: R. | E9: PLO I | F9: PPD | G9: OSEC-DAB-PLO1-12-1998 | H9: 45236 | I9: 45236 | J9: 11 | K9: 1 | L9: =IFERROR(VLOOKUP(J9, [1]DATA!$A$4:$I$36, MATCH(K9, [1]DATA!$B$3:$I$3, 0)+1, FALSE), "") -> 31705 | M9: 2000 | N9: =L9+M9 -> 33705 | O9: =ROUND(L9*9%,2) -> 2853.45 | AA9: 1468.9 | AB9: =ROUND(IF(L9>79999.99,900,IF(L9<10000.01,137.5,IF(10000<L9>80000,L9*2.5%))),2)-0.01 -> 792.62 | AE9: 200 | AF9: 0 | AG9: 100 | AN9: 2000 | AP9: 449.15 | AZ9: =ROUND(SUM(O9:AY9),2) -> 7864.12 | BA9: =ROUND(N9-AZ9,2) -> 25840.88 | BB9: =ROUND(BA9/2,2) -> 12920.44 | BC9: =BA9-BB9 -> 12920.44
A10: =A9+1 -> 3 | B10: Alberto | C10: Camilo | D10: M. | E10: DMO I | F10: CDMD | G10: OSEC-DAB-DMO1-125-2014 | H10: 35282 | I10: 42383 | J10: 11 | K10: 4 | L10: =IFERROR(VLOOKUP(J10, [1]DATA!$A$4:$I$36, MATCH(K10, [1]DATA!$B$3:$I$3, 0)+1, FALSE), "") -> 32401 | M10: 2000 | N10: =L10+M10 -> 34401 | O10: =ROUND(L10*9%,2) -> 2916.09 | S10: 3649.18 | AA10: 1587.48 | AB10: =ROUND(IF(L10>79999.99,900,IF(L10<10000.01,137.5,IF(10000<L10>80000,L10*2.5%))),2)-0.01 -> 810.02 | AC10: 6012.73 | AD10: 500 | AE10: 200 | AF10: 0 | AG10: 100 | AM10: 1000 | AS10: 0 | AW10: 0 | AY10: 5162.5 | AZ10: =ROUND(SUM(O10:AY10),2) -> 21938 | BA10: =ROUND(N10-AZ10,2) -> 12463 | BB10: =ROUND(BA10/2,2) -> 6231.5 | BC10: =BA10-BB10 -> 6231.5
A11: =A10+1 -> 4 | B11: Alcantara | C11: Justine Ann | D11: C. | E11: DMO I | F11: CDMD | G11: OSEC-DAB-DMO1-129-2014 | H11: 45665 | I11: 45665 | J11: 11 | K11: 1 | L11: =IFERROR(VLOOKUP(J11, [1]DATA!$A$4:$I$36, MATCH(K11, [1]DATA!$B$3:$I$3, 0)+1, FALSE), "") -> 31705 | M11: 2000 | N11: =L11+M11 -> 33705 | O11: =ROUND(L11*9%,2) -> 2853.45 | AA11: 1468.9 | AB11: =ROUND(IF(L11>79999.99,900,IF(L11<10000.01,137.5,IF(10000<L11>80000,L11*2.5%))),2)-0.01 -> 792.62 | AE11: 200 | AG11: 100 | AN11: 2000 | AO11: 461.39 | AP11: 704.35 | AZ11: =ROUND(SUM(O11:AY11),2) -> 8580.71 | BA11: =ROUND(N11-AZ11,2) -> 25124.29 | BB11: =ROUND(BA11/2,2) -> 12562.15 | BC11: =BA11-BB11 -> 12562.14
A12: =A11+1 -> 5 | B12: Alfonso | C12: Cindy | D12: C. | E12: PEO III | F12: PPD | G12: OSEC-DAB-PEO3-55-2014 | H12: 42278 | I12: 45737 | J12: 18 | K12: 1 | L12: =IFERROR(VLOOKUP(J12, [1]DATA!$A$4:$I$36, MATCH(K12, [1]DATA!$B$3:$I$3, 0)+1, FALSE), "") -> 53818 | M12: 2000 | N12: =L12+M12 -> 55818 | O12: =ROUND(L12*9%,2) -> 4843.62 | Y12: 9634.44 | AA12: 5936.18 | AB12: =ROUND(IF(L12>79999.99,900,IF(L12<10000.01,137.5,IF(10000<L12>80000,L12*2.5%))),2) -> 1345.45 | AE12: 200 | AF12: 0 | AG12: 100 | AS12: 500 | AW12: 0 | AZ12: =ROUND(SUM(O12:AY12),2) -> 22559.69 | BA12: =ROUND(N12-AZ12,2) -> 33258.31 | BB12: =ROUND(BA12/2,2) -> 16629.16 | BC12: =BA12-BB12 -> 16629.15
A13: =A12+1 -> 6 | B13: Alforque I | C13: G. Mark Anthony | D13: C | E13: PEO II | F13: PPD | G13: OSEC-DAB-PEO2-13-1998 | H13: 42451 | I13: 44090 | J13: 15 | K13: 2 | L13: =IFERROR(VLOOKUP(J13, [1]DATA!$A$4:$I$36, MATCH(K13, [1]DATA!$B$3:$I$3, 0)+1, FALSE), "") -> 42594 | M13: 2000 | N13: =L13+M13 -> 44594 | O13: =ROUND(L13*9%,2) -> 3833.46 | AA13: 3791.96 | AB13: =ROUND(IF(L13>79999.99,900,IF(L13<10000.01,137.5,IF(10000<L13>80000,L13*2.5%))),2) -> 1064.85 | AD13: 3000 | AE13: 1000 | AF13: 0 | AG13: 100 | AL13: 1000 | AS13: 0 | AW13: 0 | AZ13: =ROUND(SUM(O13:AY13),2) -> 13790.27 | BA13: =ROUND(N13-AZ13,2) -> 30803.73 | BB13: =ROUND(BA13/2,2) -> 15401.87 | BC13: =BA13-BB13 -> 15401.86
A14: =A13+1 -> 7 | B14: Alvarez | C14: Clarissa | D14: M. | E14: Adm. Asst. III | F14: AFU-OD | G14: OSEC-DAB-ADAS3-98-2004 | H14: 45700 | I14: 45700 | J14: 9 | K14: 1 | L14: =IFERROR(VLOOKUP(J14, [1]DATA!$A$4:$I$36, MATCH(K14, [1]DATA!$B$3:$I$3, 0)+1, FALSE), "") -> 24329 | M14: 2000 | N14: =L14+M14 -> 26329 | O14: =ROUND(L14*9%,2) -> 2189.61 | AA14: 593.27 | AB14: =ROUND(IF(L14>79999.99,900,IF(L14<10000.01,137.5,IF(10000<L14>80000,L14*2.5%))),2)-0.01 -> 608.22 | AE14: 200 | AF14: 0 | AG14: 100 | AS14: 0 | AW14: 0 | AZ14: =ROUND(SUM(O14:AY14),2) -> 3691.1 | BA14: =ROUND(N14-AZ14,2) -> 22637.9 | BB14: =ROUND(BA14/2,2) -> 11318.95 | BC14: =BA14-BB14 -> 11318.95
A15: =A14+1 -> 8 | B15: Alvarez | C15: Mark Nello | D15: B. | E15: Agric. II | F15: PAD | G15: OSEC-DAB-AG2-1317-1998 | H15: 42278 | I15: 44986 | J15: 15 | K15: 1 | L15: =IFERROR(VLOOKUP(J15, [1]DATA!$A$4:$I$36, MATCH(K15, [1]DATA!$B$3:$I$3, 0)+1, FALSE), "") -> 42178 | M15: 2000 | N15: =L15+M15 -> 44178 | O15: =ROUND(L15*9%,2) -> 3796.02 | V15: 9317.65 | AA15: 3695.42 | AB15: =ROUND(IF(L15>79999.99,900,IF(L15<10000.01,137.5,IF(10000<L15>80000,L15*2.5%))),2) -> 1054.45 | AD15: 2000 | AE15: 500 | AF15: 0 | AG15: 100 | AS15: 0 | AZ15: =ROUND(SUM(O15:AY15),2) -> 20463.54 | BA15: =ROUND(N15-AZ15,2) -> 23714.46 | BB15: =ROUND(BA15/2,2) -> 11857.23 | BC15: =BA15-BB15 -> 11857.23
A16: =A15+1 -> 9 | B16: Aninacion | C16: Joshua | D16: G. | E16: PLO II | F16: PPD | G16: OSEC-DAB-PLO2-54-2014 | H16: 43549 | I16: 44271 | J16: 15 | K16: 2 | L16: =IFERROR(VLOOKUP(J16, [1]DATA!$A$4:$I$36, MATCH(K16, [1]DATA!$B$3:$I$3, 0)+1, FALSE), "") -> 42594 | M16: 2000 | N16: =L16+M16 -> 44594 | O16: =ROUND(L16*9%,2) -> 3833.46 | AA16: 3791.96 | AB16: =ROUND(IF(L16>79999.99,900,IF(L16<10000.01,137.5,IF(10000<L16>80000,L16*2.5%))),2) -> 1064.85 | AE16: 200 | AF16: 0 | AG16: 100 | AS16: 0 | AZ16: =ROUND(SUM(O16:AY16),2) -> 8990.27 | BA16: =ROUND(N16-AZ16,2) -> 35603.73 | BB16: =ROUND(BA16/2,2) -> 17801.87 | BC16: =BA16-BB16 -> 17801.86
A17: =A16+1 -> 10 | B17: Antipas | C17: Andrea Jane | D17: M. | E17: Adm. Asst. I | F17: ISD | G17: OSEC-DAB-ADAS1-52-2004 | H17: 45376 | I17: 45376 | J17: 7 | K17: 1 | L17: =IFERROR(VLOOKUP(J17, [1]DATA!$A$4:$I$36, MATCH(K17, [1]DATA!$B$3:$I$3, 0)+1, FALSE), "") -> 20914 | M17: 2000 | N17: =L17+M17 -> 22914 | O17: =ROUND(L17*9%,2) -> 1882.26 | AA17: 0 | AB17: =ROUND(IF(L17>79999.99,900,IF(L17<10000.01,137.5,IF(10000<L17>80000,L17*2.5%))),2) -> 522.85 | AD17: 1000 | AE17: 200 | AG17: 100 | AK17: 1000 | AZ17: =ROUND(SUM(O17:AY17),2) -> 4705.11 | BA17: =ROUND(N17-AZ17,2) -> 18208.89 | BB17: =ROUND(BA17/2,2) -> 9104.45 | BC17: =BA17-BB17 -> 9104.44
A18: =A17+1 -> 11 | B18: Arceo | C18: Antonieta | D18: J. | E18: Director III | F18: OD | G18: OSEC-DAB-DIR3-55-1998 | H18: 34243 | I18: 44998 | J18: 27 | K18: 1 | L18: =IFERROR(VLOOKUP(J18, [1]DATA!$A$4:$I$36, MATCH(K18, [1]DATA!$B$3:$I$3, 0)+1, FALSE), "") -> 148940 | M18: 2000 | N18: =L18+M18 -> 150940 | O18: =ROUND(L18*9%,2) -> 13404.6 | P18: 500 | Q18: 655.56 | V18: 21327.3 | W18: 2333.33 | AA18: 33536.75 | AB18: 2500 | AD18: 0 | AE18: 200 | AF18: 3000 | AS18: 0 | AT18: 9470.26 | AW18: 0 | AY18: 7364.14 | AZ18: =ROUND(SUM(O18:AY18),2) -> 94291.94 | BA18: =ROUND(N18-AZ18,2) -> 56648.06 | BB18: =ROUND(BA18/2,2) -> 28324.03 | BC18: =BA18-BB18 -> 28324.03
A19: =A18+1 -> 12 | B19: Balangatan | C19: Jun | D19: G. | E19: OCO II | F19: ISD | G19: OSEC-DAB-OCO2-3-1998 | H19: 34078 | I19: 38628 | J19: 8 | K19: 7 | L19: =IFERROR(VLOOKUP(J19, [1]DATA!$A$4:$I$36, MATCH(K19, [1]DATA!$B$3:$I$3, 0)+1, FALSE), "") -> 23668 | M19: 2000 | N19: =L19+M19 -> 25668 | O19: =ROUND(L19*9%,2) -> 2130.12 | P19: 200 | V19: 4847.84 | AA19: 23.91 | AB19: =ROUND(IF(L19>79999.99,900,IF(L19<10000.01,137.5,IF(10000<L19>80000,L19*2.5%))),2) -> 591.7 | AC19: 4679.53 | AE19: 200 | AF19: 0 | AG19: 100 | AL19: 300 | AM19: 1000 | AS19: 0 | AW19: 0 | AY19: 4325.35 | AZ19: =ROUND(SUM(O19:AY19),2) -> 18398.45 | BA19: =ROUND(N19-AZ19,2) -> 7269.55 | BB19: =ROUND(BA19/2,2) -> 3634.78 | BC19: =BA19-BB19 -> 3634.77
A20: =A19+1 -> 13 | B20: Baluyut | C20: Julia Marie | D20: M. | E20: DMO I | F20: CDMD | G20: OSEC-DAB-DMO1-130-2014 | H20: 45376 | I20: 45376 | J20: 11 | K20: 1 | L20: =IFERROR(VLOOKUP(J20, [1]DATA!$A$4:$I$36, MATCH(K20, [1]DATA!$B$3:$I$3, 0)+1, FALSE), "") -> 31705 | M20: 2000 | N20: =L20+M20 -> 33705 | O20: =ROUND(L20*9%,2) -> 2853.45 | AA20: 1468.9 | AB20: =ROUND(IF(L20>79999.99,900,IF(L20<10000.01,137.5,IF(10000<L20>80000,L20*2.5%))),2)-0.01 -> 792.62 | AE20: 200 | AG20: 100 | AZ20: =ROUND(SUM(O20:AY20),2) -> 5414.97 | BA20: =ROUND(N20-AZ20,2) -> 28290.03 | BB20: =ROUND(BA20/2,2) -> 14145.02 | BC20: =BA20-BB20 -> 14145.01
A21: =A20+1 -> 14 | B21: Bautista | C21: Marilyn | D21: J. | E21: SG I | F21: AFU-OD | G21: OSEC-DAB-SECG1-262-1998 | H21: 34121 | I21: 34121 | J21: 3 | K21: 8 | L21: =IFERROR(VLOOKUP(J21, [1]DATA!$A$4:$I$36, MATCH(K21, [1]DATA!$B$3:$I$3, 0)+1, FALSE), "") -> 17360 | M21: 2000 | N21: =L21+M21 -> 19360 | O21: =ROUND(L21*9%,2) -> 1562.4 | Q21: 655.56 | S21: 2100.56 | T21: 0 | U21: 0 | Y21: 2837.17 | AA21: 0 | AB21: =ROUND(IF(L21>79999.99,900,IF(L21<10000.01,137.5,IF(10000<L21>80000,L21*2.5%))),2) -> 434 | AE21: 500 | AF21: 1200 | AG21: 100 | AS21: 1000 | AW21: 0 | AY21: 1820.83 | AZ21: =ROUND(SUM(O21:AY21),2) -> 12210.52 | BA21: =ROUND(N21-AZ21,2) -> 7149.48 | BB21: =ROUND(BA21/2,2) -> 3574.74 | BC21: =BA21-BB21 -> 3574.74
A22: =A21+1 -> 15 | B22: Bayot | C22: Czarina | D22: M. | E22: DMO III | F22: CDMD | G22: OSEC-DAB-DMO3-63-2014 | H22: 42451 | I22: 45397 | J22: 18 | K22: 1 | L22: =IFERROR(VLOOKUP(J22, [1]DATA!$A$4:$I$36, MATCH(K22, [1]DATA!$B$3:$I$3, 0)+1, FALSE), "") -> 53818 | M22: 2000 | N22: =L22+M22 -> 55818 | O22: =ROUND(L22*9%,2) -> 4843.62 | AA22: 6395.7 | AB22: =ROUND(IF(L22>79999.99,900,IF(L22<10000.01,137.5,IF(10000<L22>80000,L22*2.5%))),2) -> 1345.45 | AE22: 200 | AF22: 0 | AG22: 100 | AS22: 1135.55 | AX22: 891.15 | AY22: 3034.72 | AZ22: =ROUND(SUM(O22:AY22),2) -> 17946.19 | BA22: =ROUND(N22-AZ22,2) -> 37871.81 | BB22: =ROUND(BA22/2,2) -> 18935.91 | BC22: =BA22-BB22 -> 18935.9
A23: =A22+1 -> 16 | B23: Bibit | C23: Darwin | D23: C. | E23: Adm. Asst. II | F23: ISD | G23: OSEC-DAB-ADAS2-98-2004 | H23: 34073 | I23: 34073 | J23: 8 | K23: 8 | L23: =IFERROR(VLOOKUP(J23, [1]DATA!$A$4:$I$36, MATCH(K23, [1]DATA!$B$3:$I$3, 0)+1, FALSE), "") -> 23883 | M23: 2000 | N23: =L23+M23 -> 25883 | O23: =ROUND(L23*9%,2) -> 2149.47 | P23: 320 | S23: 0 | V23: 3558.84 | Y23: 5648.41 | AA23: 73.05 | AB23: =ROUND(IF(L23>79999.99,900,IF(L23<10000.01,137.5,IF(10000<L23>80000,L23*2.5%))),2)-0.01 -> 597.07 | AC23: 1195.45 | AE23: 200 | AF23: 0 | AG23: 100 | AL23: 100 | AM23: 3750 | AO23: 922.78 | AP23: 1408.7 | AS23: 0 | AW23: 0 | AZ23: =ROUND(SUM(O23:AY23),2) -> 20023.77 | BA23: =ROUND(N23-AZ23,2) -> 5859.23 | BB23: =ROUND(BA23/2,2) -> 2929.62 | BC23: =BA23-BB23 -> 2929.61
A24: =A23+1 -> 17 | B24: Bolon | C24: Richard | D24: E. | E24: Adm. Aide V | F24: AFU-OD | G24: OSEC-DAB-ADA5-17-2004 | H24: 37712 | I24: 37712 | J24: 5 | K24: 8 | L24: =IFERROR(VLOOKUP(J24, [1]DATA!$A$4:$I$36, MATCH(K24, [1]DATA!$B$3:$I$3, 0)+1, FALSE), "") -> 19565 | M24: 2000 | N24: =L24+M24 -> 21565 | O24: =ROUND(L24*9%,2) -> 1760.85 | P24: 300 | Q24: 655.56 | V24: 2698.53 | W24: 1166.67 | Y24: 3372.06 | AA24: 0 | AB24: =ROUND(IF(L24>79999.99,900,IF(L24<10000.01,137.5,IF(10000<L24>80000,L24*2.5%))),2)-0.01 -> 489.12 | AC24: 279.7 | AD24: 0 | AE24: 200 | AF24: 0 | AG24: 100 | AH24: 1336 | AS24: 500 | AW24: 0 | AY24: 2994.22 | AZ24: =ROUND(SUM(O24:AY24),2) -> 15852.71 | BA24: =ROUND(N24-AZ24,2) -> 5712.29 | BB24: =ROUND(BA24/2,2) -> 2856.15 | BC24: =BA24-BB24 -> 2856.14
A25: =A24+1 -> 18 | B25: Bombon | C25: Mary Angelyn | D25: P. | E25: DMO II | F25: CDMD | G25: OSEC-DAB-DMO2-62-2014 | H25: 44291 | I25: 45719 | J25: 15 | K25: 1 | L25: =IFERROR(VLOOKUP(J25, [1]DATA!$A$4:$I$36, MATCH(K25, [1]DATA!$B$3:$I$3, 0)+1, FALSE), "") -> 42178 | M25: 2000 | N25: =L25+M25 -> 44178 | O25: =ROUND(L25*9%,2) -> 3796.02 | AA25: 3335.99 | AB25: =ROUND(IF(L25>79999.99,900,IF(L25<10000.01,137.5,IF(10000<L25>80000,L25*2.5%))),2) -> 1054.45 | AE25: 200 | AF25: 0 | AG25: 100 | AS25: 0 | AT25: 6313.51 | AZ25: =ROUND(SUM(O25:AY25),2) -> 14799.97 | BA25: =ROUND(N25-AZ25,2) -> 29378.03 | BB25: =ROUND(BA25/2,2) -> 14689.02 | BC25: =BA25-BB25 -> 14689.01
A26: =A25+1 -> 19 | B26: Borlagdan | C26: Franco Gabriel | D26: P. | E26: ISR III | F26: ISD | G26: OSEC-DAB-INFOSR3-18-2014 | H26: 42451 | I26: 44271 | J26: 17 | K26: 2 | L26: =IFERROR(VLOOKUP(J26, [1]DATA!$A$4:$I$36, MATCH(K26, [1]DATA!$B$3:$I$3, 0)+1, FALSE), "") -> 50066 | M26: 2000 | N26: =L26+M26 -> 52066 | O26: =ROUND(L26*9%,2) -> 4505.94 | AA26: 5537.02 | AB26: =ROUND(IF(L26>79999.99,900,IF(L26<10000.01,137.5,IF(10000<L26>80000,L26*2.5%))),2) -> 1251.65 | AD26: 1000 | AE26: 200 | AF26: 0 | AG26: 100 | AS26: 0 | AW26: 0 | AZ26: =ROUND(SUM(O26:AY26),2) -> 12594.61 | BA26: =ROUND(N26-AZ26,2) -> 39471.39 | BB26: =ROUND(BA26/2,2) -> 19735.7 | BC26: =BA26-BB26 -> 19735.69
A27: =A26+1 -> 20 | B27: Borromeo | C27: Kemuel | D27: M. | E27: DMO III | F27: CDMD | G27: OSEC-DAB-DMO3-61-2014 | H27: 42383 | I27: 45027 | J27: 18 | K27: 1 | L27: =IFERROR(VLOOKUP(J27, [1]DATA!$A$4:$I$36, MATCH(K27, [1]DATA!$B$3:$I$3, 0)+1, FALSE), "") -> 53818 | M27: 2000 | N27: =L27+M27 -> 55818 | O27: =ROUND(L27*9%,2) -> 4843.62 | Q27: 655.56 | V27: 6918.77 | X27: 1966.67 | AA27: 6395.7 | AB27: =ROUND(IF(L27>79999.99,900,IF(L27<10000.01,137.5,IF(10000<L27>80000,L27*2.5%))),2) -> 1345.45 | AD27: 0 | AE27: 1500 | AF27: 0 | AG27: 100 | AL27: 500 | AS27: 707.29 | AY27: 6165.86 | AZ27: =ROUND(SUM(O27:AY27),2) -> 31098.92 | BA27: =ROUND(N27-AZ27,2) -> 24719.08 | BB27: =ROUND(BA27/2,2) -> 12359.54 | BC27: =BA27-BB27 -> 12359.54
A28: =A27+1 -> 21 | B28: Bunda | C28: Arnel | D28: R. | E28: PLO I | F28: PPD | G28: OSEC-DAB-PLO1-1-1998 | H28: 42278 | I28: 42278 | J28: 11 | K28: 4 | L28: =IFERROR(VLOOKUP(J28, [1]DATA!$A$4:$I$36, MATCH(K28, [1]DATA!$B$3:$I$3, 0)+1, FALSE), "") -> 32401 | M28: 2000 | N28: =L28+M28 -> 34401 | O28: =ROUND(L28*9%,2) -> 2916.09 | Q28: 1152.41 | V28: 4165.63 | W28: 1166.67 | AA28: 1587.48 | AB28: =ROUND(IF(L28>79999.99,900,IF(L28<10000.01,137.5,IF(10000<L28>80000,L28*2.5%))),2)-0.01 -> 810.02 | AD28: 0 | AE28: 200 | AF28: 0 | AG28: 100 | AL28: 100 | AS28: 0 | AW28: 0 | AZ28: =ROUND(SUM(O28:AY28),2) -> 12198.3 | BA28: =ROUND(N28-AZ28,2) -> 22202.7 | BB28: =ROUND(BA28/2,2) -> 11101.35 | BC28: =BA28-BB28 -> 11101.35
A29: =A28+1 -> 22 | B29: Calasagsag | C29: Joeven | D29: C. | E29: Supervising Agric. | F29: PAD | G29: OSEC-DAB-SVAG-105-1998 | H29: 42278 | I29: 45607 | J29: 22 | K29: 1 | L29: =IFERROR(VLOOKUP(J29, [1]DATA!$A$4:$I$36, MATCH(K29, [1]DATA!$B$3:$I$3, 0)+1, FALSE), "") -> 81796 | M29: 2000 | N29: =L29+M29 -> 83796 | O29: =ROUND(L29*9%,2) -> 7361.64 | AA29: 13765.43 | AB29: =L29*2.5% -> 2044.9 | AD29: 0 | AE29: 500 | AG29: 100 | AL29: 500 | AS29: 388.51 | AW29: 0 | AX29: 1201.31 | AY29: 3034.72 | AZ29: =ROUND(SUM(O29:AY29),2) -> 28896.51 | BA29: =ROUND(N29-AZ29,2) -> 54899.49 | BB29: =ROUND(BA29/2,2) -> 27449.75 | BC29: =BA29-BB29 -> 27449.74
A30: =A29+1 -> 23 | B30: Canilang | C30: Ashlee | D30: P. | E30: MPS II | F30: ISD | G30: OSEC-DAB-MPXS2-19-2014 | H30: 43481 | I30: 45027 | J30: 15 | K30: 1 | L30: =IFERROR(VLOOKUP(J30, [1]DATA!$A$4:$I$36, MATCH(K30, [1]DATA!$B$3:$I$3, 0)+1, FALSE), "") -> 42178 | M30: 2000 | N30: =L30+M30 -> 44178 | O30: =ROUND(L30*9%,2) -> 3796.02 | Q30: 1311.12 | V30: 5422.38 | W30: 1400 | X30: 1966.67 | AA30: 3695.42 | AB30: =ROUND(IF(L30>79999.99,900,IF(L30<10000.01,137.5,IF(10000<L30>80000,L30*2.5%))),2) -> 1054.45 | AC30: 984.58 | AD30: 1000 | AE30: 200 | AF30: 0 | AG30: 100 | AN30: 2000 | AO30: 527.3 | AP30: 272.21 | AS30: 0 | AW30: 0 | AY30: 3034.72 | AZ30: =ROUND(SUM(O30:AY30),2) -> 26764.87 | BA30: =ROUND(N30-AZ30,2) -> 17413.13 | BB30: =ROUND(BA30/2,2) -> 8706.57 | BC30: =BA30-BB30 -> 8706.56
A31: =A30+1 -> 24 | B31: Cosico | C31: Theresa Aurora | D31: B. | E31: DMO III | F31: CDMD | G31: OSEC-DAB-DMO3-62-2014 | H31: 37494 | I31: 42278 | J31: 18 | K31: 4 | L31: =IFERROR(VLOOKUP(J31, [1]DATA!$A$4:$I$36, MATCH(K31, [1]DATA!$B$3:$I$3, 0)+1, FALSE), "") -> 55499 | M31: 2000 | N31: =L31+M31 -> 57499 | O31: =ROUND(L31*9%,2) -> 4994.91 | P31: 300 | Q31: 1311.12 | R31: 2040.79 | T31: 263.21 | U31: 500 | V31: 8242.67 | W31: 2333.33 | X31: 1966.67 | AA31: 6798.6 | AB31: =ROUND(IF(L31>79999.99,900,IF(L31<10000.01,137.5,IF(10000<L31>80000,L31*2.5%))),2)-0.01 -> 1387.47 | AC31: 2509.62 | AE31: 200 | AG31: 100 | AL31: 100 | AM31: 1000 | AS31: 0 | AW31: 0 | AX31: 2024.84 | AY31: 5608.24 | AZ31: =ROUND(SUM(O31:AY31),2) -> 41681.47 | BA31: =ROUND(N31-AZ31,2) -> 15817.53 | BB31: =ROUND(BA31/2,2) -> 7908.77 | BC31: =BA31-BB31 -> 7908.76
A32: =A31+1 -> 25 | B32: Dacillo | C32: Edmer | D32: B. | E32: CMT II | F32: ISD | G32: OSEC-DAB-CTMT2-50-2014 | H32: 44418 | I32: 45062 | J32: 15 | K32: 1 | L32: =IFERROR(VLOOKUP(J32, [1]DATA!$A$4:$I$36, MATCH(K32, [1]DATA!$B$3:$I$3, 0)+1, FALSE), "") -> 42178 | M32: 2000 | N32: =L32+M32 -> 44178 | O32: =ROUND(L32*9%,2) -> 3796.02 | AA32: 3695.42 | AB32: =ROUND(IF(L32>79999.99,900,IF(L32<10000.01,137.5,IF(10000<L32>80000,L32*2.5%))),2) -> 1054.45 | AE32: 200 | AF32: 0 | AG32: 100 | AY32: 3034.72 | AZ32: =ROUND(SUM(O32:AY32),2) -> 11880.61 | BA32: =ROUND(N32-AZ32,2) -> 32297.39 | BB32: =ROUND(BA32/2,2) -> 16148.7 | BC32: =BA32-BB32 -> 16148.69
A33: =A32+1 -> 26 | B33: Datuin | C33: Jejorian | D33: Q. | E33: DMO II | F33: CDMD | G33: OSEC-DAB-DMO2-67-2014 | H33: 42348 | I33: 43466 | J33: 15 | K33: 3 | L33: =IFERROR(VLOOKUP(J33, [1]DATA!$A$4:$I$36, MATCH(K33, [1]DATA!$B$3:$I$3, 0)+1, FALSE), "") -> 43015 | M33: 2000 | N33: =L33+M33 -> 45015 | O33: =ROUND(L33*9%,2) -> 3871.35 | Y33: 9634.44 | AA33: 3889.58 | AB33: =ROUND(IF(L33>79999.99,900,IF(L33<10000.01,137.5,IF(10000<L33>80000,L33*2.5%))),2)-0.01 -> 1075.37 | AE33: 200 | AF33: 0 | AG33: 100 | AS33: 0 | AX33: 930.05 | AZ33: =ROUND(SUM(O33:AY33),2) -> 19700.79 | BA33: =ROUND(N33-AZ33,2) -> 25314.21 | BB33: =ROUND(BA33/2,2) -> 12657.11 | BC33: =BA33-BB33 -> 12657.1
A34: =A33+1 -> 27 | B34: de la Cruz | C34: Roy Son | D34: R. | E34: PLO III | F34: PPD | G34: OSEC-DAB-PLO3-3-1998 | H34: 42348 | I34: 46027 | J34: 18 | K34: 1 | L34: =IFERROR(VLOOKUP(J34, [1]DATA!$A$4:$I$36, MATCH(K34, [1]DATA!$B$3:$I$3, 0)+1, FALSE), "") -> 53818 | M34: 2000 | N34: =L34+M34 -> 55818 | O34: =ROUND(L34*9%,2) -> 4843.62 | V34: 1101.28 | W34: 1400 | Y34: 9634.44 | AA34: 6974.58 | AB34: =ROUND(IF(L34>79999.99,900,IF(L34<10000.01,137.5,IF(10000<L34>80000,L34*2.5%))),2) -> 1345.45 | AD34: 0 | AE34: 500 | AF34: 0 | AG34: 100 | AH34: 1336 | AS34: 910.34 | AW34: 0 | AY34: 2124.3 | AZ34: =ROUND(SUM(O34:AY34),2) -> 30270.01 | BA34: =ROUND(N34-AZ34,2) -> 25547.99 | BB34: =ROUND(BA34/2,2) -> 12774 | BC34: =BA34-BB34 -> 12773.99
A35: =A34+1 -> 28 | B35: de Mesa | C35: Maria Carmina | D35: M. | E35: Agric. I | F35: PAD | G35: OSEC-DAB-AG1-162-1998 | H35: 42998 | I35: 42998 | J35: 11 | K35: 3 | L35: =IFERROR(VLOOKUP(J35, [1]DATA!$A$4:$I$36, MATCH(K35, [1]DATA!$B$3:$I$3, 0)+1, FALSE), "") -> 32109 | M35: 2000 | N35: =L35+M35 -> 34109 | O35: =ROUND(L35*9%,2) -> 2889.81 | V35: 4126.25 | Y35: 9634.44 | AA35: 1537.23 | AB35: =ROUND(IF(L35>79999.99,900,IF(L35<10000.01,137.5,IF(10000<L35>80000,L35*2.5%))),2)-0.01 -> 802.72 | AE35: 200 | AF35: 0 | AG35: 100 | AS35: 0 | AW35: 0 | AZ35: =ROUND(SUM(O35:AY35),2) -> 19290.45 | BA35: =ROUND(N35-AZ35,2) -> 14818.55 | BB35: =ROUND(BA35/2,2) -> 7409.28 | BC35: =BA35-BB35 -> 7409.27
A36: =A35+1 -> 29 | B36: dela Cuadra | C36: Jovanee | D36: S. | E36: Agric. II | F36: PAD | G36: OSEC-DAB-AG2-1328-1998 | H36: 42278 | I36: 42278 | J36: 15 | K36: 4 | L36: =IFERROR(VLOOKUP(J36, [1]DATA!$A$4:$I$36, MATCH(K36, [1]DATA!$B$3:$I$3, 0)+1, FALSE), "") -> 43442 | M36: 2000 | N36: =L36+M36 -> 45442 | O36: =ROUND(L36*9%,2) -> 3909.78 | P36: 500 | Q36: 655.56 | V36: 5041 | X36: 1966.67 | AA36: 3998.79 | AB36: =ROUND(IF(L36>79999.99,900,IF(L36<10000.01,137.5,IF(10000<L36>80000,L36*2.5%))),2) -> 1086.05 | AC36: 667.35 | AD36: 1000 | AE36: 200 | AF36: 0 | AG36: 100 | AH36: 1336 | AS36: 1000 | AT36: 4735.13 | AW36: 0 | AY36: 3034.72 | AZ36: =ROUND(SUM(O36:AY36),2) -> 29231.05 | BA36: =ROUND(N36-AZ36,2) -> 16210.95 | BB36: =ROUND(BA36/2,2) -> 8105.48 | BC36: =BA36-BB36 -> 8105.47
A37: =A36+1 -> 30 | B37: dela Torre | C37: Julrose | D37: H. | E37: IO II | F37: ISD | G37: OSEC-DAB-INFO2-25-1998 | H37: 43468 | I37: 45670 | J37: 15 | K37: 1 | L37: =IFERROR(VLOOKUP(J37, [1]DATA!$A$4:$I$36, MATCH(K37, [1]DATA!$B$3:$I$3, 0)+1, FALSE), "") -> 42178 | M37: 2000 | N37: =L37+M37 -> 44178 | O37: =ROUND(L37*9%,2) -> 3796.02 | P37: 500 | Q37: 1311.12 | V37: 5422.38 | W37: 1400 | X37: 1966.67 | AA37: 3695.42 | AB37: =ROUND(IF(L37>79999.99,900,IF(L37<10000.01,137.5,IF(10000<L37>80000,L37*2.5%))),2) -> 1054.45 | AE37: 200 | AF37: 0 | AG37: 100 | AS37: 0 | AT37: 7180.79 | AW37: 0 | AY37: 4552.08 | AZ37: =ROUND(SUM(O37:AY37),2) -> 31178.93 | BA37: =ROUND(N37-AZ37,2) -> 12999.07 | BB37: =ROUND(BA37/2,2) -> 6499.54 | BC37: =BA37-BB37 -> 6499.53
A38: =A37+1 -> 31 | B38: Dellava | C38: Robert | D38: D. | E38: SG I | F38: AFU-OD | G38: OSEC-DAB-SECG1-258-1998 | H38: 37712 | I38: 37712 | J38: 3 | K38: 8 | L38: =IFERROR(VLOOKUP(J38, [1]DATA!$A$4:$I$36, MATCH(K38, [1]DATA!$B$3:$I$3, 0)+1, FALSE), "") -> 17360 | M38: 2000 | N38: =L38+M38 -> 19360 | O38: =ROUND(L38*9%,2) -> 1562.4 | P38: 200 | V38: 2600.69 | AA38: 0 | AB38: =ROUND(IF(L38>79999.99,900,IF(L38<10000.01,137.5,IF(10000<L38>80000,L38*2.5%))),2) -> 434 | AC38: 3737.95 | AD38: 500 | AE38: 200 | AF38: 0 | AG38: 100 | AL38: 100 | AM38: 500 | AS38: 400 | AW38: 0 | AY38: 3034.72 | AZ38: =ROUND(SUM(O38:AY38),2) -> 13369.76 | BA38: =ROUND(N38-AZ38,2) -> 5990.24 | BB38: =ROUND(BA38/2,2) -> 2995.12 | BC38: =BA38-BB38 -> 2995.12
A39: =A38+1 -> 32 | B39: delos Santos | C39: Josefina | D39: M. | E39: AO I | F39: AFU-OD | G39: OSEC-DAB-ADOF1-75-2004 | H39: 35786 | I39: 45737 | J39: 10 | K39: 1 | L39: =IFERROR(VLOOKUP(J39, [1]DATA!$A$4:$I$36, MATCH(K39, [1]DATA!$B$3:$I$3, 0)+1, FALSE), "") -> 26917 | M39: 2000 | N39: =L39+M39 -> 28917 | O39: =ROUND(L39*9%,2) -> 2422.53 | P39: 400 | Q39: 1191.88 | V39: 3986.18 | X39: 1966.67 | Y39: 2505.4 | AA39: 447.46 | AB39: =ROUND(IF(L39>79999.99,900,IF(L39<10000.01,137.5,IF(10000<L39>80000,L39*2.5%))),2)-0.01 -> 672.92 | AD39: 0 | AE39: 300 | AF39: 0 | AG39: 100 | AL39: 100 | AS39: 0 | AT39: 3156.75 | AW39: 0 | AY39: 3034.72 | AZ39: =ROUND(SUM(O39:AY39),2) -> 20284.51 | BA39: =ROUND(N39-AZ39,2) -> 8632.49 | BB39: =ROUND(BA39/2,2) -> 4316.25 | BC39: =BA39-BB39 -> 4316.24
A40: =A39+1 -> 33 | B40: Deñado | C40: Emerson | D40: R. | E40: Agric. II | F40: ISD | G40: OSEC-DAB-AG2-968-1998 | H40: 42451 | I40: 42998 | J40: 15 | K40: 3 | L40: =IFERROR(VLOOKUP(J40, [1]DATA!$A$4:$I$36, MATCH(K40, [1]DATA!$B$3:$I$3, 0)+1, FALSE), "") -> 43015 | M40: 2000 | N40: =L40+M40 -> 45015 | O40: =ROUND(L40*9%,2) -> 3871.35 | AA40: 3889.58 | AB40: =ROUND(IF(L40>79999.99,900,IF(L40<10000.01,137.5,IF(10000<L40>80000,L40*2.5%))),2)-0.01 -> 1075.37 | AD40: 1000 | AE40: 200 | AF40: 0 | AG40: 100 | AL40: 100 | AM40: 7500 | AN40: 2000 | AO40: 527.3 | AP40: 272.21 | AS40: 0 | AU40: 14749.76 | AY40: 3034.72 | AZ40: =ROUND(SUM(O40:AY40),2) -> 38320.29 | BA40: =ROUND(N40-AZ40,2) -> 6694.71 | BB40: =ROUND(BA40/2,2) -> 3347.36 | BC40: =BA40-BB40 -> 3347.35
A41: =A40+1 -> 34 | B41: Dreje | C41: Sherrie | D41: C. | E41: Sr. Agric. | F41: PAD | G41: OSEC-DAB-SRAG-162-1998 | H41: 42278 | I41: 44929 | J41: 18 | K41: 2 | L41: =IFERROR(VLOOKUP(J41, [1]DATA!$A$4:$I$36, MATCH(K41, [1]DATA!$B$3:$I$3, 0)+1, FALSE), "") -> 54371 | M41: 2000 | N41: =L41+M41 -> 56371 | O41: =ROUND(L41*9%,2) -> 4893.39 | Y41: 8646.86 | AA41: 6395.7 | AB41: =ROUND(IF(L41>79999.99,900,IF(L41<10000.01,137.5,IF(10000<L41>80000,L41*2.5%))),2) -> 1359.28 | AE41: 500 | AF41: 0 | AG41: 100 | AK41: 1000 | AN41: 2000 | AO41: 461.39 | AP41: 704.35 | AS41: 0 | AW41: 0 | AY41: 5826.67 | AZ41: =ROUND(SUM(O41:AY41),2) -> 31887.64 | BA41: =ROUND(N41-AZ41,2) -> 24483.36 | BB41: =ROUND(BA41/2,2) -> 12241.68 | BC41: =BA41-BB41 -> 12241.68
A42: =A41+1 -> 35 | B42: Drueco | C42: Janina | D42: G. | E42: DMO II | F42: CDMD | G42: OSEC-DAB-DMO2-60-2014 | H42: 42293 | I42: 42293 | J42: 15 | K42: 4 | L42: =IFERROR(VLOOKUP(J42, [1]DATA!$A$4:$I$36, MATCH(K42, [1]DATA!$B$3:$I$3, 0)+1, FALSE), "") -> 43442 | M42: 2000 | N42: =L42+M42 -> 45442 | O42: =ROUND(L42*9%,2) -> 3909.78 | AA42: 3998.79 | AB42: =ROUND(IF(L42>79999.99,900,IF(L42<10000.01,137.5,IF(10000<L42>80000,L42*2.5%))),2) -> 1086.05 | AD42: 0 | AE42: 200 | AF42: 0 | AG42: 100 | AS42: 1420.64 | AW42: 0 | AX42: 1476.39 | AZ42: =ROUND(SUM(O42:AY42),2) -> 12191.65 | BA42: =ROUND(N42-AZ42,2) -> 33250.35 | BB42: =ROUND(BA42/2,2) -> 16625.18 | BC42: =BA42-BB42 -> 16625.17
A43: =A42+1 -> 36 | B43: Espeña | C43: God Rick | D43: M. | E43: PDO I | F43: PPD | G43: OSEC-DAB-PDO1-60-2014 | H43: 44228 | I43: 44228 | J43: 11 | K43: 2 | L43: =IFERROR(VLOOKUP(J43, [1]DATA!$A$4:$I$36, MATCH(K43, [1]DATA!$B$3:$I$3, 0)+1, FALSE), "") -> 31820 | M43: 2000 | N43: =L43+M43 -> 33820 | O43: =ROUND(L43*9%,2) -> 2863.8 | AA43: 1481.83 | AB43: =ROUND(IF(L43>79999.99,900,IF(L43<10000.01,137.5,IF(10000<L43>80000,L43*2.5%))),2) -> 795.5 | AE43: 200 | AF43: 0 | AG43: 100 | AS43: 0 | AZ43: =ROUND(SUM(O43:AY43),2) -> 5441.13 | BA43: =ROUND(N43-AZ43,2) -> 28378.87 | BB43: =ROUND(BA43/2,2) -> 14189.44 | BC43: =BA43-BB43 -> 14189.43
A44: =A43+1 -> 37 | B44: Estoesta | C44: Dominador | D44: N. | E44: Adm. Aide IV | F44: AFU-OD | G44: OSEC-DAB-ADA4-412-2004 | H44: 34704 | I44: 34704 | J44: 4 | K44: 8 | L44: =IFERROR(VLOOKUP(J44, [1]DATA!$A$4:$I$36, MATCH(K44, [1]DATA!$B$3:$I$3, 0)+1, FALSE), "") -> 18433 | M44: 2000 | N44: =L44+M44 -> 20433 | O44: =ROUND(L44*9%,2) -> 1658.97 | P44: 200 | Q44: 655.56 | V44: 2561.74 | Y44: 3797.05 | AA44: 0 | AB44: =ROUND(IF(L44>79999.99,900,IF(L44<10000.01,137.5,IF(10000<L44>80000,L44*2.5%))),2)-0.01 -> 460.82 | AC44: 1295.63 | AD44: 0 | AE44: 200 | AF44: 0 | AG44: 100 | AH44: 1336 | AS44: 0 | AW44: 0 | AY44: 2124.3 | AZ44: =ROUND(SUM(O44:AY44),2) -> 14390.07 | BA44: =ROUND(N44-AZ44,2) -> 6042.93 | BB44: =ROUND(BA44/2,2) -> 3021.47 | BC44: =BA44-BB44 -> 3021.46
A45: =A44+1 -> 38 | B45: Francisco | C45: Rolaine Ruzielle | D45: O. | E45: AO III | F45: AFU-OD | G45: OSEC-DAB-ADOF3-93-2004 | H45: 42451 | I45: 45607 | J45: 14 | K45: 1 | L45: =IFERROR(VLOOKUP(J45, [1]DATA!$A$4:$I$36, MATCH(K45, [1]DATA!$B$3:$I$3, 0)+1, FALSE), "") -> 38764 | M45: 2000 | N45: =L45+M45 -> 40764 | O45: =ROUND(L45*9%,2) -> 3488.76 | Q45: 655.56 | AA45: 2899.62 | AB45: =ROUND(IF(L45>79999.99,900,IF(L45<10000.01,137.5,IF(10000<L45>80000,L45*2.5%))),2) -> 969.1 | AD45: 0 | AE45: 200 | AF45: 0 | AG45: 100 | AS45: 500 | AZ45: =ROUND(SUM(O45:AY45),2) -> 8813.04 | BA45: =ROUND(N45-AZ45,2) -> 31950.96 | BB45: =ROUND(BA45/2,2) -> 15975.48 | BC45: =BA45-BB45 -> 15975.48
A46: =A45+1 -> 39 | B46: Gabao | C46: Jenny Rose | D46: B. | E46: IO I | F46: ISD | G46: OSEC-DAB-INFO1-55-2014 | H46: 44950 | I46: 44950 | J46: 11 | K46: 1 | L46: =IFERROR(VLOOKUP(J46, [1]DATA!$A$4:$I$36, MATCH(K46, [1]DATA!$B$3:$I$3, 0)+1, FALSE), "") -> 31705 | M46: 2000 | N46: =L46+M46 -> 33705 | O46: =ROUND(L46*9%,2) -> 2853.45 | Q46: 1174.33 | V46: 1810.82 | W46: 1227.78 | AA46: 1468.9 | AB46: =ROUND(IF(L46>79999.99,900,IF(L46<10000.01,137.5,IF(10000<L46>80000,L46*2.5%))),2)-0.01 -> 792.62 | AD46: 1000 | AE46: 200 | AF46: 0 | AG46: 100 | AT46: 8523.24 | AY46: 3034.72 | AZ46: =ROUND(SUM(O46:AY46),2) -> 22185.86 | BA46: =ROUND(N46-AZ46,2) -> 11519.14 | BB46: =ROUND(BA46/2,2) -> 5759.57 | BC46: =BA46-BB46 -> 5759.57
A47: =A46+1 -> 40 | B47: Gabion | C47: Clemente | D47: A. | E47: Film Editor II | F47: ISD | G47: OSEC-DAB-FED2-1-1998 | H47: 32295 | I47: 36312 | J47: 9 | K47: 8 | L47: =IFERROR(VLOOKUP(J47, [1]DATA!$A$4:$I$36, MATCH(K47, [1]DATA!$B$3:$I$3, 0)+1, FALSE), "") -> 25725 | M47: 2000 | N47: =L47+M47 -> 27725 | O47: =ROUND(L47*9%,2) -> 2315.25 | P47: 600 | Q47: 1209.28 | V47: 3826.03 | X47: 1966.67 | Y47: 5476.25 | AA47: 418.94 | AB47: =ROUND(IF(L47>79999.99,900,IF(L47<10000.01,137.5,IF(10000<L47>80000,L47*2.5%))),2)-0.01 -> 643.12 | AC47: 3029.89 | AD47: 700 | AE47: 200 | AF47: 0 | AG47: 100 | AL47: 100 | AY47: 910.41 | AZ47: =ROUND(SUM(O47:AY47),2) -> 21495.84 | BA47: =ROUND(N47-AZ47,2) -> 6229.16 | BB47: =ROUND(BA47/2,2) -> 3114.58 | BC47: =BA47-BB47 -> 3114.58
A48: =A47+1 -> 41 | B48: Gabuyo | C48: Dyna Rose | D48: M. | E48: PLO I | F48: PPD | G48: OSEC-DAB-PLO1-16-2014 | H48: 45916 | I48: 45916 | J48: 11 | K48: 1 | L48: =IFERROR(VLOOKUP(J48, [1]DATA!$A$4:$I$36, MATCH(K48, [1]DATA!$B$3:$I$3, 0)+1, FALSE), "") -> 31705 | M48: 2000 | N48: =L48+M48 -> 33705 | O48: =ROUND(L48*9%,2) -> 2853.45 | AA48: 1360.33 | AB48: =ROUND(IF(L48>79999.99,900,IF(L48<10000.01,137.5,IF(10000<L48>80000,L48*2.5%))),2)-0.01 -> 792.62 | AE48: 200 | AF48: 0 | AG48: 100 | AJ48: 200 | AZ48: =ROUND(SUM(O48:AY48),2) -> 5506.4 | BA48: =ROUND(N48-AZ48,2) -> 28198.6 | BB48: =ROUND(BA48/2,2) -> 14099.3 | BC48: =BA48-BB48 -> 14099.3
A49: =A48+1 -> 42 | B49: Galgo | C49: Marisa | D49: O. | E49: AO V | F49: AFU-OD | G49: OSEC-DAB-ADOF5-84-2004 | H49: 34780 | I49: 42293 | J49: 18 | K49: 4 | L49: =IFERROR(VLOOKUP(J49, [1]DATA!$A$4:$I$36, MATCH(K49, [1]DATA!$B$3:$I$3, 0)+1, FALSE), "") -> 55499 | M49: 2000 | N49: =L49+M49 -> 57499 | O49: =ROUND(L49*9%,2) -> 4994.91 | P49: 200 | Q49: 1174.33 | V49: 7885.9 | W49: 2333.33 | X49: 1966.67 | AA49: 6798.6 | AB49: =ROUND(IF(L49>79999.99,900,IF(L49<10000.01,137.5,IF(10000<L49>80000,L49*2.5%))),2)-0.01 -> 1387.47 | AE49: 200 | AG49: 100 | AS49: 0 | AU49: 23789.93 | AW49: 0 | AZ49: =ROUND(SUM(O49:AY49),2) -> 50831.14 | BA49: =ROUND(N49-AZ49,2) -> 6667.86 | BB49: =ROUND(BA49/2,2) -> 3333.93 | BC49: =BA49-BB49 -> 3333.93
A50: =A49+1 -> 43 | B50: Galorio | C50: Jarien | D50: G. | E50: Librarian II | F50: ISD | G50: OSEC-DAB-LIB2-53-2014 | H50: 45695 | I50: 45695 | J50: 15 | K50: 1 | L50: =IFERROR(VLOOKUP(J50, [1]DATA!$A$4:$I$36, MATCH(K50, [1]DATA!$B$3:$I$3, 0)+1, FALSE), "") -> 42178 | M50: 2000 | N50: =L50+M50 -> 44178 | O50: =ROUND(L50*9%,2) -> 3796.02 | AA50: 3255.24 | AB50: =ROUND(IF(L50>79999.99,900,IF(L50<10000.01,137.5,IF(10000<L50>80000,L50*2.5%))),2) -> 1054.45 | AE50: 200 | AG50: 100 | AH50: 1336 | AZ50: =ROUND(SUM(O50:AY50),2) -> 9741.71 | BA50: =ROUND(N50-AZ50,2) -> 34436.29 | BB50: =ROUND(BA50/2,2) -> 17218.15 | BC50: =BA50-BB50 -> 17218.14
A51: =A50+1 -> 44 | B51: Gregorio | C51: Rechilda | D51: R. | E51: Adm. Asst. II | F51: ISD | G51: OSEC-DAB-ADAS2-111-2004 | H51: 35278 | I51: 35278 | J51: 8 | K51: 8 | L51: =IFERROR(VLOOKUP(J51, [1]DATA!$A$4:$I$36, MATCH(K51, [1]DATA!$B$3:$I$3, 0)+1, FALSE), "") -> 23883 | M51: 2000 | N51: =L51+M51 -> 25883 | O51: =ROUND(L51*9%,2) -> 2149.47 | P51: 100 | Q51: 1311.12 | V51: 4409.39 | AA51: 73.05 | AB51: =ROUND(IF(L51>79999.99,900,IF(L51<10000.01,137.5,IF(10000<L51>80000,L51*2.5%))),2)-0.01 -> 597.07 | AE51: 200 | AF51: 0 | AG51: 100 | AL51: 100 | AS51: 0 | AW51: 0 | AY51: 4703.82 | AZ51: =ROUND(SUM(O51:AY51),2) -> 13743.92 | BA51: =ROUND(N51-AZ51,2) -> 12139.08 | BB51: =ROUND(BA51/2,2) -> 6069.54 | BC51: =BA51-BB51 -> 6069.54
A52: =A51+1 -> 45 | B52: Hallares | C52: Rommel | D52: T. | E52: Agric. I | F52: ISD | G52: OSEC-DAB-AG1-115-2014 | H52: 43549 | I52: 43549 | J52: 11 | K52: 3 | L52: =IFERROR(VLOOKUP(J52, [1]DATA!$A$4:$I$36, MATCH(K52, [1]DATA!$B$3:$I$3, 0)+1, FALSE), "") -> 32109 | M52: 2000 | N52: =L52+M52 -> 34109 | O52: =ROUND(L52*9%,2) -> 2889.81 | AA52: 1353.23 | AB52: =ROUND(IF(L52>79999.99,900,IF(L52<10000.01,137.5,IF(10000<L52>80000,L52*2.5%))),2)-0.01 -> 802.72 | AE52: 200 | AF52: 0 | AG52: 100 | AS52: 0 | AZ52: =ROUND(SUM(O52:AY52),2) -> 5345.76 | BA52: =ROUND(N52-AZ52,2) -> 28763.24 | BB52: =ROUND(BA52/2,2) -> 14381.62 | BC52: =BA52-BB52 -> 14381.62
A53: =A52+1 -> 46 | B53: Interno | C53: Justin Paolo | D53: D | E53: Agric. II | F53: PAD | G53: OSEC-DAB-AG2-1077-1998 | H53: 45670 | I53: 45670 | J53: 15 | K53: 1 | L53: =IFERROR(VLOOKUP(J53, [1]DATA!$A$4:$I$36, MATCH(K53, [1]DATA!$B$3:$I$3, 0)+1, FALSE), "") -> 42178 | M53: 2000 | N53: =L53+M53 -> 44178 | O53: =ROUND(L53*9%,2) -> 3796.02 | AA53: 3263.12 | AB53: =ROUND(IF(L53>79999.99,900,IF(L53<10000.01,137.5,IF(10000<L53>80000,L53*2.5%))),2) -> 1054.45 | AD53: 500 | AE53: 200 | AG53: 100 | AH53: 1336 | AU53: 23789.93 | AZ53: =ROUND(SUM(O53:AY53),2) -> 34039.52 | BA53: =ROUND(N53-AZ53,2) -> 10138.48 | BB53: =ROUND(BA53/2,2) -> 5069.24 | BC53: =BA53-BB53 -> 5069.24
A54: =A53+1 -> 47 | B54: Jose | C54: Ladylyn | D54: R. | E54: ISR II | F54: ISD | G54: OSEC-DAB-INFOSR2-52-2014 | H54: 42348 | I54: 45384 | J54: 14 | K54: 1 | L54: =IFERROR(VLOOKUP(J54, [1]DATA!$A$4:$I$36, MATCH(K54, [1]DATA!$B$3:$I$3, 0)+1, FALSE), "") -> 38764 | M54: 2000 | N54: =L54+M54 -> 40764 | O54: =ROUND(L54*9%,2) -> 3488.76 | AA54: 2899.62 | AB54: =ROUND(IF(L54>79999.99,900,IF(L54<10000.01,137.5,IF(10000<L54>80000,L54*2.5%))),2) -> 969.1 | AD54: 0 | AE54: 200 | AF54: 0 | AG54: 100 | AS54: 0 | AW54: 0 | AZ54: =ROUND(SUM(O54:AY54),2) -> 7657.48 | BA54: =ROUND(N54-AZ54,2) -> 33106.52 | BB54: =ROUND(BA54/2,2) -> 16553.26 | BC54: =BA54-BB54 -> 16553.26
A55: =A54+1 -> 48 | B55: Katipunan | C55: Jerusha Kyle Angela | D55: M. | E55: DMO I | F55: CDMD | G55: OSEC-DAB-DMO1-126-2014 | H55: 45040 | I55: 45040 | J55: 11 | K55: 1 | L55: =IFERROR(VLOOKUP(J55, [1]DATA!$A$4:$I$36, MATCH(K55, [1]DATA!$B$3:$I$3, 0)+1, FALSE), "") -> 31705 | M55: 2000 | N55: =L55+M55 -> 33705 | O55: =ROUND(L55*9%,2) -> 2853.45 | AA55: 1468.9 | AB55: =ROUND(IF(L55>79999.99,900,IF(L55<10000.01,137.5,IF(10000<L55>80000,L55*2.5%))),2)-0.01 -> 792.62 | AE55: 200 | AF55: 0 | AG55: 100 | AZ55: =ROUND(SUM(O55:AY55),2) -> 5414.97 | BA55: =ROUND(N55-AZ55,2) -> 28290.03 | BB55: =ROUND(BA55/2,2) -> 14145.02 | BC55: =BA55-BB55 -> 14145.01
A56: =A55+1 -> 49 | B56: Labilles | C56: Ericka Shane | D56: R. | E56: PEO II | F56: PPD | G56: OSEC-DAB-PEO2-67-2014 | H56: 44228 | I56: 45607 | J56: 15 | K56: 1 | L56: =IFERROR(VLOOKUP(J56, [1]DATA!$A$4:$I$36, MATCH(K56, [1]DATA!$B$3:$I$3, 0)+1, FALSE), "") -> 42178 | M56: 2000 | N56: =L56+M56 -> 44178 | O56: =ROUND(L56*9%,2) -> 3796.02 | AA56: 3695.42 | AB56: =ROUND(IF(L56>79999.99,900,IF(L56<10000.01,137.5,IF(10000<L56>80000,L56*2.5%))),2) -> 1054.45 | AE56: 200 | AF56: 0 | AG56: 100 | AS56: 0 | AZ56: =ROUND(SUM(O56:AY56),2) -> 8845.89 | BA56: =ROUND(N56-AZ56,2) -> 35332.11 | BB56: =ROUND(BA56/2,2) -> 17666.06 | BC56: =BA56-BB56 -> 17666.05
A57: =A56+1 -> 50 | B57: Lanzon | C57: Mc Alter | D57: A. | E57: Agri II | F57: PAD | G57: OSEC-DAB-AG2-1306-1998 | H57: 44302 | I57: 44986 | J57: 15 | K57: 1 | L57: =IFERROR(VLOOKUP(J57, [1]DATA!$A$4:$I$36, MATCH(K57, [1]DATA!$B$3:$I$3, 0)+1, FALSE), "") -> 42178 | M57: 2000 | N57: =L57+M57 -> 44178 | O57: =ROUND(L57*9%,2) -> 3796.02 | AA57: 3695.42 | AB57: =ROUND(IF(L57>79999.99,900,IF(L57<10000.01,137.5,IF(10000<L57>80000,L57*2.5%))),2) -> 1054.45 | AD57: 1000 | AE57: 200 | AF57: 0 | AG57: 100 | AL57: 500 | AS57: 0 | AU57: 11894.97 | AW57: 0 | AY57: 3907.63 | AZ57: =ROUND(SUM(O57:AY57),2) -> 26148.49 | BA57: =ROUND(N57-AZ57,2) -> 18029.51 | BB57: =ROUND(BA57/2,2) -> 9014.76 | BC57: =BA57-BB57 -> 9014.75
A58: =A57+1 -> 51 | B58: Lao | C58: Rein | D58: C | E58: PEO I | F58: PPD | G58: OSEC-DAB-PEO1-58-2014 | H58: 44929 | I58: 44929 | J58: 11 | K58: 2 | L58: =IFERROR(VLOOKUP(J58, [1]DATA!$A$4:$I$36, MATCH(K58, [1]DATA!$B$3:$I$3, 0)+1, FALSE), "") -> 31820 | M58: 2000 | N58: =L58+M58 -> 33820 | O58: =ROUND(L58*9%,2) -> 2863.8 | AA58: 1468.9 | AB58: =ROUND(IF(L58>79999.99,900,IF(L58<10000.01,137.5,IF(10000<L58>80000,L58*2.5%))),2)-0.01 -> 795.49 | AD58: 500 | AE58: 200 | AF58: 0 | AG58: 100 | AS58: 0 | AZ58: =ROUND(SUM(O58:AY58),2) -> 5928.19 | BA58: =ROUND(N58-AZ58,2) -> 27891.81 | BB58: =ROUND(BA58/2,2) -> 13945.91 | BC58: =BA58-BB58 -> 13945.9
A59: =A58+1 -> 52 | B59: Legarde | C59: Donald | D59: B. | E59: AO III | F59: AFU-OD | G59: OSEC-DAB-ADOF3-95-2004 | H59: 43468 | I59: 45607 | J59: 14 | K59: 1 | L59: =IFERROR(VLOOKUP(J59, [1]DATA!$A$4:$I$36, MATCH(K59, [1]DATA!$B$3:$I$3, 0)+1, FALSE), "") -> 38764 | M59: 2000 | N59: =L59+M59 -> 40764 | O59: =ROUND(L59*9%,2) -> 3488.76 | AA59: 2899.62 | AB59: =ROUND(IF(L59>79999.99,900,IF(L59<10000.01,137.5,IF(10000<L59>80000,L59*2.5%))),2) -> 969.1 | AD59: 2000 | AE59: 200 | AF59: 0 | AG59: 100 | AS59: 0 | AW59: 0 | AY59: 5518.69 | AZ59: =ROUND(SUM(O59:AY59),2) -> 15176.17 | BA59: =ROUND(N59-AZ59,2) -> 25587.83 | BB59: =ROUND(BA59/2,2) -> 12793.92 | BC59: =BA59-BB59 -> 12793.91
A60: =A59+1 -> 53 | B60: Leonor | C60: Rose Ann | D60: P. | E60: PLO IV | F60: PPD | G60: OSEC-DAB-PLO4-3-1998 | H60: 42242 | I60: 45033 | J60: 22 | K60: 1 | L60: =IFERROR(VLOOKUP(J60, [1]DATA!$A$4:$I$36, MATCH(K60, [1]DATA!$B$3:$I$3, 0)+1, FALSE), "") -> 81796 | M60: 2000 | N60: =L60+M60 -> 83796 | O60: =ROUND(L60*9%,2) -> 7361.64 | V60: 10776.86 | Y60: 9634.44 | AA60: 13765.43 | AB60: =L60*2.5% -> 2044.9 | AE60: 500 | AG60: 100 | AS60: 444.21 | AT60: 8638.96 | AW60: 0 | AY60: 5204.88 | AZ60: =ROUND(SUM(O60:AY60),2) -> 58471.32 | BA60: =ROUND(N60-AZ60,2) -> 25324.68 | BB60: =ROUND(BA60/2,2) -> 12662.34 | BC60: =BA60-BB60 -> 12662.34
A61: =A60+1 -> 54 | B61: Linaac | C61: Mary Joy | D61: H. | E61: Agric. I | F61: PAD | G61: OSEC-DAB-AG1-120-2014 | H61: 43468 | I61: 43468 | J61: 11 | K61: 3 | L61: =IFERROR(VLOOKUP(J61, [1]DATA!$A$4:$I$36, MATCH(K61, [1]DATA!$B$3:$I$3, 0)+1, FALSE), "") -> 32109 | M61: 2000 | N61: =L61+M61 -> 34109 | O61: =ROUND(L61*9%,2) -> 2889.81 | AA61: 1537.23 | AB61: =ROUND(IF(L61>79999.99,900,IF(L61<10000.01,137.5,IF(10000<L61>80000,L61*2.5%))),2)-0.01 -> 802.72 | AD61: 1500 | AE61: 200 | AF61: 0 | AG61: 100 | AL61: 300 | AN61: 2000 | AO61: 527.3 | AP61: 496.79 | AS61: 0 | AY61: 5656.36 | AZ61: =ROUND(SUM(O61:AY61),2) -> 16010.21 | BA61: =ROUND(N61-AZ61,2) -> 18098.79 | BB61: =ROUND(BA61/2,2) -> 9049.4 | BC61: =BA61-BB61 -> 9049.39
A62: =A61+1 -> 55 | B62: Lopez | C62: Wilma | D62: P. | E62: Adm. Aide IV | F62: AFU-OD | G62: OSEC-DAB-ADA4-407-2004 | H62: 38243 | I62: 38243 | J62: 4 | K62: 8 | L62: =IFERROR(VLOOKUP(J62, [1]DATA!$A$4:$I$36, MATCH(K62, [1]DATA!$B$3:$I$3, 0)+1, FALSE), "") -> 18433 | M62: 2000 | N62: =L62+M62 -> 20433 | O62: =ROUND(L62*9%,2) -> 1658.97 | P62: 448 | Q62: 655.56 | V62: 2938.61 | Y62: 3853.78 | AA62: 0 | AB62: =ROUND(IF(L62>79999.99,900,IF(L62<10000.01,137.5,IF(10000<L62>80000,L62*2.5%))),2)-0.01 -> 460.82 | AE62: 600 | AF62: 0 | AG62: 100 | AS62: 0 | AW62: 200 | AY62: 1000 | AZ62: =ROUND(SUM(O62:AY62),2) -> 11915.74 | BA62: =ROUND(N62-AZ62,2) -> 8517.26 | BB62: =ROUND(BA62/2,2) -> 4258.63 | BC62: =BA62-BB62 -> 4258.63
A63: =A62+1 -> 56 | B63: Magpantay | C63: Maria Fae Leslie | D63: D. | E63: DMO II | F63: CDMD | G63: OSEC-DAB-DMO2-65-2014 | H63: 42348 | I63: 42348 | J63: 15 | K63: 4 | L63: =IFERROR(VLOOKUP(J63, [1]DATA!$A$4:$I$36, MATCH(K63, [1]DATA!$B$3:$I$3, 0)+1, FALSE), "") -> 43442 | M63: 2000 | N63: =L63+M63 -> 45442 | O63: =ROUND(L63*9%,2) -> 3909.78 | AA63: 3998.79 | AB63: =ROUND(IF(L63>79999.99,900,IF(L63<10000.01,137.5,IF(10000<L63>80000,L63*2.5%))),2) -> 1086.05 | AD63: 2000 | AE63: 500 | AF63: 0 | AG63: 100 | AS63: 1390.43 | AW63: 0 | AY63: 8347.22 | AZ63: =ROUND(SUM(O63:AY63),2) -> 21332.27 | BA63: =ROUND(N63-AZ63,2) -> 24109.73 | BB63: =ROUND(BA63/2,2) -> 12054.87 | BC63: =BA63-BB63 -> 12054.86
A64: =A63+1 -> 57 | B64: Mappala | C64: Pamela Mariquita | D64: G. | E64: Info. Officer IV | F64: ISD | G64: OSEC-DAB-INFO4-2-1998 | H64: 35800 | I64: 42201 | J64: 22 | K64: 4 | L64: =IFERROR(VLOOKUP(J64, [1]DATA!$A$4:$I$36, MATCH(K64, [1]DATA!$B$3:$I$3, 0)+1, FALSE), "") -> 85356 | M64: 2000 | N64: =L64+M64 -> 87356 | O64: =ROUND(L64*9%,2) -> 7682.04 | V64: 17250.45 | AA64: 14797.18 | AB64: =L64*2.5% -> 2133.9 | AD64: 1000 | AE64: 600 | AF64: 200 | AG64: 100 | AL64: 100 | AS64: 1000 | AW64: 0 | AZ64: =ROUND(SUM(O64:AY64),2) -> 44863.57 | BA64: =ROUND(N64-AZ64,2) -> 42492.43 | BB64: =ROUND(BA64/2,2) -> 21246.22 | BC64: =BA64-BB64 -> 21246.21
A65: =A64+1 -> 58 | B65: Marcos | C65: Joshua Ace | D65: J. | E65: DMO II | F65: PAD | G65: OSEC-DAB-DMO2-58-2014 | H65: 44516 | I65: 44516 | J65: 15 | K65: 2 | L65: =IFERROR(VLOOKUP(J65, [1]DATA!$A$4:$I$36, MATCH(K65, [1]DATA!$B$3:$I$3, 0)+1, FALSE), "") -> 42594 | M65: 2000 | N65: =L65+M65 -> 44594 | O65: =ROUND(L65*9%,2) -> 3833.46 | AA65: 3791.96 | AB65: =ROUND(IF(L65>79999.99,900,IF(L65<10000.01,137.5,IF(10000<L65>80000,L65*2.5%))),2) -> 1064.85 | AE65: 200 | AF65: 0 | AG65: 100 | AN65: 2000 | AO65: 922.78 | AP65: 1408.7 | AS65: 0 | AZ65: =ROUND(SUM(O65:AY65),2) -> 13321.75 | BA65: =ROUND(N65-AZ65,2) -> 31272.25 | BB65: =ROUND(BA65/2,2) -> 15636.13 | BC65: =BA65-BB65 -> 15636.12
A66: =A65+1 -> 59 | B66: Mendoza | C66: Bryll Christian | D66: S. | E66: DMO I | F66: CDMD | G66: OSEC-DAB-DMO1-124-2014 | H66: 44291 | I66: 44291 | J66: 11 | K66: 2 | L66: =IFERROR(VLOOKUP(J66, [1]DATA!$A$4:$I$36, MATCH(K66, [1]DATA!$B$3:$I$3, 0)+1, FALSE), "") -> 31820 | M66: 2000 | N66: =L66+M66 -> 33820 | O66: =ROUND(L66*9%,2) -> 2863.8 | Q66: 655.56 | V66: 3993.44 | X66: 1966.67 | AA66: 1481.83 | AB66: =ROUND(IF(L66>79999.99,900,IF(L66<10000.01,137.5,IF(10000<L66>80000,L66*2.5%))),2) -> 795.5 | AD66: 1000 | AE66: 200 | AF66: 0 | AG66: 100 | AS66: 0 | AW66: 0 | AY66: 5248.26 | AZ66: =ROUND(SUM(O66:AY66),2) -> 18305.06 | BA66: =ROUND(N66-AZ66,2) -> 15514.94 | BB66: =ROUND(BA66/2,2) -> 7757.47 | BC66: =BA66-BB66 -> 7757.47
A67: =A66+1 -> 60 | B67: Mendoza | C67: Emmanuel | D67: I. | E67: Adm. Aide VI | F67: AFU-OD | G67: OSEC-DAB-ADA6-184-2004 | H67: 32470 | I67: 32470 | J67: 6 | K67: 8 | L67: =IFERROR(VLOOKUP(J67, [1]DATA!$A$4:$I$36, MATCH(K67, [1]DATA!$B$3:$I$3, 0)+1, FALSE), "") -> 20761 | M67: 2000 | N67: =L67+M67 -> 22761 | O67: =ROUND(L67*9%,2) -> 1868.49 | V67: 3110.15 | W67: 1400 | Y67: 5780.67 | AA67: 0 | AB67: =ROUND(IF(L67>79999.99,900,IF(L67<10000.01,137.5,IF(10000<L67>80000,L67*2.5%))),2)-0.01 -> 519.02 | AE67: 200 | AF67: 0 | AG67: 100 | AS67: 0 | AT67: 3314.59 | AW67: 0 | AZ67: =ROUND(SUM(O67:AY67),2) -> 16292.92 | BA67: =ROUND(N67-AZ67,2) -> 6468.08 | BB67: =ROUND(BA67/2,2) -> 3234.04 | BC67: =BA67-BB67 -> 3234.04
A68: =A67+1 -> 61 | B68: Mercader | C68: Lyka | D68: B. | E68: PEO I | F68: PPD | G68: OSEC-DAB-PEO1-57-2014 | H68: 44243 | I68: 44243 | J68: 11 | K68: 2 | L68: =IFERROR(VLOOKUP(J68, [1]DATA!$A$4:$I$36, MATCH(K68, [1]DATA!$B$3:$I$3, 0)+1, FALSE), "") -> 31820 | M68: 2000 | N68: =L68+M68 -> 33820 | O68: =ROUND(L68*9%,2) -> 2863.8 | AA68: 1481.83 | AB68: =ROUND(IF(L68>79999.99,900,IF(L68<10000.01,137.5,IF(10000<L68>80000,L68*2.5%))),2) -> 795.5 | AE68: 200 | AF68: 0 | AG68: 100 | AH68: 1336 | AS68: 0 | AW68: 1125 | AZ68: =ROUND(SUM(O68:AY68),2) -> 7902.13 | BA68: =ROUND(N68-AZ68,2) -> 25917.87 | BB68: =ROUND(BA68/2,2) -> 12958.94 | BC68: =BA68-BB68 -> 12958.93
A69: =A68+1 -> 62 | B69: Nilo | C69: Arlene Geminiana | D69: S. | E69: AO V | F69: AFU-OD | G69: OSEC-DAB-ADOF5-85-2004 | H69: 31793 | I69: 33550 | J69: 18 | K69: 8 | L69: =IFERROR(VLOOKUP(J69, [1]DATA!$A$4:$I$36, MATCH(K69, [1]DATA!$B$3:$I$3, 0)+1, FALSE), "") -> 57842 | M69: 2000 | N69: =L69+M69 -> 59842 | O69: =ROUND(L69*9%,2) -> 5205.78 | V69: 8590.56 | AA69: 7329.2 | AB69: =ROUND(IF(L69>79999.99,900,IF(L69<10000.01,137.5,IF(10000<L69>80000,L69*2.5%))),2) -> 1446.05 | AC69: 10339.7 | AD69: 1500 | AE69: 1000 | AG69: 100 | AS69: 1000 | AW69: 0 | AZ69: =ROUND(SUM(O69:AY69),2) -> 36511.29 | BA69: =ROUND(N69-AZ69,2) -> 23330.71 | BB69: =ROUND(BA69/2,2) -> 11665.36 | BC69: =BA69-BB69 -> 11665.35
A70: =A69+1 -> 63 | B70: Nilo | C70: Daniel | D70: U. | E70: Adm. Asst. I | F70: ISD | G70: OSEC-DAB-ADAS1-54-2004 | H70: 35467 | I70: 37657 | J70: 7 | K70: 8 | L70: =IFERROR(VLOOKUP(J70, [1]DATA!$A$4:$I$36, MATCH(K70, [1]DATA!$B$3:$I$3, 0)+1, FALSE), "") -> 22022 | M70: 2000 | N70: =L70+M70 -> 24022 | O70: =ROUND(L70*9%,2) -> 1981.98 | AA70: 0 | AB70: =ROUND(IF(L70>79999.99,900,IF(L70<10000.01,137.5,IF(10000<L70>80000,L70*2.5%))),2) -> 550.55 | AD70: 1000 | AE70: 200 | AF70: 0 | AG70: 100 | AS70: 0 | AW70: 0 | AZ70: =ROUND(SUM(O70:AY70),2) -> 3832.53 | BA70: =ROUND(N70-AZ70,2) -> 20189.47 | BB70: =ROUND(BA70/2,2) -> 10094.74 | BC70: =BA70-BB70 -> 10094.73
A71: =A70+1 -> 64 | B71: Nuñez | C71: Basil | D71: F. | E71: Adm. Aide IV | F71: AFU-OD | G71: OSEC-DAB-ADA4-411-2004 | H71: 42242 | I71: 42242 | J71: 4 | K71: 4 | L71: =IFERROR(VLOOKUP(J71, [1]DATA!$A$4:$I$36, MATCH(K71, [1]DATA!$B$3:$I$3, 0)+1, FALSE), "") -> 17898 | M71: 2000 | N71: =L71+M71 -> 19898 | O71: =ROUND(L71*9%,2) -> 1610.82 | Q71: 655.56 | AA71: 0 | AB71: =ROUND(IF(L71>79999.99,900,IF(L71<10000.01,137.5,IF(10000<L71>80000,L71*2.5%))),2) -> 447.45 | AE71: 700 | AF71: 0 | AG71: 100 | AL71: 200 | AM71: 1000 | AS71: 0 | AW71: 200 | AY71: 4000 | AZ71: =ROUND(SUM(O71:AY71),2) -> 8913.83 | BA71: =ROUND(N71-AZ71,2) -> 10984.17 | BB71: =ROUND(BA71/2,2) -> 5492.09 | BC71: =BA71-BB71 -> 5492.08
A72: =A71+1 -> 65 | B72: Pangilinan | C72: Nemielynn | D72: P. | E72: Sr. Agric. | F72: PAD | G72: OSEC-DAB-SRAG-14-1998 | H72: 35571 | I72: 42242 | J72: 18 | K72: 4 | L72: =IFERROR(VLOOKUP(J72, [1]DATA!$A$4:$I$36, MATCH(K72, [1]DATA!$B$3:$I$3, 0)+1, FALSE), "") -> 55499 | M72: 2000 | N72: =L72+M72 -> 57499 | O72: =ROUND(L72*9%,2) -> 4994.91 | Q72: 1246.88 | S72: 5802.48 | AA72: 6798.6 | AB72: =ROUND(IF(L72>79999.99,900,IF(L72<10000.01,137.5,IF(10000<L72>80000,L72*2.5%))),2)-0.01 -> 1387.47 | AC72: 2205.2 | AD72: 2000 | AE72: 500 | AG72: 100 | AN72: 2000 | AO72: 461.39 | AP72: 704.35 | AS72: 1000 | AW72: 0 | AY72: 3034.72 | AZ72: =ROUND(SUM(O72:AY72),2) -> 32236 | BA72: =ROUND(N72-AZ72,2) -> 25263 | BB72: =ROUND(BA72/2,2) -> 12631.5 | BC72: =BA72-BB72 -> 12631.5
A73: =A72+1 -> 66 | B73: Panol | C73: Chandra Rachel | D73: C. | E73: PLO II | F73: PPD | G73: OSEC-DAB-PLO2-53-2014 | H73: 44348 | I73: 45376 | J73: 15 | K73: 1 | L73: =IFERROR(VLOOKUP(J73, [1]DATA!$A$4:$I$36, MATCH(K73, [1]DATA!$B$3:$I$3, 0)+1, FALSE), "") -> 42178 | M73: 2000 | N73: =L73+M73 -> 44178 | O73: =ROUND(L73*9%,2) -> 3796.02 | AA73: 3695.42 | AB73: =ROUND(IF(L73>79999.99,900,IF(L73<10000.01,137.5,IF(10000<L73>80000,L73*2.5%))),2) -> 1054.45 | AE73: 200 | AF73: 0 | AG73: 100 | AS73: 0 | AZ73: =ROUND(SUM(O73:AY73),2) -> 8845.89 | BA73: =ROUND(N73-AZ73,2) -> 35332.11 | BB73: =ROUND(BA73/2,2) -> 17666.06 | BC73: =BA73-BB73 -> 17666.05
A74: =A73+1 -> 67 | B74: Pardo | C74: Khevin | D74: A. | E74: AO II | F74: AFU-OD | G74: OSEC-DAB-ADOF2-54-2014 | H74: 45737 | I74: 45737 | J74: 11 | K74: 1 | L74: =IFERROR(VLOOKUP(J74, [1]DATA!$A$4:$I$36, MATCH(K74, [1]DATA!$B$3:$I$3, 0)+1, FALSE), "") -> 31705 | M74: 2000 | N74: =L74+M74 -> 33705 | O74: =ROUND(L74*9%,2) -> 2853.45 | AA74: 1192.23 | AB74: =ROUND(IF(L74>79999.99,900,IF(L74<10000.01,137.5,IF(10000<L74>80000,L74*2.5%))),2)-0.01 -> 792.62 | AE74: 200 | AG74: 100 | AZ74: =ROUND(SUM(O74:AY74),2) -> 5138.3 | BA74: =ROUND(N74-AZ74,2) -> 28566.7 | BB74: =ROUND(BA74/2,2) -> 14283.35 | BC74: =BA74-BB74 -> 14283.35
A75: =A74+1 -> 68 | B75: Pauig | C75: Yovina Claire | D75: A. | E75: Info. Officer III | F75: ISD | G75: OSEC-DAB-INFO3-10-1998 | H75: 42278 | I75: 42278 | J75: 18 | K75: 4 | L75: =IFERROR(VLOOKUP(J75, [1]DATA!$A$4:$I$36, MATCH(K75, [1]DATA!$B$3:$I$3, 0)+1, FALSE), "") -> 55499 | M75: 2000 | N75: =L75+M75 -> 57499 | O75: =ROUND(L75*9%,2) -> 4994.91 | V75: 5235.18 | AA75: 6797.16 | AB75: =ROUND(IF(L75>79999.99,900,IF(L75<10000.01,137.5,IF(10000<L75>80000,L75*2.5%))),2)-0.01 -> 1387.47 | AD75: 3500 | AE75: 1000 | AF75: 1400 | AG75: 100 | AL75: 500 | AM75: 3750 | AS75: 497.95 | AW75: 0 | AZ75: =ROUND(SUM(O75:AY75),2) -> 29162.67 | BA75: =ROUND(N75-AZ75,2) -> 28336.33 | BB75: =ROUND(BA75/2,2) -> 14168.17 | BC75: =BA75-BB75 -> 14168.16
A76: =A75+1 -> 69 | B76: Perez | C76: Althea | D76: D. | E76: DMO II | F76: PAD | G76: OSEC-DAB-DMO2-57-2014 | H76: 42278 | I76: 42278 | J76: 15 | K76: 4 | L76: =IFERROR(VLOOKUP(J76, [1]DATA!$A$4:$I$36, MATCH(K76, [1]DATA!$B$3:$I$3, 0)+1, FALSE), "") -> 43442 | M76: 2000 | N76: =L76+M76 -> 45442 | O76: =ROUND(L76*9%,2) -> 3909.78 | P76: 500 | Q76: 1311.12 | V76: 4608.54 | W76: 933.33 | X76: 1966.67 | Y76: 9634.44 | AA76: 3998.79 | AB76: =ROUND(IF(L76>79999.99,900,IF(L76<10000.01,137.5,IF(10000<L76>80000,L76*2.5%))),2) -> 1086.05 | AC76: 1976.23 | AD76: 0 | AE76: 300 | AF76: 0 | AG76: 100 | AS76: 0 | AT76: 6360.12 | AW76: 0 | AY76: 3000 | AZ76: =ROUND(SUM(O76:AY76),2) -> 39685.07 | BA76: =ROUND(N76-AZ76,2) -> 5756.93 | BB76: =ROUND(BA76/2,2) -> 2878.47 | BC76: =BA76-BB76 -> 2878.46
A77: =A76+1 -> 70 | B77: Perolino | C77: Mark Christopher | D77: Z. | E77: IO I | F77: ISD | G77: OSEC-DAB-INFO1-56-2014 | H77: 45062 | I77: 45062 | J77: 11 | K77: 1 | L77: =IFERROR(VLOOKUP(J77, [1]DATA!$A$4:$I$36, MATCH(K77, [1]DATA!$B$3:$I$3, 0)+1, FALSE), "") -> 31705 | M77: 2000 | N77: =L77+M77 -> 33705 | O77: =ROUND(L77*9%,2) -> 2853.45 | AA77: 1468.9 | AB77: =ROUND(IF(L77>79999.99,900,IF(L77<10000.01,137.5,IF(10000<L77>80000,L77*2.5%))),2)-0.01 -> 792.62 | AE77: 200 | AG77: 100 | AZ77: =ROUND(SUM(O77:AY77),2) -> 5414.97 | BA77: =ROUND(N77-AZ77,2) -> 28290.03 | BB77: =ROUND(BA77/2,2) -> 14145.02 | BC77: =BA77-BB77 -> 14145.01
A78: =A77+1 -> 71 | B78: Peñamora | C78: Romermart Aubigne | D78: AM. | E78: DMO III | F78: PAD | G78: OSEC-DAB-DMO3-60-2014 | H78: 43739 | I78: 45607 | J78: 18 | K78: 1 | L78: =IFERROR(VLOOKUP(J78, [1]DATA!$A$4:$I$36, MATCH(K78, [1]DATA!$B$3:$I$3, 0)+1, FALSE), "") -> 53818 | M78: 2000 | N78: =L78+M78 -> 55818 | O78: =ROUND(L78*9%,2) -> 4843.62 | AA78: 6395.7 | AB78: =ROUND(IF(L78>79999.99,900,IF(L78<10000.01,137.5,IF(10000<L78>80000,L78*2.5%))),2) -> 1345.45 | AE78: 500 | AF78: 0 | AG78: 100 | AS78: 555.3 | AW78: 0 | AZ78: =ROUND(SUM(O78:AY78),2) -> 13740.07 | BA78: =ROUND(N78-AZ78,2) -> 42077.93 | BB78: =ROUND(BA78/2,2) -> 21038.97 | BC78: =BA78-BB78 -> 21038.96
A79: =A78+1 -> 72 | B79: Pilariza | C79: Erika Nitz | D79: V. | E79: AO II | F79: AFU-OD | G79: OSEC-DAB-ADOF2-53-2004 | H79: 45931 | I79: 45931 | J79: 11 | K79: 1 | L79: =IFERROR(VLOOKUP(J79, [1]DATA!$A$4:$I$36, MATCH(K79, [1]DATA!$B$3:$I$3, 0)+1, FALSE), "") -> 31705 | M79: 2000 | N79: =L79+M79 -> 33705 | O79: =ROUND(L79*9%,2) -> 2853.45 | AA79: 1388.35 | AB79: =ROUND(IF(L79>79999.99,900,IF(L79<10000.01,137.5,IF(10000<L79>80000,L79*2.5%))),2)-0.01 -> 792.62 | AE79: 200 | AG79: 100 | AJ79: 200 | AZ79: =ROUND(SUM(O79:AY79),2) -> 5534.42 | BA79: =ROUND(N79-AZ79,2) -> 28170.58 | BB79: =ROUND(BA79/2,2) -> 14085.29 | BC79: =BA79-BB79 -> 14085.29
A80: =A79+1 -> 73 | B80: Pintac | C80: Marlene | D80: Q. | E80: AO IV | F80: AFU-OD | G80: OSEC-DAB-ADOF4-99-2004 | H80: 32752 | I80: 42348 | J80: 15 | K80: 4 | L80: =IFERROR(VLOOKUP(J80, [1]DATA!$A$4:$I$36, MATCH(K80, [1]DATA!$B$3:$I$3, 0)+1, FALSE), "") -> 43442 | M80: 2000 | N80: =L80+M80 -> 45442 | O80: =ROUND(L80*9%,2) -> 3909.78 | P80: 500 | Q80: 655.56 | S80: 5920.72 | X80: 1966.67 | AA80: 3997.66 | AB80: =ROUND(IF(L80>79999.99,900,IF(L80<10000.01,137.5,IF(10000<L80>80000,L80*2.5%))),2) -> 1086.05 | AC80: 6485.61 | AE80: 600 | AG80: 100 | AL80: 100 | AN80: 3000 | AS80: 0 | AW80: 0 | AY80: 6767.43 | AZ80: =ROUND(SUM(O80:AY80),2) -> 35089.48 | BA80: =ROUND(N80-AZ80,2) -> 10352.52 | BB80: =ROUND(BA80/2,2) -> 5176.26 | BC80: =BA80-BB80 -> 5176.26
A81: =A80+1 -> 74 | B81: Rabino | C81: Ma. Ruben Ana | D81: D. | E81: AO I | F81: AFU-OD | G81: OSEC-DAB-ADOF1-74-2004 | H81: 45040 | I81: 45040 | J81: 10 | K81: 1 | L81: =IFERROR(VLOOKUP(J81, [1]DATA!$A$4:$I$36, MATCH(K81, [1]DATA!$B$3:$I$3, 0)+1, FALSE), "") -> 26917 | M81: 2000 | N81: =L81+M81 -> 28917 | O81: =ROUND(L81*9%,2) -> 2422.53 | AA81: 630.72 | AB81: =ROUND(IF(L81>79999.99,900,IF(L81<10000.01,137.5,IF(10000<L81>80000,L81*2.5%))),2)-0.01 -> 672.92 | AD81: 1000 | AE81: 200 | AF81: 0 | AG81: 100 | AN81: 2000 | AO81: 461.39 | AP81: 704.35 | AZ81: =ROUND(SUM(O81:AY81),2) -> 8191.91 | BA81: =ROUND(N81-AZ81,2) -> 20725.09 | BB81: =ROUND(BA81/2,2) -> 10362.55 | BC81: =BA81-BB81 -> 10362.54
A82: =A81+1 -> 75 | B82: Ragua | C82: Mary Anne | D82: G. | E82: Adm. Asst. III | F82: AFU-OD | G82: OSEC-DAB-ADAS3-97-2004 | H82: 44271 | I82: 44271 | J82: 9 | K82: 2 | L82: =IFERROR(VLOOKUP(J82, [1]DATA!$A$4:$I$36, MATCH(K82, [1]DATA!$B$3:$I$3, 0)+1, FALSE), "") -> 24523 | M82: 2000 | N82: =L82+M82 -> 26523 | O82: =ROUND(L82*9%,2) -> 2207.07 | AA82: 208.1 | AB82: =ROUND(IF(L82>79999.99,900,IF(L82<10000.01,137.5,IF(10000<L82>80000,L82*2.5%))),2)-0.01 -> 613.07 | AE82: 200 | AF82: 0 | AG82: 100 | AS82: 0 | AZ82: =ROUND(SUM(O82:AY82),2) -> 3328.24 | BA82: =ROUND(N82-AZ82,2) -> 23194.76 | BB82: =ROUND(BA82/2,2) -> 11597.38 | BC82: =BA82-BB82 -> 11597.38
A83: =A82+1 -> 76 | B83: Recoter | C83: Remelyn | D83: R. | E83: Director IV | F83: OD | G83: OSEC-DAB-DIR4-1-1998 | H83: 32843 | I83: 44990 | J83: 28 | K83: 5 | L83: =IFERROR(VLOOKUP(J83, [1]DATA!$A$4:$I$36, MATCH(K83, [1]DATA!$B$3:$I$3, 0)+1, FALSE), "") -> 177545 | M83: 2000 | N83: =L83+M83 -> 179545 | O83: =ROUND(L83*9%,2) -> 15979.05 | T83: 252 | AA83: 43056.83 | AB83: 2500 | AE83: 200 | AG83: 0 | AS83: 0 | AZ83: =ROUND(SUM(O83:AY83),2) -> 61987.88 | BA83: =ROUND(N83-AZ83,2) -> 117557.12 | BB83: =ROUND(BA83/2,2) -> 58778.56 | BC83: =BA83-BB83 -> 58778.56
A84: =A83+1 -> 77 | B84: Rodriguez | C84: Moo | D84: C. | E84: PDO II | F84: PPD | G84: OSEC-DAB-PDO2-55-2014 | H84: 44508 | I84: 45607 | J84: 15 | K84: 1 | L84: =IFERROR(VLOOKUP(J84, [1]DATA!$A$4:$I$36, MATCH(K84, [1]DATA!$B$3:$I$3, 0)+1, FALSE), "") -> 42178 | M84: 2000 | N84: =L84+M84 -> 44178 | O84: =ROUND(L84*9%,2) -> 3796.02 | AA84: 3695.42 | AB84: =ROUND(IF(L84>79999.99,900,IF(L84<10000.01,137.5,IF(10000<L84>80000,L84*2.5%))),2) -> 1054.45 | AE84: 200 | AF84: 0 | AG84: 100 | AS84: 0 | AZ84: =ROUND(SUM(O84:AY84),2) -> 8845.89 | BA84: =ROUND(N84-AZ84,2) -> 35332.11 | BB84: =ROUND(BA84/2,2) -> 17666.06 | BC84: =BA84-BB84 -> 17666.05
A85: =A84+1 -> 78 | B85: Salibio | C85: Karl Louise | D85: M. | E85: MPS III | F85: ISD | G85: OSEC-DAB-MPXS3-5-1998 | H85: 42422 | I85: 43549 | J85: 18 | K85: 3 | L85: =IFERROR(VLOOKUP(J85, [1]DATA!$A$4:$I$36, MATCH(K85, [1]DATA!$B$3:$I$3, 0)+1, FALSE), "") -> 54933 | M85: 2000 | N85: =L85+M85 -> 56933 | O85: =ROUND(L85*9%,2) -> 4943.97 | Y85: 9470.66 | AA85: 6245.67 | AB85: =ROUND(IF(L85>79999.99,900,IF(L85<10000.01,137.5,IF(10000<L85>80000,L85*2.5%))),2)-0.01 -> 1373.32 | AD85: 0 | AE85: 200 | AF85: 0 | AG85: 100 | AS85: 0 | AW85: 0 | AZ85: =ROUND(SUM(O85:AY85),2) -> 22333.62 | BA85: =ROUND(N85-AZ85,2) -> 34599.38 | BB85: =ROUND(BA85/2,2) -> 17299.69 | BC85: =BA85-BB85 -> 17299.69
A86: =A85+1 -> 79 | B86: Saluib | C86: Gillian Rose | D86: L. | E86: Accountant III | F86: AFU-OD | G86: OSEC-DAB-A3-19-1998 | H86: 44508 | I86: 45659 | J86: 19 | K86: 1 | L86: =IFERROR(VLOOKUP(J86, [1]DATA!$A$4:$I$36, MATCH(K86, [1]DATA!$B$3:$I$3, 0)+1, FALSE), "") -> 59153 | M86: 2000 | N86: =L86+M86 -> 61153 | O86: =ROUND(L86*9%,2) -> 5323.77 | Q86: 655.56 | AA86: 7633.31 | AB86: =ROUND(IF(L86>79999.99,900,IF(L86<10000.01,137.5,IF(10000<L86>80000,L86*2.5%))),2)-0.01 -> 1478.82 | AC86: 1277.88 | AD86: 500 | AE86: 200 | AF86: 0 | AG86: 100 | AH86: 1336 | AS86: 0 | AZ86: =ROUND(SUM(O86:AY86),2) -> 18505.34 | BA86: =ROUND(N86-AZ86,2) -> 42647.66 | BB86: =ROUND(BA86/2,2) -> 21323.83 | BC86: =BA86-BB86 -> 21323.83
A87: =A86+1 -> 80 | B87: Salvania | C87: Dianne Marie | D87: U. | E87: DMO I | F87: CDMD | G87: OSEC-DAB-DMO1-132-2014 | H87: 45611 | I87: 45611 | J87: 11 | K87: 1 | L87: =IFERROR(VLOOKUP(J87, [1]DATA!$A$4:$I$36, MATCH(K87, [1]DATA!$B$3:$I$3, 0)+1, FALSE), "") -> 31705 | M87: 2000 | N87: =L87+M87 -> 33705 | O87: =ROUND(L87*9%,2) -> 2853.45 | AA87: 1468.9 | AB87: =ROUND(IF(L87>79999.99,900,IF(L87<10000.01,137.5,IF(10000<L87>80000,L87*2.5%))),2)-0.01 -> 792.62 | AE87: 200 | AG87: 100 | AZ87: =ROUND(SUM(O87:AY87),2) -> 5414.97 | BA87: =ROUND(N87-AZ87,2) -> 28290.03 | BB87: =ROUND(BA87/2,2) -> 14145.02 | BC87: =BA87-BB87 -> 14145.01
A88: =A87+1 -> 81 | B88: Sangalang | C88: Janice | D88: C. | E88: MPS I | F88: ISD | G88: OSEC-DAB-MPXS1-54-2014 | H88: 45670 | I88: 45670 | J88: 11 | K88: 1 | L88: =IFERROR(VLOOKUP(J88, [1]DATA!$A$4:$I$36, MATCH(K88, [1]DATA!$B$3:$I$3, 0)+1, FALSE), "") -> 31705 | M88: 2000 | N88: =L88+M88 -> 33705 | O88: =ROUND(L88*9%,2) -> 2853.45 | AA88: 1443.4 | AB88: =ROUND(IF(L88>79999.99,900,IF(L88<10000.01,137.5,IF(10000<L88>80000,L88*2.5%))),2)-0.01 -> 792.62 | AE88: 200 | AG88: 100 | AK88: 1000 | AN88: 2000 | AO88: 527.3 | AP88: 496.79 | AU88: 16652.95 | AZ88: =ROUND(SUM(O88:AY88),2) -> 26066.51 | BA88: =ROUND(N88-AZ88,2) -> 7638.49 | BB88: =ROUND(BA88/2,2) -> 3819.25 | BC88: =BA88-BB88 -> 3819.24
A89: =A88+1 -> 82 | B89: Tabor | C89: Jomar | D89: O. | E89: Agri. II | F89: PAD | G89: OSEC-DAB-AG2-1110-1998 | H89: 44075 | I89: 44986 | J89: 15 | K89: 1 | L89: =IFERROR(VLOOKUP(J89, [1]DATA!$A$4:$I$36, MATCH(K89, [1]DATA!$B$3:$I$3, 0)+1, FALSE), "") -> 42178 | M89: 2000 | N89: =L89+M89 -> 44178 | O89: =ROUND(L89*9%,2) -> 3796.02 | P89: 1000 | Q89: 1191.88 | V89: 5422.38 | W89: 1400 | AA89: 3695.42 | AB89: =ROUND(IF(L89>79999.99,900,IF(L89<10000.01,137.5,IF(10000<L89>80000,L89*2.5%))),2) -> 1054.45 | AE89: 200 | AF89: 0 | AG89: 100 | AS89: 0 | AU89: 11894.97 | AY89: 3034.72 | AZ89: =ROUND(SUM(O89:AY89),2) -> 32789.84 | BA89: =ROUND(N89-AZ89,2) -> 11388.16 | BB89: =ROUND(BA89/2,2) -> 5694.08 | BC89: =BA89-BB89 -> 5694.08
A90: =A89+1 -> 83 | B90: Tandang | C90: Bernard James | D90: R. | E90: PDO III | F90: PPD | G90: OSEC-DAB-PDO3-62-2014 | H90: 42278 | I90: 43789 | J90: 18 | K90: 3 | L90: =IFERROR(VLOOKUP(J90, [1]DATA!$A$4:$I$36, MATCH(K90, [1]DATA!$B$3:$I$3, 0)+1, FALSE), "") -> 54933 | M90: 2000 | N90: =L90+M90 -> 56933 | O90: =ROUND(L90*9%,2) -> 4943.97 | AA90: 6595.75 | AB90: =ROUND(IF(L90>79999.99,900,IF(L90<10000.01,137.5,IF(10000<L90>80000,L90*2.5%))),2)-0.01 -> 1373.32 | AE90: 200 | AF90: 0 | AG90: 100 | AS90: 0 | AW90: 0 | AZ90: =ROUND(SUM(O90:AY90),2) -> 13213.04 | BA90: =ROUND(N90-AZ90,2) -> 43719.96 | BB90: =ROUND(BA90/2,2) -> 21859.98 | BC90: =BA90-BB90 -> 21859.98
A91: =A90+1 -> 84 | B91: Taruc | C91: Jennifer | D91: D. | E91: AO IV | F91: AFU-OD | G91: OSEC-DAB-ADOF4-98-2004 | H91: 34781 | I91: 44291 | J91: 15 | K91: 2 | L91: =IFERROR(VLOOKUP(J91, [1]DATA!$A$4:$I$36, MATCH(K91, [1]DATA!$B$3:$I$3, 0)+1, FALSE), "") -> 42594 | M91: 2000 | N91: =L91+M91 -> 44594 | O91: =ROUND(L91*9%,2) -> 3833.46 | P91: 500 | Q91: 1311.12 | V91: 6325.92 | X91: 1966.67 | AA91: 3791.96 | AB91: =ROUND(IF(L91>79999.99,900,IF(L91<10000.01,137.5,IF(10000<L91>80000,L91*2.5%))),2) -> 1064.85 | AE91: 200 | AF91: 0 | AS91: 0 | AT91: 7180.79 | AU91: 11894.97 | AZ91: =ROUND(SUM(O91:AY91),2) -> 38069.74 | BA91: =ROUND(N91-AZ91,2) -> 6524.26 | BB91: =ROUND(BA91/2,2) -> 3262.13 | BC91: =BA91-BB91 -> 3262.13
A92: =A91+1 -> 85 | B92: Tolero | C92: Jonalyn | D92: T. | E92: Adm. Asst. III | F92: AFU-OD | G92: OSEC-DAB-ADAS3-47-2014 | H92: 45236 | I92: 45236 | J92: 9 | K92: 1 | L92: =IFERROR(VLOOKUP(J92, [1]DATA!$A$4:$I$36, MATCH(K92, [1]DATA!$B$3:$I$3, 0)+1, FALSE), "") -> 24329 | M92: 2000 | N92: =L92+M92 -> 26329 | O92: =ROUND(L92*9%,2) -> 2189.61 | AA92: 163.11 | AB92: =ROUND(IF(L92>79999.99,900,IF(L92<10000.01,137.5,IF(10000<L92>80000,L92*2.5%))),2)-0.01 -> 608.22 | AD92: 1000 | AE92: 600 | AF92: 0 | AG92: 100 | AL92: 100 | AZ92: =ROUND(SUM(O92:AY92),2) -> 4760.94 | BA92: =ROUND(N92-AZ92,2) -> 21568.06 | BB92: =ROUND(BA92/2,2) -> 10784.03 | BC92: =BA92-BB92 -> 10784.03
A93: =A92+1 -> 86 | B93: Turda | C93: Hershey | D93: M. | E93: DMO I | F93: CDMD | G93: OSEC-DAB-DMO1-127-2014 | H93: 45376 | I93: 45376 | J93: 11 | K93: 1 | L93: =IFERROR(VLOOKUP(J93, [1]DATA!$A$4:$I$36, MATCH(K93, [1]DATA!$B$3:$I$3, 0)+1, FALSE), "") -> 31705 | M93: 2000 | N93: =L93+M93 -> 33705 | O93: =ROUND(L93*9%,2) -> 2853.45 | AA93: 1468.9 | AB93: =ROUND(IF(L93>79999.99,900,IF(L93<10000.01,137.5,IF(10000<L93>80000,L93*2.5%))),2)-0.01 -> 792.62 | AE93: 200 | AG93: 100 | AU93: 3321.43 | AY93: 3034.72 | AZ93: =ROUND(SUM(O93:AY93),2) -> 11771.12 | BA93: =ROUND(N93-AZ93,2) -> 21933.88 | BB93: =ROUND(BA93/2,2) -> 10966.94 | BC93: =BA93-BB93 -> 10966.94
A94: =A93+1 -> 87 | B94: Urbano | C94: Milagros | D94: C. | E94: PLO V | F94: PPD | G94: OSEC-DAB-PLO5-3-1998 | H94: 31600 | I94: 42138 | J94: 24 | K94: 4 | L94: =IFERROR(VLOOKUP(J94, [1]DATA!$A$4:$I$36, MATCH(K94, [1]DATA!$B$3:$I$3, 0)+1, FALSE), "") -> 107500 | M94: 2000 | N94: =L94+M94 -> 109500 | O94: =ROUND(L94*9%,2) -> 9675 | P94: 1000 | Q94: 777.44 | S94: 0 | V94: 16026.83 | Y94: 9634.44 | AA94: 21256.81 | AB94: 2500 | AC94: 10017.81 | AD94: 0 | AE94: 200 | AG94: 100 | AH94: 1336 | AK94: 1000 | AL94: 100 | AM94: 6667 | AW94: 0 | AY94: 5790.11 | AZ94: =ROUND(SUM(O94:AY94),2) -> 86081.44 | BA94: =ROUND(N94-AZ94,2) -> 23418.56 | BB94: =ROUND(BA94/2,2) -> 11709.28 | BC94: =BA94-BB94 -> 11709.28
A95: =A94+1 -> 88 | B95: Valencia | C95: Lian Janelle | D95: DR. | E95: DMO I | F95: PAD | G95: OSEC-DAB-DMO1-123-2014 | H95: 42998 | I95: 42998 | J95: 11 | K95: 3 | L95: =IFERROR(VLOOKUP(J95, [1]DATA!$A$4:$I$36, MATCH(K95, [1]DATA!$B$3:$I$3, 0)+1, FALSE), "") -> 32109 | M95: 2000 | N95: =L95+M95 -> 34109 | O95: =ROUND(L95*9%,2) -> 2889.81 | AA95: 1537.23 | AB95: =ROUND(IF(L95>79999.99,900,IF(L95<10000.01,137.5,IF(10000<L95>80000,L95*2.5%))),2)-0.01 -> 802.72 | AE95: 500 | AF95: 0 | AG95: 100 | AN95: 2000 | AO95: 461.39 | AP95: 704.35 | AS95: 0 | AW95: 0 | AY95: 5674.93 | AZ95: =ROUND(SUM(O95:AY95),2) -> 14670.43 | BA95: =ROUND(N95-AZ95,2) -> 19438.57 | BB95: =ROUND(BA95/2,2) -> 9719.29 | BC95: =BA95-BB95 -> 9719.28
A96: =A95+1 -> 89 | B96: Vinuya | C96: Editha | D96: S. | E96: DMO V | F96: CDMD | G96: OSEC-DAB-DMO5-26-2014 | H96: 32692 | I96: 42138 | J96: 24 | K96: 4 | L96: =IFERROR(VLOOKUP(J96, [1]DATA!$A$4:$I$36, MATCH(K96, [1]DATA!$B$3:$I$3, 0)+1, FALSE), "") -> 107500 | M96: 2000 | N96: =L96+M96 -> 109500 | O96: =ROUND(L96*9%,2) -> 9675 | P96: 1000 | Q96: 1194.51 | S96: 13035.54 | W96: 2422.22 | Y96: 9634.44 | AA96: 21256.81 | AB96: 2500 | AD96: 0 | AE96: 200 | AF96: 800 | AG96: 100 | AS96: 1537.37 | AW96: 0 | AX96: 2877.71 | AY96: 5857.62 | AZ96: =ROUND(SUM(O96:AY96),2) -> 72091.22 | BA96: =ROUND(N96-AZ96,2) -> 37408.78 | BB96: =ROUND(BA96/2,2) -> 18704.39 | BC96: =BA96-BB96 -> 18704.39
A97: =A96+1 -> 90 | B97: Yago | C97: Emerson | D97: S. | E97: DMO IV | F97: CDMD | G97: OSEC-DAB-DMO4-27-2014 | H97: 42156 | I97: 44459 | J97: 22 | K97: 2 | L97: =IFERROR(VLOOKUP(J97, [1]DATA!$A$4:$I$36, MATCH(K97, [1]DATA!$B$3:$I$3, 0)+1, FALSE), "") -> 82963 | M97: 2000 | N97: =L97+M97 -> 84963 | O97: =ROUND(L97*9%,2) -> 7466.67 | Y97: 9634.44 | AA97: 14126.7 | AB97: =L97*2.5%-0.01 -> 2074.065 | AE97: 200 | AF97: 0 | AG97: 100 | AL97: 1000 | AS97: 0 | AV97: 9761.15 | AZ97: =ROUND(SUM(O97:AY97),2) -> 44363.03 | BA97: =ROUND(N97-AZ97,2) -> 40599.97 | BB97: =ROUND(BA97/2,2) -> 20299.99 | BC97: =BA97-BB97 -> 20299.98
B98: TOTAL | L98: =SUM(L8:L97) -> 3921427 | M98: =SUM(M8:M97) -> 180000 | N98: =SUM(N8:N97) -> 4101427 | O98: =SUM(O8:O97) -> 352928.43 | P98: =SUM(P8:P97) -> 9268 | Q98: =SUM(Q8:Q97) -> 26046.38 | R98: =SUM(R8:R97) -> 2040.79 | S98: =SUM(S8:S97) -> 30508.48 | ... BC98: =SUM(BC8:BC97) -> 1102272
