Workbook

Sheet MASTER DATA
A2: JOB ORDER GENERAL PAYROLL
A3: For The Period of
A4: 02-16-28-2026
A6: No. | B6: ORS Number | C6: ORS Date | E6: Name | F6: Office | G6: Position | H6: Salary Grade | I6: FUND SOURCE | J6: W/ ANNEX B2 | K6: 4th QTR. Work Schedule - | M6: Monthly Rate | N6: Quincena | O6: Daily Rate | P6: Per Hour | Q6: Per Minute | R6: Working Days | S6: Basic Salary | T6: 02-01-15-2026 | W6: =T6 -> 02-01-15-2026 | Z6: 02-16-28-2026 | AC6: =Z6 -> 02-16-28-2026 | AO6: Total | AP6: Other Deduction | AR6: Gross Amount | AS6: Withholding Tax | AU6: Deductions | AY6: Net Pay | AZ6: Remarks
T7: IN PESO | U7: Late / Under Time | W7: IN PESO | X7: Late / Under Time | Z7: IN PESO | AA7: Late / Under Time | AC7: IN PESO | AD7: Late / Under Time | AG7: Late / Under Time | AI7: IN PESO | AJ7: Late / Under Time | AM7: Late / Under Time | AP7: Clothing and Others | AQ7: Remarks | AS7: EXPANDED | AT7: PERCENTAGE | AU7: Accommodation (Staff house) | AV7: Water (Staff house) | AW7: Electricity (Staff house) | AX7: Repairs
K8: Time In | L8: Time Out | T8: Absent | U8: Hour | V8: Minute | W8: Absent | X8: Hour | Y8: Minute | Z8: Absent | AA8: Hour | AB8: Minute | AC8: Absent | AD8: Hour | AE8: Minute | AF8: Absent | AG8: Hour | AH8: Minute | AI8: Absent | AJ8: Hour | AK8: Minute | AL8: Absent | AM8: Hour | AN8: Minute | AS8: 0.02 | AT8: 0.1
A9: 1 | B9: 2 | C9: 3 | D9: 4 | E9: 5 | F9: 6 | G9: 7 | H9: 8 | L9: 10 | M9: 11 | N9: 12 | O9: 13 | P9: 14 | Q9: 15 | R9: 16 | S9: 17 | T9: 18 | U9: 19 | V9: 20 | W9: 21 | X9: 22 | Y9: 23 | Z9: 24 | AA9: 25 | AB9: 26 | AC9: 27 | AD9: 28 | AE9: 29 | AF9: 24 | AG9: 25 | AH9: 26 | AJ9: 28 | AK9: 29 | AM9: 31 | AN9: 32 | AO9: 33 | AP9: 34 | AQ9: 35 | AR9: 36 | AS9: 37 | AT9: 38 | AU9: 39 | AV9: 40 | AX9: 41 | AY9: 42 | AZ9: 43
A10: =IF(B10="","",COUNTA($B$10:B10)) -> 1 | B10: 2026-01-0016 | C10: 46036 | E10: AUSTRIA, CHRISTIAN JOCEF B. | F10: CDMD | G10: Administrative Asst. II | H10: =IF(AZ10="Payroll",VLOOKUP(E10,'CODE 2'!$R:$S,2,FALSE),"0") -> 8 | I10: O. ESETS | J10: OK | M10: =IFERROR(VLOOKUP($H10,'CODE 2'!$J:$K,2,FALSE)," ") -> 19744 | N10: =IFERROR(ROUND((M10/2),2),"") -> 9872 | O10: =IFERROR((M10/22)," ") -> 897.45455 | P10: =IFERROR((O10/8),"") -> 112.18182 | Q10: =IFERROR((P10/60),"") -> 1.869697 | R10: =IF(AZ10="Payroll","11","") -> 11 | S10: =IFERROR(ROUND((O10*R10),2)," ") -> 9872 | T10: 0 | U10: 0 | V10: 0 | W10: =IFERROR(ROUND(($O10*$T10),2)," ") -> 0 | X10: =IFERROR(ROUND(($P10*$U10),2),"") -> 0 | Y10: =IFERROR(ROUND(($Q10*$V10),2),"") -> 0 | AC10: =IFERROR(ROUND(($O10*$Z10),2)," ") -> 0 | AD10: =IFERROR(ROUND(($P10*$AA10),2),"") -> 0 | AE10: =IFERROR(ROUND(($Q10*$AB10),2),"") -> 0 | AI10: =IFERROR(ROUND(($O10*$AF10),2)," ") -> 0 | AJ10: =IFERROR(ROUND(($P10*$AG10),2),"") -> 0 | AK10: =IFERROR(ROUND(($Q10*$AH10),2),"") -> 0 | AL10: =IFERROR(ROUND(($W10+$AC10+$AI10),2),"") -> 0 | AM10: =IFERROR(ROUND(($X10+$AD10+$AJ10),2),"") -> 0 | AN10: =IFERROR(ROUND(($Y10+$AE10+$AK10),2),"") -> 0 | AO10: =SUM(AL10:AN10) -> 0 | AR10: =IFERROR(ROUND((S10-AO10-AP10),2),"") -> 9872 | AY10: =IFERROR(ROUND((AR10-AS10-AT10-AU10-AV10-AW10-AX10),2),"") -> 9872 | AZ10: Payroll | BA10: AGUAS, DERICKE DUANE C.
A11: =IF(B11="","",COUNTA($B$10:B11)) -> 2 | B11: 2026-01-0014 | C11: 46036 | E11: PASTOR, JANELLE E. | F11: CDMD | G11: Development Management Officer I | H11: =IF(AZ11="Payroll",VLOOKUP(E11,'CODE 2'!$R:$S,2,FALSE),"0") -> 11 | I11: O. ESETS | J11: OK | M11: =IFERROR(VLOOKUP($H11,'CODE 2'!$J:$K,2,FALSE)," ") -> 27000 | N11: =IFERROR(ROUND((M11/2),2),"") -> 13500 | O11: =IFERROR((M11/22)," ") -> 1227.2727 | P11: =IFERROR((O11/8),"") -> 153.40909 | Q11: =IFERROR((P11/60),"") -> 2.5568182 | R11: 11 | S11: =IFERROR(ROUND((O11*R11),2)," ") -> 13500 | T11: 0 | U11: 0 | V11: 0 | W11: =IFERROR(ROUND(($O11*$T11),2)," ") -> 0 | X11: =IFERROR(ROUND(($P11*$U11),2),"") -> 0 | Y11: =IFERROR(ROUND(($Q11*$V11),2),"") -> 0 | AC11: =IFERROR(ROUND(($O11*$Z11),2)," ") -> 0 | AD11: =IFERROR(ROUND(($P11*$AA11),2),"") -> 0 | AE11: =IFERROR(ROUND(($Q11*$AB11),2),"") -> 0 | AI11: =IFERROR(ROUND(($O11*$AF11),2)," ") -> 0 | AJ11: =IFERROR(ROUND(($P11*$AG11),2),"") -> 0 | AK11: =IFERROR(ROUND(($Q11*$AH11),2),"") -> 0 | AL11: =IFERROR(ROUND(($W11+$AC11+$AI11),2),"") -> 0 | AM11: =IFERROR(ROUND(($X11+$AD11+$AJ11),2),"") -> 0 | AN11: =IFERROR(ROUND(($Y11+$AE11+$AK11),2),"") -> 0 | AO11: =SUM(AL11:AN11) -> 0 | AR11: =IFERROR(ROUND((S11-AO11-AP11),2),"") -> 13500 | AY11: =IFERROR(ROUND((AR11-AS11-AT11-AU11-AV11-AW11-AX11),2),"") -> 13500 | AZ11: Payroll | BA11: AGUSTIN, PAULYN B.
A12: =IF(B12="","",COUNTA($B$10:B12)) -> 3 | B12: 2026-01-0015 | C12: 46036 | E12: RODRIGUEZ, MA. RUFFA A. | F12: CDMD | G12: Development Management Officer II | H12: 15 | I12: O. ESETS | J12: OK | M12: =IFERROR(VLOOKUP($H12,'CODE 2'!$J:$K,2,FALSE)," ") -> 36619 | N12: =IFERROR(ROUND((M12/2),2),"") -> 18309.5 | O12: =IFERROR((M12/22)," ") -> 1664.5 | P12: =IFERROR((O12/8),"") -> 208.0625 | Q12: =IFERROR((P12/60),"") -> 3.4677083 | R12: 11 | S12: =IFERROR(ROUND((O12*R12),2)," ") -> 18309.5 | T12: 0 | U12: 0 | V12: 0 | W12: =IFERROR(ROUND(($O12*$T12),2)," ") -> 0 | X12: =IFERROR(ROUND(($P12*$U12),2),"") -> 0 | Y12: =IFERROR(ROUND(($Q12*$V12),2),"") -> 0 | AC12: =IFERROR(ROUND(($O12*$Z12),2)," ") -> 0 | AD12: =IFERROR(ROUND(($P12*$AA12),2),"") -> 0 | AE12: =IFERROR(ROUND(($Q12*$AB12),2),"") -> 0 | AI12: =IFERROR(ROUND(($O12*$AF12),2)," ") -> 0 | AJ12: =IFERROR(ROUND(($P12*$AG12),2),"") -> 0 | AK12: =IFERROR(ROUND(($Q12*$AH12),2),"") -> 0 | AL12: =IFERROR(ROUND(($W12+$AC12+$AI12),2),"") -> 0 | AM12: =IFERROR(ROUND(($X12+$AD12+$AJ12),2),"") -> 0 | AN12: =IFERROR(ROUND(($Y12+$AE12+$AK12),2),"") -> 0 | AO12: =SUM(AL12:AN12) -> 0 | AR12: =IFERROR(ROUND((S12-AO12-AP12),2),"") -> 18309.5 | AY12: =IFERROR(ROUND((AR12-AS12-AT12-AU12-AV12-AW12-AX12),2),"") -> 18309.5 | AZ12: Payroll | BA12: AKUT, FILSAN G.
A13: =IF(B13="","",COUNTA($B$10:B13)) -> 4 | B13: 2026-01-0002 | C13: 46035 | E13: OQUINDO, SHEILA JANE G. | F13: CDMD | G13: Development Management Officer I | H13: =IF(AZ13="Payroll",VLOOKUP(E13,'CODE 2'!$R:$S,2,FALSE),"0") -> 0 | I13: CFIDP | J13: OK | M13: =IFERROR(VLOOKUP($H13,'CODE 2'!$J:$K,2,FALSE)," ") | N13: =IFERROR(ROUND((M13/2),2),"") | O13: =IFERROR((M13/22)," ") | P13: =IFERROR((O13/8),"") | Q13: =IFERROR((P13/60),"") | R13: 11 | S13: =IFERROR(ROUND((O13*R13),2)," ") | T13: 0 | U13: 0 | V13: 0 | W13: =IFERROR(ROUND(($O13*$T13),2)," ") | X13: =IFERROR(ROUND(($P13*$U13),2),"") | Y13: =IFERROR(ROUND(($Q13*$V13),2),"") | AC13: =IFERROR(ROUND(($O13*$Z13),2)," ") | AD13: =IFERROR(ROUND(($P13*$AA13),2),"") | AE13: =IFERROR(ROUND(($Q13*$AB13),2),"") | AI13: =IFERROR(ROUND(($O13*$AF13),2)," ") | AJ13: =IFERROR(ROUND(($P13*$AG13),2),"") | AK13: =IFERROR(ROUND(($Q13*$AH13),2),"") | AL13: =IFERROR(ROUND(($W13+$AC13+$AI13),2),"") | AM13: =IFERROR(ROUND(($X13+$AD13+$AJ13),2),"") | AN13: =IFERROR(ROUND(($Y13+$AE13+$AK13),2),"") | AO13: =SUM(AL13:AN13) -> 0 | AR13: =IFERROR(ROUND((S13-AO13-AP13),2),"") | AY13: =IFERROR(ROUND((AR13-AS13-AT13-AU13-AV13-AW13-AX13),2),"") | AZ13: Voucher | BA13: AMBROSIO, JOHN HAROLD F.
A14: =IF(B14="","",COUNTA($B$10:B14)) -> 5 | B14: 2026-01-0017 | C14: 46036 | E14: ESMER, GLECY R. | F14: PPD | G14: Administrative Asst. II | H14: =IF(AZ14="Payroll",VLOOKUP(E14,'CODE 2'!$R:$S,2,FALSE),"0") -> 8 | I14: O. ESETS | J14: OK | M14: =IFERROR(VLOOKUP($H14,'CODE 2'!$J:$K,2,FALSE)," ") -> 19744 | N14: =IFERROR(ROUND((M14/2),2),"") -> 9872 | O14: =IFERROR((M14/22)," ") -> 897.45455 | P14: =IFERROR((O14/8),"") -> 112.18182 | Q14: =IFERROR((P14/60),"") -> 1.869697 | R14: =IF(AZ14="Payroll","11","") -> 11 | S14: =IFERROR(ROUND((O14*R14),2)," ") -> 9872 | T14: 0 | U14: 0 | V14: 0 | W14: =IFERROR(ROUND(($O14*$T14),2)," ") -> 0 | X14: =IFERROR(ROUND(($P14*$U14),2),"") -> 0 | Y14: =IFERROR(ROUND(($Q14*$V14),2),"") -> 0 | AC14: =IFERROR(ROUND(($O14*$Z14),2)," ") -> 0 | AD14: =IFERROR(ROUND(($P14*$AA14),2),"") -> 0 | AE14: =IFERROR(ROUND(($Q14*$AB14),2),"") -> 0 | AI14: =IFERROR(ROUND(($O14*$AF14),2)," ") -> 0 | AJ14: =IFERROR(ROUND(($P14*$AG14),2),"") -> 0 | AK14: =IFERROR(ROUND(($Q14*$AH14),2),"") -> 0 | AL14: =IFERROR(ROUND(($W14+$AC14+$AI14),2),"") -> 0 | AM14: =IFERROR(ROUND(($X14+$AD14+$AJ14),2),"") -> 0 | AN14: =IFERROR(ROUND(($Y14+$AE14+$AK14),2),"") -> 0 | AO14: =SUM(AL14:AN14) -> 0 | AR14: =IFERROR(ROUND((S14-AO14-AP14),2),"") -> 9872 | AU14: 2000 | AV14: 395.48 | AY14: =IFERROR(ROUND((AR14-AS14-AT14-AU14-AV14-AW14-AX14),2),"") -> 7476.52 | AZ14: Payroll | BA14: ANDAYA, APRIL JANE G.
A15: =IF(B15="","",COUNTA($B$10:B15)) -> 6 | B15: 2026-01-0001 | C15: 46035 | E15: GALABAY, CHRISTIANEL B. | F15: PPD | G15: Planning Officer II | H15: =IF(AZ15="Payroll",VLOOKUP(E15,'CODE 2'!$R:$S,2,FALSE),"0") -> 0 | I15: CFIDP | J15: OK | M15: =IFERROR(VLOOKUP($H15,'CODE 2'!$J:$K,2,FALSE)," ") | N15: =IFERROR(ROUND((M15/2),2),"") | O15: =IFERROR((M15/22)," ") | P15: =IFERROR((O15/8),"") | Q15: =IFERROR((P15/60),"") | R15: =IF(AZ15="Payroll","11","") | S15: =IFERROR(ROUND((O15*R15),2)," ") | T15: 0 | U15: 0 | V15: 0 | W15: =IFERROR(ROUND(($O15*$T15),2)," ") | X15: =IFERROR(ROUND(($P15*$U15),2),"") | Y15: =IFERROR(ROUND(($Q15*$V15),2),"") | AC15: =IFERROR(ROUND(($O15*$Z15),2)," ") | AD15: =IFERROR(ROUND(($P15*$AA15),2),"") | AE15: =IFERROR(ROUND(($Q15*$AB15),2),"") | AI15: =IFERROR(ROUND(($O15*$AF15),2)," ") | AJ15: =IFERROR(ROUND(($P15*$AG15),2),"") | AK15: =IFERROR(ROUND(($Q15*$AH15),2),"") | AL15: =IFERROR(ROUND(($W15+$AC15+$AI15),2),"") | AM15: =IFERROR(ROUND(($X15+$AD15+$AJ15),2),"") | AN15: =IFERROR(ROUND(($Y15+$AE15+$AK15),2),"") | AO15: =SUM(AL15:AN15) -> 0 | AR15: =IFERROR(ROUND((S15-AO15-AP15),2),"") | AY15: =IFERROR(ROUND((AR15-AS15-AT15-AU15-AV15-AW15-AX15),2),"") | AZ15: Voucher | BA15: ARANAZ, CZAREE JOSIAH A.
A16: =IF(B16="","",COUNTA($B$10:B16)) -> 7 | B16: 2026-01-0018 | C16: 46036 | E16: NILO, FAITH PERL A. | F16: PPD | G16: Planning Officer I | H16: =IF(AZ16="Payroll",VLOOKUP(E16,'CODE 2'!$R:$S,2,FALSE),"0") -> 11 | I16: O. ESETS | J16: OK | M16: =IFERROR(VLOOKUP($H16,'CODE 2'!$J:$K,2,FALSE)," ") -> 27000 | N16: =IFERROR(ROUND((M16/2),2),"") -> 13500 | O16: =IFERROR((M16/22)," ") -> 1227.2727 | P16: =IFERROR((O16/8),"") -> 153.40909 | Q16: =IFERROR((P16/60),"") -> 2.5568182 | R16: =IF(AZ16="Payroll","11","") -> 11 | S16: =IFERROR(ROUND((O16*R16),2)," ") -> 13500 | T16: 0 | U16: 0 | V16: 4 | W16: =IFERROR(ROUND(($O16*$T16),2)," ") -> 0 | X16: =IFERROR(ROUND(($P16*$U16),2),"") -> 0 | Y16: =IFERROR(ROUND(($Q16*$V16),2),"") -> 10.23 | AC16: =IFERROR(ROUND(($O16*$Z16),2)," ") -> 0 | AD16: =IFERROR(ROUND(($P16*$AA16),2),"") -> 0 | AE16: =IFERROR(ROUND(($Q16*$AB16),2),"") -> 0 | AI16: =IFERROR(ROUND(($O16*$AF16),2)," ") -> 0 | AJ16: =IFERROR(ROUND(($P16*$AG16),2),"") -> 0 | AK16: =IFERROR(ROUND(($Q16*$AH16),2),"") -> 0 | AL16: =IFERROR(ROUND(($W16+$AC16+$AI16),2),"") -> 0 | AM16: =IFERROR(ROUND(($X16+$AD16+$AJ16),2),"") -> 0 | AN16: =IFERROR(ROUND(($Y16+$AE16+$AK16),2),"") -> 10.23 | AO16: =SUM(AL16:AN16) -> 10.23 | AR16: =IFERROR(ROUND((S16-AO16-AP16),2),"") -> 13489.77 | AY16: =IFERROR(ROUND((AR16-AS16-AT16-AU16-AV16-AW16-AX16),2),"") -> 13489.77 | AZ16: Payroll | BA16: AUSTRIA, CHRISTIAN JOCEF B.
A17: =IF(B17="","",COUNTA($B$10:B17)) -> 8 | B17: 2026-01-0019 | C17: 46036 | E17: VERINO, ALLYSON RYAN T. | F17: PPD | G17: Planning Development Officer I | H17: =IF(AZ17="Payroll",VLOOKUP(E17,'CODE 2'!$R:$S,2,FALSE),"0") -> 11 | I17: O. ESETS | J17: OK | M17: =IFERROR(VLOOKUP($H17,'CODE 2'!$J:$K,2,FALSE)," ") -> 27000 | N17: =IFERROR(ROUND((M17/2),2),"") -> 13500 | O17: =IFERROR((M17/22)," ") -> 1227.2727 | P17: =IFERROR((O17/8),"") -> 153.40909 | Q17: =IFERROR((P17/60),"") -> 2.5568182 | R17: =IF(AZ17="Payroll","11","") -> 11 | S17: =IFERROR(ROUND((O17*R17),2)," ") -> 13500 | T17: 0 | U17: 0 | V17: 0 | W17: =IFERROR(ROUND(($O17*$T17),2)," ") -> 0 | X17: =IFERROR(ROUND(($P17*$U17),2),"") -> 0 | Y17: =IFERROR(ROUND(($Q17*$V17),2),"") -> 0 | AC17: =IFERROR(ROUND(($O17*$Z17),2)," ") -> 0 | AD17: =IFERROR(ROUND(($P17*$AA17),2),"") -> 0 | AE17: =IFERROR(ROUND(($Q17*$AB17),2),"") -> 0 | AI17: =IFERROR(ROUND(($O17*$AF17),2)," ") -> 0 | AJ17: =IFERROR(ROUND(($P17*$AG17),2),"") -> 0 | AK17: =IFERROR(ROUND(($Q17*$AH17),2),"") -> 0 | AL17: =IFERROR(ROUND(($W17+$AC17+$AI17),2),"") -> 0 | AM17: =IFERROR(ROUND(($X17+$AD17+$AJ17),2),"") -> 0 | AN17: =IFERROR(ROUND(($Y17+$AE17+$AK17),2),"") -> 0 | AO17: =SUM(AL17:AN17) -> 0 | AR17: =IFERROR(ROUND((S17-AO17-AP17),2),"") -> 13500 | AY17: =IFERROR(ROUND((AR17-AS17-AT17-AU17-AV17-AW17-AX17),2),"") -> 13500 | AZ17: Payroll | BA17: BADILLO, ALBINO M.
A18: =IF(B18="","",COUNTA($B$10:B18)) -> 9 | B18: 2026-01-0025 | C18: 46036 | E18: LAMPAS, CHRISTIAN JOSEPH P | F18: ISD | G18: Computer Maintenance Technologist I | H18: =IF(AZ18="Payroll",VLOOKUP(E18,'CODE 2'!$R:$S,2,FALSE),"0") -> 11 | I18: FPMA/RICE | J18: OK | M18: =IFERROR(VLOOKUP($H18,'CODE 2'!$J:$K,2,FALSE)," ") -> 27000 | N18: =IFERROR(ROUND((M18/2),2),"") -> 13500 | O18: =IFERROR((M18/22)," ") -> 1227.2727 | P18: =IFERROR((O18/8),"") -> 153.40909 | Q18: =IFERROR((P18/60),"") -> 2.5568182 | R18: =IF(AZ18="Payroll","11","") -> 11 | S18: =IFERROR(ROUND((O18*R18),2)," ") -> 13500 | T18: 1 | U18: 0 | V18: 0 | W18: =IFERROR(ROUND(($O18*$T18),2)," ") -> 1227.27 | X18: =IFERROR(ROUND(($P18*$U18),2),"") -> 0 | Y18: =IFERROR(ROUND(($Q18*$V18),2),"") -> 0 | AC18: =IFERROR(ROUND(($O18*$Z18),2)," ") -> 0 | AD18: =IFERROR(ROUND(($P18*$AA18),2),"") -> 0 | AE18: =IFERROR(ROUND(($Q18*$AB18),2),"") -> 0 | AI18: =IFERROR(ROUND(($O18*$AF18),2)," ") -> 0 | AJ18: =IFERROR(ROUND(($P18*$AG18),2),"") -> 0 | AK18: =IFERROR(ROUND(($Q18*$AH18),2),"") -> 0 | AL18: =IFERROR(ROUND(($W18+$AC18+$AI18),2),"") -> 1227.27 | AM18: =IFERROR(ROUND(($X18+$AD18+$AJ18),2),"") -> 0 | AN18: =IFERROR(ROUND(($Y18+$AE18+$AK18),2),"") -> 0 | AO18: =SUM(AL18:AN18) -> 1227.27 | AR18: =IFERROR(ROUND((S18-AO18-AP18),2),"") -> 12272.73 | AY18: =IFERROR(ROUND((AR18-AS18-AT18-AU18-AV18-AW18-AX18),2),"") -> 12272.73 | AZ18: Payroll | BA18: BALA, ANGEL D.
A19: =IF(B19="","",COUNTA($B$10:B19)) -> 10 | B19: 2026-01-0022 | C19: 46036 | E19: MANDANI, AVE M. | F19: ISD | G19: Bookbinder III | H19: =IF(AZ19="Payroll",VLOOKUP(E19,'CODE 2'!$R:$S,2,FALSE),"0") -> 7 | I19: O. ESETS | J19: OK | M19: =IFERROR(VLOOKUP($H19,'CODE 2'!$J:$K,2,FALSE)," ") -> 18620 | N19: =IFERROR(ROUND((M19/2),2),"") -> 9310 | O19: =IFERROR((M19/22)," ") -> 846.36364 | P19: =IFERROR((O19/8),"") -> 105.79545 | Q19: =IFERROR((P19/60),"") -> 1.7632576 | R19: =IF(AZ19="Payroll","11","") -> 11 | S19: =IFERROR(ROUND((O19*R19),2)," ") -> 9310 | T19: 0 | U19: 0 | V19: 0 | W19: =IFERROR(ROUND(($O19*$T19),2)," ") -> 0 | X19: =IFERROR(ROUND(($P19*$U19),2),"") -> 0 | Y19: =IFERROR(ROUND(($Q19*$V19),2),"") -> 0 | AC19: =IFERROR(ROUND(($O19*$Z19),2)," ") -> 0 | AD19: =IFERROR(ROUND(($P19*$AA19),2),"") -> 0 | AE19: =IFERROR(ROUND(($Q19*$AB19),2),"") -> 0 | AI19: =IFERROR(ROUND(($O19*$AF19),2)," ") -> 0 | AJ19: =IFERROR(ROUND(($P19*$AG19),2),"") -> 0 | AK19: =IFERROR(ROUND(($Q19*$AH19),2),"") -> 0 | AL19: =IFERROR(ROUND(($W19+$AC19+$AI19),2),"") -> 0 | AM19: =IFERROR(ROUND(($X19+$AD19+$AJ19),2),"") -> 0 | AN19: =IFERROR(ROUND(($Y19+$AE19+$AK19),2),"") -> 0 | AO19: =SUM(AL19:AN19) -> 0 | AR19: =IFERROR(ROUND((S19-AO19-AP19),2),"") -> 9310 | AY19: =IFERROR(ROUND((AR19-AS19-AT19-AU19-AV19-AW19-AX19),2),"") -> 9310 | AZ19: Payroll | BA19: BALANGATAN, JUN CHRISTOPHER C.
A20: =IF(B20="","",COUNTA($B$10:B20)) -> 11 | B20: 2026-01-0021 | C20: 46036 | E20: PERNIA, JONAS S. | F20: ISD | G20: Administrative Asst. II | H20: =IF(AZ20="Payroll",VLOOKUP(E20,'CODE 2'!$R:$S,2,FALSE),"0") -> 8 | I20: O. ESETS | J20: OK | M20: =IFERROR(VLOOKUP($H20,'CODE 2'!$J:$K,2,FALSE)," ") -> 19744 | N20: =IFERROR(ROUND((M20/2),2),"") -> 9872 | O20: =IFERROR((M20/22)," ") -> 897.45455 | P20: =IFERROR((O20/8),"") -> 112.18182 | Q20: =IFERROR((P20/60),"") -> 1.869697 | R20: =IF(AZ20="Payroll","11","") -> 11 | S20: =IFERROR(ROUND((O20*R20),2)," ") -> 9872 | T20: 0 | U20: 0 | V20: 0 | W20: =IFERROR(ROUND(($O20*$T20),2)," ") -> 0 | X20: =IFERROR(ROUND(($P20*$U20),2),"") -> 0 | Y20: =IFERROR(ROUND(($Q20*$V20),2),"") -> 0 | AC20: =IFERROR(ROUND(($O20*$Z20),2)," ") -> 0 | AD20: =IFERROR(ROUND(($P20*$AA20),2),"") -> 0 | AE20: =IFERROR(ROUND(($Q20*$AB20),2),"") -> 0 | AI20: =IFERROR(ROUND(($O20*$AF20),2)," ") -> 0 | AJ20: =IFERROR(ROUND(($P20*$AG20),2),"") -> 0 | AK20: =IFERROR(ROUND(($Q20*$AH20),2),"") -> 0 | AL20: =IFERROR(ROUND(($W20+$AC20+$AI20),2),"") -> 0 | AM20: =IFERROR(ROUND(($X20+$AD20+$AJ20),2),"") -> 0 | AN20: =IFERROR(ROUND(($Y20+$AE20+$AK20),2),"") -> 0 | AO20: =SUM(AL20:AN20) -> 0 | AR20: =IFERROR(ROUND((S20-AO20-AP20),2),"") -> 9872 | AY20: =IFERROR(ROUND((AR20-AS20-AT20-AU20-AV20-AW20-AX20),2),"") -> 9872 | AZ20: Payroll | BA20: BELO, JOSHUA G.
A21: =IF(B21="","",COUNTA($B$10:B21)) -> 12 | B21: 2026-01-0023 | C21: 46036 | E21: BALANGATAN, JUN CHRISTOPHER C. | F21: ISD | G21: Media Production Specialist I | H21: =IF(AZ21="Payroll",VLOOKUP(E21,'CODE 2'!$R:$S,2,FALSE),"0") -> 11 | I21: O. ESETS | J21: OK | M21: =IFERROR(VLOOKUP($H21,'CODE 2'!$J:$K,2,FALSE)," ") -> 27000 | N21: =IFERROR(ROUND((M21/2),2),"") -> 13500 | O21: =IFERROR((M21/22)," ") -> 1227.2727 | P21: =IFERROR((O21/8),"") -> 153.40909 | Q21: =IFERROR((P21/60),"") -> 2.5568182 | R21: =IF(AZ21="Payroll","11","") -> 11 | S21: =IFERROR(ROUND((O21*R21),2)," ") -> 13500 | T21: 0 | U21: 0 | V21: 0 | W21: =IFERROR(ROUND(($O21*$T21),2)," ") -> 0 | X21: =IFERROR(ROUND(($P21*$U21),2),"") -> 0 | Y21: =IFERROR(ROUND(($Q21*$V21),2),"") -> 0 | AC21: =IFERROR(ROUND(($O21*$Z21),2)," ") -> 0 | AD21: =IFERROR(ROUND(($P21*$AA21),2),"") -> 0 | AE21: =IFERROR(ROUND(($Q21*$AB21),2),"") -> 0 | AI21: =IFERROR(ROUND(($O21*$AF21),2)," ") -> 0 | AJ21: =IFERROR(ROUND(($P21*$AG21),2),"") -> 0 | AK21: =IFERROR(ROUND(($Q21*$AH21),2),"") -> 0 | AL21: =IFERROR(ROUND(($W21+$AC21+$AI21),2),"") -> 0 | AM21: =IFERROR(ROUND(($X21+$AD21+$AJ21),2),"") -> 0 | AN21: =IFERROR(ROUND(($Y21+$AE21+$AK21),2),"") -> 0 | AO21: =SUM(AL21:AN21) -> 0 | AR21: =IFERROR(ROUND((S21-AO21-AP21),2),"") -> 13500 | AY21: =IFERROR(ROUND((AR21-AS21-AT21-AU21-AV21-AW21-AX21),2),"") -> 13500 | AZ21: Payroll | BA21: BRUZON, ANGENNITTE F.
A22: =IF(B22="","",COUNTA($B$10:B22)) -> 13 | B22: 2026-01-0024 | C22: 46036 | E22: LIM, KLEIN ANSON G. | F22: ISD | G22: Agriculturist I | H22: =IF(AZ22="Payroll",VLOOKUP(E22,'CODE 2'!$R:$S,2,FALSE),"0") -> 11 | I22: FPMA/RICE | J22: OK | M22: =IFERROR(VLOOKUP($H22,'CODE 2'!$J:$K,2,FALSE)," ") -> 27000 | N22: =IFERROR(ROUND((M22/2),2),"") -> 13500 | O22: =IFERROR((M22/22)," ") -> 1227.2727 | P22: =IFERROR((O22/8),"") -> 153.40909 | Q22: =IFERROR((P22/60),"") -> 2.5568182 | R22: =IF(AZ22="Payroll","11","") -> 11 | S22: =IFERROR(ROUND((O22*R22),2)," ") -> 13500 | T22: 0 | U22: 0 | V22: 9 | W22: =IFERROR(ROUND(($O22*$T22),2)," ") -> 0 | X22: =IFERROR(ROUND(($P22*$U22),2),"") -> 0 | Y22: =IFERROR(ROUND(($Q22*$V22),2),"") -> 23.01 | AC22: =IFERROR(ROUND(($O22*$Z22),2)," ") -> 0 | AD22: =IFERROR(ROUND(($P22*$AA22),2),"") -> 0 | AE22: =IFERROR(ROUND(($Q22*$AB22),2),"") -> 0 | AI22: =IFERROR(ROUND(($O22*$AF22),2)," ") -> 0 | AJ22: =IFERROR(ROUND(($P22*$AG22),2),"") -> 0 | AK22: =IFERROR(ROUND(($Q22*$AH22),2),"") -> 0 | AL22: =IFERROR(ROUND(($W22+$AC22+$AI22),2),"") -> 0 | AM22: =IFERROR(ROUND(($X22+$AD22+$AJ22),2),"") -> 0 | AN22: =IFERROR(ROUND(($Y22+$AE22+$AK22),2),"") -> 23.01 | AO22: =SUM(AL22:AN22) -> 23.01 | AR22: =IFERROR(ROUND((S22-AO22-AP22),2),"") -> 13476.99 | AY22: =IFERROR(ROUND((AR22-AS22-AT22-AU22-AV22-AW22-AX22),2),"") -> 13476.99 | AZ22: Payroll | BA22: CAGUMBAY, LIYANNE M.
A23: =IF(B23="","",COUNTA($B$10:B23)) -> 14 | B23: 2026-01-0020 | C23: 46036 | E23: AGUAS, DERICKE DUANE C. | F23: ISD | G23: Information Officer I | H23: 11 | I23: O. ESETS | J23: OK | M23: =IFERROR(VLOOKUP($H23,'CODE 2'!$J:$K,2,FALSE)," ") -> 27000 | N23: =IFERROR(ROUND((M23/2),2),"") -> 13500 | O23: =IFERROR((M23/22)," ") -> 1227.2727 | P23: =IFERROR((O23/8),"") -> 153.40909 | Q23: =IFERROR((P23/60),"") -> 2.5568182 | R23: =IF(AZ23="Payroll","11","") -> 11 | S23: =IFERROR(ROUND((O23*R23),2)," ") -> 13500 | T23: 0 | U23: 0 | V23: 0 | W23: =IFERROR(ROUND(($O23*$T23),2)," ") -> 0 | X23: =IFERROR(ROUND(($P23*$U23),2),"") -> 0 | Y23: =IFERROR(ROUND(($Q23*$V23),2),"") -> 0 | AC23: =IFERROR(ROUND(($O23*$Z23),2)," ") -> 0 | AD23: =IFERROR(ROUND(($P23*$AA23),2),"") -> 0 | AE23: =IFERROR(ROUND(($Q23*$AB23),2),"") -> 0 | AI23: =IFERROR(ROUND(($O23*$AF23),2)," ") -> 0 | AJ23: =IFERROR(ROUND(($P23*$AG23),2),"") -> 0 | AK23: =IFERROR(ROUND(($Q23*$AH23),2),"") -> 0 | AL23: =IFERROR(ROUND(($W23+$AC23+$AI23),2),"") -> 0 | AM23: =IFERROR(ROUND(($X23+$AD23+$AJ23),2),"") -> 0 | AN23: =IFERROR(ROUND(($Y23+$AE23+$AK23),2),"") -> 0 | AO23: =SUM(AL23:AN23) -> 0 | AR23: =IFERROR(ROUND((S23-AO23-AP23),2),"") -> 13500 | AY23: =IFERROR(ROUND((AR23-AS23-AT23-AU23-AV23-AW23-AX23),2),"") -> 13500 | AZ23: Payroll | BA23: CAIZ, LEONILA D.
A24: =IF(B24="","",COUNTA($B$10:B24)) -> 15 | B24: 2026-01-0026 | C24: 46036 | E24: BALA, ANGEL D. | F24: ISD | G24: Information Officer I | H24: 11 | I24: O. ESETS | J24: OK | M24: =IFERROR(VLOOKUP($H24,'CODE 2'!$J:$K,2,FALSE)," ") -> 27000 | N24: =IFERROR(ROUND((M24/2),2),"") -> 13500 | O24: =IFERROR((M24/22)," ") -> 1227.2727 | P24: =IFERROR((O24/8),"") -> 153.40909 | Q24: =IFERROR((P24/60),"") -> 2.5568182 | R24: =IF(AZ24="Payroll","11","") -> 11 | S24: =IFERROR(ROUND((O24*R24),2)," ") -> 13500 | T24: 0 | U24: 0 | V24: 0 | W24: =IFERROR(ROUND(($O24*$T24),2)," ") -> 0 | X24: =IFERROR(ROUND(($P24*$U24),2),"") -> 0 | Y24: =IFERROR(ROUND(($Q24*$V24),2),"") -> 0 | AC24: =IFERROR(ROUND(($O24*$Z24),2)," ") -> 0 | AD24: =IFERROR(ROUND(($P24*$AA24),2),"") -> 0 | AE24: =IFERROR(ROUND(($Q24*$AB24),2),"") -> 0 | AI24: =IFERROR(ROUND(($O24*$AF24),2)," ") -> 0 | AJ24: =IFERROR(ROUND(($P24*$AG24),2),"") -> 0 | AK24: =IFERROR(ROUND(($Q24*$AH24),2),"") -> 0 | AL24: =IFERROR(ROUND(($W24+$AC24+$AI24),2),"") -> 0 | AM24: =IFERROR(ROUND(($X24+$AD24+$AJ24),2),"") -> 0 | AN24: =IFERROR(ROUND(($Y24+$AE24+$AK24),2),"") -> 0 | AO24: =SUM(AL24:AN24) -> 0 | AR24: =IFERROR(ROUND((S24-AO24-AP24),2),"") -> 13500 | AU24: 2000 | AY24: =IFERROR(ROUND((AR24-AS24-AT24-AU24-AV24-AW24-AX24),2),"") -> 11500 | AZ24: Payroll | BA24: CALDITO, CHARISSE D.
A25: =IF(B25="","",COUNTA($B$10:B25)) -> 16 | B25: 2026-01-0047 | C25: 46036 | E25: CAGUMBAY, LIYANNE M. | F25: ADO | G25: Administrative Asst. II | H25: =IF(AZ25="Payroll",VLOOKUP(E25,'CODE 2'!$R:$S,2,FALSE),"0") -> 8 | I25: GASS | J25: OK | M25: =IFERROR(VLOOKUP($H25,'CODE 2'!$J:$K,2,FALSE)," ") -> 19744 | N25: =IFERROR(ROUND((M25/2),2),"") -> 9872 | O25: =IFERROR((M25/22)," ") -> 897.45455 | P25: =IFERROR((O25/8),"") -> 112.18182 | Q25: =IFERROR((P25/60),"") -> 1.869697 | R25: =IF(AZ25="Payroll","11","") -> 11 | S25: =IFERROR(ROUND((O25*R25),2)," ") -> 9872 | T25: 0 | U25: 0 | V25: 0 | W25: =IFERROR(ROUND(($O25*$T25),2)," ") -> 0 | X25: =IFERROR(ROUND(($P25*$U25),2),"") -> 0 | Y25: =IFERROR(ROUND(($Q25*$V25),2),"") -> 0 | AC25: =IFERROR(ROUND(($O25*$Z25),2)," ") -> 0 | AD25: =IFERROR(ROUND(($P25*$AA25),2),"") -> 0 | AE25: =IFERROR(ROUND(($Q25*$AB25),2),"") -> 0 | AI25: =IFERROR(ROUND(($O25*$AF25),2)," ") -> 0 | AJ25: =IFERROR(ROUND(($P25*$AG25),2),"") -> 0 | AK25: =IFERROR(ROUND(($Q25*$AH25),2),"") -> 0 | AL25: =IFERROR(ROUND(($W25+$AC25+$AI25),2),"") -> 0 | AM25: =IFERROR(ROUND(($X25+$AD25+$AJ25),2),"") -> 0 | AN25: =IFERROR(ROUND(($Y25+$AE25+$AK25),2),"") -> 0 | AO25: =SUM(AL25:AN25) -> 0 | AR25: =IFERROR(ROUND((S25-AO25-AP25),2),"") -> 9872 | AY25: =IFERROR(ROUND((AR25-AS25-AT25-AU25-AV25-AW25-AX25),2),"") -> 9872 | AZ25: Payroll | BA25: CAPONGCOL, MARY JANE
A26: =IF(B26="","",COUNTA($B$10:B26)) -> 17 | B26: 2026-01-48 | C26: 46036 | E26: DE GUZMAN, SWEET JESSABEL M. | F26: ADO | G26: Executive Assistant II | H26: =IF(AZ26="Payroll",VLOOKUP(E26,'CODE 2'!$R:$S,2,FALSE),"0") -> 17 | I26: O. ESETS | J26: OK | M26: =IFERROR(VLOOKUP($H26,'CODE 2'!$J:$K,2,FALSE)," ") -> 43030 | N26: =IFERROR(ROUND((M26/2),2),"") -> 21515 | O26: =IFERROR((M26/22)," ") -> 1955.9091 | P26: =IFERROR((O26/8),"") -> 244.48864 | Q26: =IFERROR((P26/60),"") -> 4.0748106 | R26: =IF(AZ26="Payroll","11","") -> 11 | S26: =IFERROR(ROUND((O26*R26),2)," ") -> 21515 | T26: 0 | U26: 0 | V26: 0 | W26: =IFERROR(ROUND(($O26*$T26),2)," ") -> 0 | X26: =IFERROR(ROUND(($P26*$U26),2),"") -> 0 | Y26: =IFERROR(ROUND(($Q26*$V26),2),"") -> 0 | AC26: =IFERROR(ROUND(($O26*$Z26),2)," ") -> 0 | AD26: =IFERROR(ROUND(($P26*$AA26),2),"") -> 0 | AE26: =IFERROR(ROUND(($Q26*$AB26),2),"") -> 0 | AI26: =IFERROR(ROUND(($O26*$AF26),2)," ") -> 0 | AJ26: =IFERROR(ROUND(($P26*$AG26),2),"") -> 0 | AK26: =IFERROR(ROUND(($Q26*$AH26),2),"") -> 0 | AL26: =IFERROR(ROUND(($W26+$AC26+$AI26),2),"") -> 0 | AM26: =IFERROR(ROUND(($X26+$AD26+$AJ26),2),"") -> 0 | AN26: =IFERROR(ROUND(($Y26+$AE26+$AK26),2),"") -> 0 | AO26: =SUM(AL26:AN26) -> 0 | AR26: =IFERROR(ROUND((S26-AO26-AP26),2),"") -> 21515 | AY26: =IFERROR(ROUND((AR26-AS26-AT26-AU26-AV26-AW26-AX26),2),"") -> 21515 | AZ26: Payroll | BA26: CATIMBANG, SHANDEE FAY O.
A27: =IF(B27="","",COUNTA($B$10:B27)) -> 18 | B27: 2026-01-0037 | C27: 46036 | E27: SALVA, IRENE U | F27: BGT. | G27: Administrative Asst. II | H27: =IF(AZ27="Payroll",VLOOKUP(E27,'CODE 2'!$R:$S,2,FALSE),"0") -> 8 | I27: O. ESETS | J27: OK | M27: =IFERROR(VLOOKUP($H27,'CODE 2'!$J:$K,2,FALSE)," ") -> 19744 | N27: =IFERROR(ROUND((M27/2),2),"") -> 9872 | O27: =IFERROR((M27/22)," ") -> 897.45455 | P27: =IFERROR((O27/8),"") -> 112.18182 | Q27: =IFERROR((P27/60),"") -> 1.869697 | R27: =IF(AZ27="Payroll","11","") -> 11 | S27: =IFERROR(ROUND((O27*R27),2)," ") -> 9872 | T27: 0 | U27: 0 | V27: 0 | W27: =IFERROR(ROUND(($O27*$T27),2)," ") -> 0 | X27: =IFERROR(ROUND(($P27*$U27),2),"") -> 0 | Y27: =IFERROR(ROUND(($Q27*$V27),2),"") -> 0 | AC27: =IFERROR(ROUND(($O27*$Z27),2)," ") -> 0 | AD27: =IFERROR(ROUND(($P27*$AA27),2),"") -> 0 | AE27: =IFERROR(ROUND(($Q27*$AB27),2),"") -> 0 | AI27: =IFERROR(ROUND(($O27*$AF27),2)," ") -> 0 | AJ27: =IFERROR(ROUND(($P27*$AG27),2),"") -> 0 | AK27: =IFERROR(ROUND(($Q27*$AH27),2),"") -> 0 | AL27: =IFERROR(ROUND(($W27+$AC27+$AI27),2),"") -> 0 | AM27: =IFERROR(ROUND(($X27+$AD27+$AJ27),2),"") -> 0 | AN27: =IFERROR(ROUND(($Y27+$AE27+$AK27),2),"") -> 0 | AO27: =SUM(AL27:AN27) -> 0 | AR27: =IFERROR(ROUND((S27-AO27-AP27),2),"") -> 9872 | AY27: =IFERROR(ROUND((AR27-AS27-AT27-AU27-AV27-AW27-AX27),2),"") -> 9872 | AZ27: Payroll | BA27: CATUBAY, ELVIS JOHN L.
A28: =IF(B28="","",COUNTA($B$10:B28)) -> 19 | B28: 2026-01-0007 | C28: 46035 | E28: SASIS, BRINGKLY B. | F28: BGT. | G28: Administrative Asst. II | H28: =IF(AZ28="Payroll",VLOOKUP(E28,'CODE 2'!$R:$S,2,FALSE),"0") -> 0 | I28: CFIDP | J28: OK | M28: =IFERROR(VLOOKUP($H28,'CODE 2'!$J:$K,2,FALSE)," ") | N28: =IFERROR(ROUND((M28/2),2),"") | O28: =IFERROR((M28/22)," ") | P28: =IFERROR((O28/8),"") | Q28: =IFERROR((P28/60),"") | R28: =IF(AZ28="Payroll","11","") | S28: =IFERROR(ROUND((O28*R28),2)," ") | T28: 0 | U28: 0 | V28: 0 | W28: =IFERROR(ROUND(($O28*#REF!),2)," ") | X28: =IFERROR(ROUND(($P28*$U28),2),"") | Y28: =IFERROR(ROUND(($Q28*$V28),2),"") | AC28: =IFERROR(ROUND(($O28*$Z28),2)," ") | AD28: =IFERROR(ROUND(($P28*$AA28),2),"") | AE28: =IFERROR(ROUND(($Q28*$AB28),2),"") | AI28: =IFERROR(ROUND(($O28*$AF28),2)," ") | AJ28: =IFERROR(ROUND(($P28*$AG28),2),"") | AK28: =IFERROR(ROUND(($Q28*$AH28),2),"") | AL28: =IFERROR(ROUND(($W28+$AC28+$AI28),2),"") | AM28: =IFERROR(ROUND(($X28+$AD28+$AJ28),2),"") | AN28: =IFERROR(ROUND(($Y28+$AE28+$AK28),2),"") | AO28: =SUM(AL28:AN28) -> 0 | AR28: =IFERROR(ROUND((S28-AO28-AP28),2),"") | AY28: =IFERROR(ROUND((AR28-AS28-AT28-AU28-AV28-AW28-AX28),2),"") | AZ28: Voucher | BA28: CELOCIA, ROSELY-ANN G.
A29: =IF(B29="","",COUNTA($B$10:B29)) -> 20 | B29: 2026-01-0038 | C29: 46036 | E29: CAIZ, LEONILA D. | F29: BGT. | G29: Financial Analyst | I29: O. ESETS | M29: =IFERROR(VLOOKUP($H29,'CODE 2'!$J:$K,2,FALSE)," ") -> 50617 | N29: =IFERROR(ROUND((M29/2),2),"") -> 25308.5 | O29: =IFERROR((M29/22)," ") -> 2300.7727 | P29: =IFERROR((O29/8),"") -> 287.59659 | Q29: =IFERROR((P29/60),"") -> 4.7932765 | R29: =IF(AZ29="Payroll","11","") -> 11 | S29: =IFERROR(ROUND((O29*R29),2)," ") -> 25308.5 | T29: 5 | U29: 1 | V29: 43 | W29: =IFERROR(ROUND(($O29*$T29),2)," ") -> 11503.86 | X29: =IFERROR(ROUND(($P29*$U29),2),"") -> 287.6 | Y29: =IFERROR(ROUND(($Q29*$V29),2),"") -> 206.11 | AC29: =IFERROR(ROUND(($O29*$Z29),2)," ") -> 0 | AD29: =IFERROR(ROUND(($P29*$AA29),2),"") -> 0 | AE29: =IFERROR(ROUND(($Q29*$AB29),2),"") -> 0 | AI29: =IFERROR(ROUND(($O29*$AF29),2)," ") -> 0 | AJ29: =IFERROR(ROUND(($P29*$AG29),2),"") -> 0 | AK29: =IFERROR(ROUND(($Q29*$AH29),2),"") -> 0 | AL29: =IFERROR(ROUND(($W29+$AC29+$AI29),2),"") -> 11503.86 | AM29: =IFERROR(ROUND(($X29+$AD29+$AJ29),2),"") -> 287.6 | AN29: =IFERROR(ROUND(($Y29+$AE29+$AK29),2),"") -> 206.11 | AO29: =SUM(AL29:AN29) -> 11997.57 | AR29: =IFERROR(ROUND((S29-AO29-AP29),2),"") -> 13310.93 | AY29: =IFERROR(ROUND((AR29-AS29-AT29-AU29-AV29-AW29-AX29),2),"") -> 13310.93 | AZ29: Payroll | BA29: COMPLETO, CRIZANTO E.
A30: =IF(B30="","",COUNTA($B$10:B30)) -> 21 | B30: 2026-01-0039 | C30: 46036 | E30: SALVANIA, JEFFREY | F30: ACCTG. | G30: Administrative Asst. II | H30: =IF(AZ30="Payroll",VLOOKUP(E30,'CODE 2'!$R:$S,2,FALSE),"0") -> 8 | I30: O. ESETS | J30: OK | M30: =IFERROR(VLOOKUP($H30,'CODE 2'!$J:$K,2,FALSE)," ") -> 19744 | N30: =IFERROR(ROUND((M30/2),2),"") -> 9872 | O30: =IFERROR((M30/22)," ") -> 897.45455 | P30: =IFERROR((O30/8),"") -> 112.18182 | Q30: =IFERROR((P30/60),"") -> 1.869697 | R30: =IF(AZ30="Payroll","11","") -> 11 | S30: =IFERROR(ROUND((O30*R30),2)," ") -> 9872 | T30: 0 | U30: 0 | V30: 0 | W30: =IFERROR(ROUND(($O30*$T28),2)," ") -> 0 | X30: =IFERROR(ROUND(($P30*$U30),2),"") -> 0 | Y30: =IFERROR(ROUND(($Q30*$V30),2),"") -> 0 | AC30: =IFERROR(ROUND(($O30*$Z30),2)," ") -> 0 | AD30: =IFERROR(ROUND(($P30*$AA30),2),"") -> 0 | AE30: =IFERROR(ROUND(($Q30*$AB30),2),"") -> 0 | AI30: =IFERROR(ROUND(($O30*$AF30),2)," ") -> 0 | AJ30: =IFERROR(ROUND(($P30*$AG30),2),"") -> 0 | AK30: =IFERROR(ROUND(($Q30*$AH30),2),"") -> 0 | AL30: =IFERROR(ROUND(($W30+$AC30+$AI30),2),"") -> 0 | AM30: =IFERROR(ROUND(($X30+$AD30+$AJ30),2),"") -> 0 | AN30: =IFERROR(ROUND(($Y30+$AE30+$AK30),2),"") -> 0 | AO30: =SUM(AL30:AN30) -> 0 | AR30: =IFERROR(ROUND((S30-AO30-AP30),2),"") -> 9872 | AY30: =IFERROR(ROUND((AR30-AS30-AT30-AU30-AV30-AW30-AX30),2),"") -> 9872 | AZ30: Payroll | BA30: CORDOVA, JOEL M.
A31: =IF(B31="","",COUNTA($B$10:B31)) -> 22 | B31: 2026-01-0012 | C31: 46036 | E31: ESTAPON, LESLIE DC. | F31: ACCTG. | G31: Administrative Asst. II | H31: =IF(AZ31="Payroll",VLOOKUP(E31,'CODE 2'!$R:$S,2,FALSE),"0") -> 0 | I31: REVOLVING FUND | J31: OK | M31: =IFERROR(VLOOKUP($H31,'CODE 2'!$J:$K,2,FALSE)," ") | N31: =IFERROR(ROUND((M31/2),2),"") | O31: =IFERROR((M31/22)," ") | P31: =IFERROR((O31/8),"") | Q31: =IFERROR((P31/60),"") | R31: 11 | S31: =IFERROR(ROUND((O31*R31),2)," ") | T31: 0 | U31: 0 | V31: 18 | W31: =IFERROR(ROUND(($O31*$T31),2)," ") | X31: =IFERROR(ROUND(($P31*$U31),2),"") | Y31: =IFERROR(ROUND(($Q31*$V31),2),"") | AC31: =IFERROR(ROUND(($O31*$Z31),2)," ") | AD31: =IFERROR(ROUND(($P31*$AA31),2),"") | AE31: =IFERROR(ROUND(($Q31*$AB31),2),"") | AI31: =IFERROR(ROUND(($O31*$AF31),2)," ") | AJ31: =IFERROR(ROUND(($P31*$AG31),2),"") | AK31: =IFERROR(ROUND(($Q31*$AH31),2),"") | AL31: =IFERROR(ROUND(($W31+$AC31+$AI31),2),"") | AM31: =IFERROR(ROUND(($X31+$AD31+$AJ31),2),"") | AN31: =IFERROR(ROUND(($Y31+$AE31+$AK31),2),"") | AO31: =SUM(AL31:AN31) -> 0 | AR31: =IFERROR(ROUND((S31-AO31-AP31),2),"") | AY31: =IFERROR(ROUND((AR31-AS31-AT31-AU31-AV31-AW31-AX31),2),"") | AZ31: Voucher | BA31: CRUZ, CLAIRE JOYCE B.
A32: =IF(B32="","",COUNTA($B$10:B32)) -> 23 | B32: 2026-01-0040 | C32: 46036 | E32: MARTIN, ORLAN LEONARD E. | F32: ACCTG. | G32: Administrative Asst. II | H32: =IF(AZ32="Payroll",VLOOKUP(E32,'CODE 2'!$R:$S,2,FALSE),"0") -> 8 | I32: O. ESETS | J32: OK | M32: =IFERROR(VLOOKUP($H32,'CODE 2'!$J:$K,2,FALSE)," ") -> 19744 | N32: =IFERROR(ROUND((M32/2),2),"") -> 9872 | O32: =IFERROR((M32/22)," ") -> 897.45455 | P32: =IFERROR((O32/8),"") -> 112.18182 | Q32: =IFERROR((P32/60),"") -> 1.869697 | R32: 11 | S32: =IFERROR(ROUND((O32*R32),2)," ") -> 9872 | T32: 0 | U32: 0 | V32: 32 | W32: =IFERROR(ROUND(($O32*$T32),2)," ") -> 0 | X32: =IFERROR(ROUND(($P32*$U32),2),"") -> 0 | Y32: =IFERROR(ROUND(($Q32*$V32),2),"") -> 59.83 | AC32: =IFERROR(ROUND(($O32*$Z32),2)," ") -> 0 | AD32: =IFERROR(ROUND(($P32*$AA32),2),"") -> 0 | AE32: =IFERROR(ROUND(($Q32*$AB32),2),"") -> 0 | AI32: =IFERROR(ROUND(($O32*$AF32),2)," ") -> 0 | AJ32: =IFERROR(ROUND(($P32*$AG32),2),"") -> 0 | AK32: =IFERROR(ROUND(($Q32*$AH32),2),"") -> 0 | AL32: =IFERROR(ROUND(($W32+$AC32+$AI32),2),"") -> 0 | AM32: =IFERROR(ROUND(($X32+$AD32+$AJ32),2),"") -> 0 | AN32: =IFERROR(ROUND(($Y32+$AE32+$AK32),2),"") -> 59.83 | AO32: =SUM(AL32:AN32) -> 59.83 | AR32: =IFERROR(ROUND((S32-AO32-AP32),2),"") -> 9812.17 | AY32: =IFERROR(ROUND((AR32-AS32-AT32-AU32-AV32-AW32-AX32),2),"") -> 9812.17 | AZ32: Payroll | BA32: CUARTERON, JOSEN L.
A33: =IF(B33="","",COUNTA($B$10:B33)) -> 24 | B33: 2026-01-0004 | C33: 46035 | E33: MAGDARAOG, CHRISTINE NAZEL C. | F33: ACCTG. | G33: Administrative Asst. II | H33: =IF(AZ33="Payroll",VLOOKUP(E33,'CODE 2'!$R:$S,2,FALSE),"0") -> 0 | I33: CFIDP | J33: OK | M33: =IFERROR(VLOOKUP($H33,'CODE 2'!$J:$K,2,FALSE)," ") | N33: =IFERROR(ROUND((M33/2),2),"") | O33: =IFERROR((M33/22)," ") | P33: =IFERROR((O33/8),"") | Q33: =IFERROR((P33/60),"") | R33: 11 | S33: =IFERROR(ROUND((O33*R33),2)," ") | T33: 0 | U33: 0 | V33: 0 | W33: =IFERROR(ROUND(($O33*$T33),2)," ") | X33: =IFERROR(ROUND(($P33*$U33),2),"") | Y33: =IFERROR(ROUND(($Q33*$V33),2),"") | AC33: =IFERROR(ROUND(($O33*$Z33),2)," ") | AD33: =IFERROR(ROUND(($P33*$AA33),2),"") | AE33: =IFERROR(ROUND(($Q33*$AB33),2),"") | AI33: =IFERROR(ROUND(($O33*$AF33),2)," ") | AJ33: =IFERROR(ROUND(($P33*$AG33),2),"") | AK33: =IFERROR(ROUND(($Q33*$AH33),2),"") | AL33: =IFERROR(ROUND(($W33+$AC33+$AI33),2),"") | AM33: =IFERROR(ROUND(($X33+$AD33+$AJ33),2),"") | AN33: =IFERROR(ROUND(($Y33+$AE33+$AK33),2),"") | AO33: =SUM(AL33:AN33) -> 0 | AR33: =IFERROR(ROUND((S33-AO33-AP33),2),"") | AY33: =IFERROR(ROUND((AR33-AS33-AT33-AU33-AV33-AW33-AX33),2),"") | AZ33: Voucher | BA33: DE GUZMAN, SWEET JESSABEL M.
A34: =IF(B34="","",COUNTA($B$10:B34)) -> 25 | B34: 2026-01-0013 | C34: 46036 | E34: LOZANO, ADRIAN D. | F34: ACCTG. | G34: Administrative Asst. II | H34: =IF(AZ34="Payroll",VLOOKUP(E34,'CODE 2'!$R:$S,2,FALSE),"0") -> 0 | I34: REVOLVING FUND | J34: OK | M34: =IFERROR(VLOOKUP($H34,'CODE 2'!$J:$K,2,FALSE)," ") | N34: =IFERROR(ROUND((M34/2),2),"") | O34: =IFERROR((M34/22)," ") | P34: =IFERROR((O34/8),"") | Q34: =IFERROR((P34/60),"") | R34: 11 | S34: =IFERROR(ROUND((O34*R34),2)," ") | T34: 0 | U34: 0 | V34: 5 | W34: =IFERROR(ROUND(($O34*$T34),2)," ") | X34: =IFERROR(ROUND(($P34*$U34),2),"") | Y34: =IFERROR(ROUND(($Q34*$V34),2),"") | AC34: =IFERROR(ROUND(($O34*$Z34),2)," ") | AD34: =IFERROR(ROUND(($P34*$AA34),2),"") | AE34: =IFERROR(ROUND(($Q34*$AB34),2),"") | AI34: =IFERROR(ROUND(($O34*$AF34),2)," ") | AJ34: =IFERROR(ROUND(($P34*$AG34),2),"") | AK34: =IFERROR(ROUND(($Q34*$AH34),2),"") | AL34: =IFERROR(ROUND(($W34+$AC34+$AI34),2),"") | AM34: =IFERROR(ROUND(($X34+$AD34+$AJ34),2),"") | AN34: =IFERROR(ROUND(($Y34+$AE34+$AK34),2),"") | AO34: =SUM(AL34:AN34) -> 0 | AR34: =IFERROR(ROUND((S34-AO34-AP34),2),"") | AY34: =IFERROR(ROUND((AR34-AS34-AT34-AU34-AV34-AW34-AX34),2),"") | AZ34: Voucher | BA34: DITCHE, ALLIAH LYN P.
A35: =IF(B35="","",COUNTA($B$10:B35)) -> 26 | B35: 2026-01-0006 | C35: 46035 | E35: OLIVO, JENNA P. | F35: ACCTG. | G35: Technical Support Staff IV | H35: =IF(AZ35="Payroll",VLOOKUP(E35,'CODE 2'!$R:$S,2,FALSE),"0") -> 0 | I35: CFIDP | J35: OK | M35: =IFERROR(VLOOKUP($H35,'CODE 2'!$J:$K,2,FALSE)," ") | N35: =IFERROR(ROUND((M35/2),2),"") | O35: =IFERROR((M35/22)," ") | P35: =IFERROR((O35/8),"") | Q35: =IFERROR((P35/60),"") | R35: 11 | S35: =IFERROR(ROUND((O35*R35),2)," ") | T35: 0 | U35: 0 | V35: 0 | W35: =IFERROR(ROUND(($O35*$T35),2)," ") | X35: =IFERROR(ROUND(($P35*$U35),2),"") | Y35: =IFERROR(ROUND(($Q35*$V35),2),"") | AC35: =IFERROR(ROUND(($O35*$Z35),2)," ") | AD35: =IFERROR(ROUND(($P35*$AA35),2),"") | AE35: =IFERROR(ROUND(($Q35*$AB35),2),"") | AI35: =IFERROR(ROUND(($O35*$AF35),2)," ") | AJ35: =IFERROR(ROUND(($P35*$AG35),2),"") | AK35: =IFERROR(ROUND(($Q35*$AH35),2),"") | AL35: =IFERROR(ROUND(($W35+$AC35+$AI35),2),"") | AM35: =IFERROR(ROUND(($X35+$AD35+$AJ35),2),"") | AN35: =IFERROR(ROUND(($Y35+$AE35+$AK35),2),"") | AO35: =SUM(AL35:AN35) -> 0 | AR35: =IFERROR(ROUND((S35-AO35-AP35),2),"") | AY35: =IFERROR(ROUND((AR35-AS35-AT35-AU35-AV35-AW35-AX35),2),"") | AZ35: Voucher | BA35: EMBALZADO, SHERYL P.
A36: =IF(B36="","",COUNTA($B$10:B36)) -> 27 | B36: 2026-01-0005 | C36: 46035 | E36: CALDITO, CHARISSE D. | F36: ACCTG. | G36: Administrative Asst. II | H36: =IF(AZ36="Payroll",VLOOKUP(E36,'CODE 2'!$R:$S,2,FALSE),"0") -> 0 | I36: CFIDP | J36: OK | M36: =IFERROR(VLOOKUP($H36,'CODE 2'!$J:$K,2,FALSE)," ") | N36: =IFERROR(ROUND((M36/2),2),"") | O36: =IFERROR((M36/22)," ") | P36: =IFERROR((O36/8),"") | Q36: =IFERROR((P36/60),"") | R36: 11 | S36: =IFERROR(ROUND((O36*R36),2)," ") | T36: 0 | U36: 0 | V36: 29 | W36: =IFERROR(ROUND(($O36*$T36),2)," ") | X36: =IFERROR(ROUND(($P36*$U36),2),"") | Y36: =IFERROR(ROUND(($Q36*$V36),2),"") | AC36: =IFERROR(ROUND(($O36*$Z36),2)," ") | AD36: =IFERROR(ROUND(($P36*$AA36),2),"") | AE36: =IFERROR(ROUND(($Q36*$AB36),2),"") | AI36: =IFERROR(ROUND(($O36*$AF36),2)," ") | AJ36: =IFERROR(ROUND(($P36*$AG36),2),"") | AK36: =IFERROR(ROUND(($Q36*$AH36),2),"") | AL36: =IFERROR(ROUND(($W36+$AC36+$AI36),2),"") | AM36: =IFERROR(ROUND(($X36+$AD36+$AJ36),2),"") | AN36: =IFERROR(ROUND(($Y36+$AE36+$AK36),2),"") | AO36: =SUM(AL36:AN36) -> 0 | AR36: =IFERROR(ROUND((S36-AO36-AP36),2),"") | AY36: =IFERROR(ROUND((AR36-AS36-AT36-AU36-AV36-AW36-AX36),2),"") | AZ36: Voucher | BA36: ESMER, GLECY R.
A37: =IF(B37="","",COUNTA($B$10:B37)) -> 28 | B37: 2026-01-0041 | C37: 46036 | E37: YUGA, MYKA ALEXZA B. | F37: ACCTG. | G37: Administrative Asst. II | H37: =IF(AZ37="Payroll",VLOOKUP(E37,'CODE 2'!$R:$S,2,FALSE),"0") -> 8 | I37: O. ESETS | J37: OK | M37: =IFERROR(VLOOKUP($H37,'CODE 2'!$J:$K,2,FALSE)," ") -> 19744 | N37: =IFERROR(ROUND((M37/2),2),"") -> 9872 | O37: =IFERROR((M37/22)," ") -> 897.45455 | P37: =IFERROR((O37/8),"") -> 112.18182 | Q37: =IFERROR((P37/60),"") -> 1.869697 | R37: 11 | S37: =IFERROR(ROUND((O37*R37),2)," ") -> 9872 | T37: 0 | U37: 0 | V37: 0 | W37: =IFERROR(ROUND(($O37*$T37),2)," ") -> 0 | X37: =IFERROR(ROUND(($P37*$U37),2),"") -> 0 | Y37: =IFERROR(ROUND(($Q37*$V37),2),"") -> 0 | AC37: =IFERROR(ROUND(($O37*$Z37),2)," ") -> 0 | AD37: =IFERROR(ROUND(($P37*$AA37),2),"") -> 0 | AE37: =IFERROR(ROUND(($Q37*$AB37),2),"") -> 0 | AI37: =IFERROR(ROUND(($O37*$AF37),2)," ") -> 0 | AJ37: =IFERROR(ROUND(($P37*$AG37),2),"") -> 0 | AK37: =IFERROR(ROUND(($Q37*$AH37),2),"") -> 0 | AL37: =IFERROR(ROUND(($W37+$AC37+$AI37),2),"") -> 0 | AM37: =IFERROR(ROUND(($X37+$AD37+$AJ37),2),"") -> 0 | AN37: =IFERROR(ROUND(($Y37+$AE37+$AK37),2),"") -> 0 | AO37: =SUM(AL37:AN37) -> 0 | AR37: =IFERROR(ROUND((S37-AO37-AP37),2),"") -> 9872 | AY37: =IFERROR(ROUND((AR37-AS37-AT37-AU37-AV37-AW37-AX37),2),"") -> 9872 | AZ37: Payroll | BA37: ESTAPON, LESLIE DC.
A38: =IF(B38="","",COUNTA($B$10:B38)) -> 29 | B38: 2026-01-0003 | C38: 46035 | E38: EMBALZADO, SHERYL P. | F38: CASHIER | G38: Administrative Asst. II | H38: =IF(AZ38="Payroll",VLOOKUP(E38,'CODE 2'!$R:$S,2,FALSE),"0") -> 0 | I38: CFIDP | J38: OK | M38: =IFERROR(VLOOKUP($H38,'CODE 2'!$J:$K,2,FALSE)," ") | N38: =IFERROR(ROUND((M38/2),2),"") | O38: =IFERROR((M38/22)," ") | P38: =IFERROR((O38/8),"") | Q38: =IFERROR((P38/60),"") | R38: 11 | S38: =IFERROR(ROUND((O38*R38),2)," ") | T38: 0 | U38: 0 | V38: 0 | W38: =IFERROR(ROUND(($O38*$T38),2)," ") | X38: =IFERROR(ROUND(($P38*$U38),2),"") | Y38: =IFERROR(ROUND(($Q38*$V38),2),"") | AC38: =IFERROR(ROUND(($O38*$Z38),2)," ") | AD38: =IFERROR(ROUND(($P38*$AA38),2),"") | AE38: =IFERROR(ROUND(($Q38*$AB38),2),"") | AI38: =IFERROR(ROUND(($O38*$AF38),2)," ") | AJ38: =IFERROR(ROUND(($P38*$AG38),2),"") | AK38: =IFERROR(ROUND(($Q38*$AH38),2),"") | AL38: =IFERROR(ROUND(($W38+$AC38+$AI38),2),"") | AM38: =IFERROR(ROUND(($X38+$AD38+$AJ38),2),"") | AN38: =IFERROR(ROUND(($Y38+$AE38+$AK38),2),"") | AO38: =SUM(AL38:AN38) -> 0 | AR38: =IFERROR(ROUND((S38-AO38+AP38),2),"") | AY38: =IFERROR(ROUND((AR38-AS38-AT38-AU38-AV38-AW38-AX38),2),"") | AZ38: Voucher | BA38: FERNANDEZ, YARI E.
A39: =IF(B39="","",COUNTA($B$10:B39)) -> 30 | B39: 2026-01-0049 | C39: 46036 | E39: CRUZ, CLAIRE JOYCE B. | F39: IAU | G39: Administrative Asst. II | H39: =IF(AZ39="Payroll",VLOOKUP(E39,'CODE 2'!$R:$S,2,FALSE),"0") -> 8 | I39: O. ESETS | J39: OK | M39: =IFERROR(VLOOKUP($H39,'CODE 2'!$J:$K,2,FALSE)," ") -> 19744 | N39: =IFERROR(ROUND((M39/2),2),"") -> 9872 | O39: =IFERROR((M39/22)," ") -> 897.45455 | P39: =IFERROR((O39/8),"") -> 112.18182 | Q39: =IFERROR((P39/60),"") -> 1.869697 | R39: =IF(AZ39="Payroll","11","") -> 11 | S39: =IFERROR(ROUND((O39*R39),2)," ") -> 9872 | T39: 0 | U39: 0 | V39: 0 | W39: =IFERROR(ROUND(($O39*$T39),2)," ") -> 0 | X39: =IFERROR(ROUND(($P39*$U39),2),"") -> 0 | Y39: =IFERROR(ROUND(($Q39*$V39),2),"") -> 0 | AC39: =IFERROR(ROUND(($O39*$Z39),2)," ") -> 0 | AD39: =IFERROR(ROUND(($P39*$AA39),2),"") -> 0 | AE39: =IFERROR(ROUND(($Q39*$AB39),2),"") -> 0 | AI39: =IFERROR(ROUND(($O39*$AF39),2)," ") -> 0 | AJ39: =IFERROR(ROUND(($P39*$AG39),2),"") -> 0 | AK39: =IFERROR(ROUND(($Q39*$AH39),2),"") -> 0 | AL39: =IFERROR(ROUND(($W39+$AC39+$AI39),2),"") -> 0 | AM39: =IFERROR(ROUND(($X39+$AD39+$AJ39),2),"") -> 0 | AN39: =IFERROR(ROUND(($Y39+$AE39+$AK39),2),"") -> 0 | AO39: =SUM(AL39:AN39) -> 0 | AR39: =IFERROR(ROUND((S39-AO39-AP39),2),"") -> 9872 | AY39: =IFERROR(ROUND((AR39-AS39-AT39-AU39-AV39-AW39-AX39),2),"") -> 9872 | AZ39: Payroll | BA39: FRANCISCO, ULYSSES H.
A40: =IF(B40="","",COUNTA($B$10:B40)) -> 31 | B40: 2026-01-0050 | C40: 46036 | E40: MARTIN, SHAIRA LEA E. | F40: IAU | G40: Administrative Asst. II | H40: =IF(AZ40="Payroll",VLOOKUP(E40,'CODE 2'!$R:$S,2,FALSE),"0") -> 8 | I40: O. ESETS | J40: OK | M40: =IFERROR(VLOOKUP($H40,'CODE 2'!$J:$K,2,FALSE)," ") -> 19744 | N40: =IFERROR(ROUND((M40/2),2),"") -> 9872 | O40: =IFERROR((M40/22)," ") -> 897.45455 | P40: =IFERROR((O40/8),"") -> 112.18182 | Q40: =IFERROR((P40/60),"") -> 1.869697 | R40: 11 | S40: =IFERROR(ROUND((O40*R40),2)," ") -> 9872 | T40: 0 | U40: 0 | V40: 0 | W40: =IFERROR(ROUND(($O40*$T40),2)," ") -> 0 | X40: =IFERROR(ROUND(($P40*$U40),2),"") -> 0 | Y40: =IFERROR(ROUND(($Q40*$V40),2),"") -> 0 | AC40: =IFERROR(ROUND(($O40*$Z40),2)," ") -> 0 | AD40: =IFERROR(ROUND(($P40*$AA40),2),"") -> 0 | AE40: =IFERROR(ROUND(($Q40*$AB40),2),"") -> 0 | AI40: =IFERROR(ROUND(($O40*$AF40),2)," ") -> 0 | AJ40: =IFERROR(ROUND(($P40*$AG40),2),"") -> 0 | AK40: =IFERROR(ROUND(($Q40*$AH40),2),"") -> 0 | AL40: =IFERROR(ROUND(($W40+$AC40+$AI40),2),"") -> 0 | AM40: =IFERROR(ROUND(($X40+$AD40+$AJ40),2),"") -> 0 | AN40: =IFERROR(ROUND(($Y40+$AE40+$AK40),2),"") -> 0 | AO40: =SUM(AL40:AN40) -> 0 | AR40: =IFERROR(ROUND((S40-AO40+AP40),2),"") -> 9872 | AY40: =IFERROR(ROUND((AR40-AS40-AT40-AU40-AV40-AW40-AX40),2),"") -> 9872 | AZ40: Payroll | BA40: GAGUCAS, MICHAEL B.
A41: =IF(B41="","",COUNTA($B$10:B41)) -> 32 | B41: 2026-01-0059 | C41: 46036 | E41: CAPONGCOL, MARY JANE | F41: RCRDS | G41: Administrative Asst. II | H41: =IF(AZ41="Payroll",VLOOKUP(E41,'CODE 2'!$R:$S,2,FALSE),"0") -> 8 | I41: O. ESETS | J41: OK | M41: =IFERROR(VLOOKUP($H41,'CODE 2'!$J:$K,2,FALSE)," ") -> 19744 | N41: =IFERROR(ROUND((M41/2),2),"") -> 9872 | O41: =IFERROR((M41/22)," ") -> 897.45455 | P41: =IFERROR((O41/8),"") -> 112.18182 | Q41: =IFERROR((P41/60),"") -> 1.869697 | R41: =IF(AZ41="Payroll","11","") -> 11 | S41: =IFERROR(ROUND((O41*R41),2)," ") -> 9872 | T41: 0 | U41: 0 | V41: 0 | W41: =IFERROR(ROUND(($O41*$T41),2)," ") -> 0 | X41: =IFERROR(ROUND(($P41*$U41),2),"") -> 0 | Y41: =IFERROR(ROUND(($Q41*$V41),2),"") -> 0 | AC41: =IFERROR(ROUND(($O41*$Z41),2)," ") -> 0 | AD41: =IFERROR(ROUND(($P41*$AA41),2),"") -> 0 | AE41: =IFERROR(ROUND(($Q41*$AB41),2),"") -> 0 | AI41: =IFERROR(ROUND(($O41*$AF41),2)," ") -> 0 | AJ41: =IFERROR(ROUND(($P41*$AG41),2),"") -> 0 | AK41: =IFERROR(ROUND(($Q41*$AH41),2),"") -> 0 | AL41: =IFERROR(ROUND(($W41+$AC41+$AI41),2),"") -> 0 | AM41: =IFERROR(ROUND(($X41+$AD41+$AJ41),2),"") -> 0 | AN41: =IFERROR(ROUND(($Y41+$AE41+$AK41),2),"") -> 0 | AO41: =SUM(AL41:AN41) -> 0 | AR41: =IFERROR(ROUND((S41-AO41+AP41),2),"") -> 9872 | AU41: 2000 | AV41: 461.39 | AY41: =IFERROR(ROUND((AR41-AS41-AT41-AU41-AV41-AW41-AX41),2),"") -> 7410.61 | AZ41: Payroll | BA41: GALABAY, CHRISTIANEL B.
A42: =IF(B42="","",COUNTA($B$10:B42)) -> 33 | B42: 2026-01-0058 | C42: 46036 | E42: FERNANDEZ, YARI E. | F42: RCRDS | G42: Administrative Asst. II | H42: =IF(AZ42="Payroll",VLOOKUP(E42,'CODE 2'!$R:$S,2,FALSE),"0") -> 8 | I42: O. ESETS | J42: OK | M42: =IFERROR(VLOOKUP($H42,'CODE 2'!$J:$K,2,FALSE)," ") -> 19744 | N42: =IFERROR(ROUND((M42/2),2),"") -> 9872 | O42: =IFERROR((M42/22)," ") -> 897.45455 | P42: =IFERROR((O42/8),"") -> 112.18182 | Q42: =IFERROR((P42/60),"") -> 1.869697 | R42: =IF(AZ42="Payroll","11","") -> 11 | S42: =IFERROR(ROUND((O42*R42),2)," ") -> 9872 | T42: 0 | U42: 4 | V42: 58 | W42: =IFERROR(ROUND(($O42*$T42),2)," ") -> 0 | X42: =IFERROR(ROUND(($P42*$U42),2),"") -> 448.73 | Y42: =IFERROR(ROUND(($Q42*$V42),2),"") -> 108.44 | AC42: =IFERROR(ROUND(($O42*$Z42),2)," ") -> 0 | AD42: =IFERROR(ROUND(($P42*$AA42),2),"") -> 0 | AE42: =IFERROR(ROUND(($Q42*$AB42),2),"") -> 0 | AI42: =IFERROR(ROUND(($O42*$AF42),2)," ") -> 0 | AJ42: =IFERROR(ROUND(($P42*$AG42),2),"") -> 0 | AK42: =IFERROR(ROUND(($Q42*$AH42),2),"") -> 0 | AL42: =IFERROR(ROUND(($W42+$AC42+$AI42),2),"") -> 0 | AM42: =IFERROR(ROUND(($X42+$AD42+$AJ42),2),"") -> 448.73 | AN42: =IFERROR(ROUND(($Y42+$AE42+$AK42),2),"") -> 108.44 | AO42: =SUM(AL42:AN42) -> 557.17 | AR42: =IFERROR(ROUND((S42-AO42-AP42),2),"") -> 9314.83 | AY42: =IFERROR(ROUND((AR42-AS42-AT42-AU42-AV42-AW42-AX42),2),"") -> 9314.83 | AZ42: Payroll | BA42: GAMBOA, ELGIE F.
A43: =IF(B43="","",COUNTA($B$10:B43)) -> 34 | B43: 2026-01-0062 | C43: 46036 | E43: CUARTERON, JOSEN L. | F43: GSS | G43: Administrative Asst. I | H43: =IF(AZ43="Payroll",VLOOKUP(E43,'CODE 2'!$R:$S,2,FALSE),"0") -> 7 | I43: O. ESETS | J43: OK | M43: =IFERROR(VLOOKUP($H43,'CODE 2'!$J:$K,2,FALSE)," ") -> 18620 | N43: =IFERROR(ROUND((M43/2),2),"") -> 9310 | O43: =IFERROR((M43/22)," ") -> 846.36364 | P43: =IFERROR((O43/8),"") -> 105.79545 | Q43: =IFERROR((P43/60),"") -> 1.7632576 | R43: =IF(AZ43="Payroll","11","") -> 11 | S43: =IFERROR(ROUND((O43*R43),2)," ") -> 9310 | T43: 0 | U43: 0 | V43: 37 | W43: =IFERROR(ROUND(($O43*$T43),2)," ") -> 0 | X43: =IFERROR(ROUND(($P43*$U43),2),"") -> 0 | Y43: =IFERROR(ROUND(($Q43*$V43),2),"") -> 65.24 | AC43: =IFERROR(ROUND(($O43*$Z43),2)," ") -> 0 | AD43: =IFERROR(ROUND(($P43*$AA43),2),"") -> 0 | AE43: =IFERROR(ROUND(($Q43*$AB43),2),"") -> 0 | AI43: =IFERROR(ROUND(($O43*$AF43),2)," ") -> 0 | AJ43: =IFERROR(ROUND(($P43*$AG43),2),"") -> 0 | AK43: =IFERROR(ROUND(($Q43*$AH43),2),"") -> 0 | AL43: =IFERROR(ROUND(($W43+$AC43+$AI43),2),"") -> 0 | AM43: =IFERROR(ROUND(($X43+$AD43+$AJ43),2),"") -> 0 | AN43: =IFERROR(ROUND(($Y43+$AE43+$AK43),2),"") -> 65.24 | AO43: =SUM(AL43:AN43) -> 65.24 | AR43: =IFERROR(ROUND((S43-AO43-AP43),2),"") -> 9244.76 | AY43: =IFERROR(ROUND((AR43-AS43-AT43-AU43-AV43-AW43-AX43),2),"") -> 9244.76 | AZ43: Payroll | BA43: GUTIERREZ, DACHIEL P.
A44: =IF(B44="","",COUNTA($B$10:B44)) -> 35 | B44: 2026-01-0060 | C44: 46036 | E44: CATUBAY, ELVIS JOHN L. | F44: GSS | G44: Administrative Asst. II | H44: =IF(AZ44="Payroll",VLOOKUP(E44,'CODE 2'!$R:$S,2,FALSE),"0") -> 8 | I44: O. ESETS | J44: OK | M44: =IFERROR(VLOOKUP($H44,'CODE 2'!$J:$K,2,FALSE)," ") -> 19744 | N44: =IFERROR(ROUND((M44/2),2),"") -> 9872 | O44: =IFERROR((M44/22)," ") -> 897.45455 | P44: =IFERROR((O44/8),"") -> 112.18182 | Q44: =IFERROR((P44/60),"") -> 1.869697 | R44: =IF(AZ44="Payroll","11","") -> 11 | S44: =IFERROR(ROUND((O44*R44),2)," ") -> 9872 | T44: 1 | U44: 0 | V44: 0 | W44: =IFERROR(ROUND(($O44*$T44),2)," ") -> 897.45 | X44: =IFERROR(ROUND(($P44*$U44),2),"") -> 0 | Y44: =IFERROR(ROUND(($Q44*$V44),2),"") -> 0 | AC44: =IFERROR(ROUND(($O44*$Z44),2)," ") -> 0 | AD44: =IFERROR(ROUND(($P44*$AA44),2),"") -> 0 | AE44: =IFERROR(ROUND(($Q44*$AB44),2),"") -> 0 | AI44: =IFERROR(ROUND(($O44*$AF44),2)," ") -> 0 | AJ44: =IFERROR(ROUND(($P44*$AG44),2),"") -> 0 | AK44: =IFERROR(ROUND(($Q44*$AH44),2),"") -> 0 | AL44: =IFERROR(ROUND(($W44+$AC44+$AI44),2),"") -> 897.45 | AM44: =IFERROR(ROUND(($X44+$AD44+$AJ44),2),"") -> 0 | AN44: =IFERROR(ROUND(($Y44+$AE44+$AK44),2),"") -> 0 | AO44: =SUM(AL44:AN44) -> 897.45 | AR44: =IFERROR(ROUND((S44-AO44-AP44),2),"") -> 8974.55 | AY44: =IFERROR(ROUND((AR44-AS44-AT44-AU44-AV44-AW44-AX44),2),"") -> 8974.55 | AZ44: Payroll | BA44: GUZMAN, JESSA MAE G.
A45: =IF(B45="","",COUNTA($B$10:B45)) -> 36 | B45: 2026-01-0063 | C45: 46036 | E45: MARCELO, FERDINAND S. | F45: GSS | G45: Administrative Asst. I | H45: =IF(AZ45="Payroll",VLOOKUP(E45,'CODE 2'!$R:$S,2,FALSE),"0") -> 7 | I45: O. ESETS | M45: =IFERROR(VLOOKUP($H45,'CODE 2'!$J:$K,2,FALSE)," ") -> 18620 | N45: =IFERROR(ROUND((M45/2),2),"") -> 9310 | O45: =IFERROR((M45/22)," ") -> 846.36364 | P45: =IFERROR((O45/8),"") -> 105.79545 | Q45: =IFERROR((P45/60),"") -> 1.7632576 | R45: =IF(AZ45="Payroll","11","") -> 11 | S45: =IFERROR(ROUND((O45*R45),2)," ") -> 9310 | T45: 0 | U45: 0 | V45: 0 | W45: =IFERROR(ROUND(($O45*$T45),2)," ") -> 0 | X45: =IFERROR(ROUND(($P45*$U45),2),"") -> 0 | Y45: =IFERROR(ROUND(($Q45*$V45),2),"") -> 0 | AC45: =IFERROR(ROUND(($O45*$Z45),2)," ") -> 0 | AD45: =IFERROR(ROUND(($P45*$AA45),2),"") -> 0 | AE45: =IFERROR(ROUND(($Q45*$AB45),2),"") -> 0 | AI45: =IFERROR(ROUND(($O45*$AF45),2)," ") -> 0 | AJ45: =IFERROR(ROUND(($P45*$AG45),2),"") -> 0 | AK45: =IFERROR(ROUND(($Q45*$AH45),2),"") -> 0 | AL45: =IFERROR(ROUND(($W45+$AC45+$AI45),2),"") -> 0 | AM45: =IFERROR(ROUND(($X45+$AD45+$AJ45),2),"") -> 0 | AN45: =IFERROR(ROUND(($Y45+$AE45+$AK45),2),"") -> 0 | AO45: =SUM(AL45:AN45) -> 0 | AR45: =IFERROR(ROUND((S45-AO45-AP45),2),"") -> 9310 | AY45: =IFERROR(ROUND((AR45-AS45-AT45-AU45-AV45-AW45-AX45),2),"") -> 9310 | AZ45: Payroll | BA45: LAMPAS, CHRISTIAN JOSEPH P
A46: =IF(B46="","",COUNTA($B$10:B46)) -> 37 | B46: 2026-01-0066 | C46: 46036 | E46: TAPIADOR, JACKSON T. | F46: GSS | G46: Administrative Asst. I | H46: =IF(AZ46="Payroll",VLOOKUP(E46,'CODE 2'!$R:$S,2,FALSE),"0") -> 7 | I46: O. ESETS | M46: =IFERROR(VLOOKUP($H46,'CODE 2'!$J:$K,2,FALSE)," ") -> 18620 | N46: =IFERROR(ROUND((M46/2),2),"") -> 9310 | O46: =IFERROR((M46/22)," ") -> 846.36364 | P46: =IFERROR((O46/8),"") -> 105.79545 | Q46: =IFERROR((P46/60),"") -> 1.7632576 | R46: =IF(AZ46="Payroll","11","") -> 11 | S46: =IFERROR(ROUND((O46*R46),2)," ") -> 9310 | T46: 0 | U46: 0 | V46: 0 | W46: =IFERROR(ROUND(($O46*$T46),2)," ") -> 0 | X46: =IFERROR(ROUND(($P46*$U46),2),"") -> 0 | Y46: =IFERROR(ROUND(($Q46*$V46),2),"") -> 0 | AC46: =IFERROR(ROUND(($O46*$Z46),2)," ") -> 0 | AD46: =IFERROR(ROUND(($P46*$AA46),2),"") -> 0 | AE46: =IFERROR(ROUND(($Q46*$AB46),2),"") -> 0 | AI46: =IFERROR(ROUND(($O46*$AF46),2)," ") -> 0 | AJ46: =IFERROR(ROUND(($P46*$AG46),2),"") -> 0 | AK46: =IFERROR(ROUND(($Q46*$AH46),2),"") -> 0 | AL46: =IFERROR(ROUND(($W46+$AC46+$AI46),2),"") -> 0 | AM46: =IFERROR(ROUND(($X46+$AD46+$AJ46),2),"") -> 0 | AN46: =IFERROR(ROUND(($Y46+$AE46+$AK46),2),"") -> 0 | AO46: =SUM(AL46:AN46) -> 0 | AR46: =IFERROR(ROUND((S46-AO46-AP46),2),"") -> 9310 | AY46: =IFERROR(ROUND((AR46-AS46-AT46-AU46-AV46-AW46-AX46),2),"") -> 9310 | AZ46: Payroll | BA46: LIM, KLEIN ANSON G.
A47: =IF(B47="","",COUNTA($B$10:B47)) -> 38 | B47: 2026-01-0064 | C47: 46036 | E47: GAMBOA, ELGIE F. | F47: GSS | G47: Administrative Asst. I | H47: =IF(AZ47="Payroll",VLOOKUP(E47,'CODE 2'!$R:$S,2,FALSE),"0") -> 7 | I47: O. ESETS | M47: =IFERROR(VLOOKUP($H47,'CODE 2'!$J:$K,2,FALSE)," ") -> 18620 | N47: =IFERROR(ROUND((M47/2),2),"") -> 9310 | O47: =IFERROR((M47/22)," ") -> 846.36364 | P47: =IFERROR((O47/8),"") -> 105.79545 | Q47: =IFERROR((P47/60),"") -> 1.7632576 | R47: =IF(AZ47="Payroll","11","") -> 11 | S47: =IFERROR(ROUND((O47*R47),2)," ") -> 9310 | T47: 3 | U47: 0 | V47: 0 | W47: =IFERROR(ROUND(($O47*$T47),2)," ") -> 2539.09 | X47: =IFERROR(ROUND(($P47*$U47),2),"") -> 0 | Y47: =IFERROR(ROUND(($Q47*$V47),2),"") -> 0 | AC47: =IFERROR(ROUND(($O47*$Z47),2)," ") -> 0 | AD47: =IFERROR(ROUND(($P47*$AA47),2),"") -> 0 | AE47: =IFERROR(ROUND(($Q47*$AB47),2),"") -> 0 | AI47: =IFERROR(ROUND(($O47*$AF47),2)," ") -> 0 | AJ47: =IFERROR(ROUND(($P47*$AG47),2),"") -> 0 | AK47: =IFERROR(ROUND(($Q47*$AH47),2),"") -> 0 | AL47: =IFERROR(ROUND(($W47+$AC47+$AI47),2),"") -> 2539.09 | AM47: =IFERROR(ROUND(($X47+$AD47+$AJ47),2),"") -> 0 | AN47: =IFERROR(ROUND(($Y47+$AE47+$AK47),2),"") -> 0 | AO47: =SUM(AL47:AN47) -> 2539.09 | AR47: =IFERROR(ROUND((S47-AO47-AP47),2),"") -> 6770.91 | AY47: =IFERROR(ROUND((AR47-AS47-AT47-AU47-AV47-AW47-AX47),2),"") -> 6770.91 | AZ47: Payroll | BA47: LIPAN, AGNES J.
A48: =IF(B48="","",COUNTA($B$10:B48)) -> 39 | B48: 2026-01-0065 | C48: 46036 | E48: TORIO, MARLON P. | F48: GSS | G48: Administrative Asst. I (Bus Driver) | H48: =IF(AZ48="Payroll",VLOOKUP(E48,'CODE 2'!$R:$S,2,FALSE),"0") -> 7 | I48: O. ESETS | M48: =IFERROR(VLOOKUP($H48,'CODE 2'!$J:$K,2,FALSE)," ") -> 18620 | N48: =IFERROR(ROUND((M48/2),2),"") -> 9310 | O48: =IFERROR((M48/22)," ") -> 846.36364 | P48: =IFERROR((O48/8),"") -> 105.79545 | Q48: =IFERROR((P48/60),"") -> 1.7632576 | R48: =IF(AZ48="Payroll","11","") -> 11 | S48: =IFERROR(ROUND((O48*R48),2)," ") -> 9310 | T48: 0 | U48: 0 | V48: 0 | W48: =IFERROR(ROUND(($O48*$T48),2)," ") -> 0 | X48: =IFERROR(ROUND(($P48*$U48),2),"") -> 0 | Y48: =IFERROR(ROUND(($Q48*$V48),2),"") -> 0 | AC48: =IFERROR(ROUND(($O48*$Z48),2)," ") -> 0 | AD48: =IFERROR(ROUND(($P48*$AA48),2),"") -> 0 | AE48: =IFERROR(ROUND(($Q48*$AB48),2),"") -> 0 | AI48: =IFERROR(ROUND(($O48*$AF48),2)," ") -> 0 | AJ48: =IFERROR(ROUND(($P48*$AG48),2),"") -> 0 | AK48: =IFERROR(ROUND(($Q48*$AH48),2),"") -> 0 | AL48: =IFERROR(ROUND(($W48+$AC48+$AI48),2),"") -> 0 | AM48: =IFERROR(ROUND(($X48+$AD48+$AJ48),2),"") -> 0 | AN48: =IFERROR(ROUND(($Y48+$AE48+$AK48),2),"") -> 0 | AO48: =SUM(AL48:AN48) -> 0 | AR48: =IFERROR(ROUND((S48-AO48+AP48),2),"") -> 9310 | AY48: =IFERROR(ROUND((AR48-AS48-AT48-AU48-AV48-AW48-AX48),2),"") -> 9310 | AZ48: Payroll | BA48: LORENA, SUSAN G
A49: =IF(B49="","",COUNTA($B$10:B49)) -> 40 | B49: 2026-01-0067 | C49: 46036 | E49: NAMOCA, SANTIAGO J. | F49: GSS | G49: Administrative Asst. I (Bus Driver) | H49: =IF(AZ49="Payroll",VLOOKUP(E49,'CODE 2'!$R:$S,2,FALSE),"0") -> 7 | I49: O. ESETS | M49: =IFERROR(VLOOKUP($H49,'CODE 2'!$J:$K,2,FALSE)," ") -> 18620 | N49: =IFERROR(ROUND((M49/2),2),"") -> 9310 | O49: =IFERROR((M49/22)," ") -> 846.36364 | P49: =IFERROR((O49/8),"") -> 105.79545 | Q49: =IFERROR((P49/60),"") -> 1.7632576 | R49: =IF(AZ49="Payroll","11","") -> 11 | S49: =IFERROR(ROUND((O49*R49),2)," ") -> 9310 | T49: 0 | U49: 0 | V49: 0 | W49: =IFERROR(ROUND(($O49*$T49),2)," ") -> 0 | X49: =IFERROR(ROUND(($P49*$U49),2),"") -> 0 | Y49: =IFERROR(ROUND(($Q49*$V49),2),"") -> 0 | AC49: =IFERROR(ROUND(($O49*$Z49),2)," ") -> 0 | AD49: =IFERROR(ROUND(($P49*$AA49),2),"") -> 0 | AE49: =IFERROR(ROUND(($Q49*$AB49),2),"") -> 0 | AI49: =IFERROR(ROUND(($O49*$AF49),2)," ") -> 0 | AJ49: =IFERROR(ROUND(($P49*$AG49),2),"") -> 0 | AK49: =IFERROR(ROUND(($Q49*$AH49),2),"") -> 0 | AL49: =IFERROR(ROUND(($W49+$AC49+$AI49),2),"") -> 0 | AM49: =IFERROR(ROUND(($X49+$AD49+$AJ49),2),"") -> 0 | AN49: =IFERROR(ROUND(($Y49+$AE49+$AK49),2),"") -> 0 | AO49: =SUM(AL49:AN49) -> 0 | AR49: =IFERROR(ROUND((S49-AO49-AP49),2),"") -> 9310 | AY49: =IFERROR(ROUND((AR49-AS49-AT49-AU49-AV49-AW49-AX49),2),"") -> 9310 | AZ49: Payroll | BA49: LOZANO, ADRIAN D.
A50: =IF(B50="","",COUNTA($B$10:B50)) -> 41 | B50: 2026-01-0068 | C50: 46036 | E50: GUTIERREZ, DACHIEL P. | F50: GSS | G50: Administrative Asst. I (Bus Driver) | H50: =IF(AZ50="Payroll",VLOOKUP(E50,'CODE 2'!$R:$S,2,FALSE),"0") -> 7 | I50: O. ESETS | M50: =IFERROR(VLOOKUP($H50,'CODE 2'!$J:$K,2,FALSE)," ") -> 18620 | N50: =IFERROR(ROUND((M50/2),2),"") -> 9310 | O50: =IFERROR((M50/22)," ") -> 846.36364 | P50: =IFERROR((O50/8),"") -> 105.79545 | Q50: =IFERROR((P50/60),"") -> 1.7632576 | R50: =IF(AZ50="Payroll","11","") -> 11 | S50: =IFERROR(ROUND((O50*R50),2)," ") -> 9310 | T50: 0 | U50: 0 | V50: 23 | W50: =IFERROR(ROUND(($O50*$T50),2)," ") -> 0 | X50: =IFERROR(ROUND(($P50*$U50),2),"") -> 0 | Y50: =IFERROR(ROUND(($Q50*$V50),2),"") -> 40.55 | AC50: =IFERROR(ROUND(($O50*$Z50),2)," ") -> 0 | AD50: =IFERROR(ROUND(($P50*$AA50),2),"") -> 0 | AE50: =IFERROR(ROUND(($Q50*$AB50),2),"") -> 0 | AI50: =IFERROR(ROUND(($O50*$AF50),2)," ") -> 0 | AJ50: =IFERROR(ROUND(($P50*$AG50),2),"") -> 0 | AK50: =IFERROR(ROUND(($Q50*$AH50),2),"") -> 0 | AL50: =IFERROR(ROUND(($W50+$AC50+$AI50),2),"") -> 0 | AM50: =IFERROR(ROUND(($X50+$AD50+$AJ50),2),"") -> 0 | AN50: =IFERROR(ROUND(($Y50+$AE50+$AK50),2),"") -> 40.55 | AO50: =SUM(AL50:AN50) -> 40.55 | AR50: =IFERROR(ROUND((S50-AO50-AP50),2),"") -> 9269.45 | AY50: =IFERROR(ROUND((AR50-AS50-AT50-AU50-AV50-AW50-AX50),2),"") -> 9269.45 | AZ50: Payroll | BA50: MAGDARAOG, CHRISTINE NAZEL C.
A51: =IF(B51="","",COUNTA($B$10:B51)) -> 42 | B51: 2026-01-0069 | C51: 46036 | E51: PERALTA, JONEL | F51: INFRA | G51: Civil Engineer II | H51: =IF(AZ51="Payroll",VLOOKUP(E51,'CODE 2'!$R:$S,2,FALSE),"0") -> 16 | I51: O. ESETS | M51: =IFERROR(VLOOKUP($H51,'CODE 2'!$J:$K,2,FALSE)," ") -> 39672 | N51: =IFERROR(ROUND((M51/2),2),"") -> 19836 | O51: =IFERROR((M51/22)," ") -> 1803.2727 | P51: =IFERROR((O51/8),"") -> 225.40909 | Q51: =IFERROR((P51/60),"") -> 3.7568182 | R51: =IF(AZ51="Payroll","11","") -> 11 | S51: =IFERROR(ROUND((O51*R51),2)," ") -> 19836 | T51: 0 | U51: 0 | V51: 0 | W51: =IFERROR(ROUND(($O51*$T51),2)," ") -> 0 | X51: =IFERROR(ROUND(($P51*$U51),2),"") -> 0 | Y51: =IFERROR(ROUND(($Q51*$V51),2),"") -> 0 | AC51: =IFERROR(ROUND(($O51*$Z51),2)," ") -> 0 | AD51: =IFERROR(ROUND(($P51*$AA51),2),"") -> 0 | AE51: =IFERROR(ROUND(($Q51*$AB51),2),"") -> 0 | AI51: =IFERROR(ROUND(($O51*$AF51),2)," ") -> 0 | AJ51: =IFERROR(ROUND(($P51*$AG51),2),"") -> 0 | AK51: =IFERROR(ROUND(($Q51*$AH51),2),"") -> 0 | AL51: =IFERROR(ROUND(($W51+$AC51+$AI51),2),"") -> 0 | AM51: =IFERROR(ROUND(($X51+$AD51+$AJ51),2),"") -> 0 | AN51: =IFERROR(ROUND(($Y51+$AE51+$AK51),2),"") -> 0 | AO51: =SUM(AL51:AN51) -> 0 | AR51: =IFERROR(ROUND((S51-AO51-AP51),2),"") -> 19836 | AT51: =IFERROR(ROUND((AR51*$AT$8),2),"") -> 1983.6 | AU51: 2000 | AV51: 922.78 | AY51: =IFERROR(ROUND((AR51-AS51-AT51-AU51-AV51-AW51-AX51),2),"") -> 14929.62 | AZ51: Payroll | BA51: MANDANI, AVE M.
A52: =IF(B52="","",COUNTA($B$10:B52)) -> 43 | B52: 2026-01-0005 | C52: 46036 | E52: RIVAS, JOSEPH S. | F52: INFRA | G52: Electrician General Forman | H52: =IF(AZ52="Payroll",VLOOKUP(E52,'CODE 2'!$R:$S,2,FALSE),"0") -> 0 | I52: REVOLVING FUND | J52: OK | M52: =IFERROR(VLOOKUP($H52,'CODE 2'!$J:$K,2,FALSE)," ") | N52: =IFERROR(ROUND((M52/2),2),"") | O52: =IFERROR((M52/22)," ") | P52: =IFERROR((O52/8),"") | Q52: =IFERROR((P52/60),"") | R52: =IF(AZ52="Payroll","11","") | S52: =IFERROR(ROUND((O52*R52),2)," ") | T52: 0 | U52: 0 | V52: 3 | W52: =IFERROR(ROUND(($O52*$T52),2)," ") | X52: =IFERROR(ROUND(($P52*$U52),2),"") | Y52: =IFERROR(ROUND(($Q52*$V52),2),"") | AC52: =IFERROR(ROUND(($O52*$Z52),2)," ") | AD52: =IFERROR(ROUND(($P52*$AA52),2),"") | AE52: =IFERROR(ROUND(($Q52*$AB52),2),"") | AI52: =IFERROR(ROUND(($O52*$AF52),2)," ") | AJ52: =IFERROR(ROUND(($P52*$AG52),2),"") | AK52: =IFERROR(ROUND(($Q52*$AH52),2),"") | AL52: =IFERROR(ROUND(($W52+$AC52+$AI52),2),"") | AM52: =IFERROR(ROUND(($X52+$AD52+$AJ52),2),"") | AN52: =IFERROR(ROUND(($Y52+$AE52+$AK52),2),"") | AO52: =SUM(AL52:AN52) -> 0 | AR52: =IFERROR(ROUND((S52-AO52-AP52),2),"") | AY52: =IFERROR(ROUND((AR52-AS52-AT52-AU52-AV52-AW52-AX52),2),"") | AZ52: Voucher | BA52: MANGILOG, ERICCA MAE V.
A53: =IF(B53="","",COUNTA($B$10:B53)) -> 44 | B53: 2026-01-0061 | C53: 46036 | E53: PATAN, LIOMYR A. | F53: INFRA | G53: Electrical Engineer I | H53: =IF(AZ53="Payroll",VLOOKUP(E53,'CODE 2'!$R:$S,2,FALSE),"0") -> 14 | I53: O. ESETS | J53: OK | M53: =IFERROR(VLOOKUP($H53,'CODE 2'!$J:$K,2,FALSE)," ") -> 33843 | N53: =IFERROR(ROUND((M53/2),2),"") -> 16921.5 | O53: =IFERROR((M53/22)," ") -> 1538.3182 | P53: =IFERROR((O53/8),"") -> 192.28977 | Q53: =IFERROR((P53/60),"") -> 3.2048295 | R53: =IF(AZ53="Payroll","11","") -> 11 | S53: =IFERROR(ROUND((O53*R53),2)," ") -> 16921.5 | T53: 1 | U53: 2 | V53: 23 | W53: =IFERROR(ROUND(($O53*$T53),2)," ") -> 1538.32 | X53: =IFERROR(ROUND(($P53*$U53),2),"") -> 384.58 | Y53: =IFERROR(ROUND(($Q53*$V53),2),"") -> 73.71 | AC53: =IFERROR(ROUND(($O53*$Z53),2)," ") -> 0 | AD53: =IFERROR(ROUND(($P53*$AA53),2),"") -> 0 | AE53: =IFERROR(ROUND(($Q53*$AB53),2),"") -> 0 | AI53: =IFERROR(ROUND(($O53*$AF53),2)," ") -> 0 | AJ53: =IFERROR(ROUND(($P53*$AG53),2),"") -> 0 | AK53: =IFERROR(ROUND(($Q53*$AH53),2),"") -> 0 | AL53: =IFERROR(ROUND(($W53+$AC53+$AI53),2),"") -> 1538.32 | AM53: =IFERROR(ROUND(($X53+$AD53+$AJ53),2),"") -> 384.58 | AN53: =IFERROR(ROUND(($Y53+$AE53+$AK53),2),"") -> 73.71 | AO53: =SUM(AL53:AN53) -> 1996.61 | AP53: 0.03 | AQ53: Nov 16-31, 2025 | AR53: =IFERROR(ROUND((S53-AO53+AP53),2),"") -> 14924.92 | AT53: =IFERROR(ROUND((AR53*$AT$8),2),"") -> 1492.49 | AY53: =IFERROR(ROUND((AR53-AS53-AT53-AU53-AV53-AW53-AX53),2),"") -> 13432.43 | AZ53: Payroll | BA53: MARCELO, FERDINAND S.
A54: =IF(B54="","",COUNTA($B$10:B54)) -> 45 | B54: 2026-01-0042 | C54: 46036 | E54: LORENA, SUSAN G | F54: COA | G54: Administrative Asst. II | H54: =IF(AZ54="Payroll",VLOOKUP(E54,'CODE 2'!$R:$S,2,FALSE),"0") -> 8 | I54: O. ESETS | J54: OK | M54: =IFERROR(VLOOKUP($H54,'CODE 2'!$J:$K,2,FALSE)," ") -> 19744 | N54: =IFERROR(ROUND((M54/2),2),"") -> 9872 | O54: =IFERROR((M54/22)," ") -> 897.45455 | P54: =IFERROR((O54/8),"") -> 112.18182 | Q54: =IFERROR((P54/60),"") -> 1.869697 | R54: =IF(AZ54="Payroll","11","") -> 11 | S54: =IFERROR(ROUND((O54*R54),2)," ") -> 9872 | T54: 0 | U54: 0 | V54: 0 | W54: =IFERROR(ROUND(($O54*$T54),2)," ") -> 0 | X54: =IFERROR(ROUND(($P54*$U54),2),"") -> 0 | Y54: =IFERROR(ROUND(($Q54*$V54),2),"") -> 0 | AC54: =IFERROR(ROUND(($O54*$Z54),2)," ") -> 0 | AD54: =IFERROR(ROUND(($P54*$AA54),2),"") -> 0 | AE54: =IFERROR(ROUND(($Q54*$AB54),2),"") -> 0 | AI54: =IFERROR(ROUND(($O54*$AF54),2)," ") -> 0 | AJ54: =IFERROR(ROUND(($P54*$AG54),2),"") -> 0 | AK54: =IFERROR(ROUND(($Q54*$AH54),2),"") -> 0 | AL54: =IFERROR(ROUND(($W54+$AC54+$AI54),2),"") -> 0 | AM54: =IFERROR(ROUND(($X54+$AD54+$AJ54),2),"") -> 0 | AN54: =IFERROR(ROUND(($Y54+$AE54+$AK54),2),"") -> 0 | AO54: =SUM(AL54:AN54) -> 0 | AR54: =IFERROR(ROUND((S54-AO54-AP54),2),"") -> 9872 | AY54: =IFERROR(ROUND((AR54-AS54-AT54-AU54-AV54-AW54-AX54),2),"") -> 9872 | AZ54: Payroll | BA54: MARTIN, ORLAN LEONARD E.
A55: =IF(B55="","",COUNTA($B$10:B55)) -> 46 | B55: 2026-01-0043 | C55: 46036 | E55: GUZMAN, JESSA MAE G. | F55: COA | G55: Administrative Asst. II | H55: =IF(AZ55="Payroll",VLOOKUP(E55,'CODE 2'!$R:$S,2,FALSE),"0") -> 8 | I55: O. ESETS | J55: OK | M55: =IFERROR(VLOOKUP($H55,'CODE 2'!$J:$K,2,FALSE)," ") -> 19744 | N55: =IFERROR(ROUND((M55/2),2),"") -> 9872 | O55: =IFERROR((M55/22)," ") -> 897.45455 | P55: =IFERROR((O55/8),"") -> 112.18182 | Q55: =IFERROR((P55/60),"") -> 1.869697 | R55: =IF(AZ55="Payroll","11","") -> 11 | S55: =IFERROR(ROUND((O55*R55),2)," ") -> 9872 | T55: 0 | U55: 1 | V55: 7 | W55: =IFERROR(ROUND(($O55*$T55),2)," ") -> 0 | X55: =IFERROR(ROUND(($P55*$U55),2),"") -> 112.18 | Y55: =IFERROR(ROUND(($Q55*$V55),2),"") -> 13.09 | AC55: =IFERROR(ROUND(($O55*$Z55),2)," ") -> 0 | AD55: =IFERROR(ROUND(($P55*$AA55),2),"") -> 0 | AE55: =IFERROR(ROUND(($Q55*$AB55),2),"") -> 0 | AI55: =IFERROR(ROUND(($O55*$AF55),2)," ") -> 0 | AJ55: =IFERROR(ROUND(($P55*$AG55),2),"") -> 0 | AK55: =IFERROR(ROUND(($Q55*$AH55),2),"") -> 0 | AL55: =IFERROR(ROUND(($W55+$AC55+$AI55),2),"") -> 0 | AM55: =IFERROR(ROUND(($X55+$AD55+$AJ55),2),"") -> 112.18 | AN55: =IFERROR(ROUND(($Y55+$AE55+$AK55),2),"") -> 13.09 | AO55: =SUM(AL55:AN55) -> 125.27 | AR55: =IFERROR(ROUND((S55-AO55-AP55),2),"") -> 9746.73 | AY55: =IFERROR(ROUND((AR55-AS55-AT55-AU55-AV55-AW55-AX55),2),"") -> 9746.73 | AZ55: Payroll | BA55: MARTIN, SHAIRA LEA E.
A56: =IF(B56="","",COUNTA($B$10:B56)) -> 47 | B56: 2026-01-0045 | C56: 46036 | E56: SERDONCILLO, RANIL G. | F56: COA | G56: Administrative Asst. I | H56: =IF(AZ56="Payroll",VLOOKUP(E56,'CODE 2'!$R:$S,2,FALSE),"0") -> 7 | I56: O. ESETS | J56: OK | M56: =IFERROR(VLOOKUP($H56,'CODE 2'!$J:$K,2,FALSE)," ") -> 18620 | N56: =IFERROR(ROUND((M56/2),2),"") -> 9310 | O56: =IFERROR((M56/22)," ") -> 846.36364 | P56: =IFERROR((O56/8),"") -> 105.79545 | Q56: =IFERROR((P56/60),"") -> 1.7632576 | R56: =IF(AZ56="Payroll","11","") -> 11 | S56: =IFERROR(ROUND((O56*R56),2)," ") -> 9310 | T56: 0 | U56: 0 | V56: 1 | W56: =IFERROR(ROUND(($O56*$T56),2)," ") -> 0 | X56: =IFERROR(ROUND(($P56*$U56),2),"") -> 0 | Y56: =IFERROR(ROUND(($Q56*$V56),2),"") -> 1.76 | AC56: =IFERROR(ROUND(($O56*$Z56),2)," ") -> 0 | AD56: =IFERROR(ROUND(($P56*$AA56),2),"") -> 0 | AE56: =IFERROR(ROUND(($Q56*$AB56),2),"") -> 0 | AI56: =IFERROR(ROUND(($O56*$AF56),2)," ") -> 0 | AJ56: =IFERROR(ROUND(($P56*$AG56),2),"") -> 0 | AK56: =IFERROR(ROUND(($Q56*$AH56),2),"") -> 0 | AL56: =IFERROR(ROUND(($W56+$AC56+$AI56),2),"") -> 0 | AM56: =IFERROR(ROUND(($X56+$AD56+$AJ56),2),"") -> 0 | AN56: =IFERROR(ROUND(($Y56+$AE56+$AK56),2),"") -> 1.76 | AO56: =SUM(AL56:AN56) -> 1.76 | AR56: =IFERROR(ROUND((S56-AO56-AP56),2),"") -> 9308.24 | AY56: =IFERROR(ROUND((AR56-AS56-AT56-AU56-AV56-AW56-AX56),2),"") -> 9308.24 | AZ56: Payroll | BA56: NAMOCA, SANTIAGO J.
A57: =IF(B57="","",COUNTA($B$10:B57)) -> 48 | B57: 2026-01-0044 | C57: 46036 | E57: COMPLETO, CRIZANTO E. | F57: COA | G57: Administrative Asst. I | H57: =IF(AZ57="Payroll",VLOOKUP(E57,'CODE 2'!$R:$S,2,FALSE),"0") -> 7 | I57: O. ESETS | J57: OK | M57: =IFERROR(VLOOKUP($H57,'CODE 2'!$J:$K,2,FALSE)," ") -> 18620 | N57: =IFERROR(ROUND((M57/2),2),"") -> 9310 | O57: =IFERROR((M57/22)," ") -> 846.36364 | P57: =IFERROR((O57/8),"") -> 105.79545 | Q57: =IFERROR((P57/60),"") -> 1.7632576 | R57: =IF(AZ57="Payroll","11","") -> 11 | S57: =IFERROR(ROUND((O57*R57),2)," ") -> 9310 | T57: 0 | U57: 0 | V57: 0 | W57: =IFERROR(ROUND(($O57*$T57),2)," ") -> 0 | X57: =IFERROR(ROUND(($P57*$U57),2),"") -> 0 | Y57: =IFERROR(ROUND(($Q57*$V57),2),"") -> 0 | AC57: =IFERROR(ROUND(($O57*$Z57),2)," ") -> 0 | AD57: =IFERROR(ROUND(($P57*$AA57),2),"") -> 0 | AE57: =IFERROR(ROUND(($Q57*$AB57),2),"") -> 0 | AI57: =IFERROR(ROUND(($O57*$AF57),2)," ") -> 0 | AJ57: =IFERROR(ROUND(($P57*$AG57),2),"") -> 0 | AK57: =IFERROR(ROUND(($Q57*$AH57),2),"") -> 0 | AL57: =IFERROR(ROUND(($W57+$AC57+$AI57),2),"") -> 0 | AM57: =IFERROR(ROUND(($X57+$AD57+$AJ57),2),"") -> 0 | AN57: =IFERROR(ROUND(($Y57+$AE57+$AK57),2),"") -> 0 | AO57: =SUM(AL57:AN57) -> 0 | AR57: =IFERROR(ROUND((S57-AO57-AP57),2),"") -> 9310 | AY57: =IFERROR(ROUND((AR57-AS57-AT57-AU57-AV57-AW57-AX57),2),"") -> 9310 | AZ57: Payroll | BA57: NILO, FAITH PERL A.
A58: =IF(B58="","",COUNTA($B$10:B58)) -> 49 | B58: 2026-01-0051 | C58: 46036 | E58: GAGUCAS, MICHAEL B. | F58: SMS | G58: Administrative Asst. II | H58: =IF(AZ58="Payroll",VLOOKUP(E58,'CODE 2'!$R:$S,2,FALSE),"0") -> 8 | I58: O. ESETS | J58: OK | M58: =IFERROR(VLOOKUP($H58,'CODE 2'!$J:$K,2,FALSE)," ") -> 19744 | N58: =IFERROR(ROUND((M58/2),2),"") -> 9872 | O58: =IFERROR((M58/22)," ") -> 897.45455 | P58: =IFERROR((O58/8),"") -> 112.18182 | Q58: =IFERROR((P58/60),"") -> 1.869697 | R58: =IF(AZ58="Payroll","11","") -> 11 | S58: =IFERROR(ROUND((O58*R58),2)," ") -> 9872 | T58: 0 | U58: 1 | V58: 6 | W58: =IFERROR(ROUND(($O58*$T58),2)," ") -> 0 | X58: =IFERROR(ROUND(($P58*$U58),2),"") -> 112.18 | Y58: =IFERROR(ROUND(($Q58*$V58),2),"") -> 11.22 | AC58: =IFERROR(ROUND(($O58*$Z58),2)," ") -> 0 | AD58: =IFERROR(ROUND(($P58*$AA58),2),"") -> 0 | AE58: =IFERROR(ROUND(($Q58*$AB58),2),"") -> 0 | AI58: =IFERROR(ROUND(($O58*$AF58),2)," ") -> 0 | AJ58: =IFERROR(ROUND(($P58*$AG58),2),"") -> 0 | AK58: =IFERROR(ROUND(($Q58*$AH58),2),"") -> 0 | AL58: =IFERROR(ROUND(($W58+$AC58+$AI58),2),"") -> 0 | AM58: =IFERROR(ROUND(($X58+$AD58+$AJ58),2),"") -> 112.18 | AN58: =IFERROR(ROUND(($Y58+$AE58+$AK58),2),"") -> 11.22 | AO58: =SUM(AL58:AN58) -> 123.4 | AR58: =IFERROR(ROUND((S58-AO58-AP58),2),"") -> 9748.6 | AY58: =IFERROR(ROUND((AR58-AS58-AT58-AU58-AV58-AW58-AX58),2),"") -> 9748.6 | AZ58: Payroll | BA58: NIÑO, COLENE MAE B.
A59: =IF(B59="","",COUNTA($B$10:B59)) -> 50 | B59: 2026-01-0052 | C59: 46036 | E59: WALICAN, CARLA S. | F59: SMS | G59: Administrative Asst. II | H59: =IF(AZ59="Payroll",VLOOKUP(E59,'CODE 2'!$R:$S,2,FALSE),"0") -> 8 | I59: O. ESETS | J59: OK | M59: =IFERROR(VLOOKUP($H59,'CODE 2'!$J:$K,2,FALSE)," ") -> 19744 | N59: =IFERROR(ROUND((M59/2),2),"") -> 9872 | O59: =IFERROR((M59/22)," ") -> 897.45455 | P59: =IFERROR((O59/8),"") -> 112.18182 | Q59: =IFERROR((P59/60),"") -> 1.869697 | R59: =IF(AZ59="Payroll","11","") -> 11 | S59: =IFERROR(ROUND((O59*R59),2)," ") -> 9872 | T59: 0 | U59: 0 | V59: 9 | W59: =IFERROR(ROUND(($O59*$T59),2)," ") -> 0 | X59: =IFERROR(ROUND(($P59*$U59),2),"") -> 0 | Y59: =IFERROR(ROUND(($Q59*$V59),2),"") -> 16.83 | AC59: =IFERROR(ROUND(($O59*$Z59),2)," ") -> 0 | AD59: =IFERROR(ROUND(($P59*$AA59),2),"") -> 0 | AE59: =IFERROR(ROUND(($Q59*$AB59),2),"") -> 0 | AI59: =IFERROR(ROUND(($O59*$AF59),2)," ") -> 0 | AJ59: =IFERROR(ROUND(($P59*$AG59),2),"") -> 0 | AK59: =IFERROR(ROUND(($Q59*$AH59),2),"") -> 0 | AL59: =IFERROR(ROUND(($W59+$AC59+$AI59),2),"") -> 0 | AM59: =IFERROR(ROUND(($X59+$AD59+$AJ59),2),"") -> 0 | AN59: =IFERROR(ROUND(($Y59+$AE59+$AK59),2),"") -> 16.83 | AO59: =SUM(AL59:AN59) -> 16.83 | AR59: =IFERROR(ROUND((S59-AO59-AP59),2),"") -> 9855.17 | AY59: =IFERROR(ROUND((AR59-AS59-AT59-AU59-AV59-AW59-AX59),2),"") -> 9855.17 | AZ59: Payroll | BA59: OLIVO, JENNA P.
A60: =IF(B60="","",COUNTA($B$10:B60)) -> 51 | B60: 2026-01-0056 | C60: 46036 | E60: AKUT, FILSAN G. | F60: BAC | G60: Administrative Asst. IV | H60: 10 | I60: O. ESETS | J60: OK | M60: =IFERROR(VLOOKUP($H60,'CODE 2'!$J:$K,2,FALSE)," ") -> 23176 | N60: =IFERROR(ROUND((M60/2),2),"") -> 11588 | O60: =IFERROR((M60/22)," ") -> 1053.4545 | P60: =IFERROR((O60/8),"") -> 131.68182 | Q60: =IFERROR((P60/60),"") -> 2.194697 | R60: =IF(AZ60="Payroll","11","") -> 11 | S60: =IFERROR(ROUND((O60*R60),2)," ") -> 11588 | T60: 0 | U60: 0 | V60: 0 | W60: =IFERROR(ROUND(($O60*$T60),2)," ") -> 0 | X60: =IFERROR(ROUND(($P60*$U60),2),"") -> 0 | Y60: =IFERROR(ROUND(($Q60*$V60),2),"") -> 0 | AC60: =IFERROR(ROUND(($O60*$Z60),2)," ") -> 0 | AD60: =IFERROR(ROUND(($P60*$AA60),2),"") -> 0 | AE60: =IFERROR(ROUND(($Q60*$AB60),2),"") -> 0 | AI60: =IFERROR(ROUND(($O60*$AF60),2)," ") -> 0 | AJ60: =IFERROR(ROUND(($P60*$AG60),2),"") -> 0 | AK60: =IFERROR(ROUND(($Q60*$AH60),2),"") -> 0 | AL60: =IFERROR(ROUND(($W60+$AC60+$AI60),2),"") -> 0 | AM60: =IFERROR(ROUND(($X60+$AD60+$AJ60),2),"") -> 0 | AN60: =IFERROR(ROUND(($Y60+$AE60+$AK60),2),"") -> 0 | AO60: =SUM(AL60:AN60) -> 0 | AR60: =IFERROR(ROUND((S60-AO60-AP60),2),"") -> 11588 | AY60: =IFERROR(ROUND((AR60-AS60-AT60-AU60-AV60-AW60-AX60),2),"") -> 11588 | AZ60: Payroll | BA60: OQUINDO, SHEILA JANE G.
A61: =IF(B61="","",COUNTA($B$10:B61)) -> 52 | B61: 2026-01-0057 | C61: 46036 | E61: LIPAN, AGNES J. | F61: BAC | G61: Administrative Asst. II | H61: 8 | I61: O. ESETS | J61: OK | M61: =IFERROR(VLOOKUP($H61,'CODE 2'!$J:$K,2,FALSE)," ") -> 19744 | N61: =IFERROR(ROUND((M61/2),2),"") -> 9872 | O61: =IFERROR((M61/22)," ") -> 897.45455 | P61: =IFERROR((O61/8),"") -> 112.18182 | Q61: =IFERROR((P61/60),"") -> 1.869697 | R61: =IF(AZ61="Payroll","11","") -> 11 | S61: =IFERROR(ROUND((O61*R61),2)," ") -> 9872 | T61: 0 | U61: 0 | V61: 5 | W61: =IFERROR(ROUND(($O61*$T61),2)," ") -> 0 | X61: =IFERROR(ROUND(($P61*$U61),2),"") -> 0 | Y61: =IFERROR(ROUND(($Q61*$V61),2),"") -> 9.35 | AC61: =IFERROR(ROUND(($O61*$Z61),2)," ") -> 0 | AD61: =IFERROR(ROUND(($P61*$AA61),2),"") -> 0 | AE61: =IFERROR(ROUND(($Q61*$AB61),2),"") -> 0 | AI61: =IFERROR(ROUND(($O61*$AF61),2)," ") -> 0 | AJ61: =IFERROR(ROUND(($P61*$AG61),2),"") -> 0 | AK61: =IFERROR(ROUND(($Q61*$AH61),2),"") -> 0 | AL61: =IFERROR(ROUND(($W61+$AC61+$AI61),2),"") -> 0 | AM61: =IFERROR(ROUND(($X61+$AD61+$AJ61),2),"") -> 0 | AN61: =IFERROR(ROUND(($Y61+$AE61+$AK61),2),"") -> 9.35 | AO61: =SUM(AL61:AN61) -> 9.35 | AR61: =IFERROR(ROUND((S61-AO61-AP61),2),"") -> 9862.65 | AY61: =IFERROR(ROUND((AR61-AS61-AT61-AU61-AV61-AW61-AX61),2),"") -> 9862.65 | AZ61: Payroll | BA61: PASTOR, JANELLE E.
A62: =IF(B62="","",COUNTA($B$10:B62)) -> 53 | B62: 2026-01-0046 | C62: 46036 | E62: CELOCIA, ROSELY-ANN G. | F62: DO | G62: Administrative Asst. II | H62: =IF(AZ62="Payroll",VLOOKUP(E62,'CODE 2'!$R:$S,2,FALSE),"0") -> 8 | I62: GASS | M62: =IFERROR(VLOOKUP($H62,'CODE 2'!$J:$K,2,FALSE)," ") -> 19744 | N62: =IFERROR(ROUND((M62/2),2),"") -> 9872 | O62: =IFERROR((M62/22)," ") -> 897.45455 | P62: =IFERROR((O62/8),"") -> 112.18182 | Q62: =IFERROR((P62/60),"") -> 1.869697 | R62: 11 | S62: =IFERROR(ROUND((O62*R62),2)," ") -> 9872 | T62: 0 | U62: 4 | V62: 22 | W62: =IFERROR(ROUND(($O62*$T62),2)," ") -> 0 | X62: =IFERROR(ROUND(($P62*$U62),2),"") -> 448.73 | Y62: =IFERROR(ROUND(($Q62*$V62),2),"") -> 41.13 | AC62: =IFERROR(ROUND(($O62*$Z62),2)," ") -> 0 | AD62: =IFERROR(ROUND(($P62*$AA62),2),"") -> 0 | AE62: =IFERROR(ROUND(($Q62*$AB62),2),"") -> 0 | AI62: =IFERROR(ROUND(($O62*$AF62),2)," ") -> 0 | AJ62: =IFERROR(ROUND(($P62*$AG62),2),"") -> 0 | AK62: =IFERROR(ROUND(($Q62*$AH62),2),"") -> 0 | AL62: =IFERROR(ROUND(($W62+$AC62+$AI62),2),"") -> 0 | AM62: =IFERROR(ROUND(($X62+$AD62+$AJ62),2),"") -> 448.73 | AN62: =IFERROR(ROUND(($Y62+$AE62+$AK62),2),"") -> 41.13 | AO62: =SUM(AL62:AN62) -> 489.86 | AR62: =IFERROR(ROUND((S62-AO62-AP62),2),"") -> 9382.14 | AY62: =IFERROR(ROUND((AR62-AS62-AT62-AU62-AV62-AW62-AX62),2),"") -> 9382.14 | AZ62: Payroll | BA62: PATAN, LIOMYR A.
A63: =IF(B63="","",COUNTA($B$10:B63)) -> 54 | B63: 2026-01-0031 | C63: 46036 | E63: BRUZON, ANGENNITTE F. | F63: PAD | G63: Administrative Asst. II | H63: =IF(AZ63="Payroll",VLOOKUP(E63,'CODE 2'!$R:$S,2,FALSE),"0") -> 8 | I63: FPMA/RICE | J63: OK | M63: =IFERROR(VLOOKUP($H63,'CODE 2'!$J:$K,2,FALSE)," ") -> 19744 | N63: =IFERROR(ROUND((M63/2),2),"") -> 9872 | O63: =IFERROR((M63/22)," ") -> 897.45455 | P63: =IFERROR((O63/8),"") -> 112.18182 | Q63: =IFERROR((P63/60),"") -> 1.869697 | R63: =IF(AZ63="Payroll","11","") -> 11 | S63: =IFERROR(ROUND((O63*R63),2)," ") -> 9872 | T63: 0 | U63: 4 | V63: 31 | W63: =IFERROR(ROUND(($O63*$T63),2)," ") -> 0 | X63: =IFERROR(ROUND(($P63*$U63),2),"") -> 448.73 | Y63: =IFERROR(ROUND(($Q63*$V63),2),"") -> 57.96 | AC63: =IFERROR(ROUND(($O63*$Z63),2)," ") -> 0 | AD63: =IFERROR(ROUND(($P63*$AA63),2),"") -> 0 | AE63: =IFERROR(ROUND(($Q63*$AB63),2),"") -> 0 | AI63: =IFERROR(ROUND(($O63*$AF63),2)," ") -> 0 | AJ63: =IFERROR(ROUND(($P63*$AG63),2),"") -> 0 | AK63: =IFERROR(ROUND(($Q63*$AH63),2),"") -> 0 | AL63: =IFERROR(ROUND(($W63+$AC63+$AI63),2),"") -> 0 | AM63: =IFERROR(ROUND(($X63+$AD63+$AJ63),2),"") -> 448.73 | AN63: =IFERROR(ROUND(($Y63+$AE63+$AK63),2),"") -> 57.96 | AO63: =SUM(AL63:AN63) -> 506.69 | AR63: =IFERROR(ROUND((S63-AO63-AP63),2),"") -> 9365.31 | AY63: =IFERROR(ROUND((AR63-AS63-AT63-AU63-AV63-AW63-AX63),2),"") -> 9365.31 | AZ63: Payroll | BA63: PERALTA, JONEL
A64: =IF(B64="","",COUNTA($B$10:B64)) -> 55 | B64: 2026-01-0033 | C64: 46036 | E64: BADILLO, ALBINO M. | F64: PAD | G64: Administrative Aide VI (Gardener) | H64: =IF(AZ64="Payroll",VLOOKUP(E64,'CODE 2'!$R:$S,2,FALSE),"0") -> 6 | I64: FPMA/NOAP | J64: OK | M64: =IFERROR(VLOOKUP($H64,'CODE 2'!$J:$K,2,FALSE)," ") -> 17553 | N64: =IFERROR(ROUND((M64/2),2),"") -> 8776.5 | O64: =IFERROR((M64/22)," ") -> 797.86364 | P64: =IFERROR((O64/8),"") -> 99.732955 | Q64: =IFERROR((P64/60),"") -> 1.6622159 | R64: =IF(AZ64="Payroll","11","") -> 11 | S64: =IFERROR(ROUND((O64*R64),2)," ") -> 8776.5 | T64: 0 | U64: 0 | V64: 0 | W64: =IFERROR(ROUND(($O64*$T64),2)," ") -> 0 | X64: =IFERROR(ROUND(($P64*$U64),2),"") -> 0 | Y64: =IFERROR(ROUND(($Q64*$V64),2),"") -> 0 | AC64: =IFERROR(ROUND(($O64*$Z64),2)," ") -> 0 | AD64: =IFERROR(ROUND(($P64*$AA64),2),"") -> 0 | AE64: =IFERROR(ROUND(($Q64*$AB64),2),"") -> 0 | AI64: =IFERROR(ROUND(($O64*$AF64),2)," ") -> 0 | AJ64: =IFERROR(ROUND(($P64*$AG64),2),"") -> 0 | AK64: =IFERROR(ROUND(($Q64*$AH64),2),"") -> 0 | AL64: =IFERROR(ROUND(($W64+$AC64+$AI64),2),"") -> 0 | AM64: =IFERROR(ROUND(($X64+$AD64+$AJ64),2),"") -> 0 | AN64: =IFERROR(ROUND(($Y64+$AE64+$AK64),2),"") -> 0 | AO64: =SUM(AL64:AN64) -> 0 | AR64: =IFERROR(ROUND((S64-AO64-AP64),2),"") -> 8776.5 | AY64: =IFERROR(ROUND((AR64-AS64-AT64-AU64-AV64-AW64-AX64),2),"") -> 8776.5 | AZ64: Payroll | BA64: PERNIA, JONAS S.
A65: =IF(B65="","",COUNTA($B$10:B65)) -> 56 | B65: 2026-01-0034 | C65: 46036 | E65: BELO, JOSHUA G. | F65: PAD | G65: Administrative Aide VI (Gardener) | H65: =IF(AZ65="Payroll",VLOOKUP(E65,'CODE 2'!$R:$S,2,FALSE),"0") -> 6 | I65: FPMA/NOAP | J65: OK | M65: =IFERROR(VLOOKUP($H65,'CODE 2'!$J:$K,2,FALSE)," ") -> 17553 | N65: =IFERROR(ROUND((M65/2),2),"") -> 8776.5 | O65: =IFERROR((M65/22)," ") -> 797.86364 | P65: =IFERROR((O65/8),"") -> 99.732955 | Q65: =IFERROR((P65/60),"") -> 1.6622159 | R65: =IF(AZ65="Payroll","11","") -> 11 | S65: =IFERROR(ROUND((O65*R65),2)," ") -> 8776.5 | T65: 0 | U65: 0 | V65: 0 | W65: =IFERROR(ROUND(($O65*$T65),2)," ") -> 0 | X65: =IFERROR(ROUND(($P65*$U65),2),"") -> 0 | Y65: =IFERROR(ROUND(($Q65*$V65),2),"") -> 0 | AC65: =IFERROR(ROUND(($O65*$Z65),2)," ") -> 0 | AD65: =IFERROR(ROUND(($P65*$AA65),2),"") -> 0 | AE65: =IFERROR(ROUND(($Q65*$AB65),2),"") -> 0 | AI65: =IFERROR(ROUND(($O65*$AF65),2)," ") -> 0 | AJ65: =IFERROR(ROUND(($P65*$AG65),2),"") -> 0 | AK65: =IFERROR(ROUND(($Q65*$AH65),2),"") -> 0 | AL65: =IFERROR(ROUND(($W65+$AC65+$AI65),2),"") -> 0 | AM65: =IFERROR(ROUND(($X65+$AD65+$AJ65),2),"") -> 0 | AN65: =IFERROR(ROUND(($Y65+$AE65+$AK65),2),"") -> 0 | AO65: =SUM(AL65:AN65) -> 0 | AR65: =IFERROR(ROUND((S65-AO65-AP65),2),"") -> 8776.5 | AY65: =IFERROR(ROUND((AR65-AS65-AT65-AU65-AV65-AW65-AX65),2),"") -> 8776.5 | AZ65: Payroll | BA65: RIVAS, JOSEPH S.
A66: =IF(B66="","",COUNTA($B$10:B66)) -> 57 | B66: 2026-01-0035 | C66: 46036 | E66: CATIMBANG, SHANDEE FAY O. | F66: PAD | G66: Agriculturist I | H66: =IF(AZ66="Payroll",VLOOKUP(E66,'CODE 2'!$R:$S,2,FALSE),"0") -> 11 | I66: FPMA/NOAP | J66: OK | M66: =IFERROR(VLOOKUP($H66,'CODE 2'!$J:$K,2,FALSE)," ") -> 27000 | N66: =IFERROR(ROUND((M66/2),2),"") -> 13500 | O66: =IFERROR((M66/22)," ") -> 1227.2727 | P66: =IFERROR((O66/8),"") -> 153.40909 | Q66: =IFERROR((P66/60),"") -> 2.5568182 | R66: =IF(AZ66="Payroll","11","") -> 11 | S66: =IFERROR(ROUND((O66*R66),2)," ") -> 13500 | T66: 0 | U66: 0 | V66: 0 | W66: =IFERROR(ROUND(($O66*$T66),2)," ") -> 0 | X66: =IFERROR(ROUND(($P66*$U66),2),"") -> 0 | Y66: =IFERROR(ROUND(($Q66*$V66),2),"") -> 0 | AC66: =IFERROR(ROUND(($O66*$Z66),2)," ") -> 0 | AD66: =IFERROR(ROUND(($P66*$AA66),2),"") -> 0 | AE66: =IFERROR(ROUND(($Q66*$AB66),2),"") -> 0 | AI66: =IFERROR(ROUND(($O66*$AF66),2)," ") -> 0 | AJ66: =IFERROR(ROUND(($P66*$AG66),2),"") -> 0 | AK66: =IFERROR(ROUND(($Q66*$AH66),2),"") -> 0 | AL66: =IFERROR(ROUND(($W66+$AC66+$AI66),2),"") -> 0 | AM66: =IFERROR(ROUND(($X66+$AD66+$AJ66),2),"") -> 0 | AN66: =IFERROR(ROUND(($Y66+$AE66+$AK66),2),"") -> 0 | AO66: =SUM(AL66:AN66) -> 0 | AR66: =IFERROR(ROUND((S66-AO66-AP66),2),"") -> 13500 | AY66: =IFERROR(ROUND((AR66-AS66-AT66-AU66-AV66-AW66-AX66),2),"") -> 13500 | AZ66: Payroll | BA66: RODRIGUEZ, MA. RUFFA A.
A67: =IF(B67="","",COUNTA($B$10:B67)) -> 58 | B67: 2026-01-0029 | C67: 46036 | E67: MANGILOG, ERICCA MAE V. | F67: PAD | G67: Technical Support Staff IV | H67: =IF(AZ67="Payroll",VLOOKUP(E67,'CODE 2'!$R:$S,2,FALSE),"0") -> 11 | I67: O. ESETS | J67: OK | M67: =IFERROR(VLOOKUP($H67,'CODE 2'!$J:$K,2,FALSE)," ") -> 27000 | N67: =IFERROR(ROUND((M67/2),2),"") -> 13500 | O67: =IFERROR((M67/22)," ") -> 1227.2727 | P67: =IFERROR((O67/8),"") -> 153.40909 | Q67: =IFERROR((P67/60),"") -> 2.5568182 | R67: =IF(AZ67="Payroll","11","") -> 11 | S67: =IFERROR(ROUND((O67*R67),2)," ") -> 13500 | T67: 0 | U67: 0 | V67: 38 | W67: =IFERROR(ROUND(($O67*$T67),2)," ") -> 0 | X67: =IFERROR(ROUND(($P67*$U67),2),"") -> 0 | Y67: =IFERROR(ROUND(($Q67*$V67),2),"") -> 97.16 | AC67: =IFERROR(ROUND(($O67*$Z67),2)," ") -> 0 | AD67: =IFERROR(ROUND(($P67*$AA67),2),"") -> 0 | AE67: =IFERROR(ROUND(($Q67*$AB67),2),"") -> 0 | AI67: =IFERROR(ROUND(($O67*$AF67),2)," ") -> 0 | AJ67: =IFERROR(ROUND(($P67*$AG67),2),"") -> 0 | AK67: =IFERROR(ROUND(($Q67*$AH67),2),"") -> 0 | AL67: =IFERROR(ROUND(($W67+$AC67+$AI67),2),"") -> 0 | AM67: =IFERROR(ROUND(($X67+$AD67+$AJ67),2),"") -> 0 | AN67: =IFERROR(ROUND(($Y67+$AE67+$AK67),2),"") -> 97.16 | AO67: =SUM(AL67:AN67) -> 97.16 | AR67: =IFERROR(ROUND((S67-AO67-AP67),2),"") -> 13402.84 | AY67: =IFERROR(ROUND((AR67-AS67-AT67-AU67-AV67-AW67-AX67),2),"") -> 13402.84 | AZ67: Payroll | BA67: SALVA, IRENE U
A68: =IF(B68="","",COUNTA($B$10:B68)) -> 59 | B68: 2026-01-0027 | C68: 46036 | E68: FRANCISCO, ULYSSES H. | F68: PAD | G68: Development Management Officer II | H68: =IF(AZ68="Payroll",VLOOKUP(E68,'CODE 2'!$R:$S,2,FALSE),"0") -> 15 | I68: O. ESETS | J68: OK | M68: =IFERROR(VLOOKUP($H68,'CODE 2'!$J:$K,2,FALSE)," ") -> 36619 | N68: =IFERROR(ROUND((M68/2),2),"") -> 18309.5 | O68: =IFERROR((M68/22)," ") -> 1664.5 | P68: =IFERROR((O68/8),"") -> 208.0625 | Q68: =IFERROR((P68/60),"") -> 3.4677083 | R68: =IF(AZ68="Payroll","11","") -> 11 | S68: =IFERROR(ROUND((O68*R68),2)," ") -> 18309.5 | T68: 0 | U68: 0 | V68: 0 | W68: =IFERROR(ROUND(($O68*$T68),2)," ") -> 0 | X68: =IFERROR(ROUND(($P68*$U68),2),"") -> 0 | Y68: =IFERROR(ROUND(($Q68*$V68),2),"") -> 0 | AC68: =IFERROR(ROUND(($O68*$Z68),2)," ") -> 0 | AD68: =IFERROR(ROUND(($P68*$AA68),2),"") -> 0 | AE68: =IFERROR(ROUND(($Q68*$AB68),2),"") -> 0 | AI68: =IFERROR(ROUND(($O68*$AF68),2)," ") -> 0 | AJ68: =IFERROR(ROUND(($P68*$AG68),2),"") -> 0 | AK68: =IFERROR(ROUND(($Q68*$AH68),2),"") -> 0 | AL68: =IFERROR(ROUND(($W68+$AC68+$AI68),2),"") -> 0 | AM68: =IFERROR(ROUND(($X68+$AD68+$AJ68),2),"") -> 0 | AN68: =IFERROR(ROUND(($Y68+$AE68+$AK68),2),"") -> 0 | AO68: =SUM(AL68:AN68) -> 0 | AR68: =IFERROR(ROUND((S68-AO68-AP68),2),"") -> 18309.5 | AY68: =IFERROR(ROUND((AR68-AS68-AT68-AU68-AV68-AW68-AX68),2),"") -> 18309.5 | AZ68: Payroll | BA68: SALVANIA, JEFFREY
A69: =IF(B69="","",COUNTA($B$10:B69)) -> 60 | B69: 2026-01-0028 | C69: 46036 | E69: DITCHE, ALLIAH LYN P. | F69: PAD | G69: Development Management Officer II | H69: =IF(AZ69="Payroll",VLOOKUP(E69,'CODE 2'!$R:$S,2,FALSE),"0") -> 15 | I69: O. ESETS | J69: OK | M69: =IFERROR(VLOOKUP($H69,'CODE 2'!$J:$K,2,FALSE)," ") -> 36619 | N69: =IFERROR(ROUND((M69/2),2),"") -> 18309.5 | O69: =IFERROR((M69/22)," ") -> 1664.5 | P69: =IFERROR((O69/8),"") -> 208.0625 | Q69: =IFERROR((P69/60),"") -> 3.4677083 | R69: =IF(AZ69="Payroll","11","") -> 11 | S69: =IFERROR(ROUND((O69*R69),2)," ") -> 18309.5 | T69: 0 | U69: 0 | V69: 2 | W69: =IFERROR(ROUND(($O69*$T69),2)," ") -> 0 | X69: =IFERROR(ROUND(($P69*$U69),2),"") -> 0 | Y69: =IFERROR(ROUND(($Q69*$V69),2),"") -> 6.94 | AC69: =IFERROR(ROUND(($O69*$Z69),2)," ") -> 0 | AD69: =IFERROR(ROUND(($P69*$AA69),2),"") -> 0 | AE69: =IFERROR(ROUND(($Q69*$AB69),2),"") -> 0 | AI69: =IFERROR(ROUND(($O69*$AF69),2)," ") -> 0 | AJ69: =IFERROR(ROUND(($P69*$AG69),2),"") -> 0 | AK69: =IFERROR(ROUND(($Q69*$AH69),2),"") -> 0 | AL69: =IFERROR(ROUND(($W69+$AC69+$AI69),2),"") -> 0 | AM69: =IFERROR(ROUND(($X69+$AD69+$AJ69),2),"") -> 0 | AN69: =IFERROR(ROUND(($Y69+$AE69+$AK69),2),"") -> 6.94 | AO69: =SUM(AL69:AN69) -> 6.94 | AR69: =IFERROR(ROUND((S69-AO69-AP69),2),"") -> 18302.56 | AY69: =IFERROR(ROUND((AR69-AS69-AT69-AU69-AV69-AW69-AX69),2),"") -> 18302.56 | AZ69: Payroll | BA69: SASIS, BRINGKLY B.
A70: =IF(B70="","",COUNTA($B$10:B70)) -> 61 | B70: 2026-01-0032 | C70: 46036 | E70: CORDOVA, JOEL M. | F70: PAD | G70: Encoder | H70: =IF(AZ70="Payroll",VLOOKUP(E70,'CODE 2'!$R:$S,2,FALSE),"0") -> 6 | I70: FPMA/CORN | J70: OK | M70: =IFERROR(VLOOKUP($H70,'CODE 2'!$J:$K,2,FALSE)," ") -> 17553 | N70: =IFERROR(ROUND((M70/2),2),"") -> 8776.5 | O70: =IFERROR((M70/22)," ") -> 797.86364 | P70: =IFERROR((O70/8),"") -> 99.732955 | Q70: =IFERROR((P70/60),"") -> 1.6622159 | R70: =IF(AZ70="Payroll","11","") -> 11 | S70: =IFERROR(ROUND((O70*R70),2)," ") -> 8776.5 | T70: 0 | U70: 0 | V70: 0 | W70: =IFERROR(ROUND(($O70*$T70),2)," ") -> 0 | X70: =IFERROR(ROUND(($P70*$U70),2),"") -> 0 | Y70: =IFERROR(ROUND(($Q70*$V70),2),"") -> 0 | AC70: =IFERROR(ROUND(($O70*$Z70),2)," ") -> 0 | AD70: =IFERROR(ROUND(($P70*$AA70),2),"") -> 0 | AE70: =IFERROR(ROUND(($Q70*$AB70),2),"") -> 0 | AI70: =IFERROR(ROUND(($O70*$AF70),2)," ") -> 0 | AJ70: =IFERROR(ROUND(($P70*$AG70),2),"") -> 0 | AK70: =IFERROR(ROUND(($Q70*$AH70),2),"") -> 0 | AL70: =IFERROR(ROUND(($W70+$AC70+$AI70),2),"") -> 0 | AM70: =IFERROR(ROUND(($X70+$AD70+$AJ70),2),"") -> 0 | AN70: =IFERROR(ROUND(($Y70+$AE70+$AK70),2),"") -> 0 | AO70: =SUM(AL70:AN70) -> 0 | AR70: =IFERROR(ROUND((S70-AO70-AP70),2),"") -> 8776.5 | AY70: =IFERROR(ROUND((AR70-AS70-AT70-AU70-AV70-AW70-AX70),2),"") -> 8776.5 | AZ70: Payroll | BA70: SERDONCILLO, RANIL G.
A71: =IF(B71="","",COUNTA($B$10:B71)) -> 62 | B71: 2026-01-0030 | C71: 46036 | E71: ARANAZ, CZAREE JOSIAH A. | F71: PAD | G71: Agriculturist I | H71: =IF(AZ71="Payroll",VLOOKUP(E71,'CODE 2'!$R:$S,2,FALSE),"0") -> 11 | I71: FPMA/RICE | J71: OK | M71: =IFERROR(VLOOKUP($H71,'CODE 2'!$J:$K,2,FALSE)," ") -> 27000 | N71: =IFERROR(ROUND((M71/2),2),"") -> 13500 | O71: =IFERROR((M71/22)," ") -> 1227.2727 | P71: =IFERROR((O71/8),"") -> 153.40909 | Q71: =IFERROR((P71/60),"") -> 2.5568182 | R71: 11 | S71: =IFERROR(ROUND((O71*R71),2)," ") -> 13500 | T71: 0 | U71: 0 | V71: 25 | W71: =IFERROR(ROUND(($O71*$T71),2)," ") -> 0 | X71: =IFERROR(ROUND(($P71*$U71),2),"") -> 0 | Y71: =IFERROR(ROUND(($Q71*$V71),2),"") -> 63.92 | AC71: =IFERROR(ROUND(($O71*$Z71),2)," ") -> 0 | AD71: =IFERROR(ROUND(($P71*$AA71),2),"") -> 0 | AE71: =IFERROR(ROUND(($Q71*$AB71),2),"") -> 0 | AI71: =IFERROR(ROUND(($O71*$AF71),2)," ") -> 0 | AJ71: =IFERROR(ROUND(($P71*$AG71),2),"") -> 0 | AK71: =IFERROR(ROUND(($Q71*$AH71),2),"") -> 0 | AL71: =IFERROR(ROUND(($W71+$AC71+$AI71),2),"") -> 0 | AM71: =IFERROR(ROUND(($X71+$AD71+$AJ71),2),"") -> 0 | AN71: =IFERROR(ROUND(($Y71+$AE71+$AK71),2),"") -> 63.92 | AO71: =SUM(AL71:AN71) -> 63.92 | AR71: =IFERROR(ROUND((S71-AO71-AP71),2),"") -> 13436.08 | AY71: =IFERROR(ROUND((AR71-AS71-AT71-AU71-AV71-AW71-AX71),2),"") -> 13436.08 | AZ71: Payroll | BA71: TAPIADOR, JACKSON T.
A72: =IF(B72="","",COUNTA($B$10:B72)) -> 63 | B72: 2026-01-0036 | C72: 46036 | E72: AGUSTIN, PAULYN B. | F72: PAD | G72: Agriculturist I | H72: =IF(AZ72="Payroll",VLOOKUP(E72,'CODE 2'!$R:$S,2,FALSE),"0") -> 11 | I72: FPMA/NOAP | J72: OK | M72: =IFERROR(VLOOKUP($H72,'CODE 2'!$J:$K,2,FALSE)," ") -> 27000 | N72: =IFERROR(ROUND((M72/2),2),"") -> 13500 | O72: =IFERROR((M72/22)," ") -> 1227.2727 | P72: =IFERROR((O72/8),"") -> 153.40909 | Q72: =IFERROR((P72/60),"") -> 2.5568182 | R72: 11 | S72: =IFERROR(ROUND((O72*R72),2)," ") -> 13500 | T72: 0 | U72: 0 | V72: 0 | W72: =IFERROR(ROUND(($O72*$T72),2)," ") -> 0 | X72: =IFERROR(ROUND(($P72*$U72),2),"") -> 0 | Y72: =IFERROR(ROUND(($Q72*$V72),2),"") -> 0 | AC72: =IFERROR(ROUND(($O72*$Z72),2)," ") -> 0 | AD72: =IFERROR(ROUND(($P72*$AA72),2),"") -> 0 | AE72: =IFERROR(ROUND(($Q72*$AB72),2),"") -> 0 | AI72: =IFERROR(ROUND(($O72*$AF72),2)," ") -> 0 | AJ72: =IFERROR(ROUND(($P72*$AG72),2),"") -> 0 | AK72: =IFERROR(ROUND(($Q72*$AH72),2),"") -> 0 | AL72: =IFERROR(ROUND(($W72+$AC72+$AI72),2),"") -> 0 | AM72: =IFERROR(ROUND(($X72+$AD72+$AJ72),2),"") -> 0 | AN72: =IFERROR(ROUND(($Y72+$AE72+$AK72),2),"") -> 0 | AO72: =SUM(AL72:AN72) -> 0 | AR72: =IFERROR(ROUND((S72-AO72-AP72),2),"") -> 13500 | AY72: =IFERROR(ROUND((AR72-AS72-AT72-AU72-AV72-AW72-AX72),2),"") -> 13500 | AZ72: Payroll | BA72: TORIO, MARLON P.
A73: =IF(B73="","",COUNTA($B$10:B73)) -> 64 | B73: 2026-01-0055 | C73: 46036 | E73: ANDAYA, APRIL JANE G. | F73: HRMO | G73: Administrative Asst. II | H73: =IF(AZ73="Payroll",VLOOKUP(E73,'CODE 2'!$R:$S,2,FALSE),"0") -> 8 | I73: O. ESETS | J73: OK | M73: =IFERROR(VLOOKUP($H73,'CODE 2'!$J:$K,2,FALSE)," ") -> 19744 | N73: =IFERROR(ROUND((M73/2),2),"") -> 9872 | O73: =IFERROR((M73/22)," ") -> 897.45455 | P73: =IFERROR((O73/8),"") -> 112.18182 | Q73: =IFERROR((P73/60),"") -> 1.869697 | R73: =IF(AZ73="Payroll","11","") -> 11 | S73: =IFERROR(ROUND((O73*R73),2)," ") -> 9872 | T73: 0 | U73: 4 | V73: 0 | W73: =IFERROR(ROUND(($O73*$T73),2)," ") -> 0 | X73: =IFERROR(ROUND(($P73*$U73),2),"") -> 448.73 | Y73: =IFERROR(ROUND(($Q73*$V73),2),"") -> 0 | AC73: =IFERROR(ROUND(($O73*$Z73),2)," ") -> 0 | AD73: =IFERROR(ROUND(($P73*$AA73),2),"") -> 0 | AE73: =IFERROR(ROUND(($Q73*$AB73),2),"") -> 0 | AI73: =IFERROR(ROUND(($O73*$AF73),2)," ") -> 0 | AJ73: =IFERROR(ROUND(($P73*$AG73),2),"") -> 0 | AK73: =IFERROR(ROUND(($Q73*$AH73),2),"") -> 0 | AL73: =IFERROR(ROUND(($W73+$AC73+$AI73),2),"") -> 0 | AM73: =IFERROR(ROUND(($X73+$AD73+$AJ73),2),"") -> 448.73 | AN73: =IFERROR(ROUND(($Y73+$AE73+$AK73),2),"") -> 0 | AO73: =SUM(AL73:AN73) -> 448.73 | AR73: =IFERROR(ROUND((S73-AO73-AP73),2),"") -> 9423.27 | AY73: =IFERROR(ROUND((AR73-AS73-AT73-AU73-AV73-AW73-AX73),2),"") -> 9423.27 | AZ73: Payroll | BA73: VERINO, ALLYSON RYAN T.
A74: =IF(B74="","",COUNTA($B$10:B74)) -> 65 | B74: 2026-01-0054 | C74: 46036 | E74: AMBROSIO, JOHN HAROLD F. | F74: HRMO | G74: Training Specialist II | H74: =IF(AZ74="Payroll",VLOOKUP(E74,'CODE 2'!$R:$S,2,FALSE),"0") -> 15 | I74: O. ESETS | J74: OK | M74: =IFERROR(VLOOKUP($H74,'CODE 2'!$J:$K,2,FALSE)," ") -> 36619 | N74: =IFERROR(ROUND((M74/2),2),"") -> 18309.5 | O74: =IFERROR((M74/22)," ") -> 1664.5 | P74: =IFERROR((O74/8),"") -> 208.0625 | Q74: =IFERROR((P74/60),"") -> 3.4677083 | R74: =IF(AZ74="Payroll","11","") -> 11 | S74: =IFERROR(ROUND((O74*R74),2)," ") -> 18309.5 | T74: 0 | U74: 0 | V74: 0 | W74: =IFERROR(ROUND(($O74*$T74),2)," ") -> 0 | X74: =IFERROR(ROUND(($P74*$U74),2),"") -> 0 | Y74: =IFERROR(ROUND(($Q74*$V74),2),"") -> 0 | AC74: =IFERROR(ROUND(($O74*$Z74),2)," ") -> 0 | AD74: =IFERROR(ROUND(($P74*$AA74),2),"") -> 0 | AE74: =IFERROR(ROUND(($Q74*$AB74),2),"") -> 0 | AI74: =IFERROR(ROUND(($O74*$AF74),2)," ") -> 0 | AJ74: =IFERROR(ROUND(($P74*$AG74),2),"") -> 0 | AK74: =IFERROR(ROUND(($Q74*$AH74),2),"") -> 0 | AL74: =IFERROR(ROUND(($W74+$AC74+$AI74),2),"") -> 0 | AM74: =IFERROR(ROUND(($X74+$AD74+$AJ74),2),"") -> 0 | AN74: =IFERROR(ROUND(($Y74+$AE74+$AK74),2),"") -> 0 | AO74: =SUM(AL74:AN74) -> 0 | AR74: =IFERROR(ROUND((S74-AO74-AP74),2),"") -> 18309.5 | AY74: =IFERROR(ROUND((AR74-AS74-AT74-AU74-AV74-AW74-AX74),2),"") -> 18309.5 | AZ74: Payroll | BA74: WALICAN, CARLA S.
A75: =IF(B75="","",COUNTA($B$10:B75)) -> 66 | B75: 2026-01-0053 | C75: 46036 | E75: NIÑO, COLENE MAE B. | F75: HRMO | G75: Training Specialist II | H75: =IF(AZ75="Payroll",VLOOKUP(E75,'CODE 2'!$R:$S,2,FALSE),"0") -> 15 | I75: O. ESETS | J75: OK | M75: =IFERROR(VLOOKUP($H75,'CODE 2'!$J:$K,2,FALSE)," ") -> 36619 | N75: =IFERROR(ROUND((M75/2),2),"") -> 18309.5 | O75: =IFERROR((M75/22)," ") -> 1664.5 | P75: =IFERROR((O75/8),"") -> 208.0625 | Q75: =IFERROR((P75/60),"") -> 3.4677083 | R75: =IF(AZ75="Payroll","11","") -> 11 | S75: =IFERROR(ROUND((O75*R75),2)," ") -> 18309.5 | T75: 0 | U75: 0 | V75: 0 | W75: =IFERROR(ROUND(($O75*$T75),2)," ") -> 0 | X75: =IFERROR(ROUND(($P75*$U75),2),"") -> 0 | Y75: =IFERROR(ROUND(($Q75*$V75),2),"") -> 0 | AC75: =IFERROR(ROUND(($O75*$Z75),2)," ") -> 0 | AD75: =IFERROR(ROUND(($P75*$AA75),2),"") -> 0 | AE75: =IFERROR(ROUND(($Q75*$AB75),2),"") -> 0 | AI75: =IFERROR(ROUND(($O75*$AF75),2)," ") -> 0 | AJ75: =IFERROR(ROUND(($P75*$AG75),2),"") -> 0 | AK75: =IFERROR(ROUND(($Q75*$AH75),2),"") -> 0 | AL75: =IFERROR(ROUND(($W75+$AC75+$AI75),2),"") -> 0 | AM75: =IFERROR(ROUND(($X75+$AD75+$AJ75),2),"") -> 0 | AN75: =IFERROR(ROUND(($Y75+$AE75+$AK75),2),"") -> 0 | AO75: =SUM(AL75:AN75) -> 0 | AR75: =IFERROR(ROUND((S75-AO75-AP75),2),"") -> 18309.5 | AY75: =IFERROR(ROUND((AR75-AS75-AT75-AU75-AV75-AW75-AX75),2),"") -> 18309.5 | AZ75: Payroll | BA75: YUGA, MYKA ALEXZA B.
W76: =IFERROR(ROUND(($O76*$T76),2)," ") -> 0 | X76: =IFERROR(ROUND(($P76*$U76),2),"") -> 0 | Y76: =IFERROR(ROUND(($Q76*$V76),2),"") -> 0 | AI76: =IFERROR(ROUND(($O76*$AF76),2)," ") -> 0 | AJ76: =IFERROR(ROUND(($P76*$AG76),2),"") -> 0 | AK76: =IFERROR(ROUND(($Q76*$AH76),2),"") -> 0 | AL76: =IFERROR(ROUND(($W76+$AC76+$AI76),2),"") -> 0 | AM76: =IFERROR(ROUND(($X76+$AD76+$AJ76),2),"") -> 0 | AN76: =IFERROR(ROUND(($Y76+$AE76+$AK76),2),"") -> 0 | AO76: =SUM(AL76:AN76) -> 0
A77: Total | N77: 0 | S77: =SUM(S10:S75) -> 675458 | AI77: =SUM(AI10:AI76) -> 0 | AJ77: =SUM(AJ10:AJ76) -> 0 | AK77: =SUM(AK10:AK76) -> 0 | AL77: =SUM(AL10:AL75) -> 17705.99 | AM77: =SUM(AM10:AM75) -> 2691.46 | AN77: =SUM(AN10:AN75) -> 906.48 | AO77: =SUM(AO10:AO75) -> 21303.93 | AP77: =SUM(AP10:AP74) -> 0.03 | AR77: =SUM(AR10:AR75) -> 654154.1 | AS77: =SUM(AS10:AS75) -> 0 | AT77: =SUM(AT10:AT75) -> 3476.09 | AU77: =SUM(AU10:AU75) -> 8000 | AV77: =SUM(AV10:AV75) -> 1779.65 | AW77: =SUM(AW10:AW75) -> 0 | AX77: =SUM(AX10:AX75) -> 0 | AY77: =SUM(AY10:AY75) -> 640898.36 | AZ77: =SUM(AZ10:AZ73) -> 0
C79: NO TAX EXEMPTION
C80: END OF CONTRACT
C82: CFIDP Voucher
C83: Revolving Fund
C84: NEW

Sheet GENERAL PAYROLL
E9: GENERAL PAYROLL
E11: Prepared by: Jonalyn T. Tolero
E13: We hereby acknowledge to have received from Valentina S. Cagumbay, Admin. Officer III, the sums herein specified opposite our respective names, being in full compensation of our
E14: services for the period of February 16-28, 2026
D15: Name | F15: Position | G15: Office | H15: Number of Days
I16: Salary per Day | J16: Half Month Salary | K16: Less | N16: Less | Q16: Less | U16: add/less | V16: GROSS AMOUNT | W16: Less | Y16: Less | AC16: Total Net Received
K17: Absences | L17: Late/UT | M17: =K17&"/"&L17 -> Absences/Late/UT | N17: Absences | O17: Late/UT | P17: Absences/Late/UT | Q17: Absences | R17: Late/UT | S17: Absences/Late/UT | T17: Total Absences/Late/UT | U17: Clothing and Others | W17: Withholding Tax | Y17: Accommodation for the Month of | Z17: Water | AA17: Electric | AB17: Repairs
K18: February 1-15, 2026 | M18: =K18 -> February 1-15, 2026 | N18: February 16-28, 2026 | P18: =N18 -> February 16-28, 2026 | S18: =Q18 -> 0 | W18: 0.02 | X18: 0.1
C20: 1-CDMD | D20: =IF(E20="","",COUNTA($E$20:E20)) -> 1 | E20: =IFERROR(VLOOKUP(C20,CODE!$B:$D,3,FALSE)," ") -> AUSTRIA, CHRISTIAN JOCEF B. | F20: =VLOOKUP($C20,CODE!$B:$F,5,FALSE) -> Administrative Asst. II | G20: =VLOOKUP($C20,CODE!$B:$F,4,FALSE) -> CDMD | H20: ='MASTER DATA'!R10 -> 11 | I20: =SUMIF('MASTER DATA'!$E:$E,'GENERAL PAYROLL'!$E20,'MASTER DATA'!$O:$O) -> 897.45455 | J20: =SUMIF('MASTER DATA'!$E:$E,'GENERAL PAYROLL'!$E20,'MASTER DATA'!$N:$N) -> 9872 | K20: =SUMIF('MASTER DATA'!$E:$E,'GENERAL PAYROLL'!$E20,'MASTER DATA'!$W:$W) -> 0 | L20: =SUMIF('MASTER DATA'!$E:$E,'GENERAL PAYROLL'!$E20,'MASTER DATA'!$X:$X)+SUMIF('MASTER DATA'!$E:$E,'GENERAL PAYROLL'!$E20,'MASTER DATA'!$Y:$Y) -> 0 | M20: =SUM(K20:L20) -> 0 | N20: =SUMIF('MASTER DATA'!$E:$E,'GENERAL PAYROLL'!$E20,'MASTER DATA'!$AC:$AC) -> 0 | O20: =SUMIF('MASTER DATA'!$E:$E,'GENERAL PAYROLL'!$E20,'MASTER DATA'!$AD:$AD)+SUMIF('MASTER DATA'!$E:$E,'GENERAL PAYROLL'!$E20,'MASTER DATA'!$AE:$AE) -> 0 | P20: =SUM(N20:O20) -> 0 | Q20: =SUMIF('MASTER DATA'!$E:$E,'GENERAL PAYROLL'!$E20,'MASTER DATA'!$AI:$AI) -> 0 | R20: =SUMIF('MASTER DATA'!$E:$E,'GENERAL PAYROLL'!$E20,'MASTER DATA'!$AJ:$AJ)+SUMIF('MASTER DATA'!$E:$E,'GENERAL PAYROLL'!$E20,'MASTER DATA'!$AK:$AK) -> 0 | S20: =SUM(Q20:R20) -> 0 | T20: =SUMIF('MASTER DATA'!$E:$E,'GENERAL PAYROLL'!$E20,'MASTER DATA'!$AO:$AO) -> 0 | U20: =SUMIF('MASTER DATA'!$E:$E,'GENERAL PAYROLL'!$E20,'MASTER DATA'!$AP:$AP) -> 0 | V20: =SUMIF('MASTER DATA'!$E:$E,'GENERAL PAYROLL'!$E20,'MASTER DATA'!$AR:$AR) -> 9872 | W20: =SUMIF('MASTER DATA'!$E:$E,'GENERAL PAYROLL'!$E20,'MASTER DATA'!$AS:$AS) -> 0 | X20: =SUMIF('MASTER DATA'!$E:$E,'GENERAL PAYROLL'!$E20,'MASTER DATA'!$AT:$AT) -> 0 | Y20: =SUMIF('MASTER DATA'!$E:$E,'GENERAL PAYROLL'!$E20,'MASTER DATA'!$AU:$AU) -> 0 | Z20: =SUMIF('MASTER DATA'!$E:$E,'GENERAL PAYROLL'!$E20,'MASTER DATA'!$AV:$AV) -> 0 | AA20: =SUMIF('MASTER DATA'!$E:$E,'GENERAL PAYROLL'!$E20,'MASTER DATA'!$AW:$AW) -> 0 | AB20: =SUMIF('MASTER DATA'!$E:$E,'GENERAL PAYROLL'!$E20,'MASTER DATA'!$AX:$AX) -> 0 | AC20: =SUMIF('MASTER DATA'!$E:$E,'GENERAL PAYROLL'!$E20,'MASTER DATA'!$AY:$AY) -> 9872 | AD20: =IF(E20>=1,"SHOW","HIDE") -> SHOW
C21: 2-CDMD | D21: =IF(E21="","",COUNTA($E$20:E21)) -> 2 | E21: =IFERROR(VLOOKUP(C21,CODE!$B:$D,3,FALSE)," ") -> PASTOR, JANELLE E. | F21: Development Management Officer I | G21: =VLOOKUP($C21,CODE!$B:$F,4,FALSE) -> CDMD | H21: 11 | I21: =SUMIF('MASTER DATA'!$E:$E,'GENERAL PAYROLL'!$E21,'MASTER DATA'!$O:$O) -> 1227.2727 | J21: =SUMIF('MASTER DATA'!$E:$E,'GENERAL PAYROLL'!$E21,'MASTER DATA'!$N:$N) -> 13500 | K21: =SUMIF('MASTER DATA'!$E:$E,'GENERAL PAYROLL'!$E21,'MASTER DATA'!$W:$W) -> 0 | L21: =SUMIF('MASTER DATA'!$E:$E,'GENERAL PAYROLL'!$E21,'MASTER DATA'!$X:$X)+SUMIF('MASTER DATA'!$E:$E,'GENERAL PAYROLL'!$E21,'MASTER DATA'!$Y:$Y) -> 0 | M21: =SUM(K21:L21) -> 0 | N21: =SUMIF('MASTER DATA'!$E:$E,'GENERAL PAYROLL'!$E21,'MASTER DATA'!$AC:$AC) -> 0 | O21: =SUMIF('MASTER DATA'!$E:$E,'GENERAL PAYROLL'!$E21,'MASTER DATA'!$AD:$AD)+SUMIF('MASTER DATA'!$E:$E,'GENERAL PAYROLL'!$E21,'MASTER DATA'!$AE:$AE) -> 0 | P21: =SUM(N21:O21) -> 0 | Q21: =SUMIF('MASTER DATA'!$E:$E,'GENERAL PAYROLL'!$E21,'MASTER DATA'!$AI:$AI) -> 0 | R21: =SUMIF('MASTER DATA'!$E:$E,'GENERAL PAYROLL'!$E21,'MASTER DATA'!$AJ:$AJ)+SUMIF('MASTER DATA'!$E:$E,'GENERAL PAYROLL'!$E21,'MASTER DATA'!$AK:$AK) -> 0 | S21: =SUM(Q21:R21) -> 0 | T21: =SUMIF('MASTER DATA'!$E:$E,'GENERAL PAYROLL'!$E21,'MASTER DATA'!$AO:$AO) -> 0 | U21: =SUMIF('MASTER DATA'!$E:$E,'GENERAL PAYROLL'!$E21,'MASTER DATA'!$AP:$AP) -> 0 | V21: =SUMIF('MASTER DATA'!$E:$E,'GENERAL PAYROLL'!$E21,'MASTER DATA'!$AR:$AR) -> 13500 | W21: =SUMIF('MASTER DATA'!$E:$E,'GENERAL PAYROLL'!$E21,'MASTER DATA'!$AS:$AS) -> 0 | X21: =SUMIF('MASTER DATA'!$E:$E,'GENERAL PAYROLL'!$E21,'MASTER DATA'!$AT:$AT) -> 0 | Y21: =SUMIF('MASTER DATA'!$E:$E,'GENERAL PAYROLL'!$E21,'MASTER DATA'!$AU:$AU) -> 0 | Z21: =SUMIF('MASTER DATA'!$E:$E,'GENERAL PAYROLL'!$E21,'MASTER DATA'!$AV:$AV) -> 0 | AA21: =SUMIF('MASTER DATA'!$E:$E,'GENERAL PAYROLL'!$E21,'MASTER DATA'!$AW:$AW) -> 0 | AB21: =SUMIF('MASTER DATA'!$E:$E,'GENERAL PAYROLL'!$E21,'MASTER DATA'!$AX:$AX) -> 0 | AC21: =SUMIF('MASTER DATA'!$E:$E,'GENERAL PAYROLL'!$E21,'MASTER DATA'!$AY:$AY) -> 13500 | AD21: =IF(E21>=1,"SHOW","HIDE") -> SHOW
C22: 3-CDMD | D22: =IF(E22="","",COUNTA($E$20:E22)) -> 3 | E22: =IFERROR(VLOOKUP(C22,CODE!$B:$D,3,FALSE)," ") -> RODRIGUEZ, MA. RUFFA A. | F22: =VLOOKUP($C22,CODE!$B:$F,5,FALSE) -> Development Management Officer II | G22: =VLOOKUP($C22,CODE!$B:$F,4,FALSE) -> CDMD | H22: 11 | I22: =SUMIF('MASTER DATA'!$E:$E,'GENERAL PAYROLL'!$E22,'MASTER DATA'!$O:$O) -> 1664.5 | J22: =SUMIF('MASTER DATA'!$E:$E,'GENERAL PAYROLL'!$E22,'MASTER DATA'!$N:$N) -> 18309.5 | K22: =SUMIF('MASTER DATA'!$E:$E,'GENERAL PAYROLL'!$E22,'MASTER DATA'!$W:$W) -> 0 | L22: =SUMIF('MASTER DATA'!$E:$E,'GENERAL PAYROLL'!$E22,'MASTER DATA'!$X:$X)+SUMIF('MASTER DATA'!$E:$E,'GENERAL PAYROLL'!$E22,'MASTER DATA'!$Y:$Y) -> 0 | M22: =SUM(K22:L22) -> 0 | N22: =SUMIF('MASTER DATA'!$E:$E,'GENERAL PAYROLL'!$E22,'MASTER DATA'!$AC:$AC) -> 0 | O22: =SUMIF('MASTER DATA'!$E:$E,'GENERAL PAYROLL'!$E22,'MASTER DATA'!$AD:$AD)+SUMIF('MASTER DATA'!$E:$E,'GENERAL PAYROLL'!$E22,'MASTER DATA'!$AE:$AE) -> 0 | P22: =SUM(N22:O22) -> 0 | Q22: =SUMIF('MASTER DATA'!$E:$E,'GENERAL PAYROLL'!$E22,'MASTER DATA'!$AI:$AI) -> 0 | R22: =SUMIF('MASTER DATA'!$E:$E,'GENERAL PAYROLL'!$E22,'MASTER DATA'!$AJ:$AJ)+SUMIF('MASTER DATA'!$E:$E,'GENERAL PAYROLL'!$E22,'MASTER DATA'!$AK:$AK) -> 0 | S22: =SUM(Q22:R22) -> 0 | T22: =SUMIF('MASTER DATA'!$E:$E,'GENERAL PAYROLL'!$E22,'MASTER DATA'!$AO:$AO) -> 0 | U22: =SUMIF('MASTER DATA'!$E:$E,'GENERAL PAYROLL'!$E22,'MASTER DATA'!$AP:$AP) -> 0 | V22: =SUMIF('MASTER DATA'!$E:$E,'GENERAL PAYROLL'!$E22,'MASTER DATA'!$AR:$AR) -> 18309.5 | W22: =SUMIF('MASTER DATA'!$E:$E,'GENERAL PAYROLL'!$E22,'MASTER DATA'!$AS:$AS) -> 0 | X22: =SUMIF('MASTER DATA'!$E:$E,'GENERAL PAYROLL'!$E22,'MASTER DATA'!$AT:$AT) -> 0 | Y22: =SUMIF('MASTER DATA'!$E:$E,'GENERAL PAYROLL'!$E22,'MASTER DATA'!$AU:$AU) -> 0 | Z22: =SUMIF('MASTER DATA'!$E:$E,'GENERAL PAYROLL'!$E22,'MASTER DATA'!$AV:$AV) -> 0 | AA22: =SUMIF('MASTER DATA'!$E:$E,'GENERAL PAYROLL'!$E22,'MASTER DATA'!$AW:$AW) -> 0 | AB22: =SUMIF('MASTER DATA'!$E:$E,'GENERAL PAYROLL'!$E22,'MASTER DATA'!$AX:$AX) -> 0 | AC22: =SUMIF('MASTER DATA'!$E:$E,'GENERAL PAYROLL'!$E22,'MASTER DATA'!$AY:$AY) -> 18309.5 | AD22: =IF(E22>=1,"SHOW","HIDE") -> SHOW
C23: 4-CDMD | D23: =IF(E23="","",COUNTA($E$20:E23)) -> 4 | E23: =IFERROR(VLOOKUP(C23,CODE!$B:$D,3,FALSE)," ") -> OQUINDO, SHEILA JANE G. | F23: =VLOOKUP($C23,CODE!$B:$F,5,FALSE) -> Development Management Officer I | G23: =VLOOKUP($C23,CODE!$B:$F,4,FALSE) -> CDMD | H23: 11 | I23: =SUMIF('MASTER DATA'!$E:$E,'GENERAL PAYROLL'!$E23,'MASTER DATA'!$O:$O) -> 0 | J23: =SUMIF('MASTER DATA'!$E:$E,'GENERAL PAYROLL'!$E23,'MASTER DATA'!$N:$N) -> 0 | K23: =SUMIF('MASTER DATA'!$E:$E,'GENERAL PAYROLL'!$E23,'MASTER DATA'!$W:$W) -> 0 | L23: =SUMIF('MASTER DATA'!$E:$E,'GENERAL PAYROLL'!$E23,'MASTER DATA'!$X:$X)+SUMIF('MASTER DATA'!$E:$E,'GENERAL PAYROLL'!$E23,'MASTER DATA'!$Y:$Y) -> 0 | M23: =SUM(K23:L23) -> 0 | N23: =SUMIF('MASTER DATA'!$E:$E,'GENERAL PAYROLL'!$E23,'MASTER DATA'!$AC:$AC) -> 0 | O23: =SUMIF('MASTER DATA'!$E:$E,'GENERAL PAYROLL'!$E23,'MASTER DATA'!$AD:$AD)+SUMIF('MASTER DATA'!$E:$E,'GENERAL PAYROLL'!$E23,'MASTER DATA'!$AE:$AE) -> 0 | P23: =SUM(N23:O23) -> 0 | Q23: =SUMIF('MASTER DATA'!$E:$E,'GENERAL PAYROLL'!$E23,'MASTER DATA'!$AI:$AI) -> 0 | R23: =SUMIF('MASTER DATA'!$E:$E,'GENERAL PAYROLL'!$E23,'MASTER DATA'!$AJ:$AJ)+SUMIF('MASTER DATA'!$E:$E,'GENERAL PAYROLL'!$E23,'MASTER DATA'!$AK:$AK) -> 0 | S23: =SUM(Q23:R23) -> 0 | T23: =SUMIF('MASTER DATA'!$E:$E,'GENERAL PAYROLL'!$E23,'MASTER DATA'!$AO:$AO) -> 0 | U23: =SUMIF('MASTER DATA'!$E:$E,'GENERAL PAYROLL'!$E23,'MASTER DATA'!$AP:$AP) -> 0 | V23: =SUMIF('MASTER DATA'!$E:$E,'GENERAL PAYROLL'!$E23,'MASTER DATA'!$AR:$AR) -> 0 | W23: =SUMIF('MASTER DATA'!$E:$E,'GENERAL PAYROLL'!$E23,'MASTER DATA'!$AS:$AS) -> 0 | X23: =SUMIF('MASTER DATA'!$E:$E,'GENERAL PAYROLL'!$E23,'MASTER DATA'!$AT:$AT) -> 0 | Y23: =SUMIF('MASTER DATA'!$E:$E,'GENERAL PAYROLL'!$E23,'MASTER DATA'!$AU:$AU) -> 0 | Z23: =SUMIF('MASTER DATA'!$E:$E,'GENERAL PAYROLL'!$E23,'MASTER DATA'!$AV:$AV) -> 0 | AA23: =SUMIF('MASTER DATA'!$E:$E,'GENERAL PAYROLL'!$E23,'MASTER DATA'!$AW:$AW) -> 0 | AB23: =SUMIF('MASTER DATA'!$E:$E,'GENERAL PAYROLL'!$E23,'MASTER DATA'!$AX:$AX) -> 0 | AC23: =SUMIF('MASTER DATA'!$E:$E,'GENERAL PAYROLL'!$E23,'MASTER DATA'!$AY:$AY) -> 0 | AD23: =IF(E23>=1,"SHOW","HIDE") -> SHOW
C24: 1-PPD | D24: =IF(E24="","",COUNTA($E$20:E24)) -> 5 | E24: =IFERROR(VLOOKUP(C24,CODE!$B:$D,3,FALSE)," ") -> ESMER, GLECY R. | F24: =VLOOKUP($C24,CODE!$B:$F,5,FALSE) -> Administrative Asst. II | G24: =VLOOKUP($C24,CODE!$B:$F,4,FALSE) -> PPD | H24: 11 | I24: =SUMIF('MASTER DATA'!$E:$E,'GENERAL PAYROLL'!$E24,'MASTER DATA'!$O:$O) -> 897.45455 | J24: =SUMIF('MASTER DATA'!$E:$E,'GENERAL PAYROLL'!$E24,'MASTER DATA'!$N:$N) -> 9872 | K24: =SUMIF('MASTER DATA'!$E:$E,'GENERAL PAYROLL'!$E24,'MASTER DATA'!$W:$W) -> 0 | L24: =SUMIF('MASTER DATA'!$E:$E,'GENERAL PAYROLL'!$E24,'MASTER DATA'!$X:$X)+SUMIF('MASTER DATA'!$E:$E,'GENERAL PAYROLL'!$E24,'MASTER DATA'!$Y:$Y) -> 0 | M24: =SUM(K24:L24) -> 0 | N24: =SUMIF('MASTER DATA'!$E:$E,'GENERAL PAYROLL'!$E24,'MASTER DATA'!$AC:$AC) -> 0 | O24: =SUMIF('MASTER DATA'!$E:$E,'GENERAL PAYROLL'!$E24,'MASTER DATA'!$AD:$AD)+SUMIF('MASTER DATA'!$E:$E,'GENERAL PAYROLL'!$E24,'MASTER DATA'!$AE:$AE) -> 0 | P24: =SUM(N24:O24) -> 0 | Q24: =SUMIF('MASTER DATA'!$E:$E,'GENERAL PAYROLL'!$E24,'MASTER DATA'!$AI:$AI) -> 0 | R24: =SUMIF('MASTER DATA'!$E:$E,'GENERAL PAYROLL'!$E24,'MASTER DATA'!$AJ:$AJ)+SUMIF('MASTER DATA'!$E:$E,'GENERAL PAYROLL'!$E24,'MASTER DATA'!$AK:$AK) -> 0 | S24: =SUM(Q24:R24) -> 0 | T24: =SUMIF('MASTER DATA'!$E:$E,'GENERAL PAYROLL'!$E24,'MASTER DATA'!$AO:$AO) -> 0 | U24: =SUMIF('MASTER DATA'!$E:$E,'GENERAL PAYROLL'!$E24,'MASTER DATA'!$AP:$AP) -> 0 | V24: =SUMIF('MASTER DATA'!$E:$E,'GENERAL PAYROLL'!$E24,'MASTER DATA'!$AR:$AR) -> 9872 | W24: =SUMIF('MASTER DATA'!$E:$E,'GENERAL PAYROLL'!$E24,'MASTER DATA'!$AS:$AS) -> 0 | X24: =SUMIF('MASTER DATA'!$E:$E,'GENERAL PAYROLL'!$E24,'MASTER DATA'!$AT:$AT) -> 0 | Y24: =SUMIF('MASTER DATA'!$E:$E,'GENERAL PAYROLL'!$E24,'MASTER DATA'!$AU:$AU) -> 2000 | Z24: =SUMIF('MASTER DATA'!$E:$E,'GENERAL PAYROLL'!$E24,'MASTER DATA'!$AV:$AV) -> 395.48 | AA24: =SUMIF('MASTER DATA'!$E:$E,'GENERAL PAYROLL'!$E24,'MASTER DATA'!$AW:$AW) -> 0 | AB24: =SUMIF('MASTER DATA'!$E:$E,'GENERAL PAYROLL'!$E24,'MASTER DATA'!$AX:$AX) -> 0 | AC24: =SUMIF('MASTER DATA'!$E:$E,'GENERAL PAYROLL'!$E24,'MASTER DATA'!$AY:$AY) -> 7476.52 | AD24: =IF(E24>=1,"SHOW","HIDE") -> SHOW
C25: 2-PPD | D25: =IF(E25="","",COUNTA($E$20:E25)) -> 6 | E25: =IFERROR(VLOOKUP(C25,CODE!$B:$D,3,FALSE)," ") -> GALABAY, CHRISTIANEL B. | F25: =VLOOKUP($C25,CODE!$B:$F,5,FALSE) -> Planning Officer II | G25: =VLOOKUP($C25,CODE!$B:$F,4,FALSE) -> PPD | H25: 11 | I25: =SUMIF('MASTER DATA'!$E:$E,'GENERAL PAYROLL'!$E25,'MASTER DATA'!$O:$O) -> 0 | J25: =SUMIF('MASTER DATA'!$E:$E,'GENERAL PAYROLL'!$E25,'MASTER DATA'!$N:$N) -> 0 | K25: =SUMIF('MASTER DATA'!$E:$E,'GENERAL PAYROLL'!$E25,'MASTER DATA'!$W:$W) -> 0 | L25: =SUMIF('MASTER DATA'!$E:$E,'GENERAL PAYROLL'!$E25,'MASTER DATA'!$X:$X)+SUMIF('MASTER DATA'!$E:$E,'GENERAL PAYROLL'!$E25,'MASTER DATA'!$Y:$Y) -> 0 | M25: =SUM(K25:L25) -> 0 | N25: =SUMIF('MASTER DATA'!$E:$E,'GENERAL PAYROLL'!$E25,'MASTER DATA'!$AC:$AC) -> 0 | O25: =SUMIF('MASTER DATA'!$E:$E,'GENERAL PAYROLL'!$E25,'MASTER DATA'!$AD:$AD)+SUMIF('MASTER DATA'!$E:$E,'GENERAL PAYROLL'!$E25,'MASTER DATA'!$AE:$AE) -> 0 | P25: =SUM(N25:O25) -> 0 | Q25: =SUMIF('MASTER DATA'!$E:$E,'GENERAL PAYROLL'!$E25,'MASTER DATA'!$AI:$AI) -> 0 | R25: =SUMIF('MASTER DATA'!$E:$E,'GENERAL PAYROLL'!$E25,'MASTER DATA'!$AJ:$AJ)+SUMIF('MASTER DATA'!$E:$E,'GENERAL PAYROLL'!$E25,'MASTER DATA'!$AK:$AK) -> 0 | S25: =SUM(Q25:R25) -> 0 | T25: =SUMIF('MASTER DATA'!$E:$E,'GENERAL PAYROLL'!$E25,'MASTER DATA'!$AO:$AO) -> 0 | U25: =SUMIF('MASTER DATA'!$E:$E,'GENERAL PAYROLL'!$E25,'MASTER DATA'!$AP:$AP) -> 0 | V25: =SUMIF('MASTER DATA'!$E:$E,'GENERAL PAYROLL'!$E25,'MASTER DATA'!$AR:$AR) -> 0 | W25: =SUMIF('MASTER DATA'!$E:$E,'GENERAL PAYROLL'!$E25,'MASTER DATA'!$AS:$AS) -> 0 | X25: =SUMIF('MASTER DATA'!$E:$E,'GENERAL PAYROLL'!$E25,'MASTER DATA'!$AT:$AT) -> 0 | Y25: =SUMIF('MASTER DATA'!$E:$E,'GENERAL PAYROLL'!$E25,'MASTER DATA'!$AU:$AU) -> 0 | Z25: =SUMIF('MASTER DATA'!$E:$E,'GENERAL PAYROLL'!$E25,'MASTER DATA'!$AV:$AV) -> 0 | AA25: =SUMIF('MASTER DATA'!$E:$E,'GENERAL PAYROLL'!$E25,'MASTER DATA'!$AW:$AW) -> 0 | AB25: =SUMIF('MASTER DATA'!$E:$E,'GENERAL PAYROLL'!$E25,'MASTER DATA'!$AX:$AX) -> 0 | AC25: =SUMIF('MASTER DATA'!$E:$E,'GENERAL PAYROLL'!$E25,'MASTER DATA'!$AY:$AY) -> 0 | AD25: =IF(E25>=1,"SHOW","HIDE") -> SHOW
C26: 4-PPD | D26: =IF(E26="","",COUNTA($E$20:E26)) -> 7 | E26: =IFERROR(VLOOKUP(C26,CODE!$B:$D,3,FALSE)," ") -> NILO, FAITH PERL A. | F26: =VLOOKUP($C26,CODE!$B:$F,5,FALSE) -> Planning Officer I | G26: =VLOOKUP($C26,CODE!$B:$F,4,FALSE) -> PPD | H26: 11 | I26: =SUMIF('MASTER DATA'!$E:$E,'GENERAL PAYROLL'!$E26,'MASTER DATA'!$O:$O) -> 1227.2727 | J26: =SUMIF('MASTER DATA'!$E:$E,'GENERAL PAYROLL'!$E26,'MASTER DATA'!$N:$N) -> 13500 | K26: =SUMIF('MASTER DATA'!$E:$E,'GENERAL PAYROLL'!$E26,'MASTER DATA'!$W:$W) -> 0 | L26: =SUMIF('MASTER DATA'!$E:$E,'GENERAL PAYROLL'!$E26,'MASTER DATA'!$X:$X)+SUMIF('MASTER DATA'!$E:$E,'GENERAL PAYROLL'!$E26,'MASTER DATA'!$Y:$Y) -> 10.23 | M26: =SUM(K26:L26) -> 10.23 | N26: =SUMIF('MASTER DATA'!$E:$E,'GENERAL PAYROLL'!$E26,'MASTER DATA'!$AC:$AC) -> 0 | O26: =SUMIF('MASTER DATA'!$E:$E,'GENERAL PAYROLL'!$E26,'MASTER DATA'!$AD:$AD)+SUMIF('MASTER DATA'!$E:$E,'GENERAL PAYROLL'!$E26,'MASTER DATA'!$AE:$AE) -> 0 | P26: =SUM(N26:O26) -> 0 | Q26: =SUMIF('MASTER DATA'!$E:$E,'GENERAL PAYROLL'!$E26,'MASTER DATA'!$AI:$AI) -> 0 | R26: =SUMIF('MASTER DATA'!$E:$E,'GENERAL PAYROLL'!$E26,'MASTER DATA'!$AJ:$AJ)+SUMIF('MASTER DATA'!$E:$E,'GENERAL PAYROLL'!$E26,'MASTER DATA'!$AK:$AK) -> 0 | S26: =SUM(Q26:R26) -> 0 | T26: =SUMIF('MASTER DATA'!$E:$E,'GENERAL PAYROLL'!$E26,'MASTER DATA'!$AO:$AO) -> 10.23 | U26: =SUMIF('MASTER DATA'!$E:$E,'GENERAL PAYROLL'!$E26,'MASTER DATA'!$AP:$AP) -> 0 | V26: =SUMIF('MASTER DATA'!$E:$E,'GENERAL PAYROLL'!$E26,'MASTER DATA'!$AR:$AR) -> 13489.77 | W26: =SUMIF('MASTER DATA'!$E:$E,'GENERAL PAYROLL'!$E26,'MASTER DATA'!$AS:$AS) -> 0 | X26: =SUMIF('MASTER DATA'!$E:$E,'GENERAL PAYROLL'!$E26,'MASTER DATA'!$AT:$AT) -> 0 | Y26: =SUMIF('MASTER DATA'!$E:$E,'GENERAL PAYROLL'!$E26,'MASTER DATA'!$AU:$AU) -> 0 | Z26: =SUMIF('MASTER DATA'!$E:$E,'GENERAL PAYROLL'!$E26,'MASTER DATA'!$AV:$AV) -> 0 | AA26: =SUMIF('MASTER DATA'!$E:$E,'GENERAL PAYROLL'!$E26,'MASTER DATA'!$AW:$AW) -> 0 | AB26: =SUMIF('MASTER DATA'!$E:$E,'GENERAL PAYROLL'!$E26,'MASTER DATA'!$AX:$AX) -> 0 | AC26: =SUMIF('MASTER DATA'!$E:$E,'GENERAL PAYROLL'!$E26,'MASTER DATA'!$AY:$AY) -> 13489.77 | AD26: =IF(E26>=1,"SHOW","HIDE") -> SHOW
C27: 5-PPD | D27: =IF(E27="","",COUNTA($E$20:E27)) -> 8 | E27: =IFERROR(VLOOKUP(C27,CODE!$B:$D,3,FALSE)," ") -> VERINO, ALLYSON RYAN T. | F27: =VLOOKUP($C27,CODE!$B:$F,5,FALSE) -> Project Development Officer I | G27: =VLOOKUP($C27,CODE!$B:$F,4,FALSE) -> PPD | H27: 11 | I27: =SUMIF('MASTER DATA'!$E:$E,'GENERAL PAYROLL'!$E27,'MASTER DATA'!$O:$O) -> 1227.2727 | J27: =SUMIF('MASTER DATA'!$E:$E,'GENERAL PAYROLL'!$E27,'MASTER DATA'!$N:$N) -> 13500 | K27: =SUMIF('MASTER DATA'!$E:$E,'GENERAL PAYROLL'!$E27,'MASTER DATA'!$W:$W) -> 0 | L27: =SUMIF('MASTER DATA'!$E:$E,'GENERAL PAYROLL'!$E27,'MASTER DATA'!$X:$X)+SUMIF('MASTER DATA'!$E:$E,'GENERAL PAYROLL'!$E27,'MASTER DATA'!$Y:$Y) -> 0 | M27: =SUM(K27:L27) -> 0 | N27: =SUMIF('MASTER DATA'!$E:$E,'GENERAL PAYROLL'!$E27,'MASTER DATA'!$AC:$AC) -> 0 | O27: =SUMIF('MASTER DATA'!$E:$E,'GENERAL PAYROLL'!$E27,'MASTER DATA'!$AD:$AD)+SUMIF('MASTER DATA'!$E:$E,'GENERAL PAYROLL'!$E27,'MASTER DATA'!$AE:$AE) -> 0 | P27: =SUM(N27:O27) -> 0 | Q27: =SUMIF('MASTER DATA'!$E:$E,'GENERAL PAYROLL'!$E27,'MASTER DATA'!$AI:$AI) -> 0 | R27: =SUMIF('MASTER DATA'!$E:$E,'GENERAL PAYROLL'!$E27,'MASTER DATA'!$AJ:$AJ)+SUMIF('MASTER DATA'!$E:$E,'GENERAL PAYROLL'!$E27,'MASTER DATA'!$AK:$AK) -> 0 | S27: =SUM(Q27:R27) -> 0 | T27: =SUMIF('MASTER DATA'!$E:$E,'GENERAL PAYROLL'!$E27,'MASTER DATA'!$AO:$AO) -> 0 | U27: =SUMIF('MASTER DATA'!$E:$E,'GENERAL PAYROLL'!$E27,'MASTER DATA'!$AP:$AP) -> 0 | V27: =SUMIF('MASTER DATA'!$E:$E,'GENERAL PAYROLL'!$E27,'MASTER DATA'!$AR:$AR) -> 13500 | W27: =SUMIF('MASTER DATA'!$E:$E,'GENERAL PAYROLL'!$E27,'MASTER DATA'!$AS:$AS) -> 0 | X27: =SUMIF('MASTER DATA'!$E:$E,'GENERAL PAYROLL'!$E27,'MASTER DATA'!$AT:$AT) -> 0 | Y27: =SUMIF('MASTER DATA'!$E:$E,'GENERAL PAYROLL'!$E27,'MASTER DATA'!$AU:$AU) -> 0 | Z27: =SUMIF('MASTER DATA'!$E:$E,'GENERAL PAYROLL'!$E27,'MASTER DATA'!$AV:$AV) -> 0 | AA27: =SUMIF('MASTER DATA'!$E:$E,'GENERAL PAYROLL'!$E27,'MASTER DATA'!$AW:$AW) -> 0 | AB27: =SUMIF('MASTER DATA'!$E:$E,'GENERAL PAYROLL'!$E27,'MASTER DATA'!$AX:$AX) -> 0 | AC27: =SUMIF('MASTER DATA'!$E:$E,'GENERAL PAYROLL'!$E27,'MASTER DATA'!$AY:$AY) -> 13500 | AD27: =IF(E27>=1,"SHOW","HIDE") -> SHOW
C28: 1-ISD | D28: =IF(E28="","",COUNTA($E$20:E28)) -> 9 | E28: =IFERROR(VLOOKUP(C28,CODE!$B:$D,3,FALSE)," ") -> LAMPAS, CHRISTIAN JOSEPH P | F28: =VLOOKUP($C28,CODE!$B:$F,5,FALSE) -> Computer Maintenance Tech. I | G28: =VLOOKUP($C28,CODE!$B:$F,4,FALSE) -> ISD | H28: 11 | I28: =SUMIF('MASTER DATA'!$E:$E,'GENERAL PAYROLL'!$E28,'MASTER DATA'!$O:$O) -> 1227.2727 | J28: =SUMIF('MASTER DATA'!$E:$E,'GENERAL PAYROLL'!$E28,'MASTER DATA'!$N:$N) -> 13500 | K28: =SUMIF('MASTER DATA'!$E:$E,'GENERAL PAYROLL'!$E28,'MASTER DATA'!$W:$W) -> 1227.27 | L28: =SUMIF('MASTER DATA'!$E:$E,'GENERAL PAYROLL'!$E28,'MASTER DATA'!$X:$X)+SUMIF('MASTER DATA'!$E:$E,'GENERAL PAYROLL'!$E28,'MASTER DATA'!$Y:$Y) -> 0 | M28: =SUM(K28:L28) -> 1227.27 | N28: =SUMIF('MASTER DATA'!$E:$E,'GENERAL PAYROLL'!$E28,'MASTER DATA'!$AC:$AC) -> 0 | O28: =SUMIF('MASTER DATA'!$E:$E,'GENERAL PAYROLL'!$E28,'MASTER DATA'!$AD:$AD)+SUMIF('MASTER DATA'!$E:$E,'GENERAL PAYROLL'!$E28,'MASTER DATA'!$AE:$AE) -> 0 | P28: =SUM(N28:O28) -> 0 | Q28: =SUMIF('MASTER DATA'!$E:$E,'GENERAL PAYROLL'!$E28,'MASTER DATA'!$AI:$AI) -> 0 | R28: =SUMIF('MASTER DATA'!$E:$E,'GENERAL PAYROLL'!$E28,'MASTER DATA'!$AJ:$AJ)+SUMIF('MASTER DATA'!$E:$E,'GENERAL PAYROLL'!$E28,'MASTER DATA'!$AK:$AK) -> 0 | S28: =SUM(Q28:R28) -> 0 | T28: =SUMIF('MASTER DATA'!$E:$E,'GENERAL PAYROLL'!$E28,'MASTER DATA'!$AO:$AO) -> 1227.27 | U28: =SUMIF('MASTER DATA'!$E:$E,'GENERAL PAYROLL'!$E28,'MASTER DATA'!$AP:$AP) -> 0 | V28: =SUMIF('MASTER DATA'!$E:$E,'GENERAL PAYROLL'!$E28,'MASTER DATA'!$AR:$AR) -> 12272.73 | W28: =SUMIF('MASTER DATA'!$E:$E,'GENERAL PAYROLL'!$E28,'MASTER DATA'!$AS:$AS) -> 0 | X28: =SUMIF('MASTER DATA'!$E:$E,'GENERAL PAYROLL'!$E28,'MASTER DATA'!$AT:$AT) -> 0 | Y28: =SUMIF('MASTER DATA'!$E:$E,'GENERAL PAYROLL'!$E28,'MASTER DATA'!$AU:$AU) -> 0 | Z28: =SUMIF('MASTER DATA'!$E:$E,'GENERAL PAYROLL'!$E28,'MASTER DATA'!$AV:$AV) -> 0 | AA28: =SUMIF('MASTER DATA'!$E:$E,'GENERAL PAYROLL'!$E28,'MASTER DATA'!$AW:$AW) -> 0 | AB28: =SUMIF('MASTER DATA'!$E:$E,'GENERAL PAYROLL'!$E28,'MASTER DATA'!$AX:$AX) -> 0 | AC28: =SUMIF('MASTER DATA'!$E:$E,'GENERAL PAYROLL'!$E28,'MASTER DATA'!$AY:$AY) -> 12272.73 | AD28: =IF(E28>=1,"SHOW","HIDE") -> SHOW
C29: 2-ISD | D29: =IF(E29="","",COUNTA($E$20:E29)) -> 10 | E29: =IFERROR(VLOOKUP(C29,CODE!$B:$D,3,FALSE)," ") -> MANDANI, AVE M. | F29: =VLOOKUP($C29,CODE!$B:$F,5,FALSE) -> Bookbinder III | G29: =VLOOKUP($C29,CODE!$B:$F,4,FALSE) -> ISD | H29: 11 | I29: =SUMIF('MASTER DATA'!$E:$E,'GENERAL PAYROLL'!$E29,'MASTER DATA'!$O:$O) -> 846.36364 | J29: =SUMIF('MASTER DATA'!$E:$E,'GENERAL PAYROLL'!$E29,'MASTER DATA'!$N:$N) -> 9310 | K29: =SUMIF('MASTER DATA'!$E:$E,'GENERAL PAYROLL'!$E29,'MASTER DATA'!$W:$W) -> 0 | L29: =SUMIF('MASTER DATA'!$E:$E,'GENERAL PAYROLL'!$E29,'MASTER DATA'!$X:$X)+SUMIF('MASTER DATA'!$E:$E,'GENERAL PAYROLL'!$E29,'MASTER DATA'!$Y:$Y) -> 0 | M29: =SUM(K29:L29) -> 0 | N29: =SUMIF('MASTER DATA'!$E:$E,'GENERAL PAYROLL'!$E29,'MASTER DATA'!$AC:$AC) -> 0 | O29: =SUMIF('MASTER DATA'!$E:$E,'GENERAL PAYROLL'!$E29,'MASTER DATA'!$AD:$AD)+SUMIF('MASTER DATA'!$E:$E,'GENERAL PAYROLL'!$E29,'MASTER DATA'!$AE:$AE) -> 0 | P29: =SUM(N29:O29) -> 0 | Q29: =SUMIF('MASTER DATA'!$E:$E,'GENERAL PAYROLL'!$E29,'MASTER DATA'!$AI:$AI) -> 0 | R29: =SUMIF('MASTER DATA'!$E:$E,'GENERAL PAYROLL'!$E29,'MASTER DATA'!$AJ:$AJ)+SUMIF('MASTER DATA'!$E:$E,'GENERAL PAYROLL'!$E29,'MASTER DATA'!$AK:$AK) -> 0 | S29: =SUM(Q29:R29) -> 0 | T29: =SUMIF('MASTER DATA'!$E:$E,'GENERAL PAYROLL'!$E29,'MASTER DATA'!$AO:$AO) -> 0 | U29: =SUMIF('MASTER DATA'!$E:$E,'GENERAL PAYROLL'!$E29,'MASTER DATA'!$AP:$AP) -> 0 | V29: =SUMIF('MASTER DATA'!$E:$E,'GENERAL PAYROLL'!$E29,'MASTER DATA'!$AR:$AR) -> 9310 | W29: =SUMIF('MASTER DATA'!$E:$E,'GENERAL PAYROLL'!$E29,'MASTER DATA'!$AS:$AS) -> 0 | X29: =SUMIF('MASTER DATA'!$E:$E,'GENERAL PAYROLL'!$E29,'MASTER DATA'!$AT:$AT) -> 0 | Y29: =SUMIF('MASTER DATA'!$E:$E,'GENERAL PAYROLL'!$E29,'MASTER DATA'!$AU:$AU) -> 0 | Z29: =SUMIF('MASTER DATA'!$E:$E,'GENERAL PAYROLL'!$E29,'MASTER DATA'!$AV:$AV) -> 0 | AA29: =SUMIF('MASTER DATA'!$E:$E,'GENERAL PAYROLL'!$E29,'MASTER DATA'!$AW:$AW) -> 0 | AB29: =SUMIF('MASTER DATA'!$E:$E,'GENERAL PAYROLL'!$E29,'MASTER DATA'!$AX:$AX) -> 0 | AC29: =SUMIF('MASTER DATA'!$E:$E,'GENERAL PAYROLL'!$E29,'MASTER DATA'!$AY:$AY) -> 9310 | AD29: =IF(E29>=1,"SHOW","HIDE") -> SHOW
C30: 3-ISD | D30: =IF(E30="","",COUNTA($E$20:E30)) -> 11 | E30: =IFERROR(VLOOKUP(C30,CODE!$B:$D,3,FALSE)," ") -> PERNIA, JONAS S. | F30: =VLOOKUP($C30,CODE!$B:$F,5,FALSE) -> Administrative Asst. II | G30: =VLOOKUP($C30,CODE!$B:$F,4,FALSE) -> ISD | H30: 11 | I30: =SUMIF('MASTER DATA'!$E:$E,'GENERAL PAYROLL'!$E30,'MASTER DATA'!$O:$O) -> 897.45455 | J30: =SUMIF('MASTER DATA'!$E:$E,'GENERAL PAYROLL'!$E30,'MASTER DATA'!$N:$N) -> 9872 | K30: =SUMIF('MASTER DATA'!$E:$E,'GENERAL PAYROLL'!$E30,'MASTER DATA'!$W:$W) -> 0 | L30: =SUMIF('MASTER DATA'!$E:$E,'GENERAL PAYROLL'!$E30,'MASTER DATA'!$X:$X)+SUMIF('MASTER DATA'!$E:$E,'GENERAL PAYROLL'!$E30,'MASTER DATA'!$Y:$Y) -> 0 | M30: =SUM(K30:L30) -> 0 | N30: =SUMIF('MASTER DATA'!$E:$E,'GENERAL PAYROLL'!$E30,'MASTER DATA'!$AC:$AC) -> 0 | O30: =SUMIF('MASTER DATA'!$E:$E,'GENERAL PAYROLL'!$E30,'MASTER DATA'!$AD:$AD)+SUMIF('MASTER DATA'!$E:$E,'GENERAL PAYROLL'!$E30,'MASTER DATA'!$AE:$AE) -> 0 | P30: =SUM(N30:O30) -> 0 | Q30: =SUMIF('MASTER DATA'!$E:$E,'GENERAL PAYROLL'!$E30,'MASTER DATA'!$AI:$AI) -> 0 | R30: =SUMIF('MASTER DATA'!$E:$E,'GENERAL PAYROLL'!$E30,'MASTER DATA'!$AJ:$AJ)+SUMIF('MASTER DATA'!$E:$E,'GENERAL PAYROLL'!$E30,'MASTER DATA'!$AK:$AK) -> 0 | S30: =SUM(Q30:R30) -> 0 | T30: =SUMIF('MASTER DATA'!$E:$E,'GENERAL PAYROLL'!$E30,'MASTER DATA'!$AO:$AO) -> 0 | U30: =SUMIF('MASTER DATA'!$E:$E,'GENERAL PAYROLL'!$E30,'MASTER DATA'!$AP:$AP) -> 0 | V30: =SUMIF('MASTER DATA'!$E:$E,'GENERAL PAYROLL'!$E30,'MASTER DATA'!$AR:$AR) -> 9872 | W30: =SUMIF('MASTER DATA'!$E:$E,'GENERAL PAYROLL'!$E30,'MASTER DATA'!$AS:$AS) -> 0 | X30: =SUMIF('MASTER DATA'!$E:$E,'GENERAL PAYROLL'!$E30,'MASTER DATA'!$AT:$AT) -> 0 | Y30: =SUMIF('MASTER DATA'!$E:$E,'GENERAL PAYROLL'!$E30,'MASTER DATA'!$AU:$AU) -> 0 | Z30: =SUMIF('MASTER DATA'!$E:$E,'GENERAL PAYROLL'!$E30,'MASTER DATA'!$AV:$AV) -> 0 | AA30: =SUMIF('MASTER DATA'!$E:$E,'GENERAL PAYROLL'!$E30,'MASTER DATA'!$AW:$AW) -> 0 | AB30: =SUMIF('MASTER DATA'!$E:$E,'GENERAL PAYROLL'!$E30,'MASTER DATA'!$AX:$AX) -> 0 | AC30: =SUMIF('MASTER DATA'!$E:$E,'GENERAL PAYROLL'!$E30,'MASTER DATA'!$AY:$AY) -> 9872 | AD30: =IF(E30>=1,"SHOW","HIDE") -> SHOW
C31: 4-ISD | D31: =IF(E31="","",COUNTA($E$20:E31)) -> 12 | E31: =IFERROR(VLOOKUP(C31,CODE!$B:$D,3,FALSE)," ") -> BALANGATAN, JUN CHRISTOPHER C. | F31: =VLOOKUP($C31,CODE!$B:$F,5,FALSE) -> Media Production Specialist I | G31: =VLOOKUP($C31,CODE!$B:$F,4,FALSE) -> ISD | H31: 11 | I31: =SUMIF('MASTER DATA'!$E:$E,'GENERAL PAYROLL'!$E31,'MASTER DATA'!$O:$O) -> 1227.2727 | J31: =SUMIF('MASTER DATA'!$E:$E,'GENERAL PAYROLL'!$E31,'MASTER DATA'!$N:$N) -> 13500 | K31: =SUMIF('MASTER DATA'!$E:$E,'GENERAL PAYROLL'!$E31,'MASTER DATA'!$W:$W) -> 0 | L31: =SUMIF('MASTER DATA'!$E:$E,'GENERAL PAYROLL'!$E31,'MASTER DATA'!$X:$X)+SUMIF('MASTER DATA'!$E:$E,'GENERAL PAYROLL'!$E31,'MASTER DATA'!$Y:$Y) -> 0 | M31: =SUM(K31:L31) -> 0 | N31: =SUMIF('MASTER DATA'!$E:$E,'GENERAL PAYROLL'!$E31,'MASTER DATA'!$AC:$AC) -> 0 | O31: =SUMIF('MASTER DATA'!$E:$E,'GENERAL PAYROLL'!$E31,'MASTER DATA'!$AD:$AD)+SUMIF('MASTER DATA'!$E:$E,'GENERAL PAYROLL'!$E31,'MASTER DATA'!$AE:$AE) -> 0 | P31: =SUM(N31:O31) -> 0 | Q31: =SUMIF('MASTER DATA'!$E:$E,'GENERAL PAYROLL'!$E31,'MASTER DATA'!$AI:$AI) -> 0 | R31: =SUMIF('MASTER DATA'!$E:$E,'GENERAL PAYROLL'!$E31,'MASTER DATA'!$AJ:$AJ)+SUMIF('MASTER DATA'!$E:$E,'GENERAL PAYROLL'!$E31,'MASTER DATA'!$AK:$AK) -> 0 | S31: =SUM(Q31:R31) -> 0 | T31: =SUMIF('MASTER DATA'!$E:$E,'GENERAL PAYROLL'!$E31,'MASTER DATA'!$AO:$AO) -> 0 | U31: =SUMIF('MASTER DATA'!$E:$E,'GENERAL PAYROLL'!$E31,'MASTER DATA'!$AP:$AP) -> 0 | V31: =SUMIF('MASTER DATA'!$E:$E,'GENERAL PAYROLL'!$E31,'MASTER DATA'!$AR:$AR) -> 13500 | W31: =SUMIF('MASTER DATA'!$E:$E,'GENERAL PAYROLL'!$E31,'MASTER DATA'!$AS:$AS) -> 0 | X31: =SUMIF('MASTER DATA'!$E:$E,'GENERAL PAYROLL'!$E31,'MASTER DATA'!$AT:$AT) -> 0 | Y31: =SUMIF('MASTER DATA'!$E:$E,'GENERAL PAYROLL'!$E31,'MASTER DATA'!$AU:$AU) -> 0 | Z31: =SUMIF('MASTER DATA'!$E:$E,'GENERAL PAYROLL'!$E31,'MASTER DATA'!$AV:$AV) -> 0 | AA31: =SUMIF('MASTER DATA'!$E:$E,'GENERAL PAYROLL'!$E31,'MASTER DATA'!$AW:$AW) -> 0 | AB31: =SUMIF('MASTER DATA'!$E:$E,'GENERAL PAYROLL'!$E31,'MASTER DATA'!$AX:$AX) -> 0 | AC31: =SUMIF('MASTER DATA'!$E:$E,'GENERAL PAYROLL'!$E31,'MASTER DATA'!$AY:$AY) -> 13500 | AD31: =IF(E31>=1,"SHOW","HIDE") -> SHOW
C32: 5-ISD | D32: =IF(E32="","",COUNTA($E$20:E32)) -> 13 | E32: =IFERROR(VLOOKUP(C32,CODE!$B:$D,3,FALSE)," ") -> LIM, KLEIN ANSON G. | F32: =VLOOKUP($C32,CODE!$B:$F,5,FALSE) -> Agriculturist I | G32: =VLOOKUP($C32,CODE!$B:$F,4,FALSE) -> ISD | H32: 11 | I32: =SUMIF('MASTER DATA'!$E:$E,'GENERAL PAYROLL'!$E32,'MASTER DATA'!$O:$O) -> 1227.2727 | J32: =SUMIF('MASTER DATA'!$E:$E,'GENERAL PAYROLL'!$E32,'MASTER DATA'!$N:$N) -> 13500 | K32: =SUMIF('MASTER DATA'!$E:$E,'GENERAL PAYROLL'!$E32,'MASTER DATA'!$W:$W) -> 0 | L32: =SUMIF('MASTER DATA'!$E:$E,'GENERAL PAYROLL'!$E32,'MASTER DATA'!$X:$X)+SUMIF('MASTER DATA'!$E:$E,'GENERAL PAYROLL'!$E32,'MASTER DATA'!$Y:$Y) -> 23.01 | M32: =SUM(K32:L32) -> 23.01 | N32: =SUMIF('MASTER DATA'!$E:$E,'GENERAL PAYROLL'!$E32,'MASTER DATA'!$AC:$AC) -> 0 | O32: =SUMIF('MASTER DATA'!$E:$E,'GENERAL PAYROLL'!$E32,'MASTER DATA'!$AD:$AD)+SUMIF('MASTER DATA'!$E:$E,'GENERAL PAYROLL'!$E32,'MASTER DATA'!$AE:$AE) -> 0 | P32: =SUM(N32:O32) -> 0 | Q32: =SUMIF('MASTER DATA'!$E:$E,'GENERAL PAYROLL'!$E32,'MASTER DATA'!$AI:$AI) -> 0 | R32: =SUMIF('MASTER DATA'!$E:$E,'GENERAL PAYROLL'!$E32,'MASTER DATA'!$AJ:$AJ)+SUMIF('MASTER DATA'!$E:$E,'GENERAL PAYROLL'!$E32,'MASTER DATA'!$AK:$AK) -> 0 | S32: =SUM(Q32:R32) -> 0 | T32: =SUMIF('MASTER DATA'!$E:$E,'GENERAL PAYROLL'!$E32,'MASTER DATA'!$AO:$AO) -> 23.01 | U32: =SUMIF('MASTER DATA'!$E:$E,'GENERAL PAYROLL'!$E32,'MASTER DATA'!$AP:$AP) -> 0 | V32: =SUMIF('MASTER DATA'!$E:$E,'GENERAL PAYROLL'!$E32,'MASTER DATA'!$AR:$AR) -> 13476.99 | W32: =SUMIF('MASTER DATA'!$E:$E,'GENERAL PAYROLL'!$E32,'MASTER DATA'!$AS:$AS) -> 0 | X32: =SUMIF('MASTER DATA'!$E:$E,'GENERAL PAYROLL'!$E32,'MASTER DATA'!$AT:$AT) -> 0 | Y32: =SUMIF('MASTER DATA'!$E:$E,'GENERAL PAYROLL'!$E32,'MASTER DATA'!$AU:$AU) -> 0 | Z32: =SUMIF('MASTER DATA'!$E:$E,'GENERAL PAYROLL'!$E32,'MASTER DATA'!$AV:$AV) -> 0 | AA32: =SUMIF('MASTER DATA'!$E:$E,'GENERAL PAYROLL'!$E32,'MASTER DATA'!$AW:$AW) -> 0 | AB32: =SUMIF('MASTER DATA'!$E:$E,'GENERAL PAYROLL'!$E32,'MASTER DATA'!$AX:$AX) -> 0 | AC32: =SUMIF('MASTER DATA'!$E:$E,'GENERAL PAYROLL'!$E32,'MASTER DATA'!$AY:$AY) -> 13476.99 | AD32: =IF(E32>=1,"SHOW","HIDE") -> SHOW
C33: 6-ISD | D33: =IF(E33="","",COUNTA($E$20:E33)) -> 14 | E33: =IFERROR(VLOOKUP(C33,CODE!$B:$D,3,FALSE)," ") -> AGUAS, DERICKE DUANE C. | F33: =VLOOKUP($C33,CODE!$B:$F,5,FALSE) -> Information Officer I | G33: =VLOOKUP($C33,CODE!$B:$F,4,FALSE) -> ISD | H33: 11 | I33: =SUMIF('MASTER DATA'!$E:$E,'GENERAL PAYROLL'!$E33,'MASTER DATA'!$O:$O) -> 1227.2727 | J33: =SUMIF('MASTER DATA'!$E:$E,'GENERAL PAYROLL'!$E33,'MASTER DATA'!$N:$N) -> 13500 | K33: =SUMIF('MASTER DATA'!$E:$E,'GENERAL PAYROLL'!$E33,'MASTER DATA'!$W:$W) -> 0 | L33: =SUMIF('MASTER DATA'!$E:$E,'GENERAL PAYROLL'!$E33,'MASTER DATA'!$X:$X)+SUMIF('MASTER DATA'!$E:$E,'GENERAL PAYROLL'!$E33,'MASTER DATA'!$Y:$Y) -> 0 | M33: =SUM(K33:L33) -> 0 | N33: =SUMIF('MASTER DATA'!$E:$E,'GENERAL PAYROLL'!$E33,'MASTER DATA'!$AC:$AC) -> 0 | O33: =SUMIF('MASTER DATA'!$E:$E,'GENERAL PAYROLL'!$E33,'MASTER DATA'!$AD:$AD)+SUMIF('MASTER DATA'!$E:$E,'GENERAL PAYROLL'!$E33,'MASTER DATA'!$AE:$AE) -> 0 | P33: =SUM(N33:O33) -> 0 | Q33: =SUMIF('MASTER DATA'!$E:$E,'GENERAL PAYROLL'!$E33,'MASTER DATA'!$AI:$AI) -> 0 | R33: =SUMIF('MASTER DATA'!$E:$E,'GENERAL PAYROLL'!$E33,'MASTER DATA'!$AJ:$AJ)+SUMIF('MASTER DATA'!$E:$E,'GENERAL PAYROLL'!$E33,'MASTER DATA'!$AK:$AK) -> 0 | S33: =SUM(Q33:R33) -> 0 | T33: =SUMIF('MASTER DATA'!$E:$E,'GENERAL PAYROLL'!$E33,'MASTER DATA'!$AO:$AO) -> 0 | U33: =SUMIF('MASTER DATA'!$E:$E,'GENERAL PAYROLL'!$E33,'MASTER DATA'!$AP:$AP) -> 0 | V33: =SUMIF('MASTER DATA'!$E:$E,'GENERAL PAYROLL'!$E33,'MASTER DATA'!$AR:$AR) -> 13500 | W33: =SUMIF('MASTER DATA'!$E:$E,'GENERAL PAYROLL'!$E33,'MASTER DATA'!$AS:$AS) -> 0 | X33: =SUMIF('MASTER DATA'!$E:$E,'GENERAL PAYROLL'!$E33,'MASTER DATA'!$AT:$AT) -> 0 | Y33: =SUMIF('MASTER DATA'!$E:$E,'GENERAL PAYROLL'!$E33,'MASTER DATA'!$AU:$AU) -> 0 | Z33: =SUMIF('MASTER DATA'!$E:$E,'GENERAL PAYROLL'!$E33,'MASTER DATA'!$AV:$AV) -> 0 | AA33: =SUMIF('MASTER DATA'!$E:$E,'GENERAL PAYROLL'!$E33,'MASTER DATA'!$AW:$AW) -> 0 | AB33: =SUMIF('MASTER DATA'!$E:$E,'GENERAL PAYROLL'!$E33,'MASTER DATA'!$AX:$AX) -> 0 | AC33: =SUMIF('MASTER DATA'!$E:$E,'GENERAL PAYROLL'!$E33,'MASTER DATA'!$AY:$AY) -> 13500
C34: 7-ISD | D34: =IF(E34="","",COUNTA($E$20:E34)) -> 15 | E34: BALA, ANGEL D. | F34: =VLOOKUP($C34,CODE!$B:$F,5,FALSE) -> Information Officer I | G34: =VLOOKUP($C34,CODE!$B:$F,4,FALSE) -> ISD | H34: 11 | I34: =SUMIF('MASTER DATA'!$E:$E,'GENERAL PAYROLL'!$E34,'MASTER DATA'!$O:$O) -> 1227.2727 | J34: =SUMIF('MASTER DATA'!$E:$E,'GENERAL PAYROLL'!$E34,'MASTER DATA'!$N:$N) -> 13500 | K34: =SUMIF('MASTER DATA'!$E:$E,'GENERAL PAYROLL'!$E34,'MASTER DATA'!$W:$W) -> 0 | L34: =SUMIF('MASTER DATA'!$E:$E,'GENERAL PAYROLL'!$E34,'MASTER DATA'!$X:$X)+SUMIF('MASTER DATA'!$E:$E,'GENERAL PAYROLL'!$E34,'MASTER DATA'!$Y:$Y) -> 0 | M34: =SUM(K34:L34) -> 0 | N34: =SUMIF('MASTER DATA'!$E:$E,'GENERAL PAYROLL'!$E34,'MASTER DATA'!$AC:$AC) -> 0 | O34: =SUMIF('MASTER DATA'!$E:$E,'GENERAL PAYROLL'!$E34,'MASTER DATA'!$AD:$AD)+SUMIF('MASTER DATA'!$E:$E,'GENERAL PAYROLL'!$E34,'MASTER DATA'!$AE:$AE) -> 0 | P34: =SUM(N34:O34) -> 0 | Q34: =SUMIF('MASTER DATA'!$E:$E,'GENERAL PAYROLL'!$E34,'MASTER DATA'!$AI:$AI) -> 0 | R34: =SUMIF('MASTER DATA'!$E:$E,'GENERAL PAYROLL'!$E34,'MASTER DATA'!$AJ:$AJ)+SUMIF('MASTER DATA'!$E:$E,'GENERAL PAYROLL'!$E34,'MASTER DATA'!$AK:$AK) -> 0 | S34: =SUM(Q34:R34) -> 0 | T34: =SUMIF('MASTER DATA'!$E:$E,'GENERAL PAYROLL'!$E34,'MASTER DATA'!$AO:$AO) -> 0 | U34: =SUMIF('MASTER DATA'!$E:$E,'GENERAL PAYROLL'!$E34,'MASTER DATA'!$AP:$AP) -> 0 | V34: =SUMIF('MASTER DATA'!$E:$E,'GENERAL PAYROLL'!$E34,'MASTER DATA'!$AR:$AR) -> 13500 | W34: =SUMIF('MASTER DATA'!$E:$E,'GENERAL PAYROLL'!$E34,'MASTER DATA'!$AS:$AS) -> 0 | X34: =SUMIF('MASTER DATA'!$E:$E,'GENERAL PAYROLL'!$E34,'MASTER DATA'!$AT:$AT) -> 0 | Y34: =SUMIF('MASTER DATA'!$E:$E,'GENERAL PAYROLL'!$E34,'MASTER DATA'!$AU:$AU) -> 2000 | Z34: =SUMIF('MASTER DATA'!$E:$E,'GENERAL PAYROLL'!$E34,'MASTER DATA'!$AV:$AV) -> 0 | AA34: =SUMIF('MASTER DATA'!$E:$E,'GENERAL PAYROLL'!$E34,'MASTER DATA'!$AW:$AW) -> 0 | AB34: =SUMIF('MASTER DATA'!$E:$E,'GENERAL PAYROLL'!$E34,'MASTER DATA'!$AX:$AX) -> 0 | AC34: =SUMIF('MASTER DATA'!$E:$E,'GENERAL PAYROLL'!$E34,'MASTER DATA'!$AY:$AY) -> 11500
C35: 1-ADO | D35: =IF(E35="","",COUNTA($E$20:E35)) -> 16 | E35: =IFERROR(VLOOKUP(C35,CODE!$B:$D,3,FALSE)," ") -> CAGUMBAY, LIYANNE M. | F35: =VLOOKUP($C35,CODE!$B:$F,5,FALSE) -> Administrative Asst. II | G35: =VLOOKUP($C35,CODE!$B:$F,4,FALSE) -> ADO | H35: 11 | I35: =SUMIF('MASTER DATA'!$E:$E,'GENERAL PAYROLL'!$E35,'MASTER DATA'!$O:$O) -> 897.45455 | J35: =SUMIF('MASTER DATA'!$E:$E,'GENERAL PAYROLL'!$E35,'MASTER DATA'!$N:$N) -> 9872 | K35: =SUMIF('MASTER DATA'!$E:$E,'GENERAL PAYROLL'!$E35,'MASTER DATA'!$W:$W) -> 0 | L35: =SUMIF('MASTER DATA'!$E:$E,'GENERAL PAYROLL'!$E35,'MASTER DATA'!$X:$X)+SUMIF('MASTER DATA'!$E:$E,'GENERAL PAYROLL'!$E35,'MASTER DATA'!$Y:$Y) -> 0 | M35: =SUM(K35:L35) -> 0 | N35: =SUMIF('MASTER DATA'!$E:$E,'GENERAL PAYROLL'!$E35,'MASTER DATA'!$AC:$AC) -> 0 | O35: =SUMIF('MASTER DATA'!$E:$E,'GENERAL PAYROLL'!$E35,'MASTER DATA'!$AD:$AD)+SUMIF('MASTER DATA'!$E:$E,'GENERAL PAYROLL'!$E35,'MASTER DATA'!$AE:$AE) -> 0 | P35: =SUM(N35:O35) -> 0 | Q35: =SUMIF('MASTER DATA'!$E:$E,'GENERAL PAYROLL'!$E35,'MASTER DATA'!$AI:$AI) -> 0 | R35: =SUMIF('MASTER DATA'!$E:$E,'GENERAL PAYROLL'!$E35,'MASTER DATA'!$AJ:$AJ)+SUMIF('MASTER DATA'!$E:$E,'GENERAL PAYROLL'!$E35,'MASTER DATA'!$AK:$AK) -> 0 | S35: =SUM(Q35:R35) -> 0 | T35: =SUMIF('MASTER DATA'!$E:$E,'GENERAL PAYROLL'!$E35,'MASTER DATA'!$AO:$AO) -> 0 | U35: =SUMIF('MASTER DATA'!$E:$E,'GENERAL PAYROLL'!$E35,'MASTER DATA'!$AP:$AP) -> 0 | V35: =SUMIF('MASTER DATA'!$E:$E,'GENERAL PAYROLL'!$E35,'MASTER DATA'!$AR:$AR) -> 9872 | W35: =SUMIF('MASTER DATA'!$E:$E,'GENERAL PAYROLL'!$E35,'MASTER DATA'!$AS:$AS) -> 0 | X35: =SUMIF('MASTER DATA'!$E:$E,'GENERAL PAYROLL'!$E35,'MASTER DATA'!$AT:$AT) -> 0 | Y35: =SUMIF('MASTER DATA'!$E:$E,'GENERAL PAYROLL'!$E35,'MASTER DATA'!$AU:$AU) -> 0 | Z35: =SUMIF('MASTER DATA'!$E:$E,'GENERAL PAYROLL'!$E35,'MASTER DATA'!$AV:$AV) -> 0 | AA35: =SUMIF('MASTER DATA'!$E:$E,'GENERAL PAYROLL'!$E35,'MASTER DATA'!$AW:$AW) -> 0 | AB35: =SUMIF('MASTER DATA'!$E:$E,'GENERAL PAYROLL'!$E35,'MASTER DATA'!$AX:$AX) -> 0 | AC35: =SUMIF('MASTER DATA'!$E:$E,'GENERAL PAYROLL'!$E35,'MASTER DATA'!$AY:$AY) -> 9872 | AD35: =IF(E35>=1,"SHOW","HIDE") -> SHOW
C36: 2-ADO | D36: =IF(E36="","",COUNTA($E$20:E36)) -> 17 | E36: =IFERROR(VLOOKUP(C36,CODE!$B:$D,3,FALSE)," ") -> DE GUZMAN, SWEET JESSABEL M. | F36: =VLOOKUP($C36,CODE!$B:$F,5,FALSE) -> Executive Assistant II | G36: =VLOOKUP($C36,CODE!$B:$F,4,FALSE) -> ADO | H36: 11 | I36: =SUMIF('MASTER DATA'!$E:$E,'GENERAL PAYROLL'!$E36,'MASTER DATA'!$O:$O) -> 1955.9091 | J36: =SUMIF('MASTER DATA'!$E:$E,'GENERAL PAYROLL'!$E36,'MASTER DATA'!$N:$N) -> 21515 | K36: =SUMIF('MASTER DATA'!$E:$E,'GENERAL PAYROLL'!$E36,'MASTER DATA'!$W:$W) -> 0 | L36: =SUMIF('MASTER DATA'!$E:$E,'GENERAL PAYROLL'!$E36,'MASTER DATA'!$X:$X)+SUMIF('MASTER DATA'!$E:$E,'GENERAL PAYROLL'!$E36,'MASTER DATA'!$Y:$Y) -> 0 | M36: =SUM(K36:L36) -> 0 | N36: =SUMIF('MASTER DATA'!$E:$E,'GENERAL PAYROLL'!$E36,'MASTER DATA'!$AC:$AC) -> 0 | O36: =SUMIF('MASTER DATA'!$E:$E,'GENERAL PAYROLL'!$E36,'MASTER DATA'!$AD:$AD)+SUMIF('MASTER DATA'!$E:$E,'GENERAL PAYROLL'!$E36,'MASTER DATA'!$AE:$AE) -> 0 | P36: =SUM(N36:O36) -> 0 | Q36: =SUMIF('MASTER DATA'!$E:$E,'GENERAL PAYROLL'!$E36,'MASTER DATA'!$AI:$AI) -> 0 | R36: =SUMIF('MASTER DATA'!$E:$E,'GENERAL PAYROLL'!$E36,'MASTER DATA'!$AJ:$AJ)+SUMIF('MASTER DATA'!$E:$E,'GENERAL PAYROLL'!$E36,'MASTER DATA'!$AK:$AK) -> 0 | S36: =SUM(Q36:R36) -> 0 | T36: =SUMIF('MASTER DATA'!$E:$E,'GENERAL PAYROLL'!$E36,'MASTER DATA'!$AO:$AO) -> 0 | U36: =SUMIF('MASTER DATA'!$E:$E,'GENERAL PAYROLL'!$E36,'MASTER DATA'!$AP:$AP) -> 0 | V36: =SUMIF('MASTER DATA'!$E:$E,'GENERAL PAYROLL'!$E36,'MASTER DATA'!$AR:$AR) -> 21515 | W36: =SUMIF('MASTER DATA'!$E:$E,'GENERAL PAYROLL'!$E36,'MASTER DATA'!$AS:$AS) -> 0 | X36: =SUMIF('MASTER DATA'!$E:$E,'GENERAL PAYROLL'!$E36,'MASTER DATA'!$AT:$AT) -> 0 | Y36: =SUMIF('MASTER DATA'!$E:$E,'GENERAL PAYROLL'!$E36,'MASTER DATA'!$AU:$AU) -> 0 | Z36: =SUMIF('MASTER DATA'!$E:$E,'GENERAL PAYROLL'!$E36,'MASTER DATA'!$AV:$AV) -> 0 | AA36: =SUMIF('MASTER DATA'!$E:$E,'GENERAL PAYROLL'!$E36,'MASTER DATA'!$AW:$AW) -> 0 | AB36: =SUMIF('MASTER DATA'!$E:$E,'GENERAL PAYROLL'!$E36,'MASTER DATA'!$AX:$AX) -> 0 | AC36: =SUMIF('MASTER DATA'!$E:$E,'GENERAL PAYROLL'!$E36,'MASTER DATA'!$AY:$AY) -> 21515 | AD36: =IF(E36>=1,"SHOW","HIDE") -> SHOW
C37: 1-BGT. | D37: =IF(E37="","",COUNTA($E$20:E37)) -> 18 | E37: =IFERROR(VLOOKUP(C37,CODE!$B:$D,3,FALSE)," ") -> SASIS, BRINGKLY B. | F37: =VLOOKUP($C37,CODE!$B:$F,5,FALSE) -> Administrative Asst. II | G37: =VLOOKUP($C37,CODE!$B:$F,4,FALSE) -> BGT. | H37: 11 | I37: =SUMIF('MASTER DATA'!$E:$E,'GENERAL PAYROLL'!$E37,'MASTER DATA'!$O:$O) -> 0 | J37: =SUMIF('MASTER DATA'!$E:$E,'GENERAL PAYROLL'!$E37,'MASTER DATA'!$N:$N) -> 0 | K37: =SUMIF('MASTER DATA'!$E:$E,'GENERAL PAYROLL'!$E37,'MASTER DATA'!$W:$W) -> 0 | L37: =SUMIF('MASTER DATA'!$E:$E,'GENERAL PAYROLL'!$E37,'MASTER DATA'!$X:$X)+SUMIF('MASTER DATA'!$E:$E,'GENERAL PAYROLL'!$E37,'MASTER DATA'!$Y:$Y) -> 0 | M37: =SUM(K37:L37) -> 0 | N37: =SUMIF('MASTER DATA'!$E:$E,'GENERAL PAYROLL'!$E37,'MASTER DATA'!$AC:$AC) -> 0 | O37: =SUMIF('MASTER DATA'!$E:$E,'GENERAL PAYROLL'!$E37,'MASTER DATA'!$AD:$AD)+SUMIF('MASTER DATA'!$E:$E,'GENERAL PAYROLL'!$E37,'MASTER DATA'!$AE:$AE) -> 0 | P37: =SUM(N37:O37) -> 0 | Q37: =SUMIF('MASTER DATA'!$E:$E,'GENERAL PAYROLL'!$E37,'MASTER DATA'!$AI:$AI) -> 0 | R37: =SUMIF('MASTER DATA'!$E:$E,'GENERAL PAYROLL'!$E37,'MASTER DATA'!$AJ:$AJ)+SUMIF('MASTER DATA'!$E:$E,'GENERAL PAYROLL'!$E37,'MASTER DATA'!$AK:$AK) -> 0 | S37: =SUM(Q37:R37) -> 0 | T37: =SUMIF('MASTER DATA'!$E:$E,'GENERAL PAYROLL'!$E37,'MASTER DATA'!$AO:$AO) -> 0 | U37: =SUMIF('MASTER DATA'!$E:$E,'GENERAL PAYROLL'!$E37,'MASTER DATA'!$AP:$AP) -> 0 | V37: =SUMIF('MASTER DATA'!$E:$E,'GENERAL PAYROLL'!$E37,'MASTER DATA'!$AR:$AR) -> 0 | W37: =SUMIF('MASTER DATA'!$E:$E,'GENERAL PAYROLL'!$E37,'MASTER DATA'!$AS:$AS) -> 0 | X37: =SUMIF('MASTER DATA'!$E:$E,'GENERAL PAYROLL'!$E37,'MASTER DATA'!$AT:$AT) -> 0 | Y37: =SUMIF('MASTER DATA'!$E:$E,'GENERAL PAYROLL'!$E37,'MASTER DATA'!$AU:$AU) -> 0 | Z37: =SUMIF('MASTER DATA'!$E:$E,'GENERAL PAYROLL'!$E37,'MASTER DATA'!$AV:$AV) -> 0 | AA37: =SUMIF('MASTER DATA'!$E:$E,'GENERAL PAYROLL'!$E37,'MASTER DATA'!$AW:$AW) -> 0 | AB37: =SUMIF('MASTER DATA'!$E:$E,'GENERAL PAYROLL'!$E37,'MASTER DATA'!$AX:$AX) -> 0 | AC37: =SUMIF('MASTER DATA'!$E:$E,'GENERAL PAYROLL'!$E37,'MASTER DATA'!$AY:$AY) -> 0 | AD37: =IF(E37>=1,"SHOW","HIDE") -> SHOW
C38: 2-BGT. | D38: =IF(E38="","",COUNTA($E$20:E38)) -> 19 | E38: =IFERROR(VLOOKUP(C38,CODE!$B:$D,3,FALSE)," ") -> SALVA, IRENE U | F38: =VLOOKUP($C38,CODE!$B:$F,5,FALSE) -> Administrative Asst. II | G38: =VLOOKUP($C38,CODE!$B:$F,4,FALSE) -> BGT. | H38: 11 | I38: =SUMIF('MASTER DATA'!$E:$E,'GENERAL PAYROLL'!$E38,'MASTER DATA'!$O:$O) -> 897.45455 | J38: =SUMIF('MASTER DATA'!$E:$E,'GENERAL PAYROLL'!$E38,'MASTER DATA'!$N:$N) -> 9872 | K38: =SUMIF('MASTER DATA'!$E:$E,'GENERAL PAYROLL'!$E38,'MASTER DATA'!$W:$W) -> 0 | L38: =SUMIF('MASTER DATA'!$E:$E,'GENERAL PAYROLL'!$E38,'MASTER DATA'!$X:$X)+SUMIF('MASTER DATA'!$E:$E,'GENERAL PAYROLL'!$E38,'MASTER DATA'!$Y:$Y) -> 0 | M38: =SUM(K38:L38) -> 0 | N38: =SUMIF('MASTER DATA'!$E:$E,'GENERAL PAYROLL'!$E38,'MASTER DATA'!$AC:$AC) -> 0 | O38: =SUMIF('MASTER DATA'!$E:$E,'GENERAL PAYROLL'!$E38,'MASTER DATA'!$AD:$AD)+SUMIF('MASTER DATA'!$E:$E,'GENERAL PAYROLL'!$E38,'MASTER DATA'!$AE:$AE) -> 0 | P38: =SUM(N38:O38) -> 0 | Q38: =SUMIF('MASTER DATA'!$E:$E,'GENERAL PAYROLL'!$E38,'MASTER DATA'!$AI:$AI) -> 0 | R38: =SUMIF('MASTER DATA'!$E:$E,'GENERAL PAYROLL'!$E38,'MASTER DATA'!$AJ:$AJ)+SUMIF('MASTER DATA'!$E:$E,'GENERAL PAYROLL'!$E38,'MASTER DATA'!$AK:$AK) -> 0 | S38: =SUM(Q38:R38) -> 0 | T38: =SUMIF('MASTER DATA'!$E:$E,'GENERAL PAYROLL'!$E38,'MASTER DATA'!$AO:$AO) -> 0 | U38: =SUMIF('MASTER DATA'!$E:$E,'GENERAL PAYROLL'!$E38,'MASTER DATA'!$AP:$AP) -> 0 | V38: =SUMIF('MASTER DATA'!$E:$E,'GENERAL PAYROLL'!$E38,'MASTER DATA'!$AR:$AR) -> 9872 | W38: =SUMIF('MASTER DATA'!$E:$E,'GENERAL PAYROLL'!$E38,'MASTER DATA'!$AS:$AS) -> 0 | X38: =SUMIF('MASTER DATA'!$E:$E,'GENERAL PAYROLL'!$E38,'MASTER DATA'!$AT:$AT) -> 0 | Y38: =SUMIF('MASTER DATA'!$E:$E,'GENERAL PAYROLL'!$E38,'MASTER DATA'!$AU:$AU) -> 0 | Z38: =SUMIF('MASTER DATA'!$E:$E,'GENERAL PAYROLL'!$E38,'MASTER DATA'!$AV:$AV) -> 0 | AA38: =SUMIF('MASTER DATA'!$E:$E,'GENERAL PAYROLL'!$E38,'MASTER DATA'!$AW:$AW) -> 0 | AB38: =SUMIF('MASTER DATA'!$E:$E,'GENERAL PAYROLL'!$E38,'MASTER DATA'!$AX:$AX) -> 0 | AC38: =SUMIF('MASTER DATA'!$E:$E,'GENERAL PAYROLL'!$E38,'MASTER DATA'!$AY:$AY) -> 9872 | AD38: =IF(E38>=1,"SHOW","HIDE") -> SHOW
C39: 3-BGT. | D39: =IF(E39="","",COUNTA($E$20:E39)) -> 20 | E39: =IFERROR(VLOOKUP(C39,CODE!$B:$D,3,FALSE)," ") -> CAIZ, LEONILA D. | F39: =VLOOKUP($C39,CODE!$B:$F,5,FALSE) -> Financial Analyst | G39: =VLOOKUP($C39,CODE!$B:$F,4,FALSE) -> BGT. | H39: 11 | I39: =SUMIF('MASTER DATA'!$E:$E,'GENERAL PAYROLL'!$E39,'MASTER DATA'!$O:$O) -> 2300.7727 | J39: =SUMIF('MASTER DATA'!$E:$E,'GENERAL PAYROLL'!$E39,'MASTER DATA'!$N:$N) -> 25308.5 | K39: =SUMIF('MASTER DATA'!$E:$E,'GENERAL PAYROLL'!$E39,'MASTER DATA'!$W:$W) -> 11503.86 | L39: =SUMIF('MASTER DATA'!$E:$E,'GENERAL PAYROLL'!$E39,'MASTER DATA'!$X:$X)+SUMIF('MASTER DATA'!$E:$E,'GENERAL PAYROLL'!$E39,'MASTER DATA'!$Y:$Y) -> 493.71 | M39: =SUM(K39:L39) -> 11997.57 | N39: =SUMIF('MASTER DATA'!$E:$E,'GENERAL PAYROLL'!$E39,'MASTER DATA'!$AC:$AC) -> 0 | O39: =SUMIF('MASTER DATA'!$E:$E,'GENERAL PAYROLL'!$E39,'MASTER DATA'!$AD:$AD)+SUMIF('MASTER DATA'!$E:$E,'GENERAL PAYROLL'!$E39,'MASTER DATA'!$AE:$AE) -> 0 | P39: =SUM(N39:O39) -> 0 | Q39: =SUMIF('MASTER DATA'!$E:$E,'GENERAL PAYROLL'!$E39,'MASTER DATA'!$AI:$AI) -> 0 | R39: =SUMIF('MASTER DATA'!$E:$E,'GENERAL PAYROLL'!$E39,'MASTER DATA'!$AJ:$AJ)+SUMIF('MASTER DATA'!$E:$E,'GENERAL PAYROLL'!$E39,'MASTER DATA'!$AK:$AK) -> 0 | S39: =SUM(Q39:R39) -> 0 | T39: =SUMIF('MASTER DATA'!$E:$E,'GENERAL PAYROLL'!$E39,'MASTER DATA'!$AO:$AO) -> 11997.57 | U39: =SUMIF('MASTER DATA'!$E:$E,'GENERAL PAYROLL'!$E39,'MASTER DATA'!$AP:$AP) -> 0 | V39: =SUMIF('MASTER DATA'!$E:$E,'GENERAL PAYROLL'!$E39,'MASTER DATA'!$AR:$AR) -> 13310.93 | W39: =SUMIF('MASTER DATA'!$E:$E,'GENERAL PAYROLL'!$E39,'MASTER DATA'!$AS:$AS) -> 0 | X39: =SUMIF('MASTER DATA'!$E:$E,'GENERAL PAYROLL'!$E39,'MASTER DATA'!$AT:$AT) -> 0 | Y39: =SUMIF('MASTER DATA'!$E:$E,'GENERAL PAYROLL'!$E39,'MASTER DATA'!$AU:$AU) -> 0 | Z39: =SUMIF('MASTER DATA'!$E:$E,'GENERAL PAYROLL'!$E39,'MASTER DATA'!$AV:$AV) -> 0 | AA39: =SUMIF('MASTER DATA'!$E:$E,'GENERAL PAYROLL'!$E39,'MASTER DATA'!$AW:$AW) -> 0 | AB39: =SUMIF('MASTER DATA'!$E:$E,'GENERAL PAYROLL'!$E39,'MASTER DATA'!$AX:$AX) -> 0 | AC39: =SUMIF('MASTER DATA'!$E:$E,'GENERAL PAYROLL'!$E39,'MASTER DATA'!$AY:$AY) -> 13310.93
C40: 1-ACCTG. | D40: =IF(E40="","",COUNTA($E$20:E40)) -> 21 | E40: =IFERROR(VLOOKUP(C40,CODE!$B:$D,3,FALSE)," ") -> SALVANIA, JEFFREY | F40: =VLOOKUP($C40,CODE!$B:$F,5,FALSE) -> Administrative Asst. II | G40: =VLOOKUP($C40,CODE!$B:$F,4,FALSE) -> ACCTG. | H40: 11 | I40: =SUMIF('MASTER DATA'!$E:$E,'GENERAL PAYROLL'!$E40,'MASTER DATA'!$O:$O) -> 897.45455 | J40: =SUMIF('MASTER DATA'!$E:$E,'GENERAL PAYROLL'!$E40,'MASTER DATA'!$N:$N) -> 9872 | K40: =SUMIF('MASTER DATA'!$E:$E,'GENERAL PAYROLL'!$E40,'MASTER DATA'!$W:$W) -> 0 | L40: =SUMIF('MASTER DATA'!$E:$E,'GENERAL PAYROLL'!$E40,'MASTER DATA'!$X:$X)+SUMIF('MASTER DATA'!$E:$E,'GENERAL PAYROLL'!$E40,'MASTER DATA'!$Y:$Y) -> 0 | M40: =SUM(K40:L40) -> 0 | N40: =SUMIF('MASTER DATA'!$E:$E,'GENERAL PAYROLL'!$E40,'MASTER DATA'!$AC:$AC) -> 0 | O40: =SUMIF('MASTER DATA'!$E:$E,'GENERAL PAYROLL'!$E40,'MASTER DATA'!$AD:$AD)+SUMIF('MASTER DATA'!$E:$E,'GENERAL PAYROLL'!$E40,'MASTER DATA'!$AE:$AE) -> 0 | P40: =SUM(N40:O40) -> 0 | Q40: =SUMIF('MASTER DATA'!$E:$E,'GENERAL PAYROLL'!$E40,'MASTER DATA'!$AI:$AI) -> 0 | R40: =SUMIF('MASTER DATA'!$E:$E,'GENERAL PAYROLL'!$E40,'MASTER DATA'!$AJ:$AJ)+SUMIF('MASTER DATA'!$E:$E,'GENERAL PAYROLL'!$E40,'MASTER DATA'!$AK:$AK) -> 0 | S40: =SUM(Q40:R40) -> 0 | T40: =SUMIF('MASTER DATA'!$E:$E,'GENERAL PAYROLL'!$E40,'MASTER DATA'!$AO:$AO) -> 0 | U40: =SUMIF('MASTER DATA'!$E:$E,'GENERAL PAYROLL'!$E40,'MASTER DATA'!$AP:$AP) -> 0 | V40: =SUMIF('MASTER DATA'!$E:$E,'GENERAL PAYROLL'!$E40,'MASTER DATA'!$AR:$AR) -> 9872 | W40: =SUMIF('MASTER DATA'!$E:$E,'GENERAL PAYROLL'!$E40,'MASTER DATA'!$AS:$AS) -> 0 | X40: =SUMIF('MASTER DATA'!$E:$E,'GENERAL PAYROLL'!$E40,'MASTER DATA'!$AT:$AT) -> 0 | Y40: =SUMIF('MASTER DATA'!$E:$E,'GENERAL PAYROLL'!$E40,'MASTER DATA'!$AU:$AU) -> 0 | Z40: =SUMIF('MASTER DATA'!$E:$E,'GENERAL PAYROLL'!$E40,'MASTER DATA'!$AV:$AV) -> 0 | AA40: =SUMIF('MASTER DATA'!$E:$E,'GENERAL PAYROLL'!$E40,'MASTER DATA'!$AW:$AW) -> 0 | AB40: =SUMIF('MASTER DATA'!$E:$E,'GENERAL PAYROLL'!$E40,'MASTER DATA'!$AX:$AX) -> 0 | AC40: =SUMIF('MASTER DATA'!$E:$E,'GENERAL PAYROLL'!$E40,'MASTER DATA'!$AY:$AY) -> 9872 | AD40: =IF(E40>=1,"SHOW","HIDE") -> SHOW
C41: 2-ACCTG. | D41: =IF(E41="","",COUNTA($E$20:E41)) -> 22 | E41: =IFERROR(VLOOKUP(C41,CODE!$B:$D,3,FALSE)," ") -> ESTAPON, LESLIE DC. | F41: =VLOOKUP($C41,CODE!$B:$F,5,FALSE) -> Administrative Asst. II | G41: =VLOOKUP($C41,CODE!$B:$F,4,FALSE) -> ACCTG. | H41: 11 | I41: =SUMIF('MASTER DATA'!$E:$E,'GENERAL PAYROLL'!$E41,'MASTER DATA'!$O:$O) -> 0 | J41: =SUMIF('MASTER DATA'!$E:$E,'GENERAL PAYROLL'!$E41,'MASTER DATA'!$N:$N) -> 0 | K41: =SUMIF('MASTER DATA'!$E:$E,'GENERAL PAYROLL'!$E41,'MASTER DATA'!$W:$W) -> 0 | L41: =SUMIF('MASTER DATA'!$E:$E,'GENERAL PAYROLL'!$E41,'MASTER DATA'!$X:$X)+SUMIF('MASTER DATA'!$E:$E,'GENERAL PAYROLL'!$E41,'MASTER DATA'!$Y:$Y) -> 0 | M41: =SUM(K41:L41) -> 0 | N41: =SUMIF('MASTER DATA'!$E:$E,'GENERAL PAYROLL'!$E41,'MASTER DATA'!$AC:$AC) -> 0 | O41: =SUMIF('MASTER DATA'!$E:$E,'GENERAL PAYROLL'!$E41,'MASTER DATA'!$AD:$AD)+SUMIF('MASTER DATA'!$E:$E,'GENERAL PAYROLL'!$E41,'MASTER DATA'!$AE:$AE) -> 0 | P41: =SUM(N41:O41) -> 0 | Q41: =SUMIF('MASTER DATA'!$E:$E,'GENERAL PAYROLL'!$E41,'MASTER DATA'!$AI:$AI) -> 0 | R41: =SUMIF('MASTER DATA'!$E:$E,'GENERAL PAYROLL'!$E41,'MASTER DATA'!$AJ:$AJ)+SUMIF('MASTER DATA'!$E:$E,'GENERAL PAYROLL'!$E41,'MASTER DATA'!$AK:$AK) -> 0 | S41: =SUM(Q41:R41) -> 0 | T41: =SUMIF('MASTER DATA'!$E:$E,'GENERAL PAYROLL'!$E41,'MASTER DATA'!$AO:$AO) -> 0 | U41: =SUMIF('MASTER DATA'!$E:$E,'GENERAL PAYROLL'!$E41,'MASTER DATA'!$AP:$AP) -> 0 | V41: =SUMIF('MASTER DATA'!$E:$E,'GENERAL PAYROLL'!$E41,'MASTER DATA'!$AR:$AR) -> 0 | W41: =SUMIF('MASTER DATA'!$E:$E,'GENERAL PAYROLL'!$E41,'MASTER DATA'!$AS:$AS) -> 0 | X41: =SUMIF('MASTER DATA'!$E:$E,'GENERAL PAYROLL'!$E41,'MASTER DATA'!$AT:$AT) -> 0 | Y41: =SUMIF('MASTER DATA'!$E:$E,'GENERAL PAYROLL'!$E41,'MASTER DATA'!$AU:$AU) -> 0 | Z41: =SUMIF('MASTER DATA'!$E:$E,'GENERAL PAYROLL'!$E41,'MASTER DATA'!$AV:$AV) -> 0 | AA41: =SUMIF('MASTER DATA'!$E:$E,'GENERAL PAYROLL'!$E41,'MASTER DATA'!$AW:$AW) -> 0 | AB41: =SUMIF('MASTER DATA'!$E:$E,'GENERAL PAYROLL'!$E41,'MASTER DATA'!$AX:$AX) -> 0 | AC41: =SUMIF('MASTER DATA'!$E:$E,'GENERAL PAYROLL'!$E41,'MASTER DATA'!$AY:$AY) -> 0 | AD41: =IF(E41>=1,"SHOW","HIDE") -> SHOW
C42: 3-ACCTG. | D42: =IF(E42="","",COUNTA($E$20:E42)) -> 23 | E42: =IFERROR(VLOOKUP(C42,CODE!$B:$D,3,FALSE)," ") -> MARTIN, ORLAN LEONARD E. | F42: =VLOOKUP($C42,CODE!$B:$F,5,FALSE) -> Administrative Asst. II | G42: =VLOOKUP($C42,CODE!$B:$F,4,FALSE) -> ACCTG. | H42: 11 | I42: =SUMIF('MASTER DATA'!$E:$E,'GENERAL PAYROLL'!$E42,'MASTER DATA'!$O:$O) -> 897.45455 | J42: =SUMIF('MASTER DATA'!$E:$E,'GENERAL PAYROLL'!$E42,'MASTER DATA'!$N:$N) -> 9872 | K42: =SUMIF('MASTER DATA'!$E:$E,'GENERAL PAYROLL'!$E42,'MASTER DATA'!$W:$W) -> 0 | L42: =SUMIF('MASTER DATA'!$E:$E,'GENERAL PAYROLL'!$E42,'MASTER DATA'!$X:$X)+SUMIF('MASTER DATA'!$E:$E,'GENERAL PAYROLL'!$E42,'MASTER DATA'!$Y:$Y) -> 59.83 | M42: =SUM(K42:L42) -> 59.83 | N42: =SUMIF('MASTER DATA'!$E:$E,'GENERAL PAYROLL'!$E42,'MASTER DATA'!$AC:$AC) -> 0 | O42: =SUMIF('MASTER DATA'!$E:$E,'GENERAL PAYROLL'!$E42,'MASTER DATA'!$AD:$AD)+SUMIF('MASTER DATA'!$E:$E,'GENERAL PAYROLL'!$E42,'MASTER DATA'!$AE:$AE) -> 0 | P42: =SUM(N42:O42) -> 0 | Q42: =SUMIF('MASTER DATA'!$E:$E,'GENERAL PAYROLL'!$E42,'MASTER DATA'!$AI:$AI) -> 0 | R42: =SUMIF('MASTER DATA'!$E:$E,'GENERAL PAYROLL'!$E42,'MASTER DATA'!$AJ:$AJ)+SUMIF('MASTER DATA'!$E:$E,'GENERAL PAYROLL'!$E42,'MASTER DATA'!$AK:$AK) -> 0 | S42: =SUM(Q42:R42) -> 0 | T42: =SUMIF('MASTER DATA'!$E:$E,'GENERAL PAYROLL'!$E42,'MASTER DATA'!$AO:$AO) -> 59.83 | U42: =SUMIF('MASTER DATA'!$E:$E,'GENERAL PAYROLL'!$E42,'MASTER DATA'!$AP:$AP) -> 0 | V42: =SUMIF('MASTER DATA'!$E:$E,'GENERAL PAYROLL'!$E42,'MASTER DATA'!$AR:$AR) -> 9812.17 | W42: =SUMIF('MASTER DATA'!$E:$E,'GENERAL PAYROLL'!$E42,'MASTER DATA'!$AS:$AS) -> 0 | X42: =SUMIF('MASTER DATA'!$E:$E,'GENERAL PAYROLL'!$E42,'MASTER DATA'!$AT:$AT) -> 0 | Y42: =SUMIF('MASTER DATA'!$E:$E,'GENERAL PAYROLL'!$E42,'MASTER DATA'!$AU:$AU) -> 0 | Z42: =SUMIF('MASTER DATA'!$E:$E,'GENERAL PAYROLL'!$E42,'MASTER DATA'!$AV:$AV) -> 0 | AA42: =SUMIF('MASTER DATA'!$E:$E,'GENERAL PAYROLL'!$E42,'MASTER DATA'!$AW:$AW) -> 0 | AB42: =SUMIF('MASTER DATA'!$E:$E,'GENERAL PAYROLL'!$E42,'MASTER DATA'!$AX:$AX) -> 0 | AC42: =SUMIF('MASTER DATA'!$E:$E,'GENERAL PAYROLL'!$E42,'MASTER DATA'!$AY:$AY) -> 9812.17 | AD42: =IF(E42>=1,"SHOW","HIDE") -> SHOW
C43: 4-ACCTG. | D43: =IF(E43="","",COUNTA($E$20:E43)) -> 24 | E43: =IFERROR(VLOOKUP(C43,CODE!$B:$D,3,FALSE)," ") -> MAGDARAOG, CHRISTINE NAZEL C. | F43: =VLOOKUP($C43,CODE!$B:$F,5,FALSE) -> Administrative Asst. II | G43: =VLOOKUP($C43,CODE!$B:$F,4,FALSE) -> ACCTG. | H43: 11 | I43: =SUMIF('MASTER DATA'!$E:$E,'GENERAL PAYROLL'!$E43,'MASTER DATA'!$O:$O) -> 0 | J43: =SUMIF('MASTER DATA'!$E:$E,'GENERAL PAYROLL'!$E43,'MASTER DATA'!$N:$N) -> 0 | K43: =SUMIF('MASTER DATA'!$E:$E,'GENERAL PAYROLL'!$E43,'MASTER DATA'!$W:$W) -> 0 | L43: =SUMIF('MASTER DATA'!$E:$E,'GENERAL PAYROLL'!$E43,'MASTER DATA'!$X:$X)+SUMIF('MASTER DATA'!$E:$E,'GENERAL PAYROLL'!$E43,'MASTER DATA'!$Y:$Y) -> 0 | M43: =SUM(K43:L43) -> 0 | N43: =SUMIF('MASTER DATA'!$E:$E,'GENERAL PAYROLL'!$E43,'MASTER DATA'!$AC:$AC) -> 0 | O43: =SUMIF('MASTER DATA'!$E:$E,'GENERAL PAYROLL'!$E43,'MASTER DATA'!$AD:$AD)+SUMIF('MASTER DATA'!$E:$E,'GENERAL PAYROLL'!$E43,'MASTER DATA'!$AE:$AE) -> 0 | P43: =SUM(N43:O43) -> 0 | Q43: =SUMIF('MASTER DATA'!$E:$E,'GENERAL PAYROLL'!$E43,'MASTER DATA'!$AI:$AI) -> 0 | R43: =SUMIF('MASTER DATA'!$E:$E,'GENERAL PAYROLL'!$E43,'MASTER DATA'!$AJ:$AJ)+SUMIF('MASTER DATA'!$E:$E,'GENERAL PAYROLL'!$E43,'MASTER DATA'!$AK:$AK) -> 0 | S43: =SUM(Q43:R43) -> 0 | T43: =SUMIF('MASTER DATA'!$E:$E,'GENERAL PAYROLL'!$E43,'MASTER DATA'!$AO:$AO) -> 0 | U43: =SUMIF('MASTER DATA'!$E:$E,'GENERAL PAYROLL'!$E43,'MASTER DATA'!$AP:$AP) -> 0 | V43: =SUMIF('MASTER DATA'!$E:$E,'GENERAL PAYROLL'!$E43,'MASTER DATA'!$AR:$AR) -> 0 | W43: =SUMIF('MASTER DATA'!$E:$E,'GENERAL PAYROLL'!$E43,'MASTER DATA'!$AS:$AS) -> 0 | X43: =SUMIF('MASTER DATA'!$E:$E,'GENERAL PAYROLL'!$E43,'MASTER DATA'!$AT:$AT) -> 0 | Y43: =SUMIF('MASTER DATA'!$E:$E,'GENERAL PAYROLL'!$E43,'MASTER DATA'!$AU:$AU) -> 0 | Z43: =SUMIF('MASTER DATA'!$E:$E,'GENERAL PAYROLL'!$E43,'MASTER DATA'!$AV:$AV) -> 0 | AA43: =SUMIF('MASTER DATA'!$E:$E,'GENERAL PAYROLL'!$E43,'MASTER DATA'!$AW:$AW) -> 0 | AB43: =SUMIF('MASTER DATA'!$E:$E,'GENERAL PAYROLL'!$E43,'MASTER DATA'!$AX:$AX) -> 0 | AC43: =SUMIF('MASTER DATA'!$E:$E,'GENERAL PAYROLL'!$E43,'MASTER DATA'!$AY:$AY) -> 0 | AD43: =IF(E43>=1,"SHOW","HIDE") -> SHOW
C44: 5-ACCTG. | D44: =IF(E44="","",COUNTA($E$20:E44)) -> 25 | E44: =IFERROR(VLOOKUP(C44,CODE!$B:$D,3,FALSE)," ") -> LOZANO, ADRIAN D. | F44: =VLOOKUP($C44,CODE!$B:$F,5,FALSE) -> Administrative Asst. II | G44: =VLOOKUP($C44,CODE!$B:$F,4,FALSE) -> ACCTG. | H44: 11 | I44: =SUMIF('MASTER DATA'!$E:$E,'GENERAL PAYROLL'!$E44,'MASTER DATA'!$O:$O) -> 0 | J44: =SUMIF('MASTER DATA'!$E:$E,'GENERAL PAYROLL'!$E44,'MASTER DATA'!$N:$N) -> 0 | K44: =SUMIF('MASTER DATA'!$E:$E,'GENERAL PAYROLL'!$E44,'MASTER DATA'!$W:$W) -> 0 | L44: =SUMIF('MASTER DATA'!$E:$E,'GENERAL PAYROLL'!$E44,'MASTER DATA'!$X:$X)+SUMIF('MASTER DATA'!$E:$E,'GENERAL PAYROLL'!$E44,'MASTER DATA'!$Y:$Y) -> 0 | M44: =SUM(K44:L44) -> 0 | N44: =SUMIF('MASTER DATA'!$E:$E,'GENERAL PAYROLL'!$E44,'MASTER DATA'!$AC:$AC) -> 0 | O44: =SUMIF('MASTER DATA'!$E:$E,'GENERAL PAYROLL'!$E44,'MASTER DATA'!$AD:$AD)+SUMIF('MASTER DATA'!$E:$E,'GENERAL PAYROLL'!$E44,'MASTER DATA'!$AE:$AE) -> 0 | P44: =SUM(N44:O44) -> 0 | Q44: =SUMIF('MASTER DATA'!$E:$E,'GENERAL PAYROLL'!$E44,'MASTER DATA'!$AI:$AI) -> 0 | R44: =SUMIF('MASTER DATA'!$E:$E,'GENERAL PAYROLL'!$E44,'MASTER DATA'!$AJ:$AJ)+SUMIF('MASTER DATA'!$E:$E,'GENERAL PAYROLL'!$E44,'MASTER DATA'!$AK:$AK) -> 0 | S44: =SUM(Q44:R44) -> 0 | T44: =SUMIF('MASTER DATA'!$E:$E,'GENERAL PAYROLL'!$E44,'MASTER DATA'!$AO:$AO) -> 0 | U44: =SUMIF('MASTER DATA'!$E:$E,'GENERAL PAYROLL'!$E44,'MASTER DATA'!$AP:$AP) -> 0 | V44: =SUMIF('MASTER DATA'!$E:$E,'GENERAL PAYROLL'!$E44,'MASTER DATA'!$AR:$AR) -> 0 | W44: =SUMIF('MASTER DATA'!$E:$E,'GENERAL PAYROLL'!$E44,'MASTER DATA'!$AS:$AS) -> 0 | X44: =SUMIF('MASTER DATA'!$E:$E,'GENERAL PAYROLL'!$E44,'MASTER DATA'!$AT:$AT) -> 0 | Y44: =SUMIF('MASTER DATA'!$E:$E,'GENERAL PAYROLL'!$E44,'MASTER DATA'!$AU:$AU) -> 0 | Z44: =SUMIF('MASTER DATA'!$E:$E,'GENERAL PAYROLL'!$E44,'MASTER DATA'!$AV:$AV) -> 0 | AA44: =SUMIF('MASTER DATA'!$E:$E,'GENERAL PAYROLL'!$E44,'MASTER DATA'!$AW:$AW) -> 0 | AB44: =SUMIF('MASTER DATA'!$E:$E,'GENERAL PAYROLL'!$E44,'MASTER DATA'!$AX:$AX) -> 0 | AC44: =SUMIF('MASTER DATA'!$E:$E,'GENERAL PAYROLL'!$E44,'MASTER DATA'!$AY:$AY) -> 0 | AD44: =IF(E44>=1,"SHOW","HIDE") -> SHOW
C45: 6-ACCTG. | D45: =IF(E45="","",COUNTA($E$20:E45)) -> 26 | E45: =IFERROR(VLOOKUP(C45,CODE!$B:$D,3,FALSE)," ") -> OLIVO, JENNA P. | F45: =VLOOKUP($C45,CODE!$B:$F,5,FALSE) -> Technical Support Staff | G45: =VLOOKUP($C45,CODE!$B:$F,4,FALSE) -> ACCTG. | H45: 11 | I45: =SUMIF('MASTER DATA'!$E:$E,'GENERAL PAYROLL'!$E45,'MASTER DATA'!$O:$O) -> 0 | J45: =SUMIF('MASTER DATA'!$E:$E,'GENERAL PAYROLL'!$E45,'MASTER DATA'!$N:$N) -> 0 | K45: =SUMIF('MASTER DATA'!$E:$E,'GENERAL PAYROLL'!$E45,'MASTER DATA'!$W:$W) -> 0 | L45: =SUMIF('MASTER DATA'!$E:$E,'GENERAL PAYROLL'!$E45,'MASTER DATA'!$X:$X)+SUMIF('MASTER DATA'!$E:$E,'GENERAL PAYROLL'!$E45,'MASTER DATA'!$Y:$Y) -> 0 | M45: =SUM(K45:L45) -> 0 | N45: =SUMIF('MASTER DATA'!$E:$E,'GENERAL PAYROLL'!$E45,'MASTER DATA'!$AC:$AC) -> 0 | O45: =SUMIF('MASTER DATA'!$E:$E,'GENERAL PAYROLL'!$E45,'MASTER DATA'!$AD:$AD)+SUMIF('MASTER DATA'!$E:$E,'GENERAL PAYROLL'!$E45,'MASTER DATA'!$AE:$AE) -> 0 | P45: =SUM(N45:O45) -> 0 | Q45: =SUMIF('MASTER DATA'!$E:$E,'GENERAL PAYROLL'!$E45,'MASTER DATA'!$AI:$AI) -> 0 | R45: =SUMIF('MASTER DATA'!$E:$E,'GENERAL PAYROLL'!$E45,'MASTER DATA'!$AJ:$AJ)+SUMIF('MASTER DATA'!$E:$E,'GENERAL PAYROLL'!$E45,'MASTER DATA'!$AK:$AK) -> 0 | S45: =SUM(Q45:R45) -> 0 | T45: =SUMIF('MASTER DATA'!$E:$E,'GENERAL PAYROLL'!$E45,'MASTER DATA'!$AO:$AO) -> 0 | U45: =SUMIF('MASTER DATA'!$E:$E,'GENERAL PAYROLL'!$E45,'MASTER DATA'!$AP:$AP) -> 0 | V45: =SUMIF('MASTER DATA'!$E:$E,'GENERAL PAYROLL'!$E45,'MASTER DATA'!$AR:$AR) -> 0 | W45: =SUMIF('MASTER DATA'!$E:$E,'GENERAL PAYROLL'!$E45,'MASTER DATA'!$AS:$AS) -> 0 | X45: =SUMIF('MASTER DATA'!$E:$E,'GENERAL PAYROLL'!$E45,'MASTER DATA'!$AT:$AT) -> 0 | Y45: =SUMIF('MASTER DATA'!$E:$E,'GENERAL PAYROLL'!$E45,'MASTER DATA'!$AU:$AU) -> 0 | Z45: =SUMIF('MASTER DATA'!$E:$E,'GENERAL PAYROLL'!$E45,'MASTER DATA'!$AV:$AV) -> 0 | AA45: =SUMIF('MASTER DATA'!$E:$E,'GENERAL PAYROLL'!$E45,'MASTER DATA'!$AW:$AW) -> 0 | AB45: =SUMIF('MASTER DATA'!$E:$E,'GENERAL PAYROLL'!$E45,'MASTER DATA'!$AX:$AX) -> 0 | AC45: =SUMIF('MASTER DATA'!$E:$E,'GENERAL PAYROLL'!$E45,'MASTER DATA'!$AY:$AY) -> 0 | AD45: =IF(E45>=1,"SHOW","HIDE") -> SHOW
C46: 7-ACCTG. | D46: =IF(E46="","",COUNTA($E$20:E46)) -> 27 | E46: =IFERROR(VLOOKUP(C46,CODE!$B:$D,3,FALSE)," ") -> CALDITO, CHARISSE D. | F46: =VLOOKUP($C46,CODE!$B:$F,5,FALSE) -> Administrative Asst. II | G46: =VLOOKUP($C46,CODE!$B:$F,4,FALSE) -> ACCTG. | H46: 11 | I46: =SUMIF('MASTER DATA'!$E:$E,'GENERAL PAYROLL'!$E46,'MASTER DATA'!$O:$O) -> 0 | J46: =SUMIF('MASTER DATA'!$E:$E,'GENERAL PAYROLL'!$E46,'MASTER DATA'!$N:$N) -> 0 | K46: =SUMIF('MASTER DATA'!$E:$E,'GENERAL PAYROLL'!$E46,'MASTER DATA'!$W:$W) -> 0 | L46: =SUMIF('MASTER DATA'!$E:$E,'GENERAL PAYROLL'!$E46,'MASTER DATA'!$X:$X)+SUMIF('MASTER DATA'!$E:$E,'GENERAL PAYROLL'!$E46,'MASTER DATA'!$Y:$Y) -> 0 | M46: =SUM(K46:L46) -> 0 | N46: =SUMIF('MASTER DATA'!$E:$E,'GENERAL PAYROLL'!$E46,'MASTER DATA'!$AC:$AC) -> 0 | O46: =SUMIF('MASTER DATA'!$E:$E,'GENERAL PAYROLL'!$E46,'MASTER DATA'!$AD:$AD)+SUMIF('MASTER DATA'!$E:$E,'GENERAL PAYROLL'!$E46,'MASTER DATA'!$AE:$AE) -> 0 | P46: =SUM(N46:O46) -> 0 | Q46: =SUMIF('MASTER DATA'!$E:$E,'GENERAL PAYROLL'!$E46,'MASTER DATA'!$AI:$AI) -> 0 | R46: =SUMIF('MASTER DATA'!$E:$E,'GENERAL PAYROLL'!$E46,'MASTER DATA'!$AJ:$AJ)+SUMIF('MASTER DATA'!$E:$E,'GENERAL PAYROLL'!$E46,'MASTER DATA'!$AK:$AK) -> 0 | S46: =SUM(Q46:R46) -> 0 | T46: =SUMIF('MASTER DATA'!$E:$E,'GENERAL PAYROLL'!$E46,'MASTER DATA'!$AO:$AO) -> 0 | U46: =SUMIF('MASTER DATA'!$E:$E,'GENERAL PAYROLL'!$E46,'MASTER DATA'!$AP:$AP) -> 0 | V46: =SUMIF('MASTER DATA'!$E:$E,'GENERAL PAYROLL'!$E46,'MASTER DATA'!$AR:$AR) -> 0 | W46: =SUMIF('MASTER DATA'!$E:$E,'GENERAL PAYROLL'!$E46,'MASTER DATA'!$AS:$AS) -> 0 | X46: =SUMIF('MASTER DATA'!$E:$E,'GENERAL PAYROLL'!$E46,'MASTER DATA'!$AT:$AT) -> 0 | Y46: =SUMIF('MASTER DATA'!$E:$E,'GENERAL PAYROLL'!$E46,'MASTER DATA'!$AU:$AU) -> 0 | Z46: =SUMIF('MASTER DATA'!$E:$E,'GENERAL PAYROLL'!$E46,'MASTER DATA'!$AV:$AV) -> 0 | AA46: =SUMIF('MASTER DATA'!$E:$E,'GENERAL PAYROLL'!$E46,'MASTER DATA'!$AW:$AW) -> 0 | AB46: =SUMIF('MASTER DATA'!$E:$E,'GENERAL PAYROLL'!$E46,'MASTER DATA'!$AX:$AX) -> 0 | AC46: =SUMIF('MASTER DATA'!$E:$E,'GENERAL PAYROLL'!$E46,'MASTER DATA'!$AY:$AY) -> 0 | AD46: =IF(E46>=1,"SHOW","HIDE") -> SHOW
C47: 8-ACCTG. | D47: =IF(E47="","",COUNTA($E$20:E47)) -> 28 | E47: =IFERROR(VLOOKUP(C47,CODE!$B:$D,3,FALSE)," ") -> YUGA, MYKA ALEXZA B. | F47: =VLOOKUP($C47,CODE!$B:$F,5,FALSE) -> Administrative Asst. II | G47: =VLOOKUP($C47,CODE!$B:$F,4,FALSE) -> ACCTG. | H47: 11 | I47: =SUMIF('MASTER DATA'!$E:$E,'GENERAL PAYROLL'!$E47,'MASTER DATA'!$O:$O) -> 897.45455 | J47: =SUMIF('MASTER DATA'!$E:$E,'GENERAL PAYROLL'!$E47,'MASTER DATA'!$N:$N) -> 9872 | K47: =SUMIF('MASTER DATA'!$E:$E,'GENERAL PAYROLL'!$E47,'MASTER DATA'!$W:$W) -> 0 | L47: =SUMIF('MASTER DATA'!$E:$E,'GENERAL PAYROLL'!$E47,'MASTER DATA'!$X:$X)+SUMIF('MASTER DATA'!$E:$E,'GENERAL PAYROLL'!$E47,'MASTER DATA'!$Y:$Y) -> 0 | M47: =SUM(K47:L47) -> 0 | N47: =SUMIF('MASTER DATA'!$E:$E,'GENERAL PAYROLL'!$E47,'MASTER DATA'!$AC:$AC) -> 0 | O47: =SUMIF('MASTER DATA'!$E:$E,'GENERAL PAYROLL'!$E47,'MASTER DATA'!$AD:$AD)+SUMIF('MASTER DATA'!$E:$E,'GENERAL PAYROLL'!$E47,'MASTER DATA'!$AE:$AE) -> 0 | P47: =SUM(N47:O47) -> 0 | Q47: =SUMIF('MASTER DATA'!$E:$E,'GENERAL PAYROLL'!$E47,'MASTER DATA'!$AI:$AI) -> 0 | R47: =SUMIF('MASTER DATA'!$E:$E,'GENERAL PAYROLL'!$E47,'MASTER DATA'!$AJ:$AJ)+SUMIF('MASTER DATA'!$E:$E,'GENERAL PAYROLL'!$E47,'MASTER DATA'!$AK:$AK) -> 0 | S47: =SUM(Q47:R47) -> 0 | T47: =SUMIF('MASTER DATA'!$E:$E,'GENERAL PAYROLL'!$E47,'MASTER DATA'!$AO:$AO) -> 0 | U47: =SUMIF('MASTER DATA'!$E:$E,'GENERAL PAYROLL'!$E47,'MASTER DATA'!$AP:$AP) -> 0 | V47: =SUMIF('MASTER DATA'!$E:$E,'GENERAL PAYROLL'!$E47,'MASTER DATA'!$AR:$AR) -> 9872 | W47: =SUMIF('MASTER DATA'!$E:$E,'GENERAL PAYROLL'!$E47,'MASTER DATA'!$AS:$AS) -> 0 | X47: =SUMIF('MASTER DATA'!$E:$E,'GENERAL PAYROLL'!$E47,'MASTER DATA'!$AT:$AT) -> 0 | Y47: =SUMIF('MASTER DATA'!$E:$E,'GENERAL PAYROLL'!$E47,'MASTER DATA'!$AU:$AU) -> 0 | Z47: =SUMIF('MASTER DATA'!$E:$E,'GENERAL PAYROLL'!$E47,'MASTER DATA'!$AV:$AV) -> 0 | AA47: =SUMIF('MASTER DATA'!$E:$E,'GENERAL PAYROLL'!$E47,'MASTER DATA'!$AW:$AW) -> 0 | AB47: =SUMIF('MASTER DATA'!$E:$E,'GENERAL PAYROLL'!$E47,'MASTER DATA'!$AX:$AX) -> 0 | AC47: =SUMIF('MASTER DATA'!$E:$E,'GENERAL PAYROLL'!$E47,'MASTER DATA'!$AY:$AY) -> 9872 | AD47: =IF(E47>=1,"SHOW","HIDE") -> SHOW
C48: 1-CASHIER | D48: =IF(E48="","",COUNTA($E$20:E48)) -> 29 | E48: =IFERROR(VLOOKUP(C48,CODE!$B:$D,3,FALSE)," ") -> EMBALZADO, SHERYL P. | F48: =VLOOKUP($C48,CODE!$B:$F,5,FALSE) -> Administrative Asst. II | G48: =VLOOKUP($C48,CODE!$B:$F,4,FALSE) -> CASHIER | H48: 11 | I48: =SUMIF('MASTER DATA'!$E:$E,'GENERAL PAYROLL'!$E48,'MASTER DATA'!$O:$O) -> 0 | J48: =SUMIF('MASTER DATA'!$E:$E,'GENERAL PAYROLL'!$E48,'MASTER DATA'!$N:$N) -> 0 | K48: =SUMIF('MASTER DATA'!$E:$E,'GENERAL PAYROLL'!$E48,'MASTER DATA'!$W:$W) -> 0 | L48: =SUMIF('MASTER DATA'!$E:$E,'GENERAL PAYROLL'!$E48,'MASTER DATA'!$X:$X)+SUMIF('MASTER DATA'!$E:$E,'GENERAL PAYROLL'!$E48,'MASTER DATA'!$Y:$Y) -> 0 | M48: =SUM(K48:L48) -> 0 | N48: =SUMIF('MASTER DATA'!$E:$E,'GENERAL PAYROLL'!$E48,'MASTER DATA'!$AC:$AC) -> 0 | O48: =SUMIF('MASTER DATA'!$E:$E,'GENERAL PAYROLL'!$E48,'MASTER DATA'!$AD:$AD)+SUMIF('MASTER DATA'!$E:$E,'GENERAL PAYROLL'!$E48,'MASTER DATA'!$AE:$AE) -> 0 | P48: =SUM(N48:O48) -> 0 | Q48: =SUMIF('MASTER DATA'!$E:$E,'GENERAL PAYROLL'!$E48,'MASTER DATA'!$AI:$AI) -> 0 | R48: =SUMIF('MASTER DATA'!$E:$E,'GENERAL PAYROLL'!$E48,'MASTER DATA'!$AJ:$AJ)+SUMIF('MASTER DATA'!$E:$E,'GENERAL PAYROLL'!$E48,'MASTER DATA'!$AK:$AK) -> 0 | S48: =SUM(Q48:R48) -> 0 | T48: =SUMIF('MASTER DATA'!$E:$E,'GENERAL PAYROLL'!$E48,'MASTER DATA'!$AO:$AO) -> 0 | U48: =SUMIF('MASTER DATA'!$E:$E,'GENERAL PAYROLL'!$E48,'MASTER DATA'!$AP:$AP) -> 0 | V48: =SUMIF('MASTER DATA'!$E:$E,'GENERAL PAYROLL'!$E48,'MASTER DATA'!$AR:$AR) -> 0 | W48: =SUMIF('MASTER DATA'!$E:$E,'GENERAL PAYROLL'!$E48,'MASTER DATA'!$AS:$AS) -> 0 | X48: =SUMIF('MASTER DATA'!$E:$E,'GENERAL PAYROLL'!$E48,'MASTER DATA'!$AT:$AT) -> 0 | Y48: =SUMIF('MASTER DATA'!$E:$E,'GENERAL PAYROLL'!$E48,'MASTER DATA'!$AU:$AU) -> 0 | Z48: =SUMIF('MASTER DATA'!$E:$E,'GENERAL PAYROLL'!$E48,'MASTER DATA'!$AV:$AV) -> 0 | AA48: =SUMIF('MASTER DATA'!$E:$E,'GENERAL PAYROLL'!$E48,'MASTER DATA'!$AW:$AW) -> 0 | AB48: =SUMIF('MASTER DATA'!$E:$E,'GENERAL PAYROLL'!$E48,'MASTER DATA'!$AX:$AX) -> 0 | AC48: =SUMIF('MASTER DATA'!$E:$E,'GENERAL PAYROLL'!$E48,'MASTER DATA'!$AY:$AY) -> 0 | AD48: =IF(E48>=1,"SHOW","HIDE") -> SHOW
C49: 1-IAU | D49: =IF(E49="","",COUNTA($E$20:E49)) -> 30 | E49: =IFERROR(VLOOKUP(C49,CODE!$B:$D,3,FALSE)," ") -> CRUZ, CLAIRE JOYCE B. | F49: =VLOOKUP($C49,CODE!$B:$F,5,FALSE) -> Administrative Asst. II | G49: =VLOOKUP($C49,CODE!$B:$F,4,FALSE) -> IAU | H49: 11 | I49: =SUMIF('MASTER DATA'!$E:$E,'GENERAL PAYROLL'!$E49,'MASTER DATA'!$O:$O) -> 897.45455 | J49: =SUMIF('MASTER DATA'!$E:$E,'GENERAL PAYROLL'!$E49,'MASTER DATA'!$N:$N) -> 9872 | K49: =SUMIF('MASTER DATA'!$E:$E,'GENERAL PAYROLL'!$E49,'MASTER DATA'!$W:$W) -> 0 | L49: =SUMIF('MASTER DATA'!$E:$E,'GENERAL PAYROLL'!$E49,'MASTER DATA'!$X:$X)+SUMIF('MASTER DATA'!$E:$E,'GENERAL PAYROLL'!$E49,'MASTER DATA'!$Y:$Y) -> 0 | M49: =SUM(K49:L49) -> 0 | N49: =SUMIF('MASTER DATA'!$E:$E,'GENERAL PAYROLL'!$E49,'MASTER DATA'!$AC:$AC) -> 0 | O49: =SUMIF('MASTER DATA'!$E:$E,'GENERAL PAYROLL'!$E49,'MASTER DATA'!$AD:$AD)+SUMIF('MASTER DATA'!$E:$E,'GENERAL PAYROLL'!$E49,'MASTER DATA'!$AE:$AE) -> 0 | P49: =SUM(N49:O49) -> 0 | Q49: =SUMIF('MASTER DATA'!$E:$E,'GENERAL PAYROLL'!$E49,'MASTER DATA'!$AI:$AI) -> 0 | R49: =SUMIF('MASTER DATA'!$E:$E,'GENERAL PAYROLL'!$E49,'MASTER DATA'!$AJ:$AJ)+SUMIF('MASTER DATA'!$E:$E,'GENERAL PAYROLL'!$E49,'MASTER DATA'!$AK:$AK) -> 0 | S49: =SUM(Q49:R49) -> 0 | T49: =SUMIF('MASTER DATA'!$E:$E,'GENERAL PAYROLL'!$E49,'MASTER DATA'!$AO:$AO) -> 0 | U49: =SUMIF('MASTER DATA'!$E:$E,'GENERAL PAYROLL'!$E49,'MASTER DATA'!$AP:$AP) -> 0 | V49: =SUMIF('MASTER DATA'!$E:$E,'GENERAL PAYROLL'!$E49,'MASTER DATA'!$AR:$AR) -> 9872 | W49: =SUMIF('MASTER DATA'!$E:$E,'GENERAL PAYROLL'!$E49,'MASTER DATA'!$AS:$AS) -> 0 | X49: =SUMIF('MASTER DATA'!$E:$E,'GENERAL PAYROLL'!$E49,'MASTER DATA'!$AT:$AT) -> 0 | Y49: =SUMIF('MASTER DATA'!$E:$E,'GENERAL PAYROLL'!$E49,'MASTER DATA'!$AU:$AU) -> 0 | Z49: =SUMIF('MASTER DATA'!$E:$E,'GENERAL PAYROLL'!$E49,'MASTER DATA'!$AV:$AV) -> 0 | AA49: =SUMIF('MASTER DATA'!$E:$E,'GENERAL PAYROLL'!$E49,'MASTER DATA'!$AW:$AW) -> 0 | AB49: =SUMIF('MASTER DATA'!$E:$E,'GENERAL PAYROLL'!$E49,'MASTER DATA'!$AX:$AX) -> 0 | AC49: =SUMIF('MASTER DATA'!$E:$E,'GENERAL PAYROLL'!$E49,'MASTER DATA'!$AY:$AY) -> 9872 | AD49: =IF(E49>=1,"SHOW","HIDE") -> SHOW
C50: 2-IAU | D50: =IF(E50="","",COUNTA($E$20:E50)) -> 31 | E50: =IFERROR(VLOOKUP(C50,CODE!$B:$D,3,FALSE)," ") -> MARTIN, SHAIRA LEA E. | F50: =VLOOKUP($C50,CODE!$B:$F,5,FALSE) -> Administrative Asst. II | G50: =VLOOKUP($C50,CODE!$B:$F,4,FALSE) -> IAU | H50: 11 | I50: =SUMIF('MASTER DATA'!$E:$E,'GENERAL PAYROLL'!$E50,'MASTER DATA'!$O:$O) -> 897.45455 | J50: =SUMIF('MASTER DATA'!$E:$E,'GENERAL PAYROLL'!$E50,'MASTER DATA'!$N:$N) -> 9872 | K50: =SUMIF('MASTER DATA'!$E:$E,'GENERAL PAYROLL'!$E50,'MASTER DATA'!$W:$W) -> 0 | L50: =SUMIF('MASTER DATA'!$E:$E,'GENERAL PAYROLL'!$E50,'MASTER DATA'!$X:$X)+SUMIF('MASTER DATA'!$E:$E,'GENERAL PAYROLL'!$E50,'MASTER DATA'!$Y:$Y) -> 0 | M50: =SUM(K50:L50) -> 0 | N50: =SUMIF('MASTER DATA'!$E:$E,'GENERAL PAYROLL'!$E50,'MASTER DATA'!$AC:$AC) -> 0 | O50: =SUMIF('MASTER DATA'!$E:$E,'GENERAL PAYROLL'!$E50,'MASTER DATA'!$AD:$AD)+SUMIF('MASTER DATA'!$E:$E,'GENERAL PAYROLL'!$E50,'MASTER DATA'!$AE:$AE) -> 0 | P50: =SUM(N50:O50) -> 0 | Q50: =SUMIF('MASTER DATA'!$E:$E,'GENERAL PAYROLL'!$E50,'MASTER DATA'!$AI:$AI) -> 0 | R50: =SUMIF('MASTER DATA'!$E:$E,'GENERAL PAYROLL'!$E50,'MASTER DATA'!$AJ:$AJ)+SUMIF('MASTER DATA'!$E:$E,'GENERAL PAYROLL'!$E50,'MASTER DATA'!$AK:$AK) -> 0 | S50: =SUM(Q50:R50) -> 0 | T50: =SUMIF('MASTER DATA'!$E:$E,'GENERAL PAYROLL'!$E50,'MASTER DATA'!$AO:$AO) -> 0 | U50: =SUMIF('MASTER DATA'!$E:$E,'GENERAL PAYROLL'!$E50,'MASTER DATA'!$AP:$AP) -> 0 | V50: =SUMIF('MASTER DATA'!$E:$E,'GENERAL PAYROLL'!$E50,'MASTER DATA'!$AR:$AR) -> 9872 | W50: =SUMIF('MASTER DATA'!$E:$E,'GENERAL PAYROLL'!$E50,'MASTER DATA'!$AS:$AS) -> 0 | X50: =SUMIF('MASTER DATA'!$E:$E,'GENERAL PAYROLL'!$E50,'MASTER DATA'!$AT:$AT) -> 0 | Y50: =SUMIF('MASTER DATA'!$E:$E,'GENERAL PAYROLL'!$E50,'MASTER DATA'!$AU:$AU) -> 0 | Z50: =SUMIF('MASTER DATA'!$E:$E,'GENERAL PAYROLL'!$E50,'MASTER DATA'!$AV:$AV) -> 0 | AA50: =SUMIF('MASTER DATA'!$E:$E,'GENERAL PAYROLL'!$E50,'MASTER DATA'!$AW:$AW) -> 0 | AB50: =SUMIF('MASTER DATA'!$E:$E,'GENERAL PAYROLL'!$E50,'MASTER DATA'!$AX:$AX) -> 0 | AC50: =SUMIF('MASTER DATA'!$E:$E,'GENERAL PAYROLL'!$E50,'MASTER DATA'!$AY:$AY) -> 9872 | AD50: =IF(E50>=1,"SHOW","HIDE") -> SHOW
C51: 1-HRMO | D51: =IF(E51="","",COUNTA($E$20:E51)) -> 32 | E51: =IFERROR(VLOOKUP(C51,CODE!$B:$D,3,FALSE)," ") -> DE GALICIA, JACQUELINE C. | F51: =VLOOKUP($C51,CODE!$B:$F,5,FALSE) -> Training Specialist II | G51: =VLOOKUP($C51,CODE!$B:$F,4,FALSE) -> HRMO | H51: 11 | I51: =SUMIF('MASTER DATA'!$E:$E,'GENERAL PAYROLL'!$E51,'MASTER DATA'!$O:$O) -> 0 | J51: =SUMIF('MASTER DATA'!$E:$E,'GENERAL PAYROLL'!$E51,'MASTER DATA'!$N:$N) -> 0 | K51: =SUMIF('MASTER DATA'!$E:$E,'GENERAL PAYROLL'!$E51,'MASTER DATA'!$W:$W) -> 0 | L51: =SUMIF('MASTER DATA'!$E:$E,'GENERAL PAYROLL'!$E51,'MASTER DATA'!$X:$X)+SUMIF('MASTER DATA'!$E:$E,'GENERAL PAYROLL'!$E51,'MASTER DATA'!$Y:$Y) -> 0 | M51: =SUM(K51:L51) -> 0 | N51: =SUMIF('MASTER DATA'!$E:$E,'GENERAL PAYROLL'!$E51,'MASTER DATA'!$AC:$AC) -> 0 | O51: =SUMIF('MASTER DATA'!$E:$E,'GENERAL PAYROLL'!$E51,'MASTER DATA'!$AD:$AD)+SUMIF('MASTER DATA'!$E:$E,'GENERAL PAYROLL'!$E51,'MASTER DATA'!$AE:$AE) -> 0 | P51: =SUM(N51:O51) -> 0 | Q51: =SUMIF('MASTER DATA'!$E:$E,'GENERAL PAYROLL'!$E51,'MASTER DATA'!$AI:$AI) -> 0 | R51: =SUMIF('MASTER DATA'!$E:$E,'GENERAL PAYROLL'!$E51,'MASTER DATA'!$AJ:$AJ)+SUMIF('MASTER DATA'!$E:$E,'GENERAL PAYROLL'!$E51,'MASTER DATA'!$AK:$AK) -> 0 | S51: =SUM(Q51:R51) -> 0 | T51: =SUMIF('MASTER DATA'!$E:$E,'GENERAL PAYROLL'!$E51,'MASTER DATA'!$AO:$AO) -> 0 | U51: =SUMIF('MASTER DATA'!$E:$E,'GENERAL PAYROLL'!$E51,'MASTER DATA'!$AP:$AP) -> 0 | V51: =SUMIF('MASTER DATA'!$E:$E,'GENERAL PAYROLL'!$E51,'MASTER DATA'!$AR:$AR) -> 0 | W51: =SUMIF('MASTER DATA'!$E:$E,'GENERAL PAYROLL'!$E51,'MASTER DATA'!$AS:$AS) -> 0 | X51: =SUMIF('MASTER DATA'!$E:$E,'GENERAL PAYROLL'!$E51,'MASTER DATA'!$AT:$AT) -> 0 | Y51: =SUMIF('MASTER DATA'!$E:$E,'GENERAL PAYROLL'!$E51,'MASTER DATA'!$AU:$AU) -> 0 | Z51: =SUMIF('MASTER DATA'!$E:$E,'GENERAL PAYROLL'!$E51,'MASTER DATA'!$AV:$AV) -> 0 | AA51: =SUMIF('MASTER DATA'!$E:$E,'GENERAL PAYROLL'!$E51,'MASTER DATA'!$AW:$AW) -> 0 | AB51: =SUMIF('MASTER DATA'!$E:$E,'GENERAL PAYROLL'!$E51,'MASTER DATA'!$AX:$AX) -> 0 | AC51: =SUMIF('MASTER DATA'!$E:$E,'GENERAL PAYROLL'!$E51,'MASTER DATA'!$AY:$AY) -> 0 | AD51: =IF(E51>=1,"SHOW","HIDE") -> SHOW
... C53: 3-HRMO | D53: =IF(E53="","",COUNTA($E$20:E53)) -> 34 | E53: =IFERROR(VLOOKUP(C53,CODE!$B:$D,3,FALSE)," ") -> AMBROSIO, JOHN HAROLD F. | F53: =VLOOKUP($C53,CODE!$B:$F,5,FALSE) -> Training Specialist II | G53: =VLOOKUP($C53,CODE!$B:$F,4,FALSE) -> HRMO | H53: 11 | I53: =SUMIF('MASTER DATA'!$E:$E,'GENERAL PAYROLL'!$E53,'MASTER DATA'!$O:$O) -> 1664.5 | J53: =SUMIF('MASTER DATA'!$E:$E,'GENERAL PAYROLL'!$E53,'MASTER DATA'!$N:$N) -> 18309.5 | K53: =SUMIF('MASTER DATA'!$E:$E,'GENERAL PAYROLL'!$E53,'MASTER DATA'!$W:$W) -> 0 | L53: =SUMIF('MASTER DATA'!$E:$E,'GENERAL PAYROLL'!$E53,'MASTER DATA'!$X:$X)+SUMIF('MASTER DATA'!$E:$E,'GENERAL PAYROLL'!$E53,'MASTER DATA'!$Y:$Y) -> 0 | M53: =SUM(K53:L53) -> 0 | N53: =SUMIF('MASTER DATA'!$E:$E,'GENERAL PAYROLL'!$E53,'MASTER DATA'!$AC:$AC) -> 0 | O53: =SUMIF('MASTER DATA'!$E:$E,'GENERAL PAYROLL'!$E53,'MASTER DATA'!$AD:$AD)+SUMIF('MASTER DATA'!$E:$E,'GENERAL PAYROLL'!$E53,'MASTER DATA'!$AE:$AE) -> 0 | P53: =SUM(N53:O53) -> 0 | Q53: =SUMIF('MASTER DATA'!$E:$E,'GENERAL PAYROLL'!$E53,'MASTER DATA'!$AI:$AI) -> 0 | R53: =SUMIF('MASTER DATA'!$E:$E,'GENERAL PAYROLL'!$E53,'MASTER DATA'!$AJ:$AJ)+SUMIF('MASTER DATA'!$E:$E,'GENERAL PAYROLL'!$E53,'MASTER DATA'!$AK:$AK) -> 0 | S53: =SUM(Q53:R53) -> 0 | T53: =SUMIF('MASTER DATA'!$E:$E,'GENERAL PAYROLL'!$E53,'MASTER DATA'!$AO:$AO) -> 0 | U53: =SUMIF('MASTER DATA'!$E:$E,'GENERAL PAYROLL'!$E53,'MASTER DATA'!$AP:$AP) -> 0 | V53: =SUMIF('MASTER DATA'!$E:$E,'GENERAL PAYROLL'!$E53,'MASTER DATA'!$AR:$AR) -> 18309.5 | W53: =SUMIF('MASTER DATA'!$E:$E,'GENERAL PAYROLL'!$E53,'MASTER DATA'!$AS:$AS) -> 0 | X53: =SUMIF('MASTER DATA'!$E:$E,'GENERAL PAYROLL'!$E53,'MASTER DATA'!$AT:$AT) -> 0 | Y53: =SUMIF('MASTER DATA'!$E:$E,'GENERAL PAYROLL'!$E53,'MASTER DATA'!$AU:$AU) -> 0 | Z53: =SUMIF('MASTER DATA'!$E:$E,'GENERAL PAYROLL'!$E53,'MASTER DATA'!$AV:$AV) -> 0 | AA53: =SUMIF('MASTER DATA'!$E:$E,'GENERAL PAYROLL'!$E53,'MASTER DATA'!$AW:$AW) -> 0 | AB53: =SUMIF('MASTER DATA'!$E:$E,'GENERAL PAYROLL'!$E53,'MASTER DATA'!$AX:$AX) -> 0 | AC53: =SUMIF('MASTER DATA'!$E:$E,'GENERAL PAYROLL'!$E53,'MASTER DATA'!$AY:$AY) -> 18309.5 | AD53: =IF(E53>=1,"SHOW","HIDE") -> SHOW
C54: 4-HRMO | D54: =IF(E54="","",COUNTA($E$20:E54)) -> 35 | E54: NIÑO, COLENE MAE B. | F54: =VLOOKUP($C54,CODE!$B:$F,5,FALSE) -> Training Specialist II | G54: =VLOOKUP($C54,CODE!$B:$F,4,FALSE) -> HRMO | H54: 11 | I54: =SUMIF('MASTER DATA'!$E:$E,'GENERAL PAYROLL'!$E54,'MASTER DATA'!$O:$O) -> 1664.5 | J54: =SUMIF('MASTER DATA'!$E:$E,'GENERAL PAYROLL'!$E54,'MASTER DATA'!$N:$N) -> 18309.5 | K54: =SUMIF('MASTER DATA'!$E:$E,'GENERAL PAYROLL'!$E54,'MASTER DATA'!$W:$W) -> 0 | L54: =SUMIF('MASTER DATA'!$E:$E,'GENERAL PAYROLL'!$E54,'MASTER DATA'!$X:$X)+SUMIF('MASTER DATA'!$E:$E,'GENERAL PAYROLL'!$E54,'MASTER DATA'!$Y:$Y) -> 0 | M54: =SUM(K54:L54) -> 0 | N54: =SUMIF('MASTER DATA'!$E:$E,'GENERAL PAYROLL'!$E54,'MASTER DATA'!$AC:$AC) -> 0 | O54: =SUMIF('MASTER DATA'!$E:$E,'GENERAL PAYROLL'!$E54,'MASTER DATA'!$AD:$AD)+SUMIF('MASTER DATA'!$E:$E,'GENERAL PAYROLL'!$E54,'MASTER DATA'!$AE:$AE) -> 0 | P54: =SUM(N54:O54) -> 0 | Q54: =SUMIF('MASTER DATA'!$E:$E,'GENERAL PAYROLL'!$E54,'MASTER DATA'!$AI:$AI) -> 0 | R54: =SUMIF('MASTER DATA'!$E:$E,'GENERAL PAYROLL'!$E54,'MASTER DATA'!$AJ:$AJ)+SUMIF('MASTER DATA'!$E:$E,'GENERAL PAYROLL'!$E54,'MASTER DATA'!$AK:$AK) -> 0 | S54: =SUM(Q54:R54) -> 0 | T54: =SUMIF('MASTER DATA'!$E:$E,'GENERAL PAYROLL'!$E54,'MASTER DATA'!$AO:$AO) -> 0 | U54: =SUMIF('MASTER DATA'!$E:$E,'GENERAL PAYROLL'!$E54,'MASTER DATA'!$AP:$AP) -> 0 | V54: =SUMIF('MASTER DATA'!$E:$E,'GENERAL PAYROLL'!$E54,'MASTER DATA'!$AR:$AR) -> 18309.5 | W54: =SUMIF('MASTER DATA'!$E:$E,'GENERAL PAYROLL'!$E54,'MASTER DATA'!$AS:$AS) -> 0 | X54: =SUMIF('MASTER DATA'!$E:$E,'GENERAL PAYROLL'!$E54,'MASTER DATA'!$AT:$AT) -> 0 | Y54: =SUMIF('MASTER DATA'!$E:$E,'GENERAL PAYROLL'!$E54,'MASTER DATA'!$AU:$AU) -> 0 | Z54: =SUMIF('MASTER DATA'!$E:$E,'GENERAL PAYROLL'!$E54,'MASTER DATA'!$AV:$AV) -> 0 | AA54: =SUMIF('MASTER DATA'!$E:$E,'GENERAL PAYROLL'!$E54,'MASTER DATA'!$AW:$AW) -> 0 | AB54: =SUMIF('MASTER DATA'!$E:$E,'GENERAL PAYROLL'!$E54,'MASTER DATA'!$AX:$AX) -> 0 | AC54: =SUMIF('MASTER DATA'!$E:$E,'GENERAL PAYROLL'!$E54,'MASTER DATA'!$AY:$AY) -> 18309.5 | AD54: =IF(E54>=1,"SHOW","HIDE") -> SHOW
C55: 1-RCRDS | D55: =IF(E55="","",COUNTA($E$20:E55)) -> 36 | E55: =IFERROR(VLOOKUP(C55,CODE!$B:$D,3,FALSE)," ") -> CAPONGCOL, MARY JANE | F55: =VLOOKUP($C55,CODE!$B:$F,5,FALSE) -> Administrative Asst. II | G55: =VLOOKUP($C55,CODE!$B:$F,4,FALSE) -> RCRDS | H55: 11 | I55: =SUMIF('MASTER DATA'!$E:$E,'GENERAL PAYROLL'!$E55,'MASTER DATA'!$O:$O) -> 897.45455 | J55: =SUMIF('MASTER DATA'!$E:$E,'GENERAL PAYROLL'!$E55,'MASTER DATA'!$N:$N) -> 9872 | K55: =SUMIF('MASTER DATA'!$E:$E,'GENERAL PAYROLL'!$E55,'MASTER DATA'!$W:$W) -> 0 | L55: =SUMIF('MASTER DATA'!$E:$E,'GENERAL PAYROLL'!$E55,'MASTER DATA'!$X:$X)+SUMIF('MASTER DATA'!$E:$E,'GENERAL PAYROLL'!$E55,'MASTER DATA'!$Y:$Y) -> 0 | M55: =SUM(K55:L55) -> 0 | N55: =SUMIF('MASTER DATA'!$E:$E,'GENERAL PAYROLL'!$E55,'MASTER DATA'!$AC:$AC) -> 0 | O55: =SUMIF('MASTER DATA'!$E:$E,'GENERAL PAYROLL'!$E55,'MASTER DATA'!$AD:$AD)+SUMIF('MASTER DATA'!$E:$E,'GENERAL PAYROLL'!$E55,'MASTER DATA'!$AE:$AE) -> 0 | P55: =SUM(N55:O55) -> 0 | Q55: =SUMIF('MASTER DATA'!$E:$E,'GENERAL PAYROLL'!$E55,'MASTER DATA'!$AI:$AI) -> 0 | R55: =SUMIF('MASTER DATA'!$E:$E,'GENERAL PAYROLL'!$E55,'MASTER DATA'!$AJ:$AJ)+SUMIF('MASTER DATA'!$E:$E,'GENERAL PAYROLL'!$E55,'MASTER DATA'!$AK:$AK) -> 0 | S55: =SUM(Q55:R55) -> 0 | T55: =SUMIF('MASTER DATA'!$E:$E,'GENERAL PAYROLL'!$E55,'MASTER DATA'!$AO:$AO) -> 0 | U55: =SUMIF('MASTER DATA'!$E:$E,'GENERAL PAYROLL'!$E55,'MASTER DATA'!$AP:$AP) -> 0 | V55: =SUMIF('MASTER DATA'!$E:$E,'GENERAL PAYROLL'!$E55,'MASTER DATA'!$AR:$AR) -> 9872 | W55: =SUMIF('MASTER DATA'!$E:$E,'GENERAL PAYROLL'!$E55,'MASTER DATA'!$AS:$AS) -> 0 | X55: =SUMIF('MASTER DATA'!$E:$E,'GENERAL PAYROLL'!$E55,'MASTER DATA'!$AT:$AT) -> 0 | Y55: =SUMIF('MASTER DATA'!$E:$E,'GENERAL PAYROLL'!$E55,'MASTER DATA'!$AU:$AU) -> 2000 | Z55: =SUMIF('MASTER DATA'!$E:$E,'GENERAL PAYROLL'!$E55,'MASTER DATA'!$AV:$AV) -> 461.39 | AA55: =SUMIF('MASTER DATA'!$E:$E,'GENERAL PAYROLL'!$E55,'MASTER DATA'!$AW:$AW) -> 0 | AB55: =SUMIF('MASTER DATA'!$E:$E,'GENERAL PAYROLL'!$E55,'MASTER DATA'!$AX:$AX) -> 0 | AC55: =SUMIF('MASTER DATA'!$E:$E,'GENERAL PAYROLL'!$E55,'MASTER DATA'!$AY:$AY) -> 7410.61 | AD55: =IF(E55>=1,"SHOW","HIDE") -> SHOW
C56: 2-RCRDS | D56: =IF(E56="","",COUNTA($E$20:E56)) -> 37 | E56: =IFERROR(VLOOKUP(C56,CODE!$B:$D,3,FALSE)," ") -> FERNANDEZ, YARI E. | F56: =VLOOKUP($C56,CODE!$B:$F,5,FALSE) -> Administrative Asst. II | G56: =VLOOKUP($C56,CODE!$B:$F,4,FALSE) -> RCRDS | H56: 11 | I56: =SUMIF('MASTER DATA'!$E:$E,'GENERAL PAYROLL'!$E56,'MASTER DATA'!$O:$O) -> 897.45455 | J56: =SUMIF('MASTER DATA'!$E:$E,'GENERAL PAYROLL'!$E56,'MASTER DATA'!$N:$N) -> 9872 | K56: =SUMIF('MASTER DATA'!$E:$E,'GENERAL PAYROLL'!$E56,'MASTER DATA'!$W:$W) -> 0 | L56: =SUMIF('MASTER DATA'!$E:$E,'GENERAL PAYROLL'!$E56,'MASTER DATA'!$X:$X)+SUMIF('MASTER DATA'!$E:$E,'GENERAL PAYROLL'!$E56,'MASTER DATA'!$Y:$Y) -> 557.17 | M56: =SUM(K56:L56) -> 557.17 | N56: =SUMIF('MASTER DATA'!$E:$E,'GENERAL PAYROLL'!$E56,'MASTER DATA'!$AC:$AC) -> 0 | O56: =SUMIF('MASTER DATA'!$E:$E,'GENERAL PAYROLL'!$E56,'MASTER DATA'!$AD:$AD)+SUMIF('MASTER DATA'!$E:$E,'GENERAL PAYROLL'!$E56,'MASTER DATA'!$AE:$AE) -> 0 | P56: =SUM(N56:O56) -> 0 | Q56: =SUMIF('MASTER DATA'!$E:$E,'GENERAL PAYROLL'!$E56,'MASTER DATA'!$AI:$AI) -> 0 | R56: =SUMIF('MASTER DATA'!$E:$E,'GENERAL PAYROLL'!$E56,'MASTER DATA'!$AJ:$AJ)+SUMIF('MASTER DATA'!$E:$E,'GENERAL PAYROLL'!$E56,'MASTER DATA'!$AK:$AK) -> 0 | S56: =SUM(Q56:R56) -> 0 | T56: =SUMIF('MASTER DATA'!$E:$E,'GENERAL PAYROLL'!$E56,'MASTER DATA'!$AO:$AO) -> 557.17 | U56: =SUMIF('MASTER DATA'!$E:$E,'GENERAL PAYROLL'!$E56,'MASTER DATA'!$AP:$AP) -> 0 | V56: =SUMIF('MASTER DATA'!$E:$E,'GENERAL PAYROLL'!$E56,'MASTER DATA'!$AR:$AR) -> 9314.83 | W56: =SUMIF('MASTER DATA'!$E:$E,'GENERAL PAYROLL'!$E56,'MASTER DATA'!$AS:$AS) -> 0 | X56: =SUMIF('MASTER DATA'!$E:$E,'GENERAL PAYROLL'!$E56,'MASTER DATA'!$AT:$AT) -> 0 | Y56: =SUMIF('MASTER DATA'!$E:$E,'GENERAL PAYROLL'!$E56,'MASTER DATA'!$AU:$AU) -> 0 | Z56: =SUMIF('MASTER DATA'!$E:$E,'GENERAL PAYROLL'!$E56,'MASTER DATA'!$AV:$AV) -> 0 | AA56: =SUMIF('MASTER DATA'!$E:$E,'GENERAL PAYROLL'!$E56,'MASTER DATA'!$AW:$AW) -> 0 | AB56: =SUMIF('MASTER DATA'!$E:$E,'GENERAL PAYROLL'!$E56,'MASTER DATA'!$AX:$AX) -> 0 | AC56: =SUMIF('MASTER DATA'!$E:$E,'GENERAL PAYROLL'!$E56,'MASTER DATA'!$AY:$AY) -> 9314.83 | AD56: =IF(E56>=1,"SHOW","HIDE") -> SHOW
C57: 1-GSS | D57: =IF(E57="","",COUNTA($E$20:E57)) -> 38 | E57: =IFERROR(VLOOKUP(C57,CODE!$B:$D,3,FALSE)," ") -> CUARTERON, JOSEN L. | F57: =VLOOKUP($C57,CODE!$B:$F,5,FALSE) -> Administrative Asst. I | G57: =VLOOKUP($C57,CODE!$B:$F,4,FALSE) -> GSS | H57: 11 | I57: =SUMIF('MASTER DATA'!$E:$E,'GENERAL PAYROLL'!$E57,'MASTER DATA'!$O:$O) -> 846.36364 | J57: =SUMIF('MASTER DATA'!$E:$E,'GENERAL PAYROLL'!$E57,'MASTER DATA'!$N:$N) -> 9310 | K57: =SUMIF('MASTER DATA'!$E:$E,'GENERAL PAYROLL'!$E57,'MASTER DATA'!$W:$W) -> 0 | L57: =SUMIF('MASTER DATA'!$E:$E,'GENERAL PAYROLL'!$E57,'MASTER DATA'!$X:$X)+SUMIF('MASTER DATA'!$E:$E,'GENERAL PAYROLL'!$E57,'MASTER DATA'!$Y:$Y) -> 65.24 | M57: =SUM(K57:L57) -> 65.24 | N57: =SUMIF('MASTER DATA'!$E:$E,'GENERAL PAYROLL'!$E57,'MASTER DATA'!$AC:$AC) -> 0 | O57: =SUMIF('MASTER DATA'!$E:$E,'GENERAL PAYROLL'!$E57,'MASTER DATA'!$AD:$AD)+SUMIF('MASTER DATA'!$E:$E,'GENERAL PAYROLL'!$E57,'MASTER DATA'!$AE:$AE) -> 0 | P57: =SUM(N57:O57) -> 0 | Q57: =SUMIF('MASTER DATA'!$E:$E,'GENERAL PAYROLL'!$E57,'MASTER DATA'!$AI:$AI) -> 0 | R57: =SUMIF('MASTER DATA'!$E:$E,'GENERAL PAYROLL'!$E57,'MASTER DATA'!$AJ:$AJ)+SUMIF('MASTER DATA'!$E:$E,'GENERAL PAYROLL'!$E57,'MASTER DATA'!$AK:$AK) -> 0 | S57: =SUM(Q57:R57) -> 0 | T57: =SUMIF('MASTER DATA'!$E:$E,'GENERAL PAYROLL'!$E57,'MASTER DATA'!$AO:$AO) -> 65.24 | U57: =SUMIF('MASTER DATA'!$E:$E,'GENERAL PAYROLL'!$E57,'MASTER DATA'!$AP:$AP) -> 0 | V57: =SUMIF('MASTER DATA'!$E:$E,'GENERAL PAYROLL'!$E57,'MASTER DATA'!$AR:$AR) -> 9244.76 | W57: =SUMIF('MASTER DATA'!$E:$E,'GENERAL PAYROLL'!$E57,'MASTER DATA'!$AS:$AS) -> 0 | X57: =SUMIF('MASTER DATA'!$E:$E,'GENERAL PAYROLL'!$E57,'MASTER DATA'!$AT:$AT) -> 0 | Y57: =SUMIF('MASTER DATA'!$E:$E,'GENERAL PAYROLL'!$E57,'MASTER DATA'!$AU:$AU) -> 0 | Z57: =SUMIF('MASTER DATA'!$E:$E,'GENERAL PAYROLL'!$E57,'MASTER DATA'!$AV:$AV) -> 0 | AA57: =SUMIF('MASTER DATA'!$E:$E,'GENERAL PAYROLL'!$E57,'MASTER DATA'!$AW:$AW) -> 0 | AB57: =SUMIF('MASTER DATA'!$E:$E,'GENERAL PAYROLL'!$E57,'MASTER DATA'!$AX:$AX) -> 0 | AC57: =SUMIF('MASTER DATA'!$E:$E,'GENERAL PAYROLL'!$E57,'MASTER DATA'!$AY:$AY) -> 9244.76 | AD57: =IF(E57>=1,"SHOW","HIDE") -> SHOW
C58: 2-GSS | D58: =IF(E58="","",COUNTA($E$20:E58)) -> 39 | E58: =IFERROR(VLOOKUP(C58,CODE!$B:$D,3,FALSE)," ") -> CATUBAY, ELVIS JOHN L. | F58: =VLOOKUP($C58,CODE!$B:$F,5,FALSE) -> Administrative Asst. II | G58: =VLOOKUP($C58,CODE!$B:$F,4,FALSE) -> GSS | H58: 11 | I58: =SUMIF('MASTER DATA'!$E:$E,'GENERAL PAYROLL'!$E58,'MASTER DATA'!$O:$O) -> 897.45455 | J58: =SUMIF('MASTER DATA'!$E:$E,'GENERAL PAYROLL'!$E58,'MASTER DATA'!$N:$N) -> 9872 | K58: =SUMIF('MASTER DATA'!$E:$E,'GENERAL PAYROLL'!$E58,'MASTER DATA'!$W:$W) -> 897.45 | L58: =SUMIF('MASTER DATA'!$E:$E,'GENERAL PAYROLL'!$E58,'MASTER DATA'!$X:$X)+SUMIF('MASTER DATA'!$E:$E,'GENERAL PAYROLL'!$E58,'MASTER DATA'!$Y:$Y) -> 0 | M58: =SUM(K58:L58) -> 897.45 | N58: =SUMIF('MASTER DATA'!$E:$E,'GENERAL PAYROLL'!$E58,'MASTER DATA'!$AC:$AC) -> 0 | O58: =SUMIF('MASTER DATA'!$E:$E,'GENERAL PAYROLL'!$E58,'MASTER DATA'!$AD:$AD)+SUMIF('MASTER DATA'!$E:$E,'GENERAL PAYROLL'!$E58,'MASTER DATA'!$AE:$AE) -> 0 | P58: =SUM(N58:O58) -> 0 | Q58: =SUMIF('MASTER DATA'!$E:$E,'GENERAL PAYROLL'!$E58,'MASTER DATA'!$AI:$AI) -> 0 | R58: =SUMIF('MASTER DATA'!$E:$E,'GENERAL PAYROLL'!$E58,'MASTER DATA'!$AJ:$AJ)+SUMIF('MASTER DATA'!$E:$E,'GENERAL PAYROLL'!$E58,'MASTER DATA'!$AK:$AK) -> 0 | S58: =SUM(Q58:R58) -> 0 | T58: =SUMIF('MASTER DATA'!$E:$E,'GENERAL PAYROLL'!$E58,'MASTER DATA'!$AO:$AO) -> 897.45 | U58: =SUMIF('MASTER DATA'!$E:$E,'GENERAL PAYROLL'!$E58,'MASTER DATA'!$AP:$AP) -> 0 | V58: =SUMIF('MASTER DATA'!$E:$E,'GENERAL PAYROLL'!$E58,'MASTER DATA'!$AR:$AR) -> 8974.55 | W58: =SUMIF('MASTER DATA'!$E:$E,'GENERAL PAYROLL'!$E58,'MASTER DATA'!$AS:$AS) -> 0 | X58: =SUMIF('MASTER DATA'!$E:$E,'GENERAL PAYROLL'!$E58,'MASTER DATA'!$AT:$AT) -> 0 | Y58: =SUMIF('MASTER DATA'!$E:$E,'GENERAL PAYROLL'!$E58,'MASTER DATA'!$AU:$AU) -> 0 | Z58: =SUMIF('MASTER DATA'!$E:$E,'GENERAL PAYROLL'!$E58,'MASTER DATA'!$AV:$AV) -> 0 | AA58: =SUMIF('MASTER DATA'!$E:$E,'GENERAL PAYROLL'!$E58,'MASTER DATA'!$AW:$AW) -> 0 | AB58: =SUMIF('MASTER DATA'!$E:$E,'GENERAL PAYROLL'!$E58,'MASTER DATA'!$AX:$AX) -> 0 | AC58: =SUMIF('MASTER DATA'!$E:$E,'GENERAL PAYROLL'!$E58,'MASTER DATA'!$AY:$AY) -> 8974.55 | AD58: =IF(E58>=1,"SHOW","HIDE") -> SHOW
C59: 3-GSS | D59: =IF(E59="","",COUNTA($E$20:E59)) -> 40 | E59: =IFERROR(VLOOKUP(C59,CODE!$B:$D,3,FALSE)," ") -> MARCELO, FERDINAND S. | F59: =VLOOKUP($C59,CODE!$B:$F,5,FALSE) -> Administrative Asst. I | G59: =VLOOKUP($C59,CODE!$B:$F,4,FALSE) -> GSS | H59: 11 | I59: =SUMIF('MASTER DATA'!$E:$E,'GENERAL PAYROLL'!$E59,'MASTER DATA'!$O:$O) -> 846.36364 | J59: =SUMIF('MASTER DATA'!$E:$E,'GENERAL PAYROLL'!$E59,'MASTER DATA'!$N:$N) -> 9310 | K59: =SUMIF('MASTER DATA'!$E:$E,'GENERAL PAYROLL'!$E59,'MASTER DATA'!$W:$W) -> 0 | L59: =SUMIF('MASTER DATA'!$E:$E,'GENERAL PAYROLL'!$E59,'MASTER DATA'!$X:$X)+SUMIF('MASTER DATA'!$E:$E,'GENERAL PAYROLL'!$E59,'MASTER DATA'!$Y:$Y) -> 0 | M59: =SUM(K59:L59) -> 0 | N59: =SUMIF('MASTER DATA'!$E:$E,'GENERAL PAYROLL'!$E59,'MASTER DATA'!$AC:$AC) -> 0 | O59: =SUMIF('MASTER DATA'!$E:$E,'GENERAL PAYROLL'!$E59,'MASTER DATA'!$AD:$AD)+SUMIF('MASTER DATA'!$E:$E,'GENERAL PAYROLL'!$E59,'MASTER DATA'!$AE:$AE) -> 0 | P59: =SUM(N59:O59) -> 0 | Q59: =SUMIF('MASTER DATA'!$E:$E,'GENERAL PAYROLL'!$E59,'MASTER DATA'!$AI:$AI) -> 0 | R59: =SUMIF('MASTER DATA'!$E:$E,'GENERAL PAYROLL'!$E59,'MASTER DATA'!$AJ:$AJ)+SUMIF('MASTER DATA'!$E:$E,'GENERAL PAYROLL'!$E59,'MASTER DATA'!$AK:$AK) -> 0 | S59: =SUM(Q59:R59) -> 0 | T59: =SUMIF('MASTER DATA'!$E:$E,'GENERAL PAYROLL'!$E59,'MASTER DATA'!$AO:$AO) -> 0 | U59: =SUMIF('MASTER DATA'!$E:$E,'GENERAL PAYROLL'!$E59,'MASTER DATA'!$AP:$AP) -> 0 | V59: =SUMIF('MASTER DATA'!$E:$E,'GENERAL PAYROLL'!$E59,'MASTER DATA'!$AR:$AR) -> 9310 | W59: =SUMIF('MASTER DATA'!$E:$E,'GENERAL PAYROLL'!$E59,'MASTER DATA'!$AS:$AS) -> 0 | X59: =SUMIF('MASTER DATA'!$E:$E,'GENERAL PAYROLL'!$E59,'MASTER DATA'!$AT:$AT) -> 0 | Y59: =SUMIF('MASTER DATA'!$E:$E,'GENERAL PAYROLL'!$E59,'MASTER DATA'!$AU:$AU) -> 0 | Z59: =SUMIF('MASTER DATA'!$E:$E,'GENERAL PAYROLL'!$E59,'MASTER DATA'!$AV:$AV) -> 0 | AA59: =SUMIF('MASTER DATA'!$E:$E,'GENERAL PAYROLL'!$E59,'MASTER DATA'!$AW:$AW) -> 0 | AB59: =SUMIF('MASTER DATA'!$E:$E,'GENERAL PAYROLL'!$E59,'MASTER DATA'!$AX:$AX) -> 0 | AC59: =SUMIF('MASTER DATA'!$E:$E,'GENERAL PAYROLL'!$E59,'MASTER DATA'!$AY:$AY) -> 9310 | AD59: =IF(E59>=1,"SHOW","HIDE") -> SHOW
C60: 4-GSS | D60: =IF(E60="","",COUNTA($E$20:E60)) -> 41 | E60: =IFERROR(VLOOKUP(C60,CODE!$B:$D,3,FALSE)," ") -> TAPIADOR, JACKSON T. | F60: =VLOOKUP($C60,CODE!$B:$F,5,FALSE) -> Administrative Asst. I | G60: =VLOOKUP($C60,CODE!$B:$F,4,FALSE) -> GSS | H60: 11 | I60: =SUMIF('MASTER DATA'!$E:$E,'GENERAL PAYROLL'!$E60,'MASTER DATA'!$O:$O) -> 846.36364 | J60: =SUMIF('MASTER DATA'!$E:$E,'GENERAL PAYROLL'!$E60,'MASTER DATA'!$N:$N) -> 9310 | K60: =SUMIF('MASTER DATA'!$E:$E,'GENERAL PAYROLL'!$E60,'MASTER DATA'!$W:$W) -> 0 | L60: =SUMIF('MASTER DATA'!$E:$E,'GENERAL PAYROLL'!$E60,'MASTER DATA'!$X:$X)+SUMIF('MASTER DATA'!$E:$E,'GENERAL PAYROLL'!$E60,'MASTER DATA'!$Y:$Y) -> 0 | M60: =SUM(K60:L60) -> 0 | N60: =SUMIF('MASTER DATA'!$E:$E,'GENERAL PAYROLL'!$E60,'MASTER DATA'!$AC:$AC) -> 0 | O60: =SUMIF('MASTER DATA'!$E:$E,'GENERAL PAYROLL'!$E60,'MASTER DATA'!$AD:$AD)+SUMIF('MASTER DATA'!$E:$E,'GENERAL PAYROLL'!$E60,'MASTER DATA'!$AE:$AE) -> 0 | P60: =SUM(N60:O60) -> 0 | Q60: =SUMIF('MASTER DATA'!$E:$E,'GENERAL PAYROLL'!$E60,'MASTER DATA'!$AI:$AI) -> 0 | R60: =SUMIF('MASTER DATA'!$E:$E,'GENERAL PAYROLL'!$E60,'MASTER DATA'!$AJ:$AJ)+SUMIF('MASTER DATA'!$E:$E,'GENERAL PAYROLL'!$E60,'MASTER DATA'!$AK:$AK) -> 0 | S60: =SUM(Q60:R60) -> 0 | T60: =SUMIF('MASTER DATA'!$E:$E,'GENERAL PAYROLL'!$E60,'MASTER DATA'!$AO:$AO) -> 0 | U60: =SUMIF('MASTER DATA'!$E:$E,'GENERAL PAYROLL'!$E60,'MASTER DATA'!$AP:$AP) -> 0 | V60: =SUMIF('MASTER DATA'!$E:$E,'GENERAL PAYROLL'!$E60,'MASTER DATA'!$AR:$AR) -> 9310 | W60: =SUMIF('MASTER DATA'!$E:$E,'GENERAL PAYROLL'!$E60,'MASTER DATA'!$AS:$AS) -> 0 | X60: =SUMIF('MASTER DATA'!$E:$E,'GENERAL PAYROLL'!$E60,'MASTER DATA'!$AT:$AT) -> 0 | Y60: =SUMIF('MASTER DATA'!$E:$E,'GENERAL PAYROLL'!$E60,'MASTER DATA'!$AU:$AU) -> 0 | Z60: =SUMIF('MASTER DATA'!$E:$E,'GENERAL PAYROLL'!$E60,'MASTER DATA'!$AV:$AV) -> 0 | AA60: =SUMIF('MASTER DATA'!$E:$E,'GENERAL PAYROLL'!$E60,'MASTER DATA'!$AW:$AW) -> 0 | AB60: =SUMIF('MASTER DATA'!$E:$E,'GENERAL PAYROLL'!$E60,'MASTER DATA'!$AX:$AX) -> 0 | AC60: =SUMIF('MASTER DATA'!$E:$E,'GENERAL PAYROLL'!$E60,'MASTER DATA'!$AY:$AY) -> 9310 | AD60: =IF(E60>=1,"SHOW","HIDE") -> SHOW
C61: 5-GSS | D61: =IF(E61="","",COUNTA($E$20:E61)) -> 42 | E61: =IFERROR(VLOOKUP(C61,CODE!$B:$D,3,FALSE)," ") -> GAMBOA, ELGIE F. | F61: =VLOOKUP($C61,CODE!$B:$F,5,FALSE) -> Administrative Asst. I | G61: =VLOOKUP($C61,CODE!$B:$F,4,FALSE) -> GSS | H61: 11 | I61: =SUMIF('MASTER DATA'!$E:$E,'GENERAL PAYROLL'!$E61,'MASTER DATA'!$O:$O) -> 846.36364 | J61: =SUMIF('MASTER DATA'!$E:$E,'GENERAL PAYROLL'!$E61,'MASTER DATA'!$N:$N) -> 9310 | K61: =SUMIF('MASTER DATA'!$E:$E,'GENERAL PAYROLL'!$E61,'MASTER DATA'!$W:$W) -> 2539.09 | L61: =SUMIF('MASTER DATA'!$E:$E,'GENERAL PAYROLL'!$E61,'MASTER DATA'!$X:$X)+SUMIF('MASTER DATA'!$E:$E,'GENERAL PAYROLL'!$E61,'MASTER DATA'!$Y:$Y) -> 0 | M61: =SUM(K61:L61) -> 2539.09 | N61: =SUMIF('MASTER DATA'!$E:$E,'GENERAL PAYROLL'!$E61,'MASTER DATA'!$AC:$AC) -> 0 | O61: =SUMIF('MASTER DATA'!$E:$E,'GENERAL PAYROLL'!$E61,'MASTER DATA'!$AD:$AD)+SUMIF('MASTER DATA'!$E:$E,'GENERAL PAYROLL'!$E61,'MASTER DATA'!$AE:$AE) -> 0 | P61: =SUM(N61:O61) -> 0 | Q61: =SUMIF('MASTER DATA'!$E:$E,'GENERAL PAYROLL'!$E61,'MASTER DATA'!$AI:$AI) -> 0 | R61: =SUMIF('MASTER DATA'!$E:$E,'GENERAL PAYROLL'!$E61,'MASTER DATA'!$AJ:$AJ)+SUMIF('MASTER DATA'!$E:$E,'GENERAL PAYROLL'!$E61,'MASTER DATA'!$AK:$AK) -> 0 | S61: =SUM(Q61:R61) -> 0 | T61: =SUMIF('MASTER DATA'!$E:$E,'GENERAL PAYROLL'!$E61,'MASTER DATA'!$AO:$AO) -> 2539.09 | U61: =SUMIF('MASTER DATA'!$E:$E,'GENERAL PAYROLL'!$E61,'MASTER DATA'!$AP:$AP) -> 0 | V61: =SUMIF('MASTER DATA'!$E:$E,'GENERAL PAYROLL'!$E61,'MASTER DATA'!$AR:$AR) -> 6770.91 | W61: =SUMIF('MASTER DATA'!$E:$E,'GENERAL PAYROLL'!$E61,'MASTER DATA'!$AS:$AS) -> 0 | X61: =SUMIF('MASTER DATA'!$E:$E,'GENERAL PAYROLL'!$E61,'MASTER DATA'!$AT:$AT) -> 0 | Y61: =SUMIF('MASTER DATA'!$E:$E,'GENERAL PAYROLL'!$E61,'MASTER DATA'!$AU:$AU) -> 0 | Z61: =SUMIF('MASTER DATA'!$E:$E,'GENERAL PAYROLL'!$E61,'MASTER DATA'!$AV:$AV) -> 0 | AA61: =SUMIF('MASTER DATA'!$E:$E,'GENERAL PAYROLL'!$E61,'MASTER DATA'!$AW:$AW) -> 0 | AB61: =SUMIF('MASTER DATA'!$E:$E,'GENERAL PAYROLL'!$E61,'MASTER DATA'!$AX:$AX) -> 0 | AC61: =SUMIF('MASTER DATA'!$E:$E,'GENERAL PAYROLL'!$E61,'MASTER DATA'!$AY:$AY) -> 6770.91 | AD61: =IF(E61>=1,"SHOW","HIDE") -> SHOW
C62: 6-GSS | D62: =IF(E62="","",COUNTA($E$20:E62)) -> 43 | E62: =IFERROR(VLOOKUP(C62,CODE!$B:$D,3,FALSE)," ") -> TORIO, MARLON P. | F62: =VLOOKUP($C62,CODE!$B:$F,5,FALSE) -> Administrative Asst. I (Bus Driver) | G62: =VLOOKUP($C62,CODE!$B:$F,4,FALSE) -> GSS | H62: 11 | I62: =SUMIF('MASTER DATA'!$E:$E,'GENERAL PAYROLL'!$E62,'MASTER DATA'!$O:$O) -> 846.36364 | J62: =SUMIF('MASTER DATA'!$E:$E,'GENERAL PAYROLL'!$E62,'MASTER DATA'!$N:$N) -> 9310 | K62: =SUMIF('MASTER DATA'!$E:$E,'GENERAL PAYROLL'!$E62,'MASTER DATA'!$W:$W) -> 0 | L62: =SUMIF('MASTER DATA'!$E:$E,'GENERAL PAYROLL'!$E62,'MASTER DATA'!$X:$X)+SUMIF('MASTER DATA'!$E:$E,'GENERAL PAYROLL'!$E62,'MASTER DATA'!$Y:$Y) -> 0 | M62: =SUM(K62:L62) -> 0 | N62: =SUMIF('MASTER DATA'!$E:$E,'GENERAL PAYROLL'!$E62,'MASTER DATA'!$AC:$AC) -> 0 | O62: =SUMIF('MASTER DATA'!$E:$E,'GENERAL PAYROLL'!$E62,'MASTER DATA'!$AD:$AD)+SUMIF('MASTER DATA'!$E:$E,'GENERAL PAYROLL'!$E62,'MASTER DATA'!$AE:$AE) -> 0 | P62: =SUM(N62:O62) -> 0 | Q62: =SUMIF('MASTER DATA'!$E:$E,'GENERAL PAYROLL'!$E62,'MASTER DATA'!$AI:$AI) -> 0 | R62: =SUMIF('MASTER DATA'!$E:$E,'GENERAL PAYROLL'!$E62,'MASTER DATA'!$AJ:$AJ)+SUMIF('MASTER DATA'!$E:$E,'GENERAL PAYROLL'!$E62,'MASTER DATA'!$AK:$AK) -> 0 | S62: =SUM(Q62:R62) -> 0 | T62: =SUMIF('MASTER DATA'!$E:$E,'GENERAL PAYROLL'!$E62,'MASTER DATA'!$AO:$AO) -> 0 | U62: =SUMIF('MASTER DATA'!$E:$E,'GENERAL PAYROLL'!$E62,'MASTER DATA'!$AP:$AP) -> 0 | V62: =SUMIF('MASTER DATA'!$E:$E,'GENERAL PAYROLL'!$E62,'MASTER DATA'!$AR:$AR) -> 9310 | W62: =SUMIF('MASTER DATA'!$E:$E,'GENERAL PAYROLL'!$E62,'MASTER DATA'!$AS:$AS) -> 0 | X62: =SUMIF('MASTER DATA'!$E:$E,'GENERAL PAYROLL'!$E62,'MASTER DATA'!$AT:$AT) -> 0 | Y62: =SUMIF('MASTER DATA'!$E:$E,'GENERAL PAYROLL'!$E62,'MASTER DATA'!$AU:$AU) -> 0 | Z62: =SUMIF('MASTER DATA'!$E:$E,'GENERAL PAYROLL'!$E62,'MASTER DATA'!$AV:$AV) -> 0 | AA62: =SUMIF('MASTER DATA'!$E:$E,'GENERAL PAYROLL'!$E62,'MASTER DATA'!$AW:$AW) -> 0 | AB62: =SUMIF('MASTER DATA'!$E:$E,'GENERAL PAYROLL'!$E62,'MASTER DATA'!$AX:$AX) -> 0 | AC62: =SUMIF('MASTER DATA'!$E:$E,'GENERAL PAYROLL'!$E62,'MASTER DATA'!$AY:$AY) -> 9310 | AD62: =IF(E62>=1,"SHOW","HIDE") -> SHOW
C63: 7-GSS | D63: =IF(E63="","",COUNTA($E$20:E63)) -> 44 | E63: =IFERROR(VLOOKUP(C63,CODE!$B:$D,3,FALSE)," ") -> NAMOCA, SANTIAGO J. | F63: =VLOOKUP($C63,CODE!$B:$F,5,FALSE) -> Administrative Asst. I (Bus Driver) | G63: =VLOOKUP($C63,CODE!$B:$F,4,FALSE) -> GSS | H63: 11 | I63: =SUMIF('MASTER DATA'!$E:$E,'GENERAL PAYROLL'!$E63,'MASTER DATA'!$O:$O) -> 846.36364 | J63: =SUMIF('MASTER DATA'!$E:$E,'GENERAL PAYROLL'!$E63,'MASTER DATA'!$N:$N) -> 9310 | K63: =SUMIF('MASTER DATA'!$E:$E,'GENERAL PAYROLL'!$E63,'MASTER DATA'!$W:$W) -> 0 | L63: =SUMIF('MASTER DATA'!$E:$E,'GENERAL PAYROLL'!$E63,'MASTER DATA'!$X:$X)+SUMIF('MASTER DATA'!$E:$E,'GENERAL PAYROLL'!$E63,'MASTER DATA'!$Y:$Y) -> 0 | M63: =SUM(K63:L63) -> 0 | N63: =SUMIF('MASTER DATA'!$E:$E,'GENERAL PAYROLL'!$E63,'MASTER DATA'!$AC:$AC) -> 0 | O63: =SUMIF('MASTER DATA'!$E:$E,'GENERAL PAYROLL'!$E63,'MASTER DATA'!$AD:$AD)+SUMIF('MASTER DATA'!$E:$E,'GENERAL PAYROLL'!$E63,'MASTER DATA'!$AE:$AE) -> 0 | P63: =SUM(N63:O63) -> 0 | Q63: =SUMIF('MASTER DATA'!$E:$E,'GENERAL PAYROLL'!$E63,'MASTER DATA'!$AI:$AI) -> 0 | R63: =SUMIF('MASTER DATA'!$E:$E,'GENERAL PAYROLL'!$E63,'MASTER DATA'!$AJ:$AJ)+SUMIF('MASTER DATA'!$E:$E,'GENERAL PAYROLL'!$E63,'MASTER DATA'!$AK:$AK) -> 0 | S63: =SUM(Q63:R63) -> 0 | T63: =SUMIF('MASTER DATA'!$E:$E,'GENERAL PAYROLL'!$E63,'MASTER DATA'!$AO:$AO) -> 0 | U63: =SUMIF('MASTER DATA'!$E:$E,'GENERAL PAYROLL'!$E63,'MASTER DATA'!$AP:$AP) -> 0 | V63: =SUMIF('MASTER DATA'!$E:$E,'GENERAL PAYROLL'!$E63,'MASTER DATA'!$AR:$AR) -> 9310 | W63: =SUMIF('MASTER DATA'!$E:$E,'GENERAL PAYROLL'!$E63,'MASTER DATA'!$AS:$AS) -> 0 | X63: =SUMIF('MASTER DATA'!$E:$E,'GENERAL PAYROLL'!$E63,'MASTER DATA'!$AT:$AT) -> 0 | Y63: =SUMIF('MASTER DATA'!$E:$E,'GENERAL PAYROLL'!$E63,'MASTER DATA'!$AU:$AU) -> 0 | Z63: =SUMIF('MASTER DATA'!$E:$E,'GENERAL PAYROLL'!$E63,'MASTER DATA'!$AV:$AV) -> 0 | AA63: =SUMIF('MASTER DATA'!$E:$E,'GENERAL PAYROLL'!$E63,'MASTER DATA'!$AW:$AW) -> 0 | AB63: =SUMIF('MASTER DATA'!$E:$E,'GENERAL PAYROLL'!$E63,'MASTER DATA'!$AX:$AX) -> 0 | AC63: =SUMIF('MASTER DATA'!$E:$E,'GENERAL PAYROLL'!$E63,'MASTER DATA'!$AY:$AY) -> 9310 | AD63: =IF(E63>=1,"SHOW","HIDE") -> SHOW
C64: 8-GSS | D64: =IF(E64="","",COUNTA($E$20:E64)) -> 45 | E64: =IFERROR(VLOOKUP(C64,CODE!$B:$D,3,FALSE)," ") -> GUTIERREZ, DACHIEL P. | F64: =VLOOKUP($C64,CODE!$B:$F,5,FALSE) -> Administrative Asst. I | G64: =VLOOKUP($C64,CODE!$B:$F,4,FALSE) -> GSS | H64: 11 | I64: =SUMIF('MASTER DATA'!$E:$E,'GENERAL PAYROLL'!$E64,'MASTER DATA'!$O:$O) -> 846.36364 | J64: =SUMIF('MASTER DATA'!$E:$E,'GENERAL PAYROLL'!$E64,'MASTER DATA'!$N:$N) -> 9310 | K64: =SUMIF('MASTER DATA'!$E:$E,'GENERAL PAYROLL'!$E64,'MASTER DATA'!$W:$W) -> 0 | L64: =SUMIF('MASTER DATA'!$E:$E,'GENERAL PAYROLL'!$E64,'MASTER DATA'!$X:$X)+SUMIF('MASTER DATA'!$E:$E,'GENERAL PAYROLL'!$E64,'MASTER DATA'!$Y:$Y) -> 40.55 | M64: =SUM(K64:L64) -> 40.55 | N64: =SUMIF('MASTER DATA'!$E:$E,'GENERAL PAYROLL'!$E64,'MASTER DATA'!$AC:$AC) -> 0 | O64: =SUMIF('MASTER DATA'!$E:$E,'GENERAL PAYROLL'!$E64,'MASTER DATA'!$AD:$AD)+SUMIF('MASTER DATA'!$E:$E,'GENERAL PAYROLL'!$E64,'MASTER DATA'!$AE:$AE) -> 0 | P64: =SUM(N64:O64) -> 0 | Q64: =SUMIF('MASTER DATA'!$E:$E,'GENERAL PAYROLL'!$E64,'MASTER DATA'!$AI:$AI) -> 0 | R64: =SUMIF('MASTER DATA'!$E:$E,'GENERAL PAYROLL'!$E64,'MASTER DATA'!$AJ:$AJ)+SUMIF('MASTER DATA'!$E:$E,'GENERAL PAYROLL'!$E64,'MASTER DATA'!$AK:$AK) -> 0 | S64: =SUM(Q64:R64) -> 0 | T64: =SUMIF('MASTER DATA'!$E:$E,'GENERAL PAYROLL'!$E64,'MASTER DATA'!$AO:$AO) -> 40.55 | U64: =SUMIF('MASTER DATA'!$E:$E,'GENERAL PAYROLL'!$E64,'MASTER DATA'!$AP:$AP) -> 0 | V64: =SUMIF('MASTER DATA'!$E:$E,'GENERAL PAYROLL'!$E64,'MASTER DATA'!$AR:$AR) -> 9269.45 | W64: =SUMIF('MASTER DATA'!$E:$E,'GENERAL PAYROLL'!$E64,'MASTER DATA'!$AS:$AS) -> 0 | X64: =SUMIF('MASTER DATA'!$E:$E,'GENERAL PAYROLL'!$E64,'MASTER DATA'!$AT:$AT) -> 0 | Y64: =SUMIF('MASTER DATA'!$E:$E,'GENERAL PAYROLL'!$E64,'MASTER DATA'!$AU:$AU) -> 0 | Z64: =SUMIF('MASTER DATA'!$E:$E,'GENERAL PAYROLL'!$E64,'MASTER DATA'!$AV:$AV) -> 0 | AA64: =SUMIF('MASTER DATA'!$E:$E,'GENERAL PAYROLL'!$E64,'MASTER DATA'!$AW:$AW) -> 0 | AB64: =SUMIF('MASTER DATA'!$E:$E,'GENERAL PAYROLL'!$E64,'MASTER DATA'!$AX:$AX) -> 0 | AC64: =SUMIF('MASTER DATA'!$E:$E,'GENERAL PAYROLL'!$E64,'MASTER DATA'!$AY:$AY) -> 9269.45 | AD64: =IF(E64>=1,"SHOW","HIDE") -> SHOW
C65: 1-INFRA | D65: =IF(E65="","",COUNTA($E$20:E65)) -> 46 | E65: =IFERROR(VLOOKUP(C65,CODE!$B:$D,3,FALSE)," ") -> PERALTA, JONEL | F65: =VLOOKUP($C65,CODE!$B:$F,5,FALSE) -> Civil Engineer II | G65: =VLOOKUP($C65,CODE!$B:$F,4,FALSE) -> INFRA | H65: 11 | I65: =SUMIF('MASTER DATA'!$E:$E,'GENERAL PAYROLL'!$E65,'MASTER DATA'!$O:$O) -> 1803.2727 | J65: =SUMIF('MASTER DATA'!$E:$E,'GENERAL PAYROLL'!$E65,'MASTER DATA'!$N:$N) -> 19836 | K65: =SUMIF('MASTER DATA'!$E:$E,'GENERAL PAYROLL'!$E65,'MASTER DATA'!$W:$W) -> 0 | L65: =SUMIF('MASTER DATA'!$E:$E,'GENERAL PAYROLL'!$E65,'MASTER DATA'!$X:$X)+SUMIF('MASTER DATA'!$E:$E,'GENERAL PAYROLL'!$E65,'MASTER DATA'!$Y:$Y) -> 0 | M65: =SUM(K65:L65) -> 0 | N65: =SUMIF('MASTER DATA'!$E:$E,'GENERAL PAYROLL'!$E65,'MASTER DATA'!$AC:$AC) -> 0 | O65: =SUMIF('MASTER DATA'!$E:$E,'GENERAL PAYROLL'!$E65,'MASTER DATA'!$AD:$AD)+SUMIF('MASTER DATA'!$E:$E,'GENERAL PAYROLL'!$E65,'MASTER DATA'!$AE:$AE) -> 0 | P65: =SUM(N65:O65) -> 0 | Q65: =SUMIF('MASTER DATA'!$E:$E,'GENERAL PAYROLL'!$E65,'MASTER DATA'!$AI:$AI) -> 0 | R65: =SUMIF('MASTER DATA'!$E:$E,'GENERAL PAYROLL'!$E65,'MASTER DATA'!$AJ:$AJ)+SUMIF('MASTER DATA'!$E:$E,'GENERAL PAYROLL'!$E65,'MASTER DATA'!$AK:$AK) -> 0 | S65: =SUM(Q65:R65) -> 0 | T65: =SUMIF('MASTER DATA'!$E:$E,'GENERAL PAYROLL'!$E65,'MASTER DATA'!$AO:$AO) -> 0 | U65: =SUMIF('MASTER DATA'!$E:$E,'GENERAL PAYROLL'!$E65,'MASTER DATA'!$AP:$AP) -> 0 | V65: =SUMIF('MASTER DATA'!$E:$E,'GENERAL PAYROLL'!$E65,'MASTER DATA'!$AR:$AR) -> 19836 | W65: =SUMIF('MASTER DATA'!$E:$E,'GENERAL PAYROLL'!$E65,'MASTER DATA'!$AS:$AS) -> 0 | X65: =SUMIF('MASTER DATA'!$E:$E,'GENERAL PAYROLL'!$E65,'MASTER DATA'!$AT:$AT) -> 1983.6 | Y65: =SUMIF('MASTER DATA'!$E:$E,'GENERAL PAYROLL'!$E65,'MASTER DATA'!$AU:$AU) -> 2000 | Z65: =SUMIF('MASTER DATA'!$E:$E,'GENERAL PAYROLL'!$E65,'MASTER DATA'!$AV:$AV) -> 922.78 | AA65: =SUMIF('MASTER DATA'!$E:$E,'GENERAL PAYROLL'!$E65,'MASTER DATA'!$AW:$AW) -> 0 | AB65: =SUMIF('MASTER DATA'!$E:$E,'GENERAL PAYROLL'!$E65,'MASTER DATA'!$AX:$AX) -> 0 | AC65: =SUMIF('MASTER DATA'!$E:$E,'GENERAL PAYROLL'!$E65,'MASTER DATA'!$AY:$AY) -> 14929.62 | AD65: =IF(E65>=1,"SHOW","HIDE") -> SHOW
C66: 2-INFRA | D66: =IF(E66="","",COUNTA($E$20:E66)) -> 47 | E66: =IFERROR(VLOOKUP(C66,CODE!$B:$D,3,FALSE)," ") -> RIVAS, JOSEPH S. | F66: =VLOOKUP($C66,CODE!$B:$F,5,FALSE) -> Electrician General Forman | G66: =VLOOKUP($C66,CODE!$B:$F,4,FALSE) -> INFRA | H66: 11 | I66: =SUMIF('MASTER DATA'!$E:$E,'GENERAL PAYROLL'!$E66,'MASTER DATA'!$O:$O) -> 0 | J66: =SUMIF('MASTER DATA'!$E:$E,'GENERAL PAYROLL'!$E66,'MASTER DATA'!$N:$N) -> 0 | K66: =SUMIF('MASTER DATA'!$E:$E,'GENERAL PAYROLL'!$E66,'MASTER DATA'!$W:$W) -> 0 | L66: =SUMIF('MASTER DATA'!$E:$E,'GENERAL PAYROLL'!$E66,'MASTER DATA'!$X:$X)+SUMIF('MASTER DATA'!$E:$E,'GENERAL PAYROLL'!$E66,'MASTER DATA'!$Y:$Y) -> 0 | M66: =SUM(K66:L66) -> 0 | N66: =SUMIF('MASTER DATA'!$E:$E,'GENERAL PAYROLL'!$E66,'MASTER DATA'!$AC:$AC) -> 0 | O66: =SUMIF('MASTER DATA'!$E:$E,'GENERAL PAYROLL'!$E66,'MASTER DATA'!$AD:$AD)+SUMIF('MASTER DATA'!$E:$E,'GENERAL PAYROLL'!$E66,'MASTER DATA'!$AE:$AE) -> 0 | P66: =SUM(N66:O66) -> 0 | Q66: =SUMIF('MASTER DATA'!$E:$E,'GENERAL PAYROLL'!$E66,'MASTER DATA'!$AI:$AI) -> 0 | R66: =SUMIF('MASTER DATA'!$E:$E,'GENERAL PAYROLL'!$E66,'MASTER DATA'!$AJ:$AJ)+SUMIF('MASTER DATA'!$E:$E,'GENERAL PAYROLL'!$E66,'MASTER DATA'!$AK:$AK) -> 0 | S66: =SUM(Q66:R66) -> 0 | T66: =SUMIF('MASTER DATA'!$E:$E,'GENERAL PAYROLL'!$E66,'MASTER DATA'!$AO:$AO) -> 0 | U66: =SUMIF('MASTER DATA'!$E:$E,'GENERAL PAYROLL'!$E66,'MASTER DATA'!$AP:$AP) -> 0 | V66: =SUMIF('MASTER DATA'!$E:$E,'GENERAL PAYROLL'!$E66,'MASTER DATA'!$AR:$AR) -> 0 | W66: =SUMIF('MASTER DATA'!$E:$E,'GENERAL PAYROLL'!$E66,'MASTER DATA'!$AS:$AS) -> 0 | X66: =SUMIF('MASTER DATA'!$E:$E,'GENERAL PAYROLL'!$E66,'MASTER DATA'!$AT:$AT) -> 0 | Y66: =SUMIF('MASTER DATA'!$E:$E,'GENERAL PAYROLL'!$E66,'MASTER DATA'!$AU:$AU) -> 0 | Z66: =SUMIF('MASTER DATA'!$E:$E,'GENERAL PAYROLL'!$E66,'MASTER DATA'!$AV:$AV) -> 0 | AA66: =SUMIF('MASTER DATA'!$E:$E,'GENERAL PAYROLL'!$E66,'MASTER DATA'!$AW:$AW) -> 0 | AB66: =SUMIF('MASTER DATA'!$E:$E,'GENERAL PAYROLL'!$E66,'MASTER DATA'!$AX:$AX) -> 0 | AC66: =SUMIF('MASTER DATA'!$E:$E,'GENERAL PAYROLL'!$E66,'MASTER DATA'!$AY:$AY) -> 0 | AD66: =IF(E66>=1,"SHOW","HIDE") -> SHOW
... C81: 5-PAD | D81: =IF(E81="","",COUNTA($E$20:E81)) -> 62 | E81: =IFERROR(VLOOKUP(C81,CODE!$B:$D,3,FALSE)," ") -> MANGILOG, ERICCA MAE V. | F81: =VLOOKUP($C81,CODE!$B:$F,5,FALSE) -> Technical Support Staff IV | G81: =VLOOKUP($C81,CODE!$B:$F,4,FALSE) -> PAD | H81: 11 | I81: =SUMIF('MASTER DATA'!$E:$E,'GENERAL PAYROLL'!$E81,'MASTER DATA'!$O:$O) -> 1227.2727 | J81: =SUMIF('MASTER DATA'!$E:$E,'GENERAL PAYROLL'!$E81,'MASTER DATA'!$N:$N) -> 13500 | K81: =SUMIF('MASTER DATA'!$E:$E,'GENERAL PAYROLL'!$E81,'MASTER DATA'!$W:$W) -> 0 | L81: =SUMIF('MASTER DATA'!$E:$E,'GENERAL PAYROLL'!$E81,'MASTER DATA'!$X:$X)+SUMIF('MASTER DATA'!$E:$E,'GENERAL PAYROLL'!$E81,'MASTER DATA'!$Y:$Y) -> 97.16 | M81: =SUM(K81:L81) -> 97.16 | N81: =SUMIF('MASTER DATA'!$E:$E,'GENERAL PAYROLL'!$E81,'MASTER DATA'!$AC:$AC) -> 0 | O81: =SUMIF('MASTER DATA'!$E:$E,'GENERAL PAYROLL'!$E81,'MASTER DATA'!$AD:$AD)+SUMIF('MASTER DATA'!$E:$E,'GENERAL PAYROLL'!$E81,'MASTER DATA'!$AE:$AE) -> 0 | P81: =SUM(N81:O81) -> 0 | Q81: =SUMIF('MASTER DATA'!$E:$E,'GENERAL PAYROLL'!$E81,'MASTER DATA'!$AI:$AI) -> 0 | R81: =SUMIF('MASTER DATA'!$E:$E,'GENERAL PAYROLL'!$E81,'MASTER DATA'!$AJ:$AJ)+SUMIF('MASTER DATA'!$E:$E,'GENERAL PAYROLL'!$E81,'MASTER DATA'!$AK:$AK) -> 0 | S81: =SUM(Q81:R81) -> 0 | T81: =SUMIF('MASTER DATA'!$E:$E,'GENERAL PAYROLL'!$E81,'MASTER DATA'!$AO:$AO) -> 97.16 | U81: =SUMIF('MASTER DATA'!$E:$E,'GENERAL PAYROLL'!$E81,'MASTER DATA'!$AP:$AP) -> 0 | V81: =SUMIF('MASTER DATA'!$E:$E,'GENERAL PAYROLL'!$E81,'MASTER DATA'!$AR:$AR) -> 13402.84 | W81: =SUMIF('MASTER DATA'!$E:$E,'GENERAL PAYROLL'!$E81,'MASTER DATA'!$AS:$AS) -> 0 | X81: =SUMIF('MASTER DATA'!$E:$E,'GENERAL PAYROLL'!$E81,'MASTER DATA'!$AT:$AT) -> 0 | Y81: =SUMIF('MASTER DATA'!$E:$E,'GENERAL PAYROLL'!$E81,'MASTER DATA'!$AU:$AU) -> 0 | Z81: =SUMIF('MASTER DATA'!$E:$E,'GENERAL PAYROLL'!$E81,'MASTER DATA'!$AV:$AV) -> 0 | AA81: =SUMIF('MASTER DATA'!$E:$E,'GENERAL PAYROLL'!$E81,'MASTER DATA'!$AW:$AW) -> 0 | AB81: =SUMIF('MASTER DATA'!$E:$E,'GENERAL PAYROLL'!$E81,'MASTER DATA'!$AX:$AX) -> 0 | AC81: =SUMIF('MASTER DATA'!$E:$E,'GENERAL PAYROLL'!$E81,'MASTER DATA'!$AY:$AY) -> 13402.84 | AD81: =IF(E81>=1,"SHOW","HIDE") -> SHOW
C82: 6-PAD | D82: =IF(E82="","",COUNTA($E$20:E82)) -> 63 | E82: =IFERROR(VLOOKUP(C82,CODE!$B:$D,3,FALSE)," ") -> FRANCISCO, ULYSSES H. | F82: =VLOOKUP($C82,CODE!$B:$F,5,FALSE) -> Development Management Officer II | G82: =VLOOKUP($C82,CODE!$B:$F,4,FALSE) -> PAD | H82: 11 | I82: =SUMIF('MASTER DATA'!$E:$E,'GENERAL PAYROLL'!$E82,'MASTER DATA'!$O:$O) -> 1664.5 | J82: =SUMIF('MASTER DATA'!$E:$E,'GENERAL PAYROLL'!$E82,'MASTER DATA'!$N:$N) -> 18309.5 | K82: =SUMIF('MASTER DATA'!$E:$E,'GENERAL PAYROLL'!$E82,'MASTER DATA'!$W:$W) -> 0 | L82: =SUMIF('MASTER DATA'!$E:$E,'GENERAL PAYROLL'!$E82,'MASTER DATA'!$X:$X)+SUMIF('MASTER DATA'!$E:$E,'GENERAL PAYROLL'!$E82,'MASTER DATA'!$Y:$Y) -> 0 | M82: =SUM(K82:L82) -> 0 | N82: =SUMIF('MASTER DATA'!$E:$E,'GENERAL PAYROLL'!$E82,'MASTER DATA'!$AC:$AC) -> 0 | O82: =SUMIF('MASTER DATA'!$E:$E,'GENERAL PAYROLL'!$E82,'MASTER DATA'!$AD:$AD)+SUMIF('MASTER DATA'!$E:$E,'GENERAL PAYROLL'!$E82,'MASTER DATA'!$AE:$AE) -> 0 | P82: =SUM(N82:O82) -> 0 | S82: =SUM(Q82:R82) -> 0 | T82: =SUMIF('MASTER DATA'!$E:$E,'GENERAL PAYROLL'!$E82,'MASTER DATA'!$AO:$AO) -> 0 | U82: =SUMIF('MASTER DATA'!$E:$E,'GENERAL PAYROLL'!$E82,'MASTER DATA'!$AP:$AP) -> 0 | V82: =SUMIF('MASTER DATA'!$E:$E,'GENERAL PAYROLL'!$E82,'MASTER DATA'!$AR:$AR) -> 18309.5 | W82: =SUMIF('MASTER DATA'!$E:$E,'GENERAL PAYROLL'!$E82,'MASTER DATA'!$AS:$AS) -> 0 | X82: =SUMIF('MASTER DATA'!$E:$E,'GENERAL PAYROLL'!$E82,'MASTER DATA'!$AT:$AT) -> 0 | Y82: =SUMIF('MASTER DATA'!$E:$E,'GENERAL PAYROLL'!$E82,'MASTER DATA'!$AU:$AU) -> 0 | Z82: =SUMIF('MASTER DATA'!$E:$E,'GENERAL PAYROLL'!$E82,'MASTER DATA'!$AV:$AV) -> 0 | AA82: =SUMIF('MASTER DATA'!$E:$E,'GENERAL PAYROLL'!$E82,'MASTER DATA'!$AW:$AW) -> 0 | AB82: =SUMIF('MASTER DATA'!$E:$E,'GENERAL PAYROLL'!$E82,'MASTER DATA'!$AX:$AX) -> 0 | AC82: =SUMIF('MASTER DATA'!$E:$E,'GENERAL PAYROLL'!$E82,'MASTER DATA'!$AY:$AY) -> 18309.5 | AD82: =IF(E82>=1,"SHOW","HIDE") -> SHOW
C83: 7-PAD | D83: =IF(E83="","",COUNTA($E$20:E83)) -> 64 | E83: =IFERROR(VLOOKUP(C83,CODE!$B:$D,3,FALSE)," ") -> DITCHE, ALLIAH LYN P. | F83: =VLOOKUP($C83,CODE!$B:$F,5,FALSE) -> Development Management Officer II | G83: =VLOOKUP($C83,CODE!$B:$F,4,FALSE) -> PAD | H83: 11 | I83: =SUMIF('MASTER DATA'!$E:$E,'GENERAL PAYROLL'!$E83,'MASTER DATA'!$O:$O) -> 1664.5 | J83: =SUMIF('MASTER DATA'!$E:$E,'GENERAL PAYROLL'!$E83,'MASTER DATA'!$N:$N) -> 18309.5 | K83: =SUMIF('MASTER DATA'!$E:$E,'GENERAL PAYROLL'!$E83,'MASTER DATA'!$W:$W) -> 0 | L83: =SUMIF('MASTER DATA'!$E:$E,'GENERAL PAYROLL'!$E83,'MASTER DATA'!$X:$X)+SUMIF('MASTER DATA'!$E:$E,'GENERAL PAYROLL'!$E83,'MASTER DATA'!$Y:$Y) -> 6.94 | M83: =SUM(K83:L83) -> 6.94 | N83: =SUMIF('MASTER DATA'!$E:$E,'GENERAL PAYROLL'!$E83,'MASTER DATA'!$AC:$AC) -> 0 | O83: =SUMIF('MASTER DATA'!$E:$E,'GENERAL PAYROLL'!$E83,'MASTER DATA'!$AD:$AD)+SUMIF('MASTER DATA'!$E:$E,'GENERAL PAYROLL'!$E83,'MASTER DATA'!$AE:$AE) -> 0 | P83: =SUM(N83:O83) -> 0 | S83: =SUM(Q83:R83) -> 0 | T83: =SUMIF('MASTER DATA'!$E:$E,'GENERAL PAYROLL'!$E83,'MASTER DATA'!$AO:$AO) -> 6.94 | U83: =SUMIF('MASTER DATA'!$E:$E,'GENERAL PAYROLL'!$E83,'MASTER DATA'!$AP:$AP) -> 0 | V83: =SUMIF('MASTER DATA'!$E:$E,'GENERAL PAYROLL'!$E83,'MASTER DATA'!$AR:$AR) -> 18302.56 | W83: =SUMIF('MASTER DATA'!$E:$E,'GENERAL PAYROLL'!$E83,'MASTER DATA'!$AS:$AS) -> 0 | X83: =SUMIF('MASTER DATA'!$E:$E,'GENERAL PAYROLL'!$E83,'MASTER DATA'!$AT:$AT) -> 0 | Y83: =SUMIF('MASTER DATA'!$E:$E,'GENERAL PAYROLL'!$E83,'MASTER DATA'!$AU:$AU) -> 0 | Z83: =SUMIF('MASTER DATA'!$E:$E,'GENERAL PAYROLL'!$E83,'MASTER DATA'!$AV:$AV) -> 0 | AA83: =SUMIF('MASTER DATA'!$E:$E,'GENERAL PAYROLL'!$E83,'MASTER DATA'!$AW:$AW) -> 0 | AB83: =SUMIF('MASTER DATA'!$E:$E,'GENERAL PAYROLL'!$E83,'MASTER DATA'!$AX:$AX) -> 0 | AC83: =SUMIF('MASTER DATA'!$E:$E,'GENERAL PAYROLL'!$E83,'MASTER DATA'!$AY:$AY) -> 18302.56
